Workbook

Sheet README
A1: MediBec - Cybersecurity Risk Scenario Selection (10-scenario portfolio)
A3: Prepared 25 September 2026 under the Scenario Selection Instructions (20 steps, output Sections A-E). Assessment horizon: 12 months (Oct 2026 - Sep 2027).
A4: Source: MediBec Business Case v2.0b (fictional teaching case) and the earlier 30-scenario CyberRiskGuardian analysis. All scores and estimates are ANALYST JUDGEMENT - VALIDATION REQUIRED.
A5: Final scenario selection remains the responsibility of the human analyst and MediBec management (Critical rule 14).
A7: Sheets (output sections):
A8: A_Context, A_AssetMap, A_Dependencies - Section A: scope, objectives, asset map, single points of failure, materiality criteria, gaps.
A9: B_Candidates - Section B: 45 candidate scenarios written as causal chains.
A10: C_Screening - Section C: 12 criteria scored 1-5 (blue = editable), escalation flags, evidence, confidence, disposition.
A11: C_Weights, C_Sensitivity - Section C / step 20: four weighting schemes; family ranking recalculates live.
A12: D_Portfolio, D_WhyTest, D_QuantPrep, D_Validation - Section D: final 10 scenarios (P01-P10), 'why this scenario' test, inputs for quantification, stakeholder validation.
A13: E_Coverage, E_Quality - Section E: coverage matrix, portfolio quality review, blind spots, evidence plan.
A14: Changes - how P01-P10 relate to S1-S30 of the earlier assessment.
... A18: Colours: blue text = input; black = formula or analyst text; green = link to another sheet.

Sheet A_Context
A1: Section A - Assessment context
A3: Element | B3: Summary | C3: Basis
A4: Organization | B4: MediBec private medical centre - Montreal head office and data centre, 10 clinics (Montreal, Quebec City, Gatineau, Saguenay). | C4: Documented (E1)
A5: Scope | B5: All clinical, administrative and supporting technology services, including cloud, clinic networks, medical equipment, vendors and staff use of external services. | C5: Analyst definition
A6: Time horizon | B6: 12 months (October 2026 - September 2027) for probability estimates. | C6: Instruction s.1 default
A7: Purpose | B7: Select 10 scenarios representing MediBec's material cyber exposure for detailed CyberRiskGuardian quantification. | C7: User request
A8: Mission | B8: Deliver high-quality healthcare supported by technology, efficient clinical workflows and secure access to patient information. | C8: Documented (E1)
A9: Strategic context | B9: 2024-2030 cybersecurity roadmap; increasing attack attempts since 2020; no confirmed breach; lean IT (15 staff, 2 in security). | C9: Documented (E3, E4)
A10: Maturity (indicative) | B10: Perimeter controls (firewalls, IDS/IPS, antimalware), EDR, encrypted storage, on/off-site backups, push MFA on remote access. No evidence of PAM, SIEM/24x7 monitoring, segmentation, immutable backup, vendor risk programme, tested IR. | C10: Documented (E2) + exercise evidence (E6) + analyst inference
A11: Known weaknesses (exercise evidence) | B11: Macro phishing lure from look-alike domain; PowerShell alert closed as low severity; MFA push approved from unusual geography; external download of medical-image export; unusual queries by ehr-sync-svc; clinic backup failures. | C11: Exercise evidence (E6) - validate
A12: Obligations | B12: Quebec and Canadian privacy expectations for health information (confidentiality incidents, register, notification where risk of serious injury), professional obligations, contracts with cloud/technology vendors, evidence preservation. | C12: Documented (s.5) - legal counsel to confirm regime
A13: Risk appetite | B13: Low appetite for patient-safety, health-data, compliance and trust risks; moderate for governed innovation. Case tolerance 0.40 normalized; analytical estimate 0.30 used in CRG calculations. Residual > 0.25 executive review; > 0.40 Board acceptance. | C13: Documented (E5) + analytical estimate
A15: Critical objectives
A16: ID | B16: Objective | C16: Critical processes
A17: O1 | B17: Safe, continuous patient care in all 10 clinics | C17: Clinical documentation, diagnostics, prescribing, appointments
A18: O2 | B18: Protection of patient health information and privacy compliance | C18: EHR access, image sharing, referrals, communications
A19: O3 | B19: Operational and financial continuity | C19: Billing, payments, supplier management, administration
A20: O4 | B20: Public and patient trust | C20: Patient communications, online services, incident communications
A21: O5 | B21: Governed modernization (2024-2030) | C21: Cloud, AI, device and application adoption
A23: Materiality criteria used for selection (risk appetite and tolerance, Instruction s.4)
A24: Dimension | B24: Scenario is material if it could...
A25: Patient safety | B25: Any credible immediate threat to patient care or clinical decisions exceeds appetite (E5).
A26: Health data | B26: Exposure of health information of many patients, or any exposure of sensitive categories, is material.
A27: Clinical availability | B27: Loss of EHR, diagnostics or scheduling at several clinics beyond a working day is material.
A28: Regulatory | B28: Reportable confidentiality incident or failure to meet notification duties.
A29: Financial | B29: Loss that would require re-prioritizing the IT/cyber budget (analyst threshold: > CAD 250k) - validate with CFO.
A30: Reputational | B30: Regional media coverage or loss of referring-partner confidence.
A31: Recoverability | B31: Any scenario that can defeat primary and recovery environments together.
A33: Assumptions and information gaps (Instruction s.1, s.15)
A34: Gap / assumption | B34: How to validate
A35: Asset and medical-device inventories; internet-exposed services | B35: Architecture review, external attack-surface scan
A36: Identity design: MFA coverage, privileged and service accounts, help-desk reset procedure | B36: IAM configuration review, interviews
A37: Backup isolation, immutability, restore-test results, RTO/RPO | B37: Backup architecture review, restore test evidence
A38: Cloud tenant configuration, sharing links, logging | B38: Cloud posture assessment
A39: Vendor list, contracts, remote-access and update mechanisms | B39: Procurement records, supplier assessments
A40: Existence of patient portal, in-house code repositories, telehealth platform | B40: Application inventory, interviews with application owners
A41: Incident history since 2020 and how attempts were detected | B41: Incident records, SOC/EDR logs
A42: Staff use of generative AI | B42: Proxy logs, staff survey
A43: IT and cybersecurity budget figures | B43: Finance

Sheet A_AssetMap
A1: Section A - Business objective -> process -> primary asset -> supporting assets -> dependencies -> consequences
A3: Objective | B3: Business process | C3: Primary asset | D3: Supporting assets | E3: Dependencies | F3: Potential consequences
A4: O1 | B4: Clinical documentation and decision-making | C4: Patient record (EHR data) and its integrity | D4: EHR application and database, workstations, tablets | E4: Identity/MFA, Montreal DC, WAN, EHR vendor | F4: Delayed or unsafe care, clinic disruption
A5: O1 | B5: Diagnostics (imaging, lab) and pharmacy | C5: Diagnostic results, images, medication data | D5: Imaging modalities, lab/pharmacy systems, HL7/DICOM interfaces | E5: Medical-device vendors, interface engine, network | F5: Wrong or delayed diagnosis, medication errors
A6: O1 | B6: Appointment and patient flow | C6: Scheduling service | D6: Scheduling system, online booking, phones | E6: Internet link, hosting provider | F6: Cancelled appointments, overload
A7: O2 | B7: Access to and sharing of health information | C7: Patient health information (all stores) | D7: Cloud storage, clinic storage units, e-mail, APIs, backups | E7: Cloud provider, identity, integration partners | F7: Privacy breach, notification, sanctions
A8: O3 | B8: Billing and payments | C8: Financial assets, billing data | D8: Billing system, accounts payable, e-mail | E8: Banks, payers, billing vendor | F8: Financial loss, cash-flow disruption
A9: O3 | B9: IT operations and recovery | C9: Ability to restore services | D9: Backup servers, off-site copies, admin tooling | E9: Backup identity, off-site provider, admin staff | F9: Prolonged outage, permanent data loss
A10: O4 | B10: Patient communications | C10: MediBec brand and patient trust | D10: Web site, SMS/e-mail senders, telehealth platform | E10: DNS, communication vendors | F10: Loss of trust, patient fraud
A11: O5 | B11: Clinical innovation (AI, cloud, devices) | C11: New digital capabilities | D11: SaaS/AI tools, cloud services, new devices | E11: External AI and SaaS providers | F11: Uncontrolled data transfer, new attack surface

Sheet A_Dependencies
A1: Section A - Dependencies, single points of failure and concentration (Instruction s.3)
A2: Peripheral = assets that receive less security oversight but reach critical systems.
A3: Dependency | B3: Type | C3: What depends on it | D3: Single point of failure / concentration | E3: Peripheral asset? | F3: Related candidates
A4: Directory, MFA and cloud identity | B4: Identity | C4: Every crown jewel; remote and cloud access | D4: Concentration - single identity plane; push MFA | E4: No | F4: C01, C20, C23, C30, C35, C41
A5: Montreal data centre and WAN hub | B5: Location / network | C5: EHR, identity, backups, imaging for all 10 clinics | D5: Single point of failure (no alternate site evidenced) | E5: No | F5: C16, C45, C02
A6: Backup infrastructure and backup administration | B6: Recovery | C6: Recovery of every service | D6: Possible shared admin domain with production - primary and recovery can fail together | E6: No | F6: C03, C31, C02
A7: Integrated EHR vendor | B7: Supplier / SaaS | C7: Clinical documentation at all clinics | D7: Supplier concentration; vendor remote access and updates | E7: No | F7: C13, C22
A8: Medical-device manufacturers | B8: Supplier | C8: Imaging and diagnostic equipment | D8: Patching controlled by manufacturers; certification limits | E8: Yes - devices often outside IT oversight | F8: C09, C27, C43
A9: Cloud storage / tenant | B9: Cloud | C9: Image transfer, exports, collaboration | D9: Tenant-wide control plane | E9: Partly - exports created ad hoc | F9: C04, C23, C05
A10: Clinic networks, Wi-Fi and local storage units | B10: Network / storage | C10: Point-of-care access in 10 clinics | D10: Flat networks assumed; local data outside central controls | E10: Yes - clinic-level assets | F10: C06, C17, C27
A11: Internet-facing edge (VPN, firewalls, admin interfaces) | B11: Network | C11: Remote access for clinicians and vendors | D11: Single gateway; exposure unknown | E11: Yes - forgotten interfaces | F11: C07, C26, C36
A12: Telecom carriers | B12: Supplier | C12: WAN and internet for all clinics | D12: Carrier concentration unknown | E12: No | F12: C16, C10
A13: Interface engine (HL7/DICOM) | B13: Application | C13: Lab, pharmacy, imaging data into EHR | D13: Single integration path | E13: Yes - legacy protocols | F13: C32
A14: External AI and SaaS services used by staff | B14: SaaS | C14: Documentation, correspondence | D14: Unmanaged; outside contracts | E14: Yes - shadow IT | F14: C29, C42
A15: Privileged IT administrators (15-person team) | B15: People | C15: All infrastructure | D15: Key-person dependency; standing privileges | E15: No | F15: C31, C35

Sheet B_Candidates
A1: Section B - Candidate scenario population (45 candidates)
A2: Generation strategy: TD top-down, BU bottom-up, TH threat-driven, GL generic localized, DP dependency-driven. Prior ID links to the 30-scenario assessment.
A3: ID | B3: Scenario name | C3: Causal scenario statement | D3: Primary asset / process | E3: Threat source / event | F3: Principal vulnerability / condition | G3: Primary consequence | H3: CIA | I3: Strategy | J3: Source ref | K3: Prior ID
A4: C01 | B4: Phishing-led compromise of clinic administrator credentials | C4: A financially motivated external actor phishes clinic administrators and billing staff with an EHR-themed lure, captures credentials and obtains approval of an MFA push prompt, gaining remote access to the EHR, billing and administrative systems, enabling unauthorized access to patient records and follow-on intrusion. | D4: CJ5 / CJ1 | E4: Cybercriminal | F4: Push-based MFA susceptible to fatigue; macro attachments delivered | G4: Unauthorized EHR and remote access | H4: C, I | I4: TH, BU | J4: MED-CYR-01, 12 | K4: S1
A5: C02 | B5: Ransomware encrypting EHR support systems, shared folders and scheduling | C5: A ransomware group gains a foothold through a macro-enabled phishing attachment or exposed service, moves laterally across an insufficiently segmented network, exfiltrates health data and encrypts EHR support servers, shared folders and scheduling systems, halting clinical and administrative operations at multiple clinics. | D5: CJ1 / CJ3 / CJ6 | E5: Ransomware group | F5: Flat internal network; weak alert triage; backups reachable | G5: Multi-clinic disruption and data theft | H5: C, I, A | I5: TD, TH | J5: MED-CYR-02 | K5: S2
A6: C03 | B6: Backup environment compromised before encryption, recovery fails | C6: An attacker holding administrative credentials reaches backup servers that share the production identity domain and network, deletes or encrypts backup sets and clinic storage copies, so that MediBec cannot restore EHR and clinic systems within clinically acceptable time after a destructive event. | D6: CJ6 | E6: Ransomware group / privileged attacker | F6: Backups in same admin domain; restore testing not evidenced | G6: Prolonged outage, loss of recoverability | H6: A, I | I6: DP, BU | J6: MED-CYR-07 | K6: S3
A7: C04 | B7: Cloud medical-image transfer storage exposed or accessed externally | C7: An opportunistic or targeted actor discovers a cloud storage location used for medical-image transfer and exports that is shared through long-lived public or weakly authenticated links, downloads large volumes of images and associated patient identifiers, and causes a large-scale health-data breach. | D7: CJ7 | E7: Opportunistic actor / cybercriminal | F7: Permissive sharing, weak cloud logging and posture management | G7: Bulk health-data exposure | H7: C | I7: BU | J7: MED-CYR-03 | K7: S4
A8: C05 | B8: API key committed to a code repository enables data access | C8: An opportunistic actor finds an API key, database connection string or cloud access token that a developer committed to a code repository, left in a log or embedded in a configuration file, and uses it to call MediBec's EHR integration or cloud storage APIs directly, extracting patient data without passing through user authentication. | D8: CJ1 / CJ7 | E8: Opportunistic actor | F8: No secret scanning or vault evidenced | G8: Direct API data extraction | H8: C | I8: GL | J8: MED-CYR-04 | K8: S11
A9: C06 | B9: Clinic Wi-Fi compromise or rogue access point | C9: An attacker in or near a clinic exploits weak wireless security, an unsegmented guest network or a rogue access point to join the clinic network, intercept credentials and reach EHR workstations and local storage. | D9: Clinic LAN | E9: Local attacker | F9: Guest/clinical Wi-Fi segmentation not evidenced | G9: Internal network foothold | H9: C, I | I9: GL | J9: MED-CYR-05 | K9: S12
A10: C07 | B10: Exploitation of unpatched internet-facing or end-of-life systems | C10: A cybercriminal or state-linked actor mass-exploits a known vulnerability in an internet-facing remote access gateway, firewall or web application that MediBec has not patched because of uptime concerns, vendor constraints or limited staff, obtaining remote code execution and a foothold for data theft or ransomware. | D10: CJ5 / CJ6 | E10: Cybercriminal / state-linked actor | F10: Patch delays from uptime and vendor constraints | G10: Remote code execution and intrusion | H10: C, I, A | I10: BU, TH | J10: MED-CYR-06 | K10: S6
A11: C08 | B11: Intrusion goes undetected because monitoring and triage are insufficient | C11: An intrusion by any external actor goes unnoticed or is misclassified because alert triage, log coverage and after-hours monitoring are insufficient for a two-person cybersecurity team, and the untested incident response plan leads to slow, uncoordinated containment, turning a contained event into a major privacy and operational incident. | D11: All | E11: Any external actor | F11: 2-person team, alert closed as low severity, log coverage unknown | G11: Extended dwell time, amplified harm | H11: C, I, A | I11: BU | J11: MED-CYR-08 | K11: S8
A12: C09 | B12: Connected medical device used as network foothold | C12: An attacker reaching a clinic network (through malware, a compromised clinic Wi-Fi or vendor access) exploits an unpatched or default-credential medical device on a network shared with EHR workstations, disrupting device operation and using it as a persistent foothold, with potential consequences for patient care. | D12: CJ8 | E12: Cybercriminal | F12: Unpatched embedded OS, incomplete inventory, weak segmentation | G12: Device disruption, lateral movement | H12: I, A | I12: TD, DP | J12: MED-CYR-09 | K12: S7
A13: C10 | B13: DDoS against patient-facing online services | C13: A hacktivist or extortion group floods MediBec's internet-facing services with traffic, making online appointment booking, patient records access and external communications unavailable for hours or days and pushing volume to clinic phone lines. | D13: CJ3 | E13: Hacktivist / extortionist | F13: No DDoS protection evidenced | G13: Online booking unavailable | H13: A | I13: TH | J13: MED-CYR-10 | K13: S13
A14: C11 | B14: Staff member exports health or billing records for unauthorized purposes | C14: A malicious or curious insider, or an attacker who has taken over the over-privileged ehr-sync-svc service account, uses legitimate but excessive EHR access to query and export large volumes of patient or billing records without triggering review, resulting in a privacy breach and loss of trust. | D14: CJ1 / CJ4 | E14: Malicious or curious insider | F14: Broad EHR roles, limited access analytics | G14: Privacy breach | H14: C | I14: TH, TD | J14: MED-CYR-11 | K14: S5
... A48: C45 | B48: Firewall single point of failure | C48: Failure of the single primary firewall pair at the Montreal hub interrupts connectivity for all clinics until hardware is replaced. | D48: CJ6 | E48: Accidental / attacker | F48: No redundancy | G48: Outage | H48: A | I48: DP | J48: Annex B #5 | K48: -

Sheet C_Weights
A1: Section C - Criteria weighting schemes (sensitivity, Instruction s.20)
A2: Blue cells are editable; screening and sensitivity recalculate.
A3: Code | B3: Criterion | C3: Question | D3: Equal | E3: Impact-led | F3: Evidence-led | G3: Decision-led
A4: BC | B4: Business criticality | C4: Does the scenario threaten an important objective or critical process? | D4: 1 | E4: 2 | F4: 1 | G4: 1
A5: AC | B5: Asset criticality | C5: Does it affect high-value information, technology, services or infrastructure? | D5: 1 | E5: 1 | F5: 1 | G5: 1
A6: TR | B6: Threat relevance | C6: Is the threat credible for this organization and sector? | D6: 1 | E6: 1 | F6: 1.5 | G6: 1
A7: EX | B7: Exposure / vulnerability | C7: Are there plausible weaknesses or predisposing conditions? | D7: 1 | E7: 1 | F7: 1.5 | G7: 1
A8: IM | B8: Potential impact | C8: Could consequences materially affect the organization? | D8: 1 | E8: 2 | F8: 1 | G8: 1
A9: RL | B9: Regulatory / legal | C9: Could it create important compliance, privacy, contractual or legal consequences? | D9: 1 | E9: 1.5 | F9: 1 | G9: 1
A10: OR | B10: Operational resilience | C10: Could it disrupt critical services or create cascading failures? | D10: 1 | E10: 1.5 | F10: 1 | G10: 1
A11: DC | B11: Dependency / concentration | C11: Does it involve important third parties or single points of failure? | D11: 1 | E11: 1 | F11: 1 | G11: 1
A12: EV | B12: Evidence strength | C12: Is there organizational, technical, historical, sector or threat-intelligence evidence? | D12: 1 | E12: 1 | F12: 2 | G12: 1
A13: RV | B13: Risk velocity | C13: Could material consequences develop rapidly? | D13: 1 | E13: 1 | F13: 1 | G13: 1
A14: CU | B14: Control uncertainty | C14: Is it uncertain whether existing controls would prevent or contain it? | D14: 1 | E14: 1 | F14: 1 | G14: 1.5
A15: DU | B15: Decision usefulness | C15: Would analysing it potentially change a management decision? | D15: 1 | E15: 1 | F15: 1 | G15: 2

Sheet C_Screening
A1: Section C - Screening matrix (scores 1-5; blue = editable)
A2: Total and weighted scores are screening aids only. Escalation flags: S = Human safety; ES = Essential service interruption; CD = Catastrophic data loss; SY = Systemic organizational failure; PV = Severe privacy consequences; RG = Major regulatory breach; FN = Existential financial loss; PI = Compromise of highly privileged infrastructure; BK = Destruction of backup/recovery; PR = Simultaneous failure of primary and recovery; SC = Critical supply-chain concentration; MU = Spread across multiple units/clinics
A3: ID | B3: Scenario | C3: BC | D3: AC | E3: TR | F3: EX | G3: IM | H3: RL | I3: OR | J3: DC | K3: EV | L3: RV | M3: CU | N3: DU | O3: Total (/60) | P3: Weighted - Equal | Q3: Weighted - Impact-led | R3: Weighted - Evidence-led | S3: Weighted - Decision-led | T3: Rank (equal) | U3: Escalation flags | V3: # flags | W3: Evidence basis | X3: Selection confidence | Y3: Disposition | Z3: Family / target | AA3: Rationale for scores and disposition | AB3: Family key
A4: C01 | B4: Phishing-led compromise of clinic administrator credentials | C4: 5 | D4: 5 | E4: 5 | F4: 4 | G4: 4 | H4: 4 | I4: 3 | J4: 4 | K4: 5 | L4: 4 | M4: 4 | N4: 5 | O4: =SUM(C4:N4) -> 52 | P4: =C4*C_Weights!$D$4+D4*C_Weights!$D$5+E4*C_Weights!$D$6+F4*C_Weights!$D$7+G4*C_Weights!$D$8+H4*C_Weights!$D$9+I4*C_Weights!$D$10+J4*C_Weights!$D$11+K4*C_Weights!$D$12+L4*C_Weights!$D$13+M4*C_Weights!$D$14+N4*C_Weights!$D$15 -> 52 | Q4: =C4*C_Weights!$E$4+D4*C_Weights!$E$5+E4*C_Weights!$E$6+F4*C_Weights!$E$7+G4*C_Weights!$E$8+H4*C_Weights!$E$9+I4*C_Weights!$E$10+J4*C_Weights!$E$11+K4*C_Weights!$E$12+L4*C_Weights!$E$13+M4*C_Weights!$E$14+N4*C_Weights!$E$15 -> 64.5 | R4: =C4*C_Weights!$F$4+D4*C_Weights!$F$5+E4*C_Weights!$F$6+F4*C_Weights!$F$7+G4*C_Weights!$F$8+H4*C_Weights!$F$9+I4*C_Weights!$F$10+J4*C_Weights!$F$11+K4*C_Weights!$F$12+L4*C_Weights!$F$13+M4*C_Weights!$F$14+N4*C_Weights!$F$15 -> 61.5 | S4: =C4*C_Weights!$G$4+D4*C_Weights!$G$5+E4*C_Weights!$G$6+F4*C_Weights!$G$7+G4*C_Weights!$G$8+H4*C_Weights!$G$9+I4*C_Weights!$G$10+J4*C_Weights!$G$11+K4*C_Weights!$G$12+L4*C_Weights!$G$13+M4*C_Weights!$G$14+N4*C_Weights!$G$15 -> 59 | T4: =RANK(O4,$O$4:$O$48) -> 5 | U4: PV, PI, MU | V4: =IF(U4="-",0,LEN(U4)-LEN(SUBSTITUTE(U4,",",""))+1) -> 3 | W4: Verified org evidence (exercise) + sector | X4: High | Y4: Select | Z4: P01 | AA4: High: phishing targeting clinic/billing staff observed (E6) and push MFA approved from unusual geography; identity gates every crown jewel. Lower: direct operational impact limited unless escalated. | AB4: =IF(AND(LEFT(Z4,1)="P",LEN(Z4)=3),Z4,A4) -> P01
A5: C02 | B5: Ransomware encrypting EHR support systems, shared folders and scheduling | C5: 5 | D5: 5 | E5: 5 | F5: 4 | G5: 5 | H5: 5 | I5: 5 | J5: 4 | K5: 4 | L5: 5 | M5: 4 | N5: 5 | O5: =SUM(C5:N5) -> 56 | P5: =C5*C_Weights!$D$4+D5*C_Weights!$D$5+E5*C_Weights!$D$6+F5*C_Weights!$D$7+G5*C_Weights!$D$8+H5*C_Weights!$D$9+I5*C_Weights!$D$10+J5*C_Weights!$D$11+K5*C_Weights!$D$12+L5*C_Weights!$D$13+M5*C_Weights!$D$14+N5*C_Weights!$D$15 -> 56 | Q5: =C5*C_Weights!$E$4+D5*C_Weights!$E$5+E5*C_Weights!$E$6+F5*C_Weights!$E$7+G5*C_Weights!$E$8+H5*C_Weights!$E$9+I5*C_Weights!$E$10+J5*C_Weights!$E$11+K5*C_Weights!$E$12+L5*C_Weights!$E$13+M5*C_Weights!$E$14+N5*C_Weights!$E$15 -> 71 | R5: =C5*C_Weights!$F$4+D5*C_Weights!$F$5+E5*C_Weights!$F$6+F5*C_Weights!$F$7+G5*C_Weights!$F$8+H5*C_Weights!$F$9+I5*C_Weights!$F$10+J5*C_Weights!$F$11+K5*C_Weights!$F$12+L5*C_Weights!$F$13+M5*C_Weights!$F$14+N5*C_Weights!$F$15 -> 64.5 | S5: =C5*C_Weights!$G$4+D5*C_Weights!$G$5+E5*C_Weights!$G$6+F5*C_Weights!$G$7+G5*C_Weights!$G$8+H5*C_Weights!$G$9+I5*C_Weights!$G$10+J5*C_Weights!$G$11+K5*C_Weights!$G$12+L5*C_Weights!$G$13+M5*C_Weights!$G$14+N5*C_Weights!$G$15 -> 63 | T5: =RANK(O5,$O$4:$O$48) -> 1 | U5: S, ES, CD, SY, PV, RG, BK, MU | V5: =IF(U5="-",0,LEN(U5)-LEN(SUBSTITUTE(U5,",",""))+1) -> 8 | W5: Verified org evidence (exercise) + sector | X5: High | Y5: Select | Z5: P02 | AA5: High on all dimensions: network-wide clinical disruption, data theft, velocity of hours; full chain visible in exercise timeline (E6). Evidence 4: chain is simulated, not a confirmed incident. | AB5: =IF(AND(LEFT(Z5,1)="P",LEN(Z5)=3),Z5,A5) -> P02
A6: C03 | B6: Backup environment compromised before encryption, recovery fails | C6: 5 | D6: 5 | E6: 4 | F6: 4 | G6: 5 | H6: 3 | I6: 5 | J6: 5 | K6: 4 | L6: 4 | M6: 5 | N6: 5 | O6: =SUM(C6:N6) -> 54 | P6: =C6*C_Weights!$D$4+D6*C_Weights!$D$5+E6*C_Weights!$D$6+F6*C_Weights!$D$7+G6*C_Weights!$D$8+H6*C_Weights!$D$9+I6*C_Weights!$D$10+J6*C_Weights!$D$11+K6*C_Weights!$D$12+L6*C_Weights!$D$13+M6*C_Weights!$D$14+N6*C_Weights!$D$15 -> 54 | Q6: =C6*C_Weights!$E$4+D6*C_Weights!$E$5+E6*C_Weights!$E$6+F6*C_Weights!$E$7+G6*C_Weights!$E$8+H6*C_Weights!$E$9+I6*C_Weights!$E$10+J6*C_Weights!$E$11+K6*C_Weights!$E$12+L6*C_Weights!$E$13+M6*C_Weights!$E$14+N6*C_Weights!$E$15 -> 68 | R6: =C6*C_Weights!$F$4+D6*C_Weights!$F$5+E6*C_Weights!$F$6+F6*C_Weights!$F$7+G6*C_Weights!$F$8+H6*C_Weights!$F$9+I6*C_Weights!$F$10+J6*C_Weights!$F$11+K6*C_Weights!$F$12+L6*C_Weights!$F$13+M6*C_Weights!$F$14+N6*C_Weights!$F$15 -> 62 | S6: =C6*C_Weights!$G$4+D6*C_Weights!$G$5+E6*C_Weights!$G$6+F6*C_Weights!$G$7+G6*C_Weights!$G$8+H6*C_Weights!$G$9+I6*C_Weights!$G$10+J6*C_Weights!$G$11+K6*C_Weights!$G$12+L6*C_Weights!$G$13+M6*C_Weights!$G$14+N6*C_Weights!$G$15 -> 61.5 | T6: =RANK(O6,$O$4:$O$48) -> 2 | U6: CD, BK, PR | V6: =IF(U6="-",0,LEN(U6)-LEN(SUBSTITUTE(U6,",",""))+1) -> 3 | W6: Verified org evidence (exercise) | X6: Medium | Y6: Consolidate | Z6: P02 | AA6: Backup failures before encryption (E6) and no isolation evidence; defeats recovery of every service. Stage of C02 rather than independent exposure. | AB6: =IF(AND(LEFT(Z6,1)="P",LEN(Z6)=3),Z6,A6) -> P02
A7: C04 | B7: Cloud medical-image transfer storage exposed or accessed externally | C7: 4 | D7: 5 | E7: 4 | F7: 4 | G7: 4 | H7: 5 | I7: 2 | J7: 3 | K7: 4 | L7: 4 | M7: 4 | N7: 4 | O7: =SUM(C7:N7) -> 47 | P7: =C7*C_Weights!$D$4+D7*C_Weights!$D$5+E7*C_Weights!$D$6+F7*C_Weights!$D$7+G7*C_Weights!$D$8+H7*C_Weights!$D$9+I7*C_Weights!$D$10+J7*C_Weights!$D$11+K7*C_Weights!$D$12+L7*C_Weights!$D$13+M7*C_Weights!$D$14+N7*C_Weights!$D$15 -> 47 | Q7: =C7*C_Weights!$E$4+D7*C_Weights!$E$5+E7*C_Weights!$E$6+F7*C_Weights!$E$7+G7*C_Weights!$E$8+H7*C_Weights!$E$9+I7*C_Weights!$E$10+J7*C_Weights!$E$11+K7*C_Weights!$E$12+L7*C_Weights!$E$13+M7*C_Weights!$E$14+N7*C_Weights!$E$15 -> 58.5 | R7: =C7*C_Weights!$F$4+D7*C_Weights!$F$5+E7*C_Weights!$F$6+F7*C_Weights!$F$7+G7*C_Weights!$F$8+H7*C_Weights!$F$9+I7*C_Weights!$F$10+J7*C_Weights!$F$11+K7*C_Weights!$F$12+L7*C_Weights!$F$13+M7*C_Weights!$F$14+N7*C_Weights!$F$15 -> 55 | S7: =C7*C_Weights!$G$4+D7*C_Weights!$G$5+E7*C_Weights!$G$6+F7*C_Weights!$G$7+G7*C_Weights!$G$8+H7*C_Weights!$G$9+I7*C_Weights!$G$10+J7*C_Weights!$G$11+K7*C_Weights!$G$12+L7*C_Weights!$G$13+M7*C_Weights!$G$14+N7*C_Weights!$G$15 -> 53 | T7: =RANK(O7,$O$4:$O$48) -> 15 | U7: PV, RG | V7: =IF(U7="-",0,LEN(U7)-LEN(SUBSTITUTE(U7,",",""))+1) -> 2 | W7: Verified org evidence (exercise) | X7: Medium | Y7: Select | Z7: P07 | AA7: External download of medical_image_export.zip (E6); bulk PHI; high regulatory weight. Limited operational impact. | AB7: =IF(AND(LEFT(Z7,1)="P",LEN(Z7)=3),Z7,A7) -> P07
A8: C05 | B8: API key committed to a code repository enables data access | C8: 3 | D8: 4 | E8: 3 | F8: 3 | G8: 4 | H8: 4 | I8: 2 | J8: 2 | K8: 2 | L8: 4 | M8: 4 | N8: 3 | O8: =SUM(C8:N8) -> 38 | P8: =C8*C_Weights!$D$4+D8*C_Weights!$D$5+E8*C_Weights!$D$6+F8*C_Weights!$D$7+G8*C_Weights!$D$8+H8*C_Weights!$D$9+I8*C_Weights!$D$10+J8*C_Weights!$D$11+K8*C_Weights!$D$12+L8*C_Weights!$D$13+M8*C_Weights!$D$14+N8*C_Weights!$D$15 -> 38 | Q8: =C8*C_Weights!$E$4+D8*C_Weights!$E$5+E8*C_Weights!$E$6+F8*C_Weights!$E$7+G8*C_Weights!$E$8+H8*C_Weights!$E$9+I8*C_Weights!$E$10+J8*C_Weights!$E$11+K8*C_Weights!$E$12+L8*C_Weights!$E$13+M8*C_Weights!$E$14+N8*C_Weights!$E$15 -> 48 | R8: =C8*C_Weights!$F$4+D8*C_Weights!$F$5+E8*C_Weights!$F$6+F8*C_Weights!$F$7+G8*C_Weights!$F$8+H8*C_Weights!$F$9+I8*C_Weights!$F$10+J8*C_Weights!$F$11+K8*C_Weights!$F$12+L8*C_Weights!$F$13+M8*C_Weights!$F$14+N8*C_Weights!$F$15 -> 43 | S8: =C8*C_Weights!$G$4+D8*C_Weights!$G$5+E8*C_Weights!$G$6+F8*C_Weights!$G$7+G8*C_Weights!$G$8+H8*C_Weights!$G$9+I8*C_Weights!$G$10+J8*C_Weights!$G$11+K8*C_Weights!$G$12+L8*C_Weights!$G$13+M8*C_Weights!$G$14+N8*C_Weights!$G$15 -> 43 | T8: =RANK(O8,$O$4:$O$48) -> 27 | U8: PV | V8: =IF(U8="-",0,LEN(U8)-LEN(SUBSTITUTE(U8,",",""))+1) -> 1 | W8: Assumption + sector | X8: Low | Y8: Consolidate | Z8: P07 | AA8: Plausible where in-house development exists (E3) but repositories and secret practices unknown - evidence weak. | AB8: =IF(AND(LEFT(Z8,1)="P",LEN(Z8)=3),Z8,A8) -> P07
A9: C06 | B9: Clinic Wi-Fi compromise or rogue access point | C9: 3 | D9: 3 | E9: 3 | F9: 3 | G9: 3 | H9: 3 | I9: 3 | J9: 2 | K9: 2 | L9: 3 | M9: 4 | N9: 3 | O9: =SUM(C9:N9) -> 35 | P9: =C9*C_Weights!$D$4+D9*C_Weights!$D$5+E9*C_Weights!$D$6+F9*C_Weights!$D$7+G9*C_Weights!$D$8+H9*C_Weights!$D$9+I9*C_Weights!$D$10+J9*C_Weights!$D$11+K9*C_Weights!$D$12+L9*C_Weights!$D$13+M9*C_Weights!$D$14+N9*C_Weights!$D$15 -> 35 | Q9: =C9*C_Weights!$E$4+D9*C_Weights!$E$5+E9*C_Weights!$E$6+F9*C_Weights!$E$7+G9*C_Weights!$E$8+H9*C_Weights!$E$9+I9*C_Weights!$E$10+J9*C_Weights!$E$11+K9*C_Weights!$E$12+L9*C_Weights!$E$13+M9*C_Weights!$E$14+N9*C_Weights!$E$15 -> 44 | R9: =C9*C_Weights!$F$4+D9*C_Weights!$F$5+E9*C_Weights!$F$6+F9*C_Weights!$F$7+G9*C_Weights!$F$8+H9*C_Weights!$F$9+I9*C_Weights!$F$10+J9*C_Weights!$F$11+K9*C_Weights!$F$12+L9*C_Weights!$F$13+M9*C_Weights!$F$14+N9*C_Weights!$F$15 -> 40 | S9: =C9*C_Weights!$G$4+D9*C_Weights!$G$5+E9*C_Weights!$G$6+F9*C_Weights!$G$7+G9*C_Weights!$G$8+H9*C_Weights!$G$9+I9*C_Weights!$G$10+J9*C_Weights!$G$11+K9*C_Weights!$G$12+L9*C_Weights!$G$13+M9*C_Weights!$G$14+N9*C_Weights!$G$15 -> 40 | T9: =RANK(O9,$O$4:$O$48) -> 31 | U9: - | V9: =IF(U9="-",0,LEN(U9)-LEN(SUBSTITUTE(U9,",",""))+1) -> 0 | W9: Assumption + sector | X9: Low | Y9: Consolidate | Z9: P04 | AA9: Wireless controls listed for audit (E7) with no evidence either way; consequence arises mainly as an entry path to other scenarios. | AB9: =IF(AND(LEFT(Z9,1)="P",LEN(Z9)=3),Z9,A9) -> P04
A10: C07 | B10: Exploitation of unpatched internet-facing or end-of-life systems | C10: 5 | D10: 5 | E10: 5 | F10: 4 | G10: 5 | H10: 4 | I10: 4 | J10: 4 | K10: 3 | L10: 5 | M10: 4 | N10: 5 | O10: =SUM(C10:N10) -> 53 | P10: =C10*C_Weights!$D$4+D10*C_Weights!$D$5+E10*C_Weights!$D$6+F10*C_Weights!$D$7+G10*C_Weights!$D$8+H10*C_Weights!$D$9+I10*C_Weights!$D$10+J10*C_Weights!$D$11+K10*C_Weights!$D$12+L10*C_Weights!$D$13+M10*C_Weights!$D$14+N10*C_Weights!$D$15 -> 53 | Q10: =C10*C_Weights!$E$4+D10*C_Weights!$E$5+E10*C_Weights!$E$6+F10*C_Weights!$E$7+G10*C_Weights!$E$8+H10*C_Weights!$E$9+I10*C_Weights!$E$10+J10*C_Weights!$E$11+K10*C_Weights!$E$12+L10*C_Weights!$E$13+M10*C_Weights!$E$14+N10*C_Weights!$E$15 -> 67 | R10: =C10*C_Weights!$F$4+D10*C_Weights!$F$5+E10*C_Weights!$F$6+F10*C_Weights!$F$7+G10*C_Weights!$F$8+H10*C_Weights!$F$9+I10*C_Weights!$F$10+J10*C_Weights!$F$11+K10*C_Weights!$F$12+L10*C_Weights!$F$13+M10*C_Weights!$F$14+N10*C_Weights!$F$15 -> 60.5 | S10: =C10*C_Weights!$G$4+D10*C_Weights!$G$5+E10*C_Weights!$G$6+F10*C_Weights!$G$7+G10*C_Weights!$G$8+H10*C_Weights!$G$9+I10*C_Weights!$G$10+J10*C_Weights!$G$11+K10*C_Weights!$G$12+L10*C_Weights!$G$13+M10*C_Weights!$G$14+N10*C_Weights!$G$15 -> 60 | T10: =RANK(O10,$O$4:$O$48) -> 3 | U10: PI, MU | V10: =IF(U10="-",0,LEN(U10)-LEN(SUBSTITUTE(U10,",",""))+1) -> 2 | W10: External/sector + case | X10: Medium | Y10: Select | Z10: P03 | AA10: Edge-device exploitation is a leading sector vector; patching lag documented (E3, E7); high velocity. Exposure inventory unknown. | AB10: =IF(AND(LEFT(Z10,1)="P",LEN(Z10)=3),Z10,A10) -> P03
A11: C08 | B11: Intrusion goes undetected because monitoring and triage are insufficient | C11: 5 | D11: 5 | E11: 5 | F11: 4 | G11: 4 | H11: 4 | I11: 4 | J11: 3 | K11: 5 | L11: 3 | M11: 5 | N11: 5 | O11: =SUM(C11:N11) -> 52 | P11: =C11*C_Weights!$D$4+D11*C_Weights!$D$5+E11*C_Weights!$D$6+F11*C_Weights!$D$7+G11*C_Weights!$D$8+H11*C_Weights!$D$9+I11*C_Weights!$D$10+J11*C_Weights!$D$11+K11*C_Weights!$D$12+L11*C_Weights!$D$13+M11*C_Weights!$D$14+N11*C_Weights!$D$15 -> 52 | Q11: =C11*C_Weights!$E$4+D11*C_Weights!$E$5+E11*C_Weights!$E$6+F11*C_Weights!$E$7+G11*C_Weights!$E$8+H11*C_Weights!$E$9+I11*C_Weights!$E$10+J11*C_Weights!$E$11+K11*C_Weights!$E$12+L11*C_Weights!$E$13+M11*C_Weights!$E$14+N11*C_Weights!$E$15 -> 65 | R11: =C11*C_Weights!$F$4+D11*C_Weights!$F$5+E11*C_Weights!$F$6+F11*C_Weights!$F$7+G11*C_Weights!$F$8+H11*C_Weights!$F$9+I11*C_Weights!$F$10+J11*C_Weights!$F$11+K11*C_Weights!$F$12+L11*C_Weights!$F$13+M11*C_Weights!$F$14+N11*C_Weights!$F$15 -> 61.5 | S11: =C11*C_Weights!$G$4+D11*C_Weights!$G$5+E11*C_Weights!$G$6+F11*C_Weights!$G$7+G11*C_Weights!$G$8+H11*C_Weights!$G$9+I11*C_Weights!$G$10+J11*C_Weights!$G$11+K11*C_Weights!$G$12+L11*C_Weights!$G$13+M11*C_Weights!$G$14+N11*C_Weights!$G$15 -> 59.5 | T11: =RANK(O11,$O$4:$O$48) -> 5 | U11: SY, MU | V11: =IF(U11="-",0,LEN(U11)-LEN(SUBSTITUTE(U11,",",""))+1) -> 2 | W11: Verified org evidence (case + exercise) | X11: High | Y11: Consolidate | Z11: P02 | AA11: Strong evidence: 2-person team, PowerShell alert closed, uncorrelated signals (E3, E6). A control condition that amplifies other scenarios rather than a distinct threat chain. | AB11: =IF(AND(LEFT(Z11,1)="P",LEN(Z11)=3),Z11,A11) -> P02
A12: C09 | B12: Connected medical device used as network foothold | C12: 5 | D12: 5 | E12: 3 | F12: 4 | G12: 5 | H12: 4 | I12: 4 | J12: 4 | K12: 3 | L12: 4 | M12: 5 | N12: 5 | O12: =SUM(C12:N12) -> 51 | P12: =C12*C_Weights!$D$4+D12*C_Weights!$D$5+E12*C_Weights!$D$6+F12*C_Weights!$D$7+G12*C_Weights!$D$8+H12*C_Weights!$D$9+I12*C_Weights!$D$10+J12*C_Weights!$D$11+K12*C_Weights!$D$12+L12*C_Weights!$D$13+M12*C_Weights!$D$14+N12*C_Weights!$D$15 -> 51 | Q12: =C12*C_Weights!$E$4+D12*C_Weights!$E$5+E12*C_Weights!$E$6+F12*C_Weights!$E$7+G12*C_Weights!$E$8+H12*C_Weights!$E$9+I12*C_Weights!$E$10+J12*C_Weights!$E$11+K12*C_Weights!$E$12+L12*C_Weights!$E$13+M12*C_Weights!$E$14+N12*C_Weights!$E$15 -> 65 | R12: =C12*C_Weights!$F$4+D12*C_Weights!$F$5+E12*C_Weights!$F$6+F12*C_Weights!$F$7+G12*C_Weights!$F$8+H12*C_Weights!$F$9+I12*C_Weights!$F$10+J12*C_Weights!$F$11+K12*C_Weights!$F$12+L12*C_Weights!$F$13+M12*C_Weights!$F$14+N12*C_Weights!$F$15 -> 57.5 | S12: =C12*C_Weights!$G$4+D12*C_Weights!$G$5+E12*C_Weights!$G$6+F12*C_Weights!$G$7+G12*C_Weights!$G$8+H12*C_Weights!$G$9+I12*C_Weights!$G$10+J12*C_Weights!$G$11+K12*C_Weights!$G$12+L12*C_Weights!$G$13+M12*C_Weights!$G$14+N12*C_Weights!$G$15 -> 58.5 | T12: =RANK(O12,$O$4:$O$48) -> 9 | U12: S, ES | V12: =IF(U12="-",0,LEN(U12)-LEN(SUBSTITUTE(U12,",",""))+1) -> 2 | W12: Case + external/sector | X12: Medium | Y12: Select | Z12: P04 | AA12: Only direct patient-safety path via equipment; inventory and segmentation unknown (E4); certification constrains patching. Threat frequency lower than IT-focused attacks. | AB12: =IF(AND(LEFT(Z12,1)="P",LEN(Z12)=3),Z12,A12) -> P04
A13: C10 | B13: DDoS against patient-facing online services | C13: 2 | D13: 3 | E13: 3 | F13: 4 | G13: 2 | H13: 1 | I13: 3 | J13: 3 | K13: 2 | L13: 5 | M13: 3 | N13: 2 | O13: =SUM(C13:N13) -> 33 | P13: =C13*C_Weights!$D$4+D13*C_Weights!$D$5+E13*C_Weights!$D$6+F13*C_Weights!$D$7+G13*C_Weights!$D$8+H13*C_Weights!$D$9+I13*C_Weights!$D$10+J13*C_Weights!$D$11+K13*C_Weights!$D$12+L13*C_Weights!$D$13+M13*C_Weights!$D$14+N13*C_Weights!$D$15 -> 33 | Q13: =C13*C_Weights!$E$4+D13*C_Weights!$E$5+E13*C_Weights!$E$6+F13*C_Weights!$E$7+G13*C_Weights!$E$8+H13*C_Weights!$E$9+I13*C_Weights!$E$10+J13*C_Weights!$E$11+K13*C_Weights!$E$12+L13*C_Weights!$E$13+M13*C_Weights!$E$14+N13*C_Weights!$E$15 -> 39 | R13: =C13*C_Weights!$F$4+D13*C_Weights!$F$5+E13*C_Weights!$F$6+F13*C_Weights!$F$7+G13*C_Weights!$F$8+H13*C_Weights!$F$9+I13*C_Weights!$F$10+J13*C_Weights!$F$11+K13*C_Weights!$F$12+L13*C_Weights!$F$13+M13*C_Weights!$F$14+N13*C_Weights!$F$15 -> 38.5 | S13: =C13*C_Weights!$G$4+D13*C_Weights!$G$5+E13*C_Weights!$G$6+F13*C_Weights!$G$7+G13*C_Weights!$G$8+H13*C_Weights!$G$9+I13*C_Weights!$G$10+J13*C_Weights!$G$11+K13*C_Weights!$G$12+L13*C_Weights!$G$13+M13*C_Weights!$G$14+N13*C_Weights!$G$15 -> 36.5 | T13: =RANK(O13,$O$4:$O$48) -> 35 | U13: - | V13: =IF(U13="-",0,LEN(U13)-LEN(SUBSTITUTE(U13,",",""))+1) -> 0 | W13: Assumption + sector | X13: Low | Y13: Defer | Z13: Watch list | AA13: Fast-moving but clinics continue in person; low regulatory weight; online-service criticality not documented. | AB13: =IF(AND(LEFT(Z13,1)="P",LEN(Z13)=3),Z13,A13) -> C10
A14: C11 | B14: Staff member exports health or billing records for unauthorized purposes | C14: 4 | D14: 5 | E14: 5 | F14: 4 | G14: 4 | H14: 5 | I14: 1 | J14: 2 | K14: 4 | L14: 2 | M14: 4 | N14: 4 | O14: =SUM(C14:N14) -> 44 | P14: =C14*C_Weights!$D$4+D14*C_Weights!$D$5+E14*C_Weights!$D$6+F14*C_Weights!$D$7+G14*C_Weights!$D$8+H14*C_Weights!$D$9+I14*C_Weights!$D$10+J14*C_Weights!$D$11+K14*C_Weights!$D$12+L14*C_Weights!$D$13+M14*C_Weights!$D$14+N14*C_Weights!$D$15 -> 44 | Q14: =C14*C_Weights!$E$4+D14*C_Weights!$E$5+E14*C_Weights!$E$6+F14*C_Weights!$E$7+G14*C_Weights!$E$8+H14*C_Weights!$E$9+I14*C_Weights!$E$10+J14*C_Weights!$E$11+K14*C_Weights!$E$12+L14*C_Weights!$E$13+M14*C_Weights!$E$14+N14*C_Weights!$E$15 -> 55 | R14: =C14*C_Weights!$F$4+D14*C_Weights!$F$5+E14*C_Weights!$F$6+F14*C_Weights!$F$7+G14*C_Weights!$F$8+H14*C_Weights!$F$9+I14*C_Weights!$F$10+J14*C_Weights!$F$11+K14*C_Weights!$F$12+L14*C_Weights!$F$13+M14*C_Weights!$F$14+N14*C_Weights!$F$15 -> 52.5 | S14: =C14*C_Weights!$G$4+D14*C_Weights!$G$5+E14*C_Weights!$G$6+F14*C_Weights!$G$7+G14*C_Weights!$G$8+H14*C_Weights!$G$9+I14*C_Weights!$G$10+J14*C_Weights!$G$11+K14*C_Weights!$G$12+L14*C_Weights!$G$13+M14*C_Weights!$G$14+N14*C_Weights!$G$15 -> 50 | T14: =RANK(O14,$O$4:$O$48) -> 21 | U14: PV, RG | V14: =IF(U14="-",0,LEN(U14)-LEN(SUBSTITUTE(U14,",",""))+1) -> 2 | W14: External/sector + case | X14: Medium | Y14: Select | Z14: P06 | AA14: Insider snooping is recurrent in healthcare; EHR access central (E7); high privacy weight. Little operational impact. | AB14: =IF(AND(LEFT(Z14,1)="P",LEN(Z14)=3),Z14,A14) -> P06
A15: C12 | B15: Alteration of patient, medication or billing records | C15: 5 | D15: 5 | E15: 2 | F15: 3 | G15: 5 | H15: 5 | I15: 3 | J15: 3 | K15: 2 | L15: 3 | M15: 5 | N15: 4 | O15: =SUM(C15:N15) -> 45 | P15: =C15*C_Weights!$D$4+D15*C_Weights!$D$5+E15*C_Weights!$D$6+F15*C_Weights!$D$7+G15*C_Weights!$D$8+H15*C_Weights!$D$9+I15*C_Weights!$D$10+J15*C_Weights!$D$11+K15*C_Weights!$D$12+L15*C_Weights!$D$13+M15*C_Weights!$D$14+N15*C_Weights!$D$15 -> 45 | Q15: =C15*C_Weights!$E$4+D15*C_Weights!$E$5+E15*C_Weights!$E$6+F15*C_Weights!$E$7+G15*C_Weights!$E$8+H15*C_Weights!$E$9+I15*C_Weights!$E$10+J15*C_Weights!$E$11+K15*C_Weights!$E$12+L15*C_Weights!$E$13+M15*C_Weights!$E$14+N15*C_Weights!$E$15 -> 59 | R15: =C15*C_Weights!$F$4+D15*C_Weights!$F$5+E15*C_Weights!$F$6+F15*C_Weights!$F$7+G15*C_Weights!$F$8+H15*C_Weights!$F$9+I15*C_Weights!$F$10+J15*C_Weights!$F$11+K15*C_Weights!$F$12+L15*C_Weights!$F$13+M15*C_Weights!$F$14+N15*C_Weights!$F$15 -> 49.5 | S15: =C15*C_Weights!$G$4+D15*C_Weights!$G$5+E15*C_Weights!$G$6+F15*C_Weights!$G$7+G15*C_Weights!$G$8+H15*C_Weights!$G$9+I15*C_Weights!$G$10+J15*C_Weights!$G$11+K15*C_Weights!$G$12+L15*C_Weights!$G$13+M15*C_Weights!$G$14+N15*C_Weights!$G$15 -> 51.5 | T15: =RANK(O15,$O$4:$O$48) -> 18 | U15: S | V15: =IF(U15="-",0,LEN(U15)-LEN(SUBSTITUTE(U15,",",""))+1) -> 1 | W15: Assumption + sector | X15: Low | Y15: Select | Z15: P05 | AA15: Severe patient-safety and regulatory consequence; integrity controls absent (E8). Threat relevance and evidence low - classic low-frequency/high-consequence. | AB15: =IF(AND(LEFT(Z15,1)="P",LEN(Z15)=3),Z15,A15) -> P05
... A48: C45 | B48: Firewall single point of failure | C48: 4 | D48: 4 | E48: 3 | F48: 3 | G48: 4 | H48: 2 | I48: 5 | J48: 5 | K48: 2 | L48: 5 | M48: 3 | N48: 4 | O48: =SUM(C48:N48) -> 44 | P48: =C48*C_Weights!$D$4+D48*C_Weights!$D$5+E48*C_Weights!$D$6+F48*C_Weights!$D$7+G48*C_Weights!$D$8+H48*C_Weights!$D$9+I48*C_Weights!$D$10+J48*C_Weights!$D$11+K48*C_Weights!$D$12+L48*C_Weights!$D$13+M48*C_Weights!$D$14+N48*C_Weights!$D$15 -> 44 | Q48: =C48*C_Weights!$E$4+D48*C_Weights!$E$5+E48*C_Weights!$E$6+F48*C_Weights!$E$7+G48*C_Weights!$E$8+H48*C_Weights!$E$9+I48*C_Weights!$E$10+J48*C_Weights!$E$11+K48*C_Weights!$E$12+L48*C_Weights!$E$13+M48*C_Weights!$E$14+N48*C_Weights!$E$15 -> 55.5 | R48: =C48*C_Weights!$F$4+D48*C_Weights!$F$5+E48*C_Weights!$F$6+F48*C_Weights!$F$7+G48*C_Weights!$F$8+H48*C_Weights!$F$9+I48*C_Weights!$F$10+J48*C_Weights!$F$11+K48*C_Weights!$F$12+L48*C_Weights!$F$13+M48*C_Weights!$F$14+N48*C_Weights!$F$15 -> 49 | S48: =C48*C_Weights!$G$4+D48*C_Weights!$G$5+E48*C_Weights!$G$6+F48*C_Weights!$G$7+G48*C_Weights!$G$8+H48*C_Weights!$G$9+I48*C_Weights!$G$10+J48*C_Weights!$G$11+K48*C_Weights!$G$12+L48*C_Weights!$G$13+M48*C_Weights!$G$14+N48*C_Weights!$G$15 -> 49.5 | T48: =RANK(O48,$O$4:$O$48) -> 21 | U48: ES, SY | V48: =IF(U48="-",0,LEN(U48)-LEN(SUBSTITUTE(U48,",",""))+1) -> 2 | W48: Assumption + sector | X48: Low | Y48: Consolidate | Z48: P09 | AA48: Component of hub single point of failure (C16). | AB48: =IF(AND(LEFT(Z48,1)="P",LEN(Z48)=3),Z48,A48) -> P09
B50: Disposition counts
B51: Select | C51: =COUNTIF($Y$4:$Y$48,"Select") -> 10
B52: Consolidate | C52: =COUNTIF($Y$4:$Y$48,"Consolidate") -> 24
B53: Consider | C53: =COUNTIF($Y$4:$Y$48,"Consider") -> 2
B54: Defer | C54: =COUNTIF($Y$4:$Y$48,"Defer") -> 9
B55: Escalation-flagged candidates not selected or consolidated (explicit review required) | C55: =COUNTIFS($V$4:$V$48,">0",$Y$4:$Y$48,"Consider")+COUNTIFS($V$4:$V$48,">0",$Y$4:$Y$48,"Defer") -> 2

Sheet C_Sensitivity
A1: Section C / Instruction s.20 - Does the selection hold under different weighting schemes?
A2: Family score = highest weighted score of any candidate consolidated into that family (so variants do not add up). Ranks recalculate from C_Weights.
A4: Family | B4: Name / candidate | C4: Status | D4: Score - Equal | E4: Score - Impact-led | F4: Score - Evidence-led | G4: Score - Decision-led | H4: Rank - Equal | I4: Rank - Impact-led | J4: Rank - Evidence-led | K4: Rank - Decision-led | L4: In top 10 under all schemes? | M4: Selected? | N4: Consistency
A5: P01 | B5: Identity takeover of clinical, privileged or cloud-administrator accounts | C5: Selected | D5: =_xlfn.MAXIFS(C_Screening!$P$4:$P$48,C_Screening!$AB$4:$AB$48,A5) -> 52 | E5: =_xlfn.MAXIFS(C_Screening!$Q$4:$Q$48,C_Screening!$AB$4:$AB$48,A5) -> 64.5 | F5: =_xlfn.MAXIFS(C_Screening!$R$4:$R$48,C_Screening!$AB$4:$AB$48,A5) -> 61.5 | G5: =_xlfn.MAXIFS(C_Screening!$S$4:$S$48,C_Screening!$AB$4:$AB$48,A5) -> 59 | H5: =RANK(D5,D$5:D$25) -> 4 | I5: =RANK(E5,E$5:E$25) -> 6 | J5: =RANK(F5,F$5:F$25) -> 2 | K5: =RANK(G5,G$5:G$25) -> 4 | L5: =IF(MAX(H5:K5)<=10,"Yes",IF(MIN(H5:K5)<=10,"Sometimes","No")) -> Yes | M5: Yes | N5: =IF(AND(M5="Yes",L5<>"Yes"),"Selected by judgement - see rationale",IF(AND(M5="No",L5<>"No"),"Scores support selection - explicit review",""))
A6: P02 | B6: Ransomware with data theft and backup destruction halting multi-clinic operations | C6: Selected | D6: =_xlfn.MAXIFS(C_Screening!$P$4:$P$48,C_Screening!$AB$4:$AB$48,A6) -> 56 | E6: =_xlfn.MAXIFS(C_Screening!$Q$4:$Q$48,C_Screening!$AB$4:$AB$48,A6) -> 71 | F6: =_xlfn.MAXIFS(C_Screening!$R$4:$R$48,C_Screening!$AB$4:$AB$48,A6) -> 64.5 | G6: =_xlfn.MAXIFS(C_Screening!$S$4:$S$48,C_Screening!$AB$4:$AB$48,A6) -> 63 | H6: =RANK(D6,D$5:D$25) -> 1 | I6: =RANK(E6,E$5:E$25) -> 1 | J6: =RANK(F6,F$5:F$25) -> 1 | K6: =RANK(G6,G$5:G$25) -> 1 | L6: =IF(MAX(H6:K6)<=10,"Yes",IF(MIN(H6:K6)<=10,"Sometimes","No")) -> Yes | M6: Yes | N6: =IF(AND(M6="Yes",L6<>"Yes"),"Selected by judgement - see rationale",IF(AND(M6="No",L6<>"No"),"Scores support selection - explicit review",""))
A7: P03 | B7: Exploitation of exposed internet-facing systems (unpatched edge devices, admin interfaces, end-of-life systems) | C7: Selected | D7: =_xlfn.MAXIFS(C_Screening!$P$4:$P$48,C_Screening!$AB$4:$AB$48,A7) -> 53 | E7: =_xlfn.MAXIFS(C_Screening!$Q$4:$Q$48,C_Screening!$AB$4:$AB$48,A7) -> 67 | F7: =_xlfn.MAXIFS(C_Screening!$R$4:$R$48,C_Screening!$AB$4:$AB$48,A7) -> 60.5 | G7: =_xlfn.MAXIFS(C_Screening!$S$4:$S$48,C_Screening!$AB$4:$AB$48,A7) -> 60 | H7: =RANK(D7,D$5:D$25) -> 2 | I7: =RANK(E7,E$5:E$25) -> 2 | J7: =RANK(F7,F$5:F$25) -> 3 | K7: =RANK(G7,G$5:G$25) -> 3 | L7: =IF(MAX(H7:K7)<=10,"Yes",IF(MIN(H7:K7)<=10,"Sometimes","No")) -> Yes | M7: Yes | N7: =IF(AND(M7="Yes",L7<>"Yes"),"Selected by judgement - see rationale",IF(AND(M7="No",L7<>"No"),"Scores support selection - explicit review",""))
A8: P04 | B8: Compromise of connected medical devices disrupting diagnostics and threatening patient safety | C8: Selected | D8: =_xlfn.MAXIFS(C_Screening!$P$4:$P$48,C_Screening!$AB$4:$AB$48,A8) -> 51 | E8: =_xlfn.MAXIFS(C_Screening!$Q$4:$Q$48,C_Screening!$AB$4:$AB$48,A8) -> 65 | F8: =_xlfn.MAXIFS(C_Screening!$R$4:$R$48,C_Screening!$AB$4:$AB$48,A8) -> 57.5 | G8: =_xlfn.MAXIFS(C_Screening!$S$4:$S$48,C_Screening!$AB$4:$AB$48,A8) -> 58.5 | H8: =RANK(D8,D$5:D$25) -> 6 | I8: =RANK(E8,E$5:E$25) -> 5 | J8: =RANK(F8,F$5:F$25) -> 6 | K8: =RANK(G8,G$5:G$25) -> 6 | L8: =IF(MAX(H8:K8)<=10,"Yes",IF(MIN(H8:K8)<=10,"Sometimes","No")) -> Yes | M8: Yes | N8: =IF(AND(M8="Yes",L8<>"Yes"),"Selected by judgement - see rationale",IF(AND(M8="No",L8<>"No"),"Scores support selection - explicit review",""))
A9: P05 | B9: Manipulation of clinical data (records or interface messages) leading to unsafe care | C9: Selected | D9: =_xlfn.MAXIFS(C_Screening!$P$4:$P$48,C_Screening!$AB$4:$AB$48,A9) -> 45 | E9: =_xlfn.MAXIFS(C_Screening!$Q$4:$Q$48,C_Screening!$AB$4:$AB$48,A9) -> 59 | F9: =_xlfn.MAXIFS(C_Screening!$R$4:$R$48,C_Screening!$AB$4:$AB$48,A9) -> 49.5 | G9: =_xlfn.MAXIFS(C_Screening!$S$4:$S$48,C_Screening!$AB$4:$AB$48,A9) -> 51.5 | H9: =RANK(D9,D$5:D$25) -> 10 | I9: =RANK(E9,E$5:E$25) -> 8 | J9: =RANK(F9,F$5:F$25) -> 11 | K9: =RANK(G9,G$5:G$25) -> 10 | L9: =IF(MAX(H9:K9)<=10,"Yes",IF(MIN(H9:K9)<=10,"Sometimes","No")) -> Sometimes | M9: Yes | N9: =IF(AND(M9="Yes",L9<>"Yes"),"Selected by judgement - see rationale",IF(AND(M9="No",L9<>"No"),"Scores support selection - explicit review","")) -> Selected by judgement - see rationale
A10: P06 | B10: Misuse of legitimate EHR or service-account access to extract patient records | C10: Selected | D10: =_xlfn.MAXIFS(C_Screening!$P$4:$P$48,C_Screening!$AB$4:$AB$48,A10) -> 46 | E10: =_xlfn.MAXIFS(C_Screening!$Q$4:$Q$48,C_Screening!$AB$4:$AB$48,A10) -> 57 | F10: =_xlfn.MAXIFS(C_Screening!$R$4:$R$48,C_Screening!$AB$4:$AB$48,A10) -> 55 | G10: =_xlfn.MAXIFS(C_Screening!$S$4:$S$48,C_Screening!$AB$4:$AB$48,A10) -> 52 | H10: =RANK(D10,D$5:D$25) -> 9 | I10: =RANK(E10,E$5:E$25) -> 10 | J10: =RANK(F10,F$5:F$25) -> 7 | K10: =RANK(G10,G$5:G$25) -> 9 | L10: =IF(MAX(H10:K10)<=10,"Yes",IF(MIN(H10:K10)<=10,"Sometimes","No")) -> Yes | M10: Yes | N10: =IF(AND(M10="Yes",L10<>"Yes"),"Selected by judgement - see rationale",IF(AND(M10="No",L10<>"No"),"Scores support selection - explicit review",""))
A11: P07 | B11: Bulk exposure of health data held outside core systems (cloud exports, APIs, clinic storage) | C11: Selected | D11: =_xlfn.MAXIFS(C_Screening!$P$4:$P$48,C_Screening!$AB$4:$AB$48,A11) -> 47 | E11: =_xlfn.MAXIFS(C_Screening!$Q$4:$Q$48,C_Screening!$AB$4:$AB$48,A11) -> 58.5 | F11: =_xlfn.MAXIFS(C_Screening!$R$4:$R$48,C_Screening!$AB$4:$AB$48,A11) -> 55 | G11: =_xlfn.MAXIFS(C_Screening!$S$4:$S$48,C_Screening!$AB$4:$AB$48,A11) -> 53 | H11: =RANK(D11,D$5:D$25) -> 8 | I11: =RANK(E11,E$5:E$25) -> 9 | J11: =RANK(F11,F$5:F$25) -> 7 | K11: =RANK(G11,G$5:G$25) -> 8 | L11: =IF(MAX(H11:K11)<=10,"Yes",IF(MIN(H11:K11)<=10,"Sometimes","No")) -> Yes | M11: Yes | N11: =IF(AND(M11="Yes",L11<>"Yes"),"Selected by judgement - see rationale",IF(AND(M11="No",L11<>"No"),"Scores support selection - explicit review",""))
A12: P08 | B12: Compromise through a critical supplier (vendor remote access or trojanized software update) | C12: Selected | D12: =_xlfn.MAXIFS(C_Screening!$P$4:$P$48,C_Screening!$AB$4:$AB$48,A12) -> 53 | E12: =_xlfn.MAXIFS(C_Screening!$Q$4:$Q$48,C_Screening!$AB$4:$AB$48,A12) -> 67 | F12: =_xlfn.MAXIFS(C_Screening!$R$4:$R$48,C_Screening!$AB$4:$AB$48,A12) -> 60 | G12: =_xlfn.MAXIFS(C_Screening!$S$4:$S$48,C_Screening!$AB$4:$AB$48,A12) -> 60.5 | H12: =RANK(D12,D$5:D$25) -> 2 | I12: =RANK(E12,E$5:E$25) -> 2 | J12: =RANK(F12,F$5:F$25) -> 4 | K12: =RANK(G12,G$5:G$25) -> 2 | L12: =IF(MAX(H12:K12)<=10,"Yes",IF(MIN(H12:K12)<=10,"Sometimes","No")) -> Yes | M12: Yes | N12: =IF(AND(M12="Yes",L12<>"Yes"),"Selected by judgement - see rationale",IF(AND(M12="No",L12<>"No"),"Scores support selection - explicit review",""))
A13: P09 | B13: Loss of the Montreal hub or WAN isolating all clinics from clinical systems | C13: Selected | D13: =_xlfn.MAXIFS(C_Screening!$P$4:$P$48,C_Screening!$AB$4:$AB$48,A13) -> 52 | E13: =_xlfn.MAXIFS(C_Screening!$Q$4:$Q$48,C_Screening!$AB$4:$AB$48,A13) -> 66 | F13: =_xlfn.MAXIFS(C_Screening!$R$4:$R$48,C_Screening!$AB$4:$AB$48,A13) -> 58.5 | G13: =_xlfn.MAXIFS(C_Screening!$S$4:$S$48,C_Screening!$AB$4:$AB$48,A13) -> 59 | H13: =RANK(D13,D$5:D$25) -> 4 | I13: =RANK(E13,E$5:E$25) -> 4 | J13: =RANK(F13,F$5:F$25) -> 5 | K13: =RANK(G13,G$5:G$25) -> 4 | L13: =IF(MAX(H13:K13)<=10,"Yes",IF(MIN(H13:K13)<=10,"Sometimes","No")) -> Yes | M13: Yes | N13: =IF(AND(M13="Yes",L13<>"Yes"),"Selected by judgement - see rationale",IF(AND(M13="No",L13<>"No"),"Scores support selection - explicit review",""))
A14: P10 | B14: Uncontrolled disclosure of patient information by staff through unapproved AI tools and communications | C14: Selected | D14: =_xlfn.MAXIFS(C_Screening!$P$4:$P$48,C_Screening!$AB$4:$AB$48,A14) -> 44 | E14: =_xlfn.MAXIFS(C_Screening!$Q$4:$Q$48,C_Screening!$AB$4:$AB$48,A14) -> 53 | F14: =_xlfn.MAXIFS(C_Screening!$R$4:$R$48,C_Screening!$AB$4:$AB$48,A14) -> 51.5 | G14: =_xlfn.MAXIFS(C_Screening!$S$4:$S$48,C_Screening!$AB$4:$AB$48,A14) -> 51.5 | H14: =RANK(D14,D$5:D$25) -> 11 | I14: =RANK(E14,E$5:E$25) -> 11 | J14: =RANK(F14,F$5:F$25) -> 10 | K14: =RANK(G14,G$5:G$25) -> 10 | L14: =IF(MAX(H14:K14)<=10,"Yes",IF(MIN(H14:K14)<=10,"Sometimes","No")) -> Sometimes | M14: Yes | N14: =IF(AND(M14="Yes",L14<>"Yes"),"Selected by judgement - see rationale",IF(AND(M14="No",L14<>"No"),"Scores support selection - explicit review","")) -> Selected by judgement - see rationale
A15: C10 | B15: DDoS against patient-facing online services | C15: Defer | D15: =_xlfn.MAXIFS(C_Screening!$P$4:$P$48,C_Screening!$AB$4:$AB$48,A15) -> 33 | E15: =_xlfn.MAXIFS(C_Screening!$Q$4:$Q$48,C_Screening!$AB$4:$AB$48,A15) -> 39 | F15: =_xlfn.MAXIFS(C_Screening!$R$4:$R$48,C_Screening!$AB$4:$AB$48,A15) -> 38.5 | G15: =_xlfn.MAXIFS(C_Screening!$S$4:$S$48,C_Screening!$AB$4:$AB$48,A15) -> 36.5 | H15: =RANK(D15,D$5:D$25) -> 13 | I15: =RANK(E15,E$5:E$25) -> 13 | J15: =RANK(F15,F$5:F$25) -> 15 | K15: =RANK(G15,G$5:G$25) -> 14 | L15: =IF(MAX(H15:K15)<=10,"Yes",IF(MIN(H15:K15)<=10,"Sometimes","No")) -> No | M15: No | N15: =IF(AND(M15="Yes",L15<>"Yes"),"Selected by judgement - see rationale",IF(AND(M15="No",L15<>"No"),"Scores support selection - explicit review",""))
A16: C18 | B16: Business e-mail compromise diverts billing payments | C16: Defer | D16: =_xlfn.MAXIFS(C_Screening!$P$4:$P$48,C_Screening!$AB$4:$AB$48,A16) -> 33 | E16: =_xlfn.MAXIFS(C_Screening!$Q$4:$Q$48,C_Screening!$AB$4:$AB$48,A16) -> 39 | F16: =_xlfn.MAXIFS(C_Screening!$R$4:$R$48,C_Screening!$AB$4:$AB$48,A16) -> 40 | G16: =_xlfn.MAXIFS(C_Screening!$S$4:$S$48,C_Screening!$AB$4:$AB$48,A16) -> 37.5 | H16: =RANK(D16,D$5:D$25) -> 13 | I16: =RANK(E16,E$5:E$25) -> 13 | J16: =RANK(F16,F$5:F$25) -> 13 | K16: =RANK(G16,G$5:G$25) -> 13 | L16: =IF(MAX(H16:K16)<=10,"Yes",IF(MIN(H16:K16)<=10,"Sometimes","No")) -> No | M16: No | N16: =IF(AND(M16="Yes",L16<>"Yes"),"Selected by judgement - see rationale",IF(AND(M16="No",L16<>"No"),"Scores support selection - explicit review",""))
... A25: C39 | B25: Physical intrusion into clinic server closet | C25: Defer | D25: =_xlfn.MAXIFS(C_Screening!$P$4:$P$48,C_Screening!$AB$4:$AB$48,A25) -> 27 | E25: =_xlfn.MAXIFS(C_Screening!$Q$4:$Q$48,C_Screening!$AB$4:$AB$48,A25) -> 34 | F25: =_xlfn.MAXIFS(C_Screening!$R$4:$R$48,C_Screening!$AB$4:$AB$48,A25) -> 30.5 | G25: =_xlfn.MAXIFS(C_Screening!$S$4:$S$48,C_Screening!$AB$4:$AB$48,A25) -> 30.5 | H25: =RANK(D25,D$5:D$25) -> 18 | I25: =RANK(E25,E$5:E$25) -> 17 | J25: =RANK(F25,F$5:F$25) -> 18 | K25: =RANK(G25,G$5:G$25) -> 18 | L25: =IF(MAX(H25:K25)<=10,"Yes",IF(MIN(H25:K25)<=10,"Sometimes","No")) -> No | M25: No | N25: =IF(AND(M25="Yes",L25<>"Yes"),"Selected by judgement - see rationale",IF(AND(M25="No",L25<>"No"),"Scores support selection - explicit review",""))
A27: Reading: P01-P04, P06-P09 rank in the top 10 families under every scheme. P05 (integrity) and P10 (AI disclosure) are selected by judgement; C31 (admin sabotage) outranks P10 under all schemes.
A28: P05 is kept as a low-frequency/high-consequence patient-safety scenario (Instruction s.4, s.10). P10 is kept for portfolio coverage and decision usefulness (s.12-13): no other scenario covers negligent insiders or AI, and it drives unique decisions.
A29: C31 is not selected because its treatments (PAM, immutable backup, offboarding) are delivered through P01/P02; management should confirm this reliance (E_Quality, blind spots).
A30: Candidate-level note: a raw top-10 by total score would contain four ransomware-chain variants (C02, C03, C08, C34) and three identity variants (C01, C20, C23) - the variant domination Instruction s.11 and Critical rule 10 warn against.

Sheet D_Portfolio
A1: Section D - Final selected portfolio (10 scenarios)
A3: ID | B3: Scenario name | C3: Scenario statement | D3: Business objective / process | E3: Critical assets | F3: Threat source / event | G3: Vulnerabilities / predisposing conditions | H3: Principal consequences | I3: Key dependencies | J3: Existing controls known | K3: Risk-appetite / tolerance relevance | L3: Selection rationale | M3: Evidence basis | N3: Confidence | O3: Information requiring validation | P3: Candidates consolidated | Q3: Prior IDs (30-scenario)
A4: P01 | B4: Identity takeover of clinical, privileged or cloud-administrator accounts | C4: A cybercriminal obtains valid credentials or session tokens for clinic administrators, clinicians or cloud administrators - through EHR-themed phishing, MFA push fatigue, help-desk reset fraud or token theft - and exploits push-only MFA, absent conditional access and weak reset verification to access the EHR, mail and the cloud tenant, leading to health-data exposure and a foothold for destructive attacks. | D4: O2 health information; O1 clinical continuity (as precursor) | E4: Identity/MFA, cloud tenant, EHR, mail | F4: Cybercriminal / initial-access broker | G4: Push MFA without number matching or phishing resistance; no conditional access or token binding; help-desk reset verification unknown; users can consent to apps | H4: Unauthorized access to patient records and mail; reportable confidentiality incident; persistence for ransomware (P02) | I4: Directory and cloud IdP (concentration) | J4: Push MFA on remote access (E6); e-mail filtering (E2) | K4: Health-data exposure of many patients exceeds low appetite; precursor to safety-relevant outages | L4: Most evidenced and most frequent entry path; one identity plane gates every crown jewel. Four variants (phishing, MFA fatigue, help-desk reset, token theft) consolidated so the portfolio is not dominated by identity attacks; they share owner (CIO) and treatment family (phishing-resistant MFA, conditional access, reset verification). | M4: Verified org evidence (exercise injects E6: phishing, MFA approval); external/sector; assumption (reset procedure, tenant settings) | N4: High | O4: MFA method and coverage; conditional-access policies; help-desk reset procedure; cloud app-consent setting; sign-in logs for E6 indicators | P4: C01, C20, C23, C30, C41 | Q4: S1, S20, S27
A5: P02 | B5: Ransomware with data theft and backup destruction halting multi-clinic operations | C5: A ransomware affiliate enters through P01 or P03, is not detected because alerts are mis-triaged and logs are incomplete, escalates to domain administrator through Active Directory weaknesses, deletes backups reachable from the production domain, exfiltrates health data and encrypts servers, hypervisors and clinic storage, halting EHR, scheduling and diagnostics across clinics while recovery fails. | D5: O1 clinical continuity; O2; O3; O4 | E5: EHR, hypervisors, file shares, scheduling, backup servers, clinic storage | F5: Ransomware-as-a-service affiliate (double extortion) | G5: Weak alert triage and no 24x7 monitoring; flat network; backups in production admin domain; untested restore and IR | H5: Multi-day multi-clinic outage; delayed care; data theft and notification; possible permanent loss if recovery fails; media attention | I5: Montreal DC, backup infrastructure, AD, EDR/MDR | J5: Firewalls, IDS/IPS, antimalware, EDR (E2, E6); on/off-site backups (E2 - isolation unknown); defined incident roles (E6 - untested) | K5: Credible immediate threat to patient care - no residual acceptable without Board decision | L5: Highest combined consequence; full chain visible in exercise; hits several escalation criteria (safety, essential service, backup destruction, primary+recovery failure). Detection gaps, untested IR and backup compromise are stages of this chain, so they are analysed inside it rather than as separate scenarios. | M5: Verified org evidence (exercise timeline E6); case (E2, E7); external/sector | N5: High | O5: EDR coverage and triage records; log sources and retention; AD security assessment; backup isolation and last restore test; IR plan test history | P5: C02, C03, C08, C14, C34, C35, C40 | Q5: S2, S3, S8
A6: P03 | B6: Exploitation of exposed internet-facing systems (unpatched edge devices, admin interfaces, end-of-life systems) | C6: A cybercriminal or state-linked actor exploits a known vulnerability in an unpatched VPN or firewall appliance, or default/stuffed credentials on an internet-exposed management interface, because MediBec lacks an attack-surface inventory and timely patching, gaining administrative access to infrastructure and a path to data theft or P02. | D6: O1; O2 | E6: Remote-access gateway, firewalls, hypervisor/storage management interfaces, end-of-life systems | F6: Cybercriminal / state-linked actor (mass exploitation) | G6: Patch delays (E3, E7); unknown internet exposure (E4); admin interfaces without MFA (assumption) | H6: Infrastructure compromise; outage; data access | I6: Edge gateway (single remote-access path) | J6: Firewalls, IDS/IPS (E2) | K6: Critical vulnerabilities on internet-facing systems must be fixed within a short timeframe (E5) | L6: Technical entry path distinct from identity (P01): different controls (attack-surface management, patch SLAs), owner (Infrastructure) and velocity (days from disclosure to exploitation). Directly tied to an explicit appetite rule on critical vulnerabilities. | M6: Case (E3, E7); external/sector; unknown (actual exposure) | N6: Medium | O6: External attack-surface scan; patch status of edge devices; list of internet-exposed admin interfaces; EOL inventory | P6: C07, C26, C36 | Q6: S6, S23
A7: P04 | B7: Compromise of connected medical devices disrupting diagnostics and threatening patient safety | C7: An attacker or spreading malware reaches a clinic network - via infected workstation, clinic Wi-Fi, patient-supplied imaging media or building IoT - and exploits unpatched or default-credential medical devices sharing that network, disrupting imaging and diagnostic equipment, altering device data and using devices as persistent footholds. | D7: O1 safe care | E7: Imaging modalities and consoles, diagnostic devices, clinic LAN | F7: Cybercriminal / commodity malware | G7: Incomplete device inventory (E4); patching restricted by certification (E3); no segmentation evidence; media import without scanning (assumption) | H7: Postponed procedures; incorrect or unavailable diagnostics; patient-safety review | I7: Device manufacturers; clinic networks (peripheral assets) | J7: Hub firewalls and IDS/IPS (E2 - east-west coverage unknown) | K7: Patient-safety clause - no credible immediate threat to care may be accepted (E5) | L7: Only scenario where the cyber event directly affects medical equipment; peripheral assets outside IT oversight (instruction s.2-3); certification limits make treatment a distinct management decision. Wi-Fi, media and IoT are entry paths into the same exposure. | M7: Case (E2, E4); external/sector; assumption (segmentation, media handling) | N7: Medium | O7: Networked device inventory with OS/patch level; MDS2 forms; network segmentation diagrams; Wi-Fi and guest isolation; media import procedure | P7: C09, C06, C27, C43 | Q7: S7, S24, S12
A8: P05 | B8: Manipulation of clinical data (records or interface messages) leading to unsafe care | C8: An attacker using a compromised clinical account, a malicious insider, or an attacker positioned on the network alters medication, allergy, laboratory or imaging data - in the EHR or in cleartext HL7/DICOM interface traffic - without detection because integrity monitoring and reconciliation are absent, leading to incorrect clinical decisions. | D8: O1 safe care; O4 trust | E8: EHR records, lab/pharmacy results, interface engine | F8: Extortion-motivated attacker, saboteur or malicious insider | G8: No integrity monitoring or reconciliation (E8); cleartext interfaces (assumption); broad write privileges (assumption) | H8: Wrong medication or diagnosis; clinical safety review; loss of trust in the record | I8: Interface engine; EHR vendor | J8: EHR audit logging (E6) | K8: Patient-safety clause (E5); low-frequency/high-consequence - must not be excluded for low probability | L8: Low-frequency/high-consequence integrity risk; the portfolio would otherwise treat integrity only as a side effect. Distinct controls (integrity monitoring, reconciliation, interface encryption) and owner (CMO/Clinical Ops). | M8: Case (E8 control expectation); assumption; very limited sector frequency data | N8: Low | O8: EHR audit-trail capability; interface protocols (TLS or cleartext); reconciliation practices; write-privilege model | P8: C12, C32 | Q8: S10, S29
A9: P06 | B9: Misuse of legitimate EHR or service-account access to extract patient records | C9: A malicious or curious employee, or an attacker who has taken over the over-privileged ehr-sync-svc service account, uses legitimate but excessive access to query and export patient or billing records, because access is broad, service accounts are not vaulted and EHR access is not monitored, resulting in a privacy breach. | D9: O2 privacy | E9: EHR data, billing data, service accounts | F9: Malicious/curious insider; attacker using a service account | G9: Broad roles (assumption); un-vaulted service account (E6); no access analytics or recertification (E7); no DLP | H9: Privacy breach, disciplinary and legal action, notification | I9: EHR role model; integration accounts | J9: EHR audit log exists (E6); encrypted storage (E2) | K9: High-risk data stores must have access control, logging and monitoring (E5) | L9: Insider misuse is a recurrent healthcare exposure and is directly evidenced by the service-account anomaly. Distinct from P01 (legitimate access, no perimeter crossing) and P10 (malicious intent); owner is the Privacy officer. | M9: Verified org evidence (exercise: ehr-sync-svc); external/sector; assumption (role model) | N9: Medium | O9: EHR role matrix; service-account inventory and privileges; audit-log review practice; last access recertification | P9: C11, C15 | Q9: S5
A10: P07 | B10: Bulk exposure of health data held outside core systems (cloud exports, APIs, clinic storage) | C10: An opportunistic actor or intruder obtains bulk patient data from stores that sit outside the EHR's controls - cloud storage used for image transfer shared through long-lived links, API keys leaked from code or configuration, and unmanaged local clinic storage - because posture management, secret management and data minimization are absent, causing a large reportable breach. | D10: O2 privacy; O4 trust | E10: Cloud storage, API integrations, local clinic storage, exports | F10: Opportunistic scanner / cybercriminal | G10: Permissive sharing and weak cloud logging (E4, E6); no secret management (E7); data sprawl (E4); excessive retention | H10: Large-scale health-data exposure; notification; reputational harm | I10: Cloud provider; integration partners | J10: Encrypted storage (E2 - does not prevent valid-link or key access) | K10: High-risk data stores must have encryption, access control, logging and monitoring (E5) | L10: Data-at-rest exposure outside the EHR is evidenced (external download of image export) and produces the largest breach volumes. Consolidates three variants that share the treatment decision (data discovery, posture management, minimization) and owner. | M10: Verified org evidence (exercise: cloud download); case (E2, E4); assumption (repositories) | N10: Medium | O10: Cloud sharing configuration and object logs; inventory of exports; secret-scanning of repositories; content of clinic storage units | P10: C04, C05, C17, C44 | Q10: S4, S11, S17
A11: P08 | B11: Compromise through a critical supplier (vendor remote access or trojanized software update) | C11: A threat actor compromises an EHR, diagnostic, device or IT-support supplier and enters MediBec through the supplier's standing remote access or a malicious signed software update, bypassing perimeter controls, because supplier assurance, contract clauses, access brokering and update staging are absent. | D11: O1; O2 | E11: Vendor-managed systems, EHR components, endpoints running supplier agents | F11: Supply-chain attacker (criminal or state-linked) | G11: Standing vendor access (assumption); no vendor tiering or assessments (E7); automatic updates without staging (assumption) | H11: Trusted-path intrusion across many systems; outage; breach; contractual disputes | I11: EHR vendor and critical suppliers (concentration) | J11: Firewalls (E2); vendor coordination role in IR (E6) | K11: Critical vendors must meet security expectations and support incident notification (E5) | L11: Critical supply-chain concentration is a mandatory escalation criterion; residual stays above tolerance even with funding, so it drives transfer and acceptance decisions rather than spending. Remote-access and update vectors share owner (Procurement/CIO) and the supplier-assurance decision. | M11: Case (E2, E5, E7); external/sector; assumption (access design) | N11: Medium | O11: Critical supplier list; remote-access methods; contract clauses (notification, audit); update mechanisms of critical software | P11: C13, C22 | Q11: S9, S19
A12: P09 | B12: Loss of the Montreal hub or WAN isolating all clinics from clinical systems | C12: A carrier failure, attack on edge network devices, failure of the single primary firewall pair or data-centre incident takes the Montreal hub offline; because all clinics depend on it without tested redundancy, alternate site or rehearsed downtime procedures, EHR, imaging and pharmacy access is lost network-wide. | D12: O1 clinical continuity | E12: Montreal DC, WAN, firewalls, carrier links | F12: Technical failure, carrier outage or attacker targeting network infrastructure | G12: Single hub and possibly single carrier (assumption); firewall redundancy unknown; no alternate site evidenced; downtime procedures untested (E7) | H12: Network-wide loss of clinical systems for hours to days; safety risk from missing history | I12: Hub, carriers, firewalls (single point of failure) | J12: High-speed fibre links (E2); off-site backups (E2) | K12: Clinical services must have tested recovery and workaround procedures (E5) | L12: Instruction s.3 requires explicit analysis of single points of failure; this is the organization's largest concentration risk and is independent of any attacker, so it is not captured by P02. Distinct decision (redundancy / alternate site investment, IT-funded). | M12: Case architecture (E2); assumption (redundancy) | N12: Medium | O12: Network architecture; carrier diversity; firewall HA; DR site; clinic downtime procedures and last test | P12: C16, C45 | Q12: S16
A13: P10 | B13: Uncontrolled disclosure of patient information by staff through unapproved AI tools and communications | C13: Clinicians and administrative staff paste identifiable patient information into public generative-AI or unassessed AI-scribe services, or misdirect e-mails and faxes, because MediBec has no AI acceptable-use policy, sanctioned tool, web/DLP controls or secure referral channel, resulting in systemic uncontrolled disclosure of health information and possible cross-border transfer. | D13: O2 privacy; O5 governed innovation | E13: Clinical notes, correspondence, referrals | F13: Negligent insider; external AI/SaaS provider handling | G13: No AI policy or approved tool; no web category or DLP controls; manual referral channels (assumption) | H13: Systemic privacy non-compliance; notification; clinical errors from unchecked AI output | I13: External AI and SaaS providers (unmanaged) | J13: Privacy and compliance function exists (s.4) | K13: Low appetite for health-data confidentiality; moderate appetite for governed innovation (E5) | L13: Chosen over the higher-scoring C31 (admin sabotage) for portfolio coverage and decision usefulness: it is the only material negligent-insider and emerging-technology exposure, is near-certain to occur, and drives decisions (AI policy, sanctioned tool, controls) that no other scenario triggers. C31's treatments are largely delivered by P01/P02 controls. | M13: External/sector (AI adoption); assumption (MediBec usage); case (appetite for governed innovation) | N13: Medium | O13: Proxy/DNS logs for AI services; staff survey; referral channels in use; any AI scribe pilots | P13: C29, C24, C42 | Q13: S26, S21

Sheet D_WhyTest
A1: Section D - 'Why this scenario?' test (Instruction s.14)
A3: ID | B3: Scenario | C3: 1. Why relevant to MediBec? | D3: 2. Organizational evidence | E3: 3. Asset / objective threatened | F3: 4. Weakness or condition | G3: 5. Material consequence | H3: 6. Why selected over others?
A4: P01 | B4: Identity takeover of clinical, privileged or cloud-administrator accounts | C4: Identity gates every crown jewel and remote/cloud access is central to MediBec's model. | D4: Phishing lure and approved MFA push from unusual geography (E6). | E4: Health-data confidentiality (O2); precursor to O1 disruption. | F4: Push-only MFA, no conditional access, unknown reset verification. | G4: Unauthorized EHR/mail access; reportable breach; ransomware foothold. | H4: Highest likelihood entry path with strongest evidence; variants consolidated.
A5: P02 | B5: Ransomware with data theft and backup destruction halting multi-clinic operations | C5: Clinics depend on central services; healthcare is a sustained ransomware target. | D5: Full exercise timeline; backup failures; alert closed as low (E6). | E5: Safe continuous care (O1) and all others. | F5: Weak triage, flat network, backups reachable, untested IR. | G5: Multi-clinic outage, data theft, failed recovery. | H5: Largest combined consequence; several mandatory escalation criteria.
A6: P03 | B6: Exploitation of exposed internet-facing systems (unpatched edge devices, admin interfaces, end-of-life systems) | C6: Remote access is essential and edge devices are prime targets. | D6: Documented patching constraints (E3, E7); exposure unknown (E4). | E6: O1 and O2 via infrastructure compromise. | F6: Patch lag, unknown exposed interfaces, possible default credentials. | G6: Infrastructure takeover, outage, data access. | H6: Distinct control set and owner; tied to explicit appetite rule on critical vulnerabilities.
A7: P04 | B7: Compromise of connected medical devices disrupting diagnostics and threatening patient safety | C7: Medical equipment is interconnected with the EHR environment (E2). | D7: Inventory and segmentation are open questions (E4); certification constraints (E3). | E7: Safe care (O1). | F7: Unpatchable devices on shared networks; peripheral entry paths. | G7: Unavailable or incorrect diagnostics; patient-safety risk. | H7: Only direct safety path through equipment; peripheral assets.
A8: P05 | B8: Manipulation of clinical data (records or interface messages) leading to unsafe care | C8: Clinical decisions rely on EHR, lab and pharmacy data (E1). | D8: Integrity controls listed as expected but absent (E8). | E8: Safe care (O1) and trust (O4). | F8: No integrity monitoring; cleartext interfaces; broad write access. | G8: Wrong treatment; loss of confidence in the record. | H8: Low-frequency/high-consequence; only integrity-centred scenario.
A9: P06 | B9: Misuse of legitimate EHR or service-account access to extract patient records | C9: EHR access is central and broad; insiders are frequent actors in healthcare. | D9: ehr-sync-svc anomaly (E6); access reviews not evidenced (E7). | E9: Privacy (O2). | F9: Broad roles; un-vaulted service account; no monitoring. | G9: Privacy breach, legal and HR consequences. | H9: Distinct actor and controls from P01/P10; direct evidence.
A10: P07 | B10: Bulk exposure of health data held outside core systems (cloud exports, APIs, clinic storage) | C10: Image sharing and exports use cloud storage; data spread across clinics. | D10: External download of image export (E6); sprawl question (E4). | E10: Privacy (O2), trust (O4). | F10: Permissive sharing, no posture or secret management, data sprawl. | G10: Large-scale reportable breach. | H10: Largest breach volumes; evidenced; consolidates variants.
A11: P08 | B11: Compromise through a critical supplier (vendor remote access or trojanized software update) | C11: MediBec relies on EHR, device, cloud and support vendors. | D11: Vendor controls listed only as expectations (E5, E7). | E11: O1 and O2 through trusted paths. | F11: Standing vendor access; no assurance; unstaged updates. | G11: Trusted-path intrusion across many systems. | H11: Mandatory supply-chain concentration criterion; drives transfer decisions.
A12: P09 | B12: Loss of the Montreal hub or WAN isolating all clinics from clinical systems | C12: All clinics connect through one Montreal hub (E2). | D12: Architecture documented; redundancy not evidenced. | E12: Clinical continuity (O1). | F12: Single hub, possible single carrier/firewall pair, no alternate site. | G12: Network-wide loss of clinical systems. | H12: Largest single point of failure; independent of attackers so not covered by P02.
A13: P10 | B13: Uncontrolled disclosure of patient information by staff through unapproved AI tools and communications | C13: Clinicians are adopting AI; MediBec pursues governed innovation (E5). | D13: Sector evidence; no MediBec policy documented. | E13: Privacy (O2), governed innovation (O5). | F13: No AI policy, sanctioned tool or controls. | G13: Systemic uncontrolled disclosure; clinical errors. | H13: Only negligent-insider/emerging-tech exposure; unique decisions.

Sheet D_QuantPrep
A1: Section D / Instruction s.19 - Preparation for quantitative analysis
A2: Preliminary values are taken from the constituent scenarios of the 30-scenario assessment: anchor = lead constituent (core causal chain); range = min-max across constituents. Analytical estimate — validation required.
A4: ID | B4: Constituents | C4: Anchor | D4: Pb(A) anchor | E4: Pb(psi,A) anchor | F4: de anchor | G4: dm anchor | H4: theta anchor | I4: mu(E) anchor | J4: Pb(A) range | K4: Pb(psi,A) range | L4: de range | M4: dm range | N4: theta range | O4: mu(E) range | P4: Lowest param. confidence | Q4: CVSS applicability | R4: Current control effectiveness (FAIR resistance) | S4: FAIR: threat event frequency | T4: FAIR: threat capability | U4: FAIR: loss magnitude | V4: Proposed mitigation (initiatives) | W4: Prob. reduction (portfolio / 2nd wave) | X4: Impact reduction (portfolio / 2nd wave) | Y4: Indicative Y1 cost of treatment (CAD) | Z4: Evidence required for validation
A5: P01 | B5: S1, S20, S27 | C5: S1 | D5: 0.85 | E5: 0.55 | F5: 0.55 | G5: 0.85 | H5: 0.4 | I5: 0.85 | J5: 0.55-0.85 | K5: 0.40-0.55 | L5: 0.55 | M5: 0.85-0.90 | N5: 0.40 | O5: 0.85 | P5: Low | Q5: Limited for S27; anchor CVSS-B 9.3 | R5: Low (weak existing controls) | S5: High | T5: Medium | U5: High | V5: I01 Phishing-resistant MFA and conditional access; I02 Privileged access and service-account management (PAM); I03 24/7 managed detection and response with centralized logging; I08 Cloud security posture and secure image transfer; I12 Governance, awareness and risk reporting; I21 Help-desk identity verification | W5: 0.80 / 0.85 | X5: 0.75 / 0.80 | Y5: 376000 | Z5: MFA method and coverage; conditional-access policies; help-desk reset procedure; cloud app-consent setting; sign-in logs for E6 indicators
A6: P02 | B6: S2, S3, S8 | C6: S2 | D6: 0.75 | E6: 0.5 | F6: 0.7 | G6: 0.95 | H6: 0.35 | I6: 0.95 | J6: 0.55-0.80 | K6: 0.50-0.60 | L6: 0.60-0.70 | M6: 0.90-0.95 | N6: 0.30-0.35 | O6: 0.85-0.95 | P6: Low | Q6: Limited for S8; anchor CVSS-B 9.3 | R6: Low (weak existing controls) | S6: High | T6: High | U6: Very high | V6: I01 Phishing-resistant MFA and conditional access; I02 Privileged access and service-account management (PAM); I03 24/7 managed detection and response with centralized logging; I04 Immutable and isolated backup with tested recovery; I05 Risk-based vulnerability and patch management; I06 Network segmentation and network access control; I11 Incident response and clinical continuity readiness; I12 Governance, awareness and risk reporting | W6: 0.75 / 0.80 | X6: 0.75 / 0.80 | Y6: 732000 | Z6: EDR coverage and triage records; log sources and retention; AD security assessment; backup isolation and last restore test; IR plan test history
A7: P03 | B7: S6, S23 | C7: S6 | D7: 0.8 | E7: 0.5 | F7: 0.6 | G7: 0.9 | H7: 0.4 | I7: 0.85 | J7: 0.70-0.80 | K7: 0.35-0.50 | L7: 0.60 | M7: 0.90 | N7: 0.40 | O7: 0.85 | P7: Low | Q7: Applicable (representative weakness); anchor CVSS-B 10.0 | R7: Low (weak existing controls) | S7: High | T7: High | U7: High | V7: I01 Phishing-resistant MFA and conditional access; I02 Privileged access and service-account management (PAM); I03 24/7 managed detection and response with centralized logging; I05 Risk-based vulnerability and patch management; I06 Network segmentation and network access control | W7: 0.85 / 0.90 | X7: 0.70 / 0.70 | Y7: 365000 | Z7: External attack-surface scan; patch status of edge devices; list of internet-exposed admin interfaces; EOL inventory
A8: P04 | B8: S7, S24, S12 | C8: S7 | D8: 0.45 | E8: 0.5 | F8: 0.55 | G8: 0.95 | H8: 0.35 | I8: 0.9 | J8: 0.35-0.45 | K8: 0.40-0.50 | L8: 0.40-0.55 | M8: 0.75-0.95 | N8: 0.35-0.40 | O8: 0.70-0.90 | P8: Low | Q8: Applicable (representative weakness); anchor CVSS-B 8.7 | R8: Low (weak existing controls) | S8: Medium | T8: Medium | U8: Very high | V8: I03 24/7 managed detection and response with centralized logging; I05 Risk-based vulnerability and patch management; I06 Network segmentation and network access control; I07 Medical device security programme; I12 Governance, awareness and risk reporting | W8: 0.70 / 0.80 | X8: 0.60 / 0.72 | Y8: 655000 | Z8: Networked device inventory with OS/patch level; MDS2 forms; network segmentation diagrams; Wi-Fi and guest isolation; media import procedure
A9: P05 | B9: S10, S29 | C9: S10 | D9: 0.3 | E9: 0.4 | F9: 0.55 | G9: 0.95 | H9: 0.4 | I9: 0.95 | J9: 0.25-0.30 | K9: 0.40 | L9: 0.45-0.55 | M9: 0.85-0.95 | N9: 0.40 | O9: 0.85-0.95 | P9: Low | Q9: Applicable (representative weakness); anchor CVSS-B 8.3 | R9: Low (weak existing controls) | S9: Low | T9: Medium | U9: Very high | V9: I01 Phishing-resistant MFA and conditional access; I02 Privileged access and service-account management (PAM); I03 24/7 managed detection and response with centralized logging; I04 Immutable and isolated backup with tested recovery; I06 Network segmentation and network access control; I09 Data access governance and EHR privacy monitoring; I11 Incident response and clinical continuity readiness; I13 Clinical data integrity controls; I22 Secure clinical communications and interfaces | W9: 0.70 / 0.75 | X9: 0.75 / 0.80 | Y9: 569000 | Z9: EHR audit-trail capability; interface protocols (TLS or cleartext); reconciliation practices; write-privilege model
A10: P06 | B10: S5 | C10: S5 | D10: 0.6 | E10: 0.55 | F10: 0.45 | G10: 0.75 | H10: 0.4 | I10: 0.8 | J10: 0.60 | K10: 0.55 | L10: 0.45 | M10: 0.75 | N10: 0.40 | O10: 0.80 | P10: Medium | Q10: Limited for S5; anchor CVSS-B 7.1 | R10: Low (weak existing controls) | S10: Medium | T10: Low | U10: High | V10: I02 Privileged access and service-account management (PAM); I03 24/7 managed detection and response with centralized logging; I09 Data access governance and EHR privacy monitoring; I12 Governance, awareness and risk reporting | W10: 0.60 / 0.70 | X10: 0.65 / 0.70 | Y10: 147000 | Z10: EHR role matrix; service-account inventory and privileges; audit-log review practice; last access recertification
A11: P07 | B11: S4, S11, S17 | C11: S4 | D11: 0.6 | E11: 0.45 | F11: 0.55 | G11: 0.8 | H11: 0.4 | I11: 0.75 | J11: 0.45-0.60 | K11: 0.45 | L11: 0.40-0.55 | M11: 0.70-0.80 | N11: 0.40 | O11: 0.65-0.75 | P11: Low | Q11: Applicable (representative weakness); anchor CVSS-B 8.7 | R11: Low (weak existing controls) | S11: High | T11: Low | U11: High | V11: I03 24/7 managed detection and response with centralized logging; I08 Cloud security posture and secure image transfer; I09 Data access governance and EHR privacy monitoring; I14 Application security and secrets management; I17 Mobile device management, encryption and secure disposal; I19 Data lifecycle and minimization | W11: 0.85 / 0.90 | X11: 0.70 / 0.75 | Y11: 453000 | Z11: Cloud sharing configuration and object logs; inventory of exports; secret-scanning of repositories; content of clinic storage units
A12: P08 | B12: S9, S19 | C12: S9 | D12: 0.55 | E12: 0.45 | F12: 0.6 | G12: 0.9 | H12: 0.35 | I12: 0.85 | J12: 0.25-0.55 | K12: 0.45-0.50 | L12: 0.60 | M12: 0.90-0.95 | N12: 0.35 | O12: 0.85 | P12: Low | Q12: Limited for S9, S19; anchor CVSS-B 9.0 | R12: Low (weak existing controls) | S12: Medium | T12: High | U12: Very high | V12: I01 Phishing-resistant MFA and conditional access; I02 Privileged access and service-account management (PAM); I03 24/7 managed detection and response with centralized logging; I10 Third-party cyber risk management; I11 Incident response and clinical continuity readiness | W12: 0.55 / 0.60 | X12: 0.70 / 0.75 | Y12: 348000 | Z12: Critical supplier list; remote-access methods; contract clauses (notification, audit); update mechanisms of critical software
A13: P09 | B13: S16 | C13: S16 | D13: 0.35 | E13: 0.5 | F13: 0.55 | G13: 0.85 | H13: 0.35 | I13: 0.95 | J13: 0.35 | K13: 0.50 | L13: 0.55 | M13: 0.85 | N13: 0.35 | O13: 0.95 | P13: Low | Q13: Limited for S16; anchor CVSS-B 8.9 | R13: Low (weak existing controls) | S13: Medium | T13: n/a (includes non-malicious) | U13: Very high | V13: I11 Incident response and clinical continuity readiness; I18 Network and hosting resilience | W13: 0.70 / 0.85 | X13: 0.65 / 0.80 | Y13: 492000 | Z13: Network architecture; carrier diversity; firewall HA; DR site; clinic downtime procedures and last test
A14: P10 | B14: S26, S21 | C14: S26 | D14: 0.8 | E14: 0.55 | F14: 0.35 | G14: 0.65 | H14: 0.4 | I14: 0.7 | J14: 0.80-0.85 | K14: 0.50-0.55 | L14: 0.20-0.35 | M14: 0.45-0.65 | N14: 0.40-0.45 | O14: 0.60-0.70 | P14: Low | Q14: Limited for S26, S21; anchor CVSS-B 6.0 | R14: Low (weak existing controls) | S14: Very high | T14: Low | U14: Medium | V14: I09 Data access governance and EHR privacy monitoring; I12 Governance, awareness and risk reporting; I19 Data lifecycle and minimization; I20 Responsible use of generative AI | W14: 0.65 / 0.75 | X14: 0.55 / 0.65 | Y14: 301000 | Z14: Proxy/DNS logs for AI services; staff survey; referral channels in use; any AI scribe pilots
A17: Cost = sum of the constituents' allocated Year-1 cost from the 30-scenario model (shared initiatives already split, so no double counting). Re-quantify each P scenario as a whole before management use.

Sheet D_Validation
A1: Section D / Instruction s.17 - Cross-functional validation
A2: R = must validate, C = consult, - = not needed. Anticipated disagreements are recorded, not hidden.
A3: ID | B3: Scenario | C3: Executive mgmt | D3: Cybersecurity | E3: IT operations | F3: ERM / risk | G3: Clinical Ops / CMO | H3: Privacy | I3: Legal | J3: Compliance | K3: Finance | L3: Internal audit | M3: Procurement / vendor mgmt | N3: BCP | O3: Biomedical engineering | P3: Clinic managers | Q3: Anticipated disagreement
A4: P01 | B4: Identity takeover of clinical, privileged or cloud-administrator accounts | C4: C | D4: R | E4: R | F4: C | G4: C | H4: R | I4: - | J4: - | K4: - | L4: C | M4: - | N4: - | O4: - | P4: C | Q4: Clinicians may resist stronger MFA and conditional access at point of care; IT vs Clinical Ops on login friction.
A5: P02 | B5: Ransomware with data theft and backup destruction halting multi-clinic operations | C5: R | D5: R | E5: R | F5: R | G5: R | H5: R | I5: R | J5: C | K5: C | L5: C | M5: C | N5: R | O5: C | P5: R | Q5: Containment speed (Cybersecurity) vs care continuity (Clinical Ops); ransom stance (Executive vs Legal/Finance).
A6: P03 | B6: Exploitation of exposed internet-facing systems (unpatched edge devices, admin interfaces, end-of-life systems) | C6: C | D6: R | E6: R | F6: C | G6: - | H6: - | I6: - | J6: C | K6: - | L6: C | M6: C | N6: - | O6: - | P6: - | Q6: Patch windows: IT operations and clinics prefer fewer outages than security SLAs imply.
A7: P04 | B7: Compromise of connected medical devices disrupting diagnostics and threatening patient safety | C7: C | D7: R | E7: R | F7: C | G7: R | H7: - | I7: - | J7: C | K7: - | L7: C | M7: C | N7: C | O7: R | P7: R | Q7: Biomedical engineering and manufacturers may dispute feasibility of patching/segmentation; Clinical Ops on device downtime.
A8: P05 | B8: Manipulation of clinical data (records or interface messages) leading to unsafe care | C8: C | D8: R | E8: C | F8: C | G8: R | H8: R | I8: R | J8: C | K8: - | L8: C | M8: - | N8: - | O8: C | P8: C | Q8: Likelihood contested - Clinical Ops may rate it very low; Cybersecurity emphasizes consequence.
A9: P06 | B9: Misuse of legitimate EHR or service-account access to extract patient records | C9: C | D9: R | E9: C | F9: C | G9: C | H9: R | I9: R | J9: R | K9: - | L9: C | M9: - | N9: - | O9: - | P9: C | Q9: Privacy vs clinical staff on monitoring of access; HR/legal on employee monitoring limits.
A10: P07 | B10: Bulk exposure of health data held outside core systems (cloud exports, APIs, clinic storage) | C10: C | D10: R | E10: R | F10: C | G10: C | H10: R | I10: R | J10: R | K10: - | L10: C | M10: C | N10: - | O10: - | P10: C | Q10: Radiology needs easy external sharing; Privacy wants restrictions.
A11: P08 | B11: Compromise through a critical supplier (vendor remote access or trojanized software update) | C11: R | D11: R | E11: R | F11: R | G11: C | H11: C | I11: R | J11: C | K11: R | L11: C | M11: R | N11: C | O11: C | P11: - | Q11: Procurement and vendors resist new contract clauses; Finance on cost of assurance.
A12: P09 | B12: Loss of the Montreal hub or WAN isolating all clinics from clinical systems | C12: R | D12: C | E12: R | F12: R | G12: R | H12: - | I12: - | J12: - | K12: R | L12: C | M12: C | N12: R | O12: - | P12: R | Q12: Whether this is a cyber scenario at all (IT/BCP view) and who funds redundancy (IT vs cyber budget).
A13: P10 | B13: Uncontrolled disclosure of patient information by staff through unapproved AI tools and communications | C13: R | D13: R | E13: C | F13: C | G13: R | H13: R | I13: R | J13: R | K13: - | L13: C | M13: C | N13: - | O13: - | P13: C | Q13: Clinicians see AI as productivity gain; Privacy/Legal see uncontrolled transfer - calibrate between ban and sanctioned tool.
B15: Scenarios each stakeholder must validate (R) | C15: =COUNTIF(C4:C13,"R") -> 4 | D15: =COUNTIF(D4:D13,"R") -> 9 | E15: =COUNTIF(E4:E13,"R") -> 7 | F15: =COUNTIF(F4:F13,"R") -> 3 | G15: =COUNTIF(G4:G13,"R") -> 5 | H15: =COUNTIF(H4:H13,"R") -> 6 | I15: =COUNTIF(I4:I13,"R") -> 6 | J15: =COUNTIF(J4:J13,"R") -> 3 | ... P15: =COUNTIF(P4:P13,"R") -> 3

Sheet E_Coverage
A1: Section E - Portfolio coverage (Instruction s.12)
A2: 1 = scenario materially represents the category. Categories are included only where a credible material exposure exists.
A3: Category | B3: P01 | C3: P02 | D3: P03 | E3: P04 | F3: P05 | G3: P06 | H3: P07 | I3: P08 | J3: P09 | K3: P10 | L3: # scenarios | M3: Status
A4: Confidentiality | B4: 1 | C4: 1 | D4: 1 | G4: 1 | H4: 1 | I4: 1 | K4: 1 | L4: =SUM(B4:K4) -> 7 | M4: =IF(L4=0,"Gap - review",IF(L4>=8,"Heavily represented - check for variants","Covered")) -> Covered
A5: Integrity | B5: 1 | C5: 1 | E5: 1 | F5: 1 | I5: 1 | L5: =SUM(B5:K5) -> 5 | M5: =IF(L5=0,"Gap - review",IF(L5>=8,"Heavily represented - check for variants","Covered")) -> Covered
A6: Availability | C6: 1 | D6: 1 | E6: 1 | I6: 1 | J6: 1 | L6: =SUM(B6:K6) -> 5 | M6: =IF(L6=0,"Gap - review",IF(L6>=8,"Heavily represented - check for variants","Covered")) -> Covered
A7: Identity & privileged access | B7: 1 | C7: 1 | D7: 1 | G7: 1 | I7: 1 | L7: =SUM(B7:K7) -> 5 | M7: =IF(L7=0,"Gap - review",IF(L7>=8,"Heavily represented - check for variants","Covered")) -> Covered
A8: Ransomware / destructive | C8: 1 | L8: =SUM(B8:K8) -> 1 | M8: =IF(L8=0,"Gap - review",IF(L8>=8,"Heavily represented - check for variants","Covered")) -> Covered
A9: Cloud & SaaS | B9: 1 | H9: 1 | K9: 1 | L9: =SUM(B9:K9) -> 3 | M9: =IF(L9=0,"Gap - review",IF(L9>=8,"Heavily represented - check for variants","Covered")) -> Covered
A10: Third-party / supply chain | I10: 1 | J10: 1 | L10: =SUM(B10:K10) -> 2 | M10: =IF(L10=0,"Gap - review",IF(L10>=8,"Heavily represented - check for variants","Covered")) -> Covered
A11: Insider | F11: 1 | G11: 1 | K11: 1 | L11: =SUM(B11:K11) -> 3 | M11: =IF(L11=0,"Gap - review",IF(L11>=8,"Heavily represented - check for variants","Covered")) -> Covered
A12: Application / API | D12: 1 | F12: 1 | H12: 1 | L12: =SUM(B12:K12) -> 3 | M12: =IF(L12=0,"Gap - review",IF(L12>=8,"Heavily represented - check for variants","Covered")) -> Covered
A13: Infrastructure / network | C13: 1 | D13: 1 | E13: 1 | J13: 1 | L13: =SUM(B13:K13) -> 4 | M13: =IF(L13=0,"Gap - review",IF(L13>=8,"Heavily represented - check for variants","Covered")) -> Covered
A14: Endpoint | B14: 1 | C14: 1 | E14: 1 | L14: =SUM(B14:K14) -> 3 | M14: =IF(L14=0,"Gap - review",IF(L14>=8,"Heavily represented - check for variants","Covered")) -> Covered
A15: OT / IoT / medical devices | E15: 1 | L15: =SUM(B15:K15) -> 1 | M15: =IF(L15=0,"Gap - review",IF(L15>=8,"Heavily represented - check for variants","Covered")) -> Covered
A16: Data protection / privacy | B16: 1 | C16: 1 | G16: 1 | H16: 1 | K16: 1 | L16: =SUM(B16:K16) -> 5 | M16: =IF(L16=0,"Gap - review",IF(L16>=8,"Heavily represented - check for variants","Covered")) -> Covered
A17: Fraud / BEC | L17: =SUM(B17:K17) -> 0 | M17: =IF(L17=0,"Gap - Not covered - deferred (C18); bounded financial exposure","Covered") -> Gap - Not covered - deferred (C18); bounded financial exposure
A18: Resilience / DR | C18: 1 | J18: 1 | L18: =SUM(B18:K18) -> 2 | M18: =IF(L18=0,"Gap - review",IF(L18>=8,"Heavily represented - check for variants","Covered")) -> Covered
A19: Emerging technology (AI) | K19: 1 | L19: =SUM(B19:K19) -> 1 | M19: =IF(L19=0,"Gap - review",IF(L19>=8,"Heavily represented - check for variants","Covered")) -> Covered
A20: Patient safety | C20: 1 | E20: 1 | F20: 1 | J20: 1 | L20: =SUM(B20:K20) -> 4 | M20: =IF(L20=0,"Gap - review",IF(L20>=8,"Heavily represented - check for variants","Covered")) -> Covered
A22: Categories per scenario | B22: =SUM(B4:B20) -> 6 | C22: =SUM(C4:C20) -> 10 | D22: =SUM(D4:D20) -> 5 | E22: =SUM(E4:E20) -> 6 | F22: =SUM(F4:F20) -> 4 | G22: =SUM(G4:G20) -> 4 | H22: =SUM(H4:H20) -> 4 | I22: =SUM(I4:I20) -> 5 | ... K22: =SUM(K4:K20) -> 5

Sheet E_Quality
A1: Section E - Portfolio quality review
A3: Question | B3: Assessment | C3: Explanation
A4: Adequately represents material cybersecurity exposure? | B4: Yes | C4: All five objectives and the eight crown-jewel groups are threatened by at least one selected scenario; the largest consequences (P02, P09, P04, P05) and most evidenced paths (P01, P06, P07) are included.
A5: Contains unnecessary duplication? | B5: No (after consolidation) | C5: Identity variants (4), ransomware stages (6), data-store variants (3) and supplier vectors (2) were consolidated. Residual overlap: P01 is a precursor to P02 - kept separate because P01 has its own confidentiality consequence and owner.
A6: Overlooks major dependencies? | B6: Partly | C6: Identity, hub, backup, EHR vendor, device manufacturers, cloud and external AI are covered. Not explicitly covered: DNS and telecom carriers beyond the hub (P09 partly), payment/banking providers (C18 deferred).
A7: Addresses low-frequency/high-impact risks? | B7: Yes | C7: P05 (integrity), P08 (supply chain), P09 (hub) and P04 (devices) retained despite low probability. Admin sabotage (C31) kept on the watch list for explicit review.
A8: Represents C, I and A exposures? | B8: Yes | C8: Confidentiality 7, integrity 5, availability 5 scenarios (Coverage sheet).
A9: Includes material third-party and systemic risks? | B9: Yes | C9: P08 (suppliers), P09 (hub concentration), P02 (enterprise-wide), P01 (single identity plane).
A10: Reflects regulatory and safety considerations? | B10: Yes | C10: Patient safety: P02, P04, P05, P09. Privacy/regulatory: P01, P02, P06, P07, P10.
A11: Supports meaningful management decisions? | B11: Yes | C11: Each scenario maps to a distinct decision: MFA/identity (P01), MDR/backup isolation (P02), attack-surface/patch SLAs (P03), device programme (P04), integrity controls (P05), access governance (P06), data posture (P07), supplier assurance/transfer (P08), redundancy investment (P09), AI policy (P10).
A13: Blind spots and watch list
A14: Exposure | B14: Treatment in this portfolio | C14: Explanation / trigger to promote
A15: Fraud / BEC (C18) | B15: Not in portfolio | C15: Consequence bounded and treated by low-cost finance controls; confirm payment-verification procedure with Finance. Promote if procedure is absent and payment volumes are large.
A16: Privileged-insider sabotage (C31) | B16: Watch list - explicit review | C16: Scores higher than P10 on raw criteria and triggers escalation flags (privileged infrastructure, backup destruction). Excluded because PAM, immutable backup and offboarding controls in P01/P02 treat it; management should confirm this reliance.
A17: Patient-facing application flaws (C21) | B17: Watch list | C17: Existence of a patient portal is unconfirmed; promote immediately if confirmed.
A18: Patient-targeted impersonation (C33) | B18: Deferred | C18: Look-alike domain observed; harm largely outside MediBec systems; handle through communications and domain monitoring.
A19: DDoS on online services (C10) | B19: Deferred | C19: Online-service criticality undocumented; revisit if online booking becomes essential.
A20: Physical security (C39) | B20: Out of scope | C20: Not assessed; coordinate with physical security owner.
A22: Recommended evidence collection before quantification
A23: Evidence activity | B23: Scenarios | C23: Owner | D23: Timing
A24: Identity and cloud configuration review (MFA, conditional access, app consent, help-desk reset) | B24: P01, P06 | C24: Cybersecurity lead | D24: 30 days
A25: Compromise assessment of the exercise indicators if any reflect real activity | B25: P01, P02, P06, P07 | C25: Cybersecurity lead + IR retainer | D25: Immediate
A26: Backup architecture and restore test; AD security assessment; EDR/log coverage review | B26: P02 | C26: CIO | D26: 60 days
A27: External attack-surface scan and patch-status report | B27: P03 | C27: CIO (Infrastructure) | D27: 30 days
A28: Networked medical-device inventory, MDS2 collection, segmentation review | B28: P04 | C28: Biomedical engineering | D28: 90 days
A29: EHR audit-trail and interface-protocol review; reconciliation practices | B29: P05 | C29: Clinical Ops + integration team | D29: 90 days
A30: EHR role matrix and service-account review; access-log sampling | B30: P06 | C30: Privacy officer | D30: 60 days
A31: Cloud storage and sharing review; repository secret scan; clinic storage content survey | B31: P07 | C31: CIO + Privacy | D31: 60 days
A32: Critical supplier register, contracts and remote-access/update mechanisms | B32: P08 | C32: Procurement | D32: 90 days
A33: Network resilience and DR review; carrier diversity; downtime-procedure test | B33: P09 | C33: CIO + BCP | D33: 90 days
A34: AI usage discovery (proxy logs, staff survey) | B34: P10 | C34: Privacy officer | D34: 30 days
A35: Cross-functional validation workshop of this portfolio | B35: All | C35: Executive sponsor | D35: 45 days
A37: Critical-rules check
A38: Rule | B38: Status
A39: Threat not equated with scenario | B39: Met - every candidate and final scenario is a causal chain.
A40: Not selected on technical severity / CVSS | B40: Met - CVSS not used in screening.
A41: Probability not confused with impact | B41: Met - separate criteria; low-frequency/high-impact retained (P05, P08, P09).
A42: Generic threats not treated as evidence | B42: Met - evidence basis recorded per candidate; sector-only items marked.
A43: No double counting of overlapping scenarios | B43: Met - 24 candidates consolidated into the 10 selected families.
A44: No artificial precision | B44: Met - 1-5 scale; quantitative values flagged as preliminary.
A45: AI assumptions not presented as facts | B45: Met - evidence basis and confidence columns.
A46: Portfolio not dominated by one technique | B46: Met - identity and ransomware variants consolidated.
A47: Business consequences connected | B47: Met - consequence and objective columns.
A48: Selection documented | B48: Met - rationale and why-test per scenario.
A49: Assumptions and gaps identified | B49: Met - A_Context and validation columns.
A50: Human accountability | B50: Pending - requires analyst and cross-functional validation (D_Validation).

Sheet Changes
A1: Relationship to the earlier 30-scenario assessment
A2: The 30-scenario quantification (S1-S30) remains valid as analysis of individual exposures; the P01-P10 portfolio re-groups them for management decision-making.
A3: Prior ID | B3: Prior scenario | C3: Candidate | D3: Disposition now | E3: New family / status
A4: S1 | B4: Credential compromise of clinical administrator accounts through phishing and MFA fatigue | C4: C01 | D4: Select | E4: P01
A5: S2 | B5: Ransomware disrupting EHR access and clinic operations across the network | C5: C02 | D5: Select | E5: P02
A6: S3 | B6: Backup environment compromised, preventing recovery after a destructive attack | C6: C03 | D6: Consolidate | E6: P02
A7: S4 | B7: Cloud medical-image transfer storage exposed, enabling bulk health-data exfiltration | C7: C04 | D7: Select | E7: P07
A8: S5 | B8: Misuse of legitimate clinical, privileged or service-account access to extract patient records | C8: C11 | D8: Select | E8: P06
A9: S6 | B9: Exploitation of unpatched internet-facing or end-of-life systems | C9: C07 | D9: Select | E9: P03
A10: S7 | B10: Connected medical device used as a foothold to disrupt clinical equipment and reach the EHR network | C10: C09 | D10: Select | E10: P04
A11: S8 | B11: Detection and response gaps allow an intrusion to persist and escalate | C11: C08 | D11: Consolidate | E11: P02
A12: S9 | B12: Compromise of a critical vendor with remote access to MediBec systems | C12: C13 | D12: Select | E12: P08
A13: S10 | B13: Manipulation of patient, medication or billing records undermining clinical decisions | C13: C12 | D13: Select | E13: P05
A14: S11 | B14: API key or secret exposed in code, logs or configuration enables direct data access | C14: C05 | D14: Consolidate | E14: P07
... A33: S30 | B33: Criminals impersonate MediBec to defraud or phish patients | C33: C33 | D33: Defer | E33: Watch list - communications controls
A35: Previous 10 (S1-S10) vs new 10: S3 (backup) and S8 (detection) are now stages inside P02 rather than stand-alone scenarios; S1 widened into P01 (identity, incl. S20, S27); S6 widened into P03 (incl. S23); S4 widened into P07 (incl. S11, S17); S9 widened into P08 (incl. S19); S10 widened into P05 (incl. S29).
A36: New in the 10-scenario portfolio: P09 hub single point of failure (S16) and P10 staff disclosure via AI and misdirected communications (S26, S21).
A37: Implication: the CRG risk indices, treatment portfolio and budget were computed on S1-S30 and remain usable; re-quantify P01-P10 as whole scenarios before presenting a 10-scenario register to management.
