Workbook

Sheet README
A1: MediBec - CyberRiskGuardian Risk Assessment Workbook
A3: Assessment period: next 12 months (October 2026 - September 2027). Currency: CAD. Cost basis: Year-1 = initial implementation + first-year recurring.
A4: 30-scenario assessment (S1-S10 carried over unchanged from the 10-scenario assessment; S11-S30 added). Source: MediBec Business Case v2.0b (fictional teaching case, M.-A. Leger) and CyberRiskGuardian Excel Guide v1.0c formulas.
A5: All parameter values, CVSS vectors, costs and reductions are analytical estimates (Analytical estimate — validation required). Scores are relative decision-support indicators, not loss predictions.
A7: Colour legend: blue text = input you may edit | black = formula | green = link to another sheet | yellow fill = key assumption.
A9: Sheets:
A10: Parameters - risk appetite, multiplication factor, tolerance band (edit here).
A11: Inputs - S1-S30 quantitative parameters, CVSS v4.0 vector/score, reductions, confidence.
A12: Analyse - estimated, tolerated, mitigated, residual risk, ratio, classification, cost-effectiveness (live formulas).
A13: Portfolio - 23 initiatives, costs and scenario mapping; shared costs split equally across scenarios addressed (no double-counting).
A14: Sensitivity - lower / central / higher cases for ten key scenarios (all parameters shifted by +/- delta).
A15: Case_View - case-native escalation view (s.8 of the case): T x E x I x (1 - C), with the 0.25 / 0.40 escalation thresholds.
... A25: How to use: change blue cells on Parameters / Inputs / Portfolio, then recalculate (Formulas > Calculate Now if manual).

Sheet Analyse
A1: Analyse - CyberRiskGuardian risk indices (Excel Guide v1.0c formulas)
A2: Green = linked from Inputs / Portfolio / Parameters; black = formula.
A4: ID | B4: Scenario | C4: Pb(A) | D4: Pb(psi,A) | E4: CVSS-B | F4: de | G4: dm | H4: mu(E) | I4: theta | J4: Appetite | K4: Factor | L4: Estimated risk | M4: Tolerated risk | N4: Pre-treatment ratio | O4: Allocated Y1 cost | P4: Prob. reduction | Q4: Impact reduction | R4: Mitigated | S4: Residual | T4: Residual / Tolerated | U4: Classification | V4: Cost-effectiveness (per $1k) | W4: Validity (P,Q in 0-1)
A5: =Inputs!A4 -> S1 | B5: =Inputs!B4 -> Credential compromise of clinical administrator accounts through phishing and MFA fatigue | C5: =Inputs!C4 -> 0.85 | D5: =Inputs!D4 -> 0.55 | E5: =Inputs!J4 -> 9.3 | F5: =Inputs!E4 -> 0.55 | G5: =Inputs!F4 -> 0.85 | H5: =Inputs!H4 -> 0.85 | I5: =Inputs!G4 -> 0.4 | J5: =Parameters!$B$4 -> 0.3 | K5: =Parameters!$B$5 -> 1000 | L5: =C5*D5*E5*((F5+G5)/2)*H5/I5*K5 -> 6467.2781 | M5: =C5*D5*E5*J5*H5/I5*K5 -> 2771.6906 | N5: =L5/M5 -> 2.3333333 | O5: =Portfolio!K27 -> 123422.97 | P5: =Inputs!K4 -> 0.8 | Q5: =Inputs!L4 -> 0.75 | R5: =L5*P5*Q5 -> 3880.3669 | S5: =L5-R5 -> 2586.9113 | T5: =S5/M5 -> 0.93333333 | U5: =IF(T5<Parameters!$B$6,"Below tolerance",IF(T5<=Parameters!$B$7,"Approximately at tolerance","Above tolerance")) -> Approximately at tolerance | V5: =IF(O5=0,0,(L5-S5)/O5*1000) -> 31.439585 | W5: =IF(AND(P5>=0,P5<=1,Q5>=0,Q5<=1),"OK","CHECK") -> OK
A6: =Inputs!A5 -> S2 | B6: =Inputs!B5 -> Ransomware disrupting EHR access and clinic operations across the network | C6: =Inputs!C5 -> 0.75 | D6: =Inputs!D5 -> 0.5 | E6: =Inputs!J5 -> 9.3 | F6: =Inputs!E5 -> 0.7 | G6: =Inputs!F5 -> 0.95 | H6: =Inputs!H5 -> 0.95 | I6: =Inputs!G5 -> 0.35 | J6: =Parameters!$B$4 -> 0.3 | K6: =Parameters!$B$5 -> 1000 | L6: =C6*D6*E6*((F6+G6)/2)*H6/I6*K6 -> 7809.5089 | M6: =C6*D6*E6*J6*H6/I6*K6 -> 2839.8214 | N6: =L6/M6 -> 2.75 | O6: =Portfolio!L27 -> 356345.19 | P6: =Inputs!K5 -> 0.75 | Q6: =Inputs!L5 -> 0.75 | R6: =L6*P6*Q6 -> 4392.8488 | S6: =L6-R6 -> 3416.6602 | T6: =S6/M6 -> 1.203125 | U6: =IF(T6<Parameters!$B$6,"Below tolerance",IF(T6<=Parameters!$B$7,"Approximately at tolerance","Above tolerance")) -> Above tolerance | V6: =IF(O6=0,0,(L6-S6)/O6*1000) -> 12.32751 | W6: =IF(AND(P6>=0,P6<=1,Q6>=0,Q6<=1),"OK","CHECK") -> OK
A7: =Inputs!A6 -> S3 | B7: =Inputs!B6 -> Backup environment compromised, preventing recovery after a destructive attack | C7: =Inputs!C6 -> 0.55 | D7: =Inputs!D6 -> 0.5 | E7: =Inputs!J6 -> 9.2 | F7: =Inputs!E6 -> 0.6 | G7: =Inputs!F6 -> 0.9 | H7: =Inputs!H6 -> 0.9 | I7: =Inputs!G6 -> 0.35 | J7: =Parameters!$B$4 -> 0.3 | K7: =Parameters!$B$5 -> 1000 | L7: =C7*D7*E7*((F7+G7)/2)*H7/I7*K7 -> 4879.2857 | M7: =C7*D7*E7*J7*H7/I7*K7 -> 1951.7143 | N7: =L7/M7 -> 2.5 | O7: =Portfolio!M27 -> 267145.19 | P7: =Inputs!K6 -> 0.8 | Q7: =Inputs!L6 -> 0.85 | R7: =L7*P7*Q7 -> 3317.9143 | S7: =L7-R7 -> 1561.3714 | T7: =S7/M7 -> 0.8 | U7: =IF(T7<Parameters!$B$6,"Below tolerance",IF(T7<=Parameters!$B$7,"Approximately at tolerance","Above tolerance")) -> Below tolerance | V7: =IF(O7=0,0,(L7-S7)/O7*1000) -> 12.419891 | W7: =IF(AND(P7>=0,P7<=1,Q7>=0,Q7<=1),"OK","CHECK") -> OK
A8: =Inputs!A7 -> S4 | B8: =Inputs!B7 -> Cloud medical-image transfer storage exposed, enabling bulk health-data exfiltration | C8: =Inputs!C7 -> 0.6 | D8: =Inputs!D7 -> 0.45 | E8: =Inputs!J7 -> 8.7 | F8: =Inputs!E7 -> 0.55 | G8: =Inputs!F7 -> 0.8 | H8: =Inputs!H7 -> 0.75 | I8: =Inputs!G7 -> 0.4 | J8: =Parameters!$B$4 -> 0.3 | K8: =Parameters!$B$5 -> 1000 | L8: =C8*D8*E8*((F8+G8)/2)*H8/I8*K8 -> 2972.9531 | M8: =C8*D8*E8*J8*H8/I8*K8 -> 1321.3125 | N8: =L8/M8 -> 2.25 | O8: =Portfolio!N27 -> 154470.59 | P8: =Inputs!K7 -> 0.85 | Q8: =Inputs!L7 -> 0.7 | R8: =L8*P8*Q8 -> 1768.9071 | S8: =L8-R8 -> 1204.046 | T8: =S8/M8 -> 0.91125 | U8: =IF(T8<Parameters!$B$6,"Below tolerance",IF(T8<=Parameters!$B$7,"Approximately at tolerance","Above tolerance")) -> Approximately at tolerance | V8: =IF(O8=0,0,(L8-S8)/O8*1000) -> 11.451417 | W8: =IF(AND(P8>=0,P8<=1,Q8>=0,Q8<=1),"OK","CHECK") -> OK
A9: =Inputs!A8 -> S5 | B9: =Inputs!B8 -> Misuse of legitimate clinical, privileged or service-account access to extract patient records | C9: =Inputs!C8 -> 0.6 | D9: =Inputs!D8 -> 0.55 | E9: =Inputs!J8 -> 7.1 | F9: =Inputs!E8 -> 0.45 | G9: =Inputs!F8 -> 0.75 | H9: =Inputs!H8 -> 0.8 | I9: =Inputs!G8 -> 0.4 | J9: =Parameters!$B$4 -> 0.3 | K9: =Parameters!$B$5 -> 1000 | L9: =C9*D9*E9*((F9+G9)/2)*H9/I9*K9 -> 2811.6 | M9: =C9*D9*E9*J9*H9/I9*K9 -> 1405.8 | N9: =L9/M9 -> 2 | O9: =Portfolio!O27 -> 147137.25 | P9: =Inputs!K8 -> 0.6 | Q9: =Inputs!L8 -> 0.65 | R9: =L9*P9*Q9 -> 1096.524 | S9: =L9-R9 -> 1715.076 | T9: =S9/M9 -> 1.22 | U9: =IF(T9<Parameters!$B$6,"Below tolerance",IF(T9<=Parameters!$B$7,"Approximately at tolerance","Above tolerance")) -> Above tolerance | V9: =IF(O9=0,0,(L9-S9)/O9*1000) -> 7.4523886 | W9: =IF(AND(P9>=0,P9<=1,Q9>=0,Q9<=1),"OK","CHECK") -> OK
A10: =Inputs!A9 -> S6 | B10: =Inputs!B9 -> Exploitation of unpatched internet-facing or end-of-life systems | C10: =Inputs!C9 -> 0.8 | D10: =Inputs!D9 -> 0.5 | E10: =Inputs!J9 -> 10 | F10: =Inputs!E9 -> 0.6 | G10: =Inputs!F9 -> 0.9 | H10: =Inputs!H9 -> 0.85 | I10: =Inputs!G9 -> 0.4 | J10: =Parameters!$B$4 -> 0.3 | K10: =Parameters!$B$5 -> 1000 | L10: =C10*D10*E10*((F10+G10)/2)*H10/I10*K10 -> 6375 | M10: =C10*D10*E10*J10*H10/I10*K10 -> 2550 | N10: =L10/M10 -> 2.5 | O10: =Portfolio!P27 -> 183956.3 | P10: =Inputs!K9 -> 0.85 | Q10: =Inputs!L9 -> 0.7 | R10: =L10*P10*Q10 -> 3793.125 | S10: =L10-R10 -> 2581.875 | T10: =S10/M10 -> 1.0125 | U10: =IF(T10<Parameters!$B$6,"Below tolerance",IF(T10<=Parameters!$B$7,"Approximately at tolerance","Above tolerance")) -> Approximately at tolerance | V10: =IF(O10=0,0,(L10-S10)/O10*1000) -> 20.619707 | W10: =IF(AND(P10>=0,P10<=1,Q10>=0,Q10<=1),"OK","CHECK") -> OK
A11: =Inputs!A10 -> S7 | B11: =Inputs!B10 -> Connected medical device used as a foothold to disrupt clinical equipment and reach the EHR network | C11: =Inputs!C10 -> 0.45 | D11: =Inputs!D10 -> 0.5 | E11: =Inputs!J10 -> 8.7 | F11: =Inputs!E10 -> 0.55 | G11: =Inputs!F10 -> 0.95 | H11: =Inputs!H10 -> 0.9 | I11: =Inputs!G10 -> 0.35 | J11: =Parameters!$B$4 -> 0.3 | K11: =Parameters!$B$5 -> 1000 | L11: =C11*D11*E11*((F11+G11)/2)*H11/I11*K11 -> 3775.1786 | M11: =C11*D11*E11*J11*H11/I11*K11 -> 1510.0714 | N11: =L11/M11 -> 2.5 | O11: =Portfolio!Q27 -> 282485.71 | P11: =Inputs!K10 -> 0.7 | Q11: =Inputs!L10 -> 0.6 | R11: =L11*P11*Q11 -> 1585.575 | S11: =L11-R11 -> 2189.6036 | T11: =S11/M11 -> 1.45 | U11: =IF(T11<Parameters!$B$6,"Below tolerance",IF(T11<=Parameters!$B$7,"Approximately at tolerance","Above tolerance")) -> Above tolerance | V11: =IF(O11=0,0,(L11-S11)/O11*1000) -> 5.6129387 | W11: =IF(AND(P11>=0,P11<=1,Q11>=0,Q11<=1),"OK","CHECK") -> OK
A12: =Inputs!A11 -> S8 | B12: =Inputs!B11 -> Detection and response gaps allow an intrusion to persist and escalate | C12: =Inputs!C11 -> 0.8 | D12: =Inputs!D11 -> 0.6 | E12: =Inputs!J11 -> 9.2 | F12: =Inputs!E11 -> 0.6 | G12: =Inputs!F11 -> 0.9 | H12: =Inputs!H11 -> 0.85 | I12: =Inputs!G11 -> 0.3 | J12: =Parameters!$B$4 -> 0.3 | K12: =Parameters!$B$5 -> 1000 | L12: =C12*D12*E12*((F12+G12)/2)*H12/I12*K12 -> 9384 | M12: =C12*D12*E12*J12*H12/I12*K12 -> 3753.6 | N12: =L12/M12 -> 2.5 | O12: =Portfolio!R27 -> 108978.52 | P12: =Inputs!K11 -> 0.7 | Q12: =Inputs!L11 -> 0.8 | R12: =L12*P12*Q12 -> 5255.04 | S12: =L12-R12 -> 4128.96 | T12: =S12/M12 -> 1.1 | U12: =IF(T12<Parameters!$B$6,"Below tolerance",IF(T12<=Parameters!$B$7,"Approximately at tolerance","Above tolerance")) -> Approximately at tolerance | V12: =IF(O12=0,0,(L12-S12)/O12*1000) -> 48.220877 | W12: =IF(AND(P12>=0,P12<=1,Q12>=0,Q12<=1),"OK","CHECK") -> OK
A13: =Inputs!A12 -> S9 | B13: =Inputs!B12 -> Compromise of a critical vendor with remote access to MediBec systems | C13: =Inputs!C12 -> 0.55 | D13: =Inputs!D12 -> 0.45 | E13: =Inputs!J12 -> 9 | F13: =Inputs!E12 -> 0.6 | G13: =Inputs!F12 -> 0.9 | H13: =Inputs!H12 -> 0.85 | I13: =Inputs!G12 -> 0.35 | J13: =Parameters!$B$4 -> 0.3 | K13: =Parameters!$B$5 -> 1000 | L13: =C13*D13*E13*((F13+G13)/2)*H13/I13*K13 -> 4057.2321 | M13: =C13*D13*E13*J13*H13/I13*K13 -> 1622.8929 | N13: =L13/M13 -> 2.5 | O13: =Portfolio!S27 -> 209645.19 | P13: =Inputs!K12 -> 0.55 | Q13: =Inputs!L12 -> 0.7 | R13: =L13*P13*Q13 -> 1562.0344 | S13: =L13-R13 -> 2495.1978 | T13: =S13/M13 -> 1.5375 | U13: =IF(T13<Parameters!$B$6,"Below tolerance",IF(T13<=Parameters!$B$7,"Approximately at tolerance","Above tolerance")) -> Above tolerance | V13: =IF(O13=0,0,(L13-S13)/O13*1000) -> 7.4508476 | W13: =IF(AND(P13>=0,P13<=1,Q13>=0,Q13<=1),"OK","CHECK") -> OK
A14: =Inputs!A13 -> S10 | B14: =Inputs!B13 -> Manipulation of patient, medication or billing records undermining clinical decisions | C14: =Inputs!C13 -> 0.3 | D14: =Inputs!D13 -> 0.4 | E14: =Inputs!J13 -> 8.3 | F14: =Inputs!E13 -> 0.55 | G14: =Inputs!F13 -> 0.95 | H14: =Inputs!H13 -> 0.95 | I14: =Inputs!G13 -> 0.4 | J14: =Parameters!$B$4 -> 0.3 | K14: =Parameters!$B$5 -> 1000 | L14: =C14*D14*E14*((F14+G14)/2)*H14/I14*K14 -> 1774.125 | M14: =C14*D14*E14*J14*H14/I14*K14 -> 709.65 | N14: =L14/M14 -> 2.5 | O14: =Portfolio!T27 -> 355145.19 | P14: =Inputs!K13 -> 0.7 | Q14: =Inputs!L13 -> 0.75 | R14: =L14*P14*Q14 -> 931.41562 | S14: =L14-R14 -> 842.70938 | T14: =S14/M14 -> 1.1875 | U14: =IF(T14<Parameters!$B$6,"Below tolerance",IF(T14<=Parameters!$B$7,"Approximately at tolerance","Above tolerance")) -> Above tolerance | V14: =IF(O14=0,0,(L14-S14)/O14*1000) -> 2.6226334 | W14: =IF(AND(P14>=0,P14<=1,Q14>=0,Q14<=1),"OK","CHECK") -> OK
A15: =Inputs!A14 -> S11 | B15: =Inputs!B14 -> API key or secret exposed in code, logs or configuration enables direct data access | C15: =Inputs!C14 -> 0.45 | D15: =Inputs!D14 -> 0.45 | E15: =Inputs!J14 -> 8.3 | F15: =Inputs!E14 -> 0.5 | G15: =Inputs!F14 -> 0.8 | H15: =Inputs!H14 -> 0.75 | I15: =Inputs!G14 -> 0.4 | J15: =Parameters!$B$4 -> 0.3 | K15: =Parameters!$B$5 -> 1000 | L15: =C15*D15*E15*((F15+G15)/2)*H15/I15*K15 -> 2048.4141 | M15: =C15*D15*E15*J15*H15/I15*K15 -> 945.42188 | N15: =L15/M15 -> 2.1666667 | O15: =Portfolio!U27 -> 201470.59 | P15: =Inputs!K14 -> 0.85 | Q15: =Inputs!L14 -> 0.6 | R15: =L15*P15*Q15 -> 1044.6912 | S15: =L15-R15 -> 1003.7229 | T15: =S15/M15 -> 1.0616667 | U15: =IF(T15<Parameters!$B$6,"Below tolerance",IF(T15<=Parameters!$B$7,"Approximately at tolerance","Above tolerance")) -> Approximately at tolerance | V15: =IF(O15=0,0,(L15-S15)/O15*1000) -> 5.1853284 | W15: =IF(AND(P15>=0,P15<=1,Q15>=0,Q15<=1),"OK","CHECK") -> OK
A16: =Inputs!A15 -> S12 | B16: =Inputs!B15 -> Clinic Wi-Fi compromise or rogue access point gives access to the clinical network | C16: =Inputs!C15 -> 0.4 | D16: =Inputs!D15 -> 0.45 | E16: =Inputs!J15 -> 6.4 | F16: =Inputs!E15 -> 0.4 | G16: =Inputs!F15 -> 0.75 | H16: =Inputs!H15 -> 0.7 | I16: =Inputs!G15 -> 0.4 | J16: =Parameters!$B$4 -> 0.3 | K16: =Parameters!$B$5 -> 1000 | L16: =C16*D16*E16*((F16+G16)/2)*H16/I16*K16 -> 1159.2 | M16: =C16*D16*E16*J16*H16/I16*K16 -> 604.8 | N16: =L16/M16 -> 1.9166667 | O16: =Portfolio!V27 -> 110756.3 | P16: =Inputs!K15 -> 0.8 | Q16: =Inputs!L15 -> 0.65 | R16: =L16*P16*Q16 -> 602.784 | S16: =L16-R16 -> 556.416 | T16: =S16/M16 -> 0.92 | U16: =IF(T16<Parameters!$B$6,"Below tolerance",IF(T16<=Parameters!$B$7,"Approximately at tolerance","Above tolerance")) -> Approximately at tolerance | V16: =IF(O16=0,0,(L16-S16)/O16*1000) -> 5.4424352 | W16: =IF(AND(P16>=0,P16<=1,Q16>=0,Q16<=1),"OK","CHECK") -> OK
A17: =Inputs!A16 -> S13 | B17: =Inputs!B16 -> DDoS attack disrupts online booking, patient portal and communications | C17: =Inputs!C16 -> 0.5 | D17: =Inputs!D16 -> 0.6 | E17: =Inputs!J16 -> 8.7 | F17: =Inputs!E16 -> 0.3 | G17: =Inputs!F16 -> 0.55 | H17: =Inputs!H16 -> 0.55 | I17: =Inputs!G16 -> 0.45 | J17: =Parameters!$B$4 -> 0.3 | K17: =Parameters!$B$5 -> 1000 | L17: =C17*D17*E17*((F17+G17)/2)*H17/I17*K17 -> 1355.75 | M17: =C17*D17*E17*J17*H17/I17*K17 -> 957 | N17: =L17/M17 -> 1.4166667 | O17: =Portfolio!W27 -> 72222.222 | P17: =Inputs!K16 -> 0.8 | Q17: =Inputs!L16 -> 0.7 | R17: =L17*P17*Q17 -> 759.22 | S17: =L17-R17 -> 596.53 | T17: =S17/M17 -> 0.62333333 | U17: =IF(T17<Parameters!$B$6,"Below tolerance",IF(T17<=Parameters!$B$7,"Approximately at tolerance","Above tolerance")) -> Below tolerance | V17: =IF(O17=0,0,(L17-S17)/O17*1000) -> 10.512277 | W17: =IF(AND(P17>=0,P17<=1,Q17>=0,Q17<=1),"OK","CHECK") -> OK
A18: =Inputs!A17 -> S14 | B18: =Inputs!B17 -> Business e-mail compromise diverts vendor or billing payments | C18: =Inputs!C17 -> 0.65 | D18: =Inputs!D17 -> 0.4 | E18: =Inputs!J17 -> 5.1 | F18: =Inputs!E17 -> 0.35 | G18: =Inputs!F17 -> 0.6 | H18: =Inputs!H17 -> 0.55 | I18: =Inputs!G17 -> 0.45 | J18: =Parameters!$B$4 -> 0.3 | K18: =Parameters!$B$5 -> 1000 | L18: =C18*D18*E18*((F18+G18)/2)*H18/I18*K18 -> 769.81667 | M18: =C18*D18*E18*J18*H18/I18*K18 -> 486.2 | N18: =L18/M18 -> 1.5833333 | O18: =Portfolio!X27 -> 38500 | P18: =Inputs!K17 -> 0.8 | Q18: =Inputs!L17 -> 0.6 | R18: =L18*P18*Q18 -> 369.512 | S18: =L18-R18 -> 400.30467 | T18: =S18/M18 -> 0.82333333 | U18: =IF(T18<Parameters!$B$6,"Below tolerance",IF(T18<=Parameters!$B$7,"Approximately at tolerance","Above tolerance")) -> Below tolerance | V18: =IF(O18=0,0,(L18-S18)/O18*1000) -> 9.5977143 | W18: =IF(AND(P18>=0,P18<=1,Q18>=0,Q18<=1),"OK","CHECK") -> OK
A19: =Inputs!A18 -> S15 | B19: =Inputs!B18 -> Lost or stolen tablet or handheld exposes patient data | C19: =Inputs!C18 -> 0.7 | D19: =Inputs!D18 -> 0.3 | E19: =Inputs!J18 -> 5.1 | F19: =Inputs!E18 -> 0.25 | G19: =Inputs!F18 -> 0.55 | H19: =Inputs!H18 -> 0.6 | I19: =Inputs!G18 -> 0.45 | J19: =Parameters!$B$4 -> 0.3 | K19: =Parameters!$B$5 -> 1000 | L19: =C19*D19*E19*((F19+G19)/2)*H19/I19*K19 -> 571.2 | M19: =C19*D19*E19*J19*H19/I19*K19 -> 428.4 | N19: =L19/M19 -> 1.3333333 | O19: =Portfolio!Y27 -> 43333.333 | P19: =Inputs!K18 -> 0.75 | Q19: =Inputs!L18 -> 0.8 | R19: =L19*P19*Q19 -> 342.72 | S19: =L19-R19 -> 228.48 | T19: =S19/M19 -> 0.53333333 | U19: =IF(T19<Parameters!$B$6,"Below tolerance",IF(T19<=Parameters!$B$7,"Approximately at tolerance","Above tolerance")) -> Below tolerance | V19: =IF(O19=0,0,(L19-S19)/O19*1000) -> 7.9089231 | W19: =IF(AND(P19>=0,P19<=1,Q19>=0,Q19<=1),"OK","CHECK") -> OK
A20: =Inputs!A19 -> S16 | B20: =Inputs!B19 -> Loss of the Montreal hub or WAN isolates clinics from central clinical systems | C20: =Inputs!C19 -> 0.35 | D20: =Inputs!D19 -> 0.5 | E20: =Inputs!J19 -> 8.9 | F20: =Inputs!E19 -> 0.55 | G20: =Inputs!F19 -> 0.85 | H20: =Inputs!H19 -> 0.95 | I20: =Inputs!G19 -> 0.35 | J20: =Parameters!$B$4 -> 0.3 | K20: =Parameters!$B$5 -> 1000 | L20: =C20*D20*E20*((F20+G20)/2)*H20/I20*K20 -> 2959.25 | M20: =C20*D20*E20*J20*H20/I20*K20 -> 1268.25 | N20: =L20/M20 -> 2.3333333 | O20: =Portfolio!Z27 -> 492222.22 | P20: =Inputs!K19 -> 0.7 | Q20: =Inputs!L19 -> 0.65 | R20: =L20*P20*Q20 -> 1346.4588 | S20: =L20-R20 -> 1612.7912 | T20: =S20/M20 -> 1.2716667 | U20: =IF(T20<Parameters!$B$6,"Below tolerance",IF(T20<=Parameters!$B$7,"Approximately at tolerance","Above tolerance")) -> Above tolerance | V20: =IF(O20=0,0,(L20-S20)/O20*1000) -> 2.7354692 | W20: =IF(AND(P20>=0,P20<=1,Q20>=0,Q20<=1),"OK","CHECK") -> OK
A21: =Inputs!A20 -> S17 | B21: =Inputs!B20 -> Unmanaged patient data on local clinic storage is exposed or lost | C21: =Inputs!C20 -> 0.45 | D21: =Inputs!D20 -> 0.45 | E21: =Inputs!J20 -> 7 | F21: =Inputs!E20 -> 0.4 | G21: =Inputs!F20 -> 0.7 | H21: =Inputs!H20 -> 0.65 | I21: =Inputs!G20 -> 0.4 | J21: =Parameters!$B$4 -> 0.3 | K21: =Parameters!$B$5 -> 1000 | L21: =C21*D21*E21*((F21+G21)/2)*H21/I21*K21 -> 1266.8906 | M21: =C21*D21*E21*J21*H21/I21*K21 -> 691.03125 | N21: =L21/M21 -> 1.8333333 | O21: =Portfolio!AA27 -> 96666.667 | P21: =Inputs!K20 -> 0.7 | Q21: =Inputs!L20 -> 0.7 | R21: =L21*P21*Q21 -> 620.77641 | S21: =L21-R21 -> 646.11422 | T21: =S21/M21 -> 0.935 | U21: =IF(T21<Parameters!$B$6,"Below tolerance",IF(T21<=Parameters!$B$7,"Approximately at tolerance","Above tolerance")) -> Approximately at tolerance | V21: =IF(O21=0,0,(L21-S21)/O21*1000) -> 6.4218249 | W21: =IF(AND(P21>=0,P21<=1,Q21>=0,Q21<=1),"OK","CHECK") -> OK
A22: =Inputs!A21 -> S18 | B22: =Inputs!B21 -> Web application flaw in the patient portal exposes other patients' records | C22: =Inputs!C21 -> 0.5 | D22: =Inputs!D21 -> 0.35 | E22: =Inputs!J21 -> 7.1 | F22: =Inputs!E21 -> 0.5 | G22: =Inputs!F21 -> 0.85 | H22: =Inputs!H21 -> 0.75 | I22: =Inputs!G21 -> 0.4 | J22: =Parameters!$B$4 -> 0.3 | K22: =Parameters!$B$5 -> 1000 | L22: =C22*D22*E22*((F22+G22)/2)*H22/I22*K22 -> 1572.5391 | M22: =C22*D22*E22*J22*H22/I22*K22 -> 698.90625 | N22: =L22/M22 -> 2.25 | O22: =Portfolio!AB27 -> 264670.59 | P22: =Inputs!K21 -> 0.8 | Q22: =Inputs!L21 -> 0.6 | R22: =L22*P22*Q22 -> 754.81875 | S22: =L22-R22 -> 817.72031 | T22: =S22/M22 -> 1.17 | U22: =IF(T22<Parameters!$B$6,"Below tolerance",IF(T22<=Parameters!$B$7,"Approximately at tolerance","Above tolerance")) -> Above tolerance | V22: =IF(O22=0,0,(L22-S22)/O22*1000) -> 2.8519178 | W22: =IF(AND(P22>=0,P22<=1,Q22>=0,Q22<=1),"OK","CHECK") -> OK
A23: =Inputs!A22 -> S19 | B23: =Inputs!B22 -> Trojanized software update from a clinical or IT software supplier | C23: =Inputs!C22 -> 0.25 | D23: =Inputs!D22 -> 0.5 | E23: =Inputs!J22 -> 9.5 | F23: =Inputs!E22 -> 0.6 | G23: =Inputs!F22 -> 0.95 | H23: =Inputs!H22 -> 0.85 | I23: =Inputs!G22 -> 0.35 | J23: =Parameters!$B$4 -> 0.3 | K23: =Parameters!$B$5 -> 1000 | L23: =C23*D23*E23*((F23+G23)/2)*H23/I23*K23 -> 2235.0446 | M23: =C23*D23*E23*J23*H23/I23*K23 -> 865.17857 | N23: =L23/M23 -> 2.5833333 | O23: =Portfolio!AC27 -> 138692.81 | P23: =Inputs!K22 -> 0.4 | Q23: =Inputs!L22 -> 0.65 | R23: =L23*P23*Q23 -> 581.11161 | S23: =L23-R23 -> 1653.933 | T23: =S23/M23 -> 1.9116667 | U23: =IF(T23<Parameters!$B$6,"Below tolerance",IF(T23<=Parameters!$B$7,"Approximately at tolerance","Above tolerance")) -> Above tolerance | V23: =IF(O23=0,0,(L23-S23)/O23*1000) -> 4.1899188 | W23: =IF(AND(P23>=0,P23<=1,Q23>=0,Q23<=1),"OK","CHECK") -> OK
A24: =Inputs!A23 -> S20 | B24: =Inputs!B23 -> Takeover of cloud tenant administration through token theft or malicious app consent | C24: =Inputs!C23 -> 0.55 | D24: =Inputs!D23 -> 0.4 | E24: =Inputs!J23 -> 9.4 | F24: =Inputs!E23 -> 0.55 | G24: =Inputs!F23 -> 0.9 | H24: =Inputs!H23 -> 0.85 | I24: =Inputs!G23 -> 0.4 | J24: =Parameters!$B$4 -> 0.3 | K24: =Parameters!$B$5 -> 1000 | L24: =C24*D24*E24*((F24+G24)/2)*H24/I24*K24 -> 3186.0125 | M24: =C24*D24*E24*J24*H24/I24*K24 -> 1318.35 | N24: =L24/M24 -> 2.4166667 | O24: =Portfolio!AD27 -> 167422.97 | P24: =Inputs!K23 -> 0.8 | Q24: =Inputs!L23 -> 0.65 | R24: =L24*P24*Q24 -> 1656.7265 | S24: =L24-R24 -> 1529.286 | T24: =S24/M24 -> 1.16 | U24: =IF(T24<Parameters!$B$6,"Below tolerance",IF(T24<=Parameters!$B$7,"Approximately at tolerance","Above tolerance")) -> Above tolerance | V24: =IF(O24=0,0,(L24-S24)/O24*1000) -> 9.8954553 | W24: =IF(AND(P24>=0,P24<=1,Q24>=0,Q24<=1),"OK","CHECK") -> OK
A25: =Inputs!A24 -> S21 | B25: =Inputs!B24 -> Accidental disclosure of patient information by staff | C25: =Inputs!C24 -> 0.85 | D25: =Inputs!D24 -> 0.5 | E25: =Inputs!J24 -> 4.8 | F25: =Inputs!E24 -> 0.2 | G25: =Inputs!F24 -> 0.45 | H25: =Inputs!H24 -> 0.6 | I25: =Inputs!G24 -> 0.45 | J25: =Parameters!$B$4 -> 0.3 | K25: =Parameters!$B$5 -> 1000 | L25: =C25*D25*E25*((F25+G25)/2)*H25/I25*K25 -> 884 | M25: =C25*D25*E25*J25*H25/I25*K25 -> 816 | N25: =L25/M25 -> 1.0833333 | O25: =Portfolio!AE27 -> 127333.33 | P25: =Inputs!K24 -> 0.6 | Q25: =Inputs!L24 -> 0.55 | R25: =L25*P25*Q25 -> 291.72 | S25: =L25-R25 -> 592.28 | T25: =S25/M25 -> 0.72583333 | U25: =IF(T25<Parameters!$B$6,"Below tolerance",IF(T25<=Parameters!$B$7,"Approximately at tolerance","Above tolerance")) -> Below tolerance | V25: =IF(O25=0,0,(L25-S25)/O25*1000) -> 2.2909948 | W25: =IF(AND(P25>=0,P25<=1,Q25>=0,Q25<=1),"OK","CHECK") -> OK
A26: =Inputs!A25 -> S22 | B26: =Inputs!B25 -> Interception or exposure of teleconsultations and clinical messaging | C26: =Inputs!C25 -> 0.35 | D26: =Inputs!D25 -> 0.35 | E26: =Inputs!J25 -> 8.2 | F26: =Inputs!E25 -> 0.3 | G26: =Inputs!F25 -> 0.55 | H26: =Inputs!H25 -> 0.6 | I26: =Inputs!G25 -> 0.45 | J26: =Parameters!$B$4 -> 0.3 | K26: =Parameters!$B$5 -> 1000 | L26: =C26*D26*E26*((F26+G26)/2)*H26/I26*K26 -> 569.21667 | M26: =C26*D26*E26*J26*H26/I26*K26 -> 401.8 | N26: =L26/M26 -> 1.4166667 | O26: =Portfolio!AF27 -> 70000 | P26: =Inputs!K25 -> 0.75 | Q26: =Inputs!L25 -> 0.6 | R26: =L26*P26*Q26 -> 256.1475 | S26: =L26-R26 -> 313.06917 | T26: =S26/M26 -> 0.77916667 | U26: =IF(T26<Parameters!$B$6,"Below tolerance",IF(T26<=Parameters!$B$7,"Approximately at tolerance","Above tolerance")) -> Below tolerance | V26: =IF(O26=0,0,(L26-S26)/O26*1000) -> 3.65925 | W26: =IF(AND(P26>=0,P26<=1,Q26>=0,Q26<=1),"OK","CHECK") -> OK
A27: =Inputs!A26 -> S23 | B27: =Inputs!B26 -> Brute force or credential stuffing against exposed administrative interfaces | C27: =Inputs!C26 -> 0.7 | D27: =Inputs!D26 -> 0.35 | E27: =Inputs!J26 -> 9.5 | F27: =Inputs!E26 -> 0.6 | G27: =Inputs!F26 -> 0.9 | H27: =Inputs!H26 -> 0.85 | I27: =Inputs!G26 -> 0.4 | J27: =Parameters!$B$4 -> 0.3 | K27: =Parameters!$B$5 -> 1000 | L27: =C27*D27*E27*((F27+G27)/2)*H27/I27*K27 -> 3709.4531 | M27: =C27*D27*E27*J27*H27/I27*K27 -> 1483.7812 | N27: =L27/M27 -> 2.5 | O27: =Portfolio!AG27 -> 180622.97 | P27: =Inputs!K26 -> 0.85 | Q27: =Inputs!L26 -> 0.65 | R27: =L27*P27*Q27 -> 2049.4729 | S27: =L27-R27 -> 1659.9803 | T27: =S27/M27 -> 1.11875 | U27: =IF(T27<Parameters!$B$6,"Below tolerance",IF(T27<=Parameters!$B$7,"Approximately at tolerance","Above tolerance")) -> Above tolerance | V27: =IF(O27=0,0,(L27-S27)/O27*1000) -> 11.34669 | W27: =IF(AND(P27>=0,P27<=1,Q27>=0,Q27<=1),"OK","CHECK") -> OK
A28: =Inputs!A27 -> S24 | B28: =Inputs!B27 -> Malware introduced through patient-supplied imaging media or USB devices | C28: =Inputs!C27 -> 0.35 | D28: =Inputs!D27 -> 0.4 | E28: =Inputs!J27 -> 7 | F28: =Inputs!E27 -> 0.45 | G28: =Inputs!F27 -> 0.8 | H28: =Inputs!H27 -> 0.8 | I28: =Inputs!G27 -> 0.4 | J28: =Parameters!$B$4 -> 0.3 | K28: =Parameters!$B$5 -> 1000 | L28: =C28*D28*E28*((F28+G28)/2)*H28/I28*K28 -> 1225 | M28: =C28*D28*E28*J28*H28/I28*K28 -> 588 | N28: =L28/M28 -> 2.0833333 | O28: =Portfolio!AH27 -> 261756.3 | P28: =Inputs!K27 -> 0.75 | Q28: =Inputs!L27 -> 0.65 | R28: =L28*P28*Q28 -> 597.1875 | S28: =L28-R28 -> 627.8125 | T28: =S28/M28 -> 1.0677083 | U28: =IF(T28<Parameters!$B$6,"Below tolerance",IF(T28<=Parameters!$B$7,"Approximately at tolerance","Above tolerance")) -> Approximately at tolerance | V28: =IF(O28=0,0,(L28-S28)/O28*1000) -> 2.2814637 | W28: =IF(AND(P28>=0,P28<=1,Q28>=0,Q28<=1),"OK","CHECK") -> OK
A29: =Inputs!A28 -> S25 | B29: =Inputs!B28 -> Retired devices or medical equipment released with recoverable patient data | C29: =Inputs!C28 -> 0.4 | D29: =Inputs!D28 -> 0.35 | E29: =Inputs!J28 -> 5.1 | F29: =Inputs!E28 -> 0.35 | G29: =Inputs!F28 -> 0.65 | H29: =Inputs!H28 -> 0.55 | I29: =Inputs!G28 -> 0.45 | J29: =Parameters!$B$4 -> 0.3 | K29: =Parameters!$B$5 -> 1000 | L29: =C29*D29*E29*((F29+G29)/2)*H29/I29*K29 -> 436.33333 | M29: =C29*D29*E29*J29*H29/I29*K29 -> 261.8 | N29: =L29/M29 -> 1.6666667 | O29: =Portfolio!AI27 -> 96666.667 | P29: =Inputs!K28 -> 0.85 | Q29: =Inputs!L28 -> 0.6 | R29: =L29*P29*Q29 -> 222.53 | S29: =L29-R29 -> 213.80333 | T29: =S29/M29 -> 0.81666667 | U29: =IF(T29<Parameters!$B$6,"Below tolerance",IF(T29<=Parameters!$B$7,"Approximately at tolerance","Above tolerance")) -> Below tolerance | V29: =IF(O29=0,0,(L29-S29)/O29*1000) -> 2.3020345 | W29: =IF(AND(P29>=0,P29<=1,Q29>=0,Q29<=1),"OK","CHECK") -> OK
A30: =Inputs!A29 -> S26 | B30: =Inputs!B29 -> Staff paste patient data into unapproved generative-AI tools | C30: =Inputs!C29 -> 0.8 | D30: =Inputs!D29 -> 0.55 | E30: =Inputs!J29 -> 6 | F30: =Inputs!E29 -> 0.35 | G30: =Inputs!F29 -> 0.65 | H30: =Inputs!H29 -> 0.7 | I30: =Inputs!G29 -> 0.4 | J30: =Parameters!$B$4 -> 0.3 | K30: =Parameters!$B$5 -> 1000 | L30: =C30*D30*E30*((F30+G30)/2)*H30/I30*K30 -> 2310 | M30: =C30*D30*E30*J30*H30/I30*K30 -> 1386 | N30: =L30/M30 -> 1.6666667 | O30: =Portfolio!AJ27 -> 174000 | P30: =Inputs!K29 -> 0.65 | Q30: =Inputs!L29 -> 0.55 | R30: =L30*P30*Q30 -> 825.825 | S30: =L30-R30 -> 1484.175 | T30: =S30/M30 -> 1.0708333 | U30: =IF(T30<Parameters!$B$6,"Below tolerance",IF(T30<=Parameters!$B$7,"Approximately at tolerance","Above tolerance")) -> Approximately at tolerance | V30: =IF(O30=0,0,(L30-S30)/O30*1000) -> 4.7461207 | W30: =IF(AND(P30>=0,P30<=1,Q30>=0,Q30<=1),"OK","CHECK") -> OK
A31: =Inputs!A30 -> S27 | B31: =Inputs!B30 -> Help-desk impersonation leads to MFA reset and account takeover | C31: =Inputs!C30 -> 0.55 | D31: =Inputs!D30 -> 0.5 | E31: =Inputs!J30 -> 9.3 | F31: =Inputs!E30 -> 0.55 | G31: =Inputs!F30 -> 0.9 | H31: =Inputs!H30 -> 0.85 | I31: =Inputs!G30 -> 0.4 | J31: =Parameters!$B$4 -> 0.3 | K31: =Parameters!$B$5 -> 1000 | L31: =C31*D31*E31*((F31+G31)/2)*H31/I31*K31 -> 3940.1484 | M31: =C31*D31*E31*J31*H31/I31*K31 -> 1630.4062 | N31: =L31/M31 -> 2.4166667 | O31: =Portfolio!AK27 -> 85285.714 | P31: =Inputs!K30 -> 0.8 | Q31: =Inputs!L30 -> 0.6 | R31: =L31*P31*Q31 -> 1891.2713 | S31: =L31-R31 -> 2048.8772 | T31: =S31/M31 -> 1.2566667 | U31: =IF(T31<Parameters!$B$6,"Below tolerance",IF(T31<=Parameters!$B$7,"Approximately at tolerance","Above tolerance")) -> Above tolerance | V31: =IF(O31=0,0,(L31-S31)/O31*1000) -> 22.17571 | W31: =IF(AND(P31>=0,P31<=1,Q31>=0,Q31<=1),"OK","CHECK") -> OK
A32: =Inputs!A31 -> S28 | B32: =Inputs!B31 -> Malicious or departing IT administrator sabotages systems | C32: =Inputs!C31 -> 0.15 | D32: =Inputs!D31 -> 0.6 | E32: =Inputs!J31 -> 9.4 | F32: =Inputs!E31 -> 0.6 | G32: =Inputs!F31 -> 0.95 | H32: =Inputs!H31 -> 0.9 | I32: =Inputs!G31 -> 0.35 | J32: =Parameters!$B$4 -> 0.3 | K32: =Parameters!$B$5 -> 1000 | L32: =C32*D32*E32*((F32+G32)/2)*H32/I32*K32 -> 1685.9571 | M32: =C32*D32*E32*J32*H32/I32*K32 -> 652.62857 | N32: =L32/M32 -> 2.5833333 | O32: =Portfolio!AL27 -> 192859.48 | P32: =Inputs!K31 -> 0.55 | Q32: =Inputs!L31 -> 0.6 | R32: =L32*P32*Q32 -> 556.36586 | S32: =L32-R32 -> 1129.5913 | T32: =S32/M32 -> 1.7308333 | U32: =IF(T32<Parameters!$B$6,"Below tolerance",IF(T32<=Parameters!$B$7,"Approximately at tolerance","Above tolerance")) -> Above tolerance | V32: =IF(O32=0,0,(L32-S32)/O32*1000) -> 2.8848251 | W32: =IF(AND(P32>=0,P32<=1,Q32>=0,Q32<=1),"OK","CHECK") -> OK
A33: =Inputs!A32 -> S29 | B33: =Inputs!B32 -> Interception or tampering of unencrypted clinical interface traffic (HL7/DICOM) | C33: =Inputs!C32 -> 0.25 | D33: =Inputs!D32 -> 0.4 | E33: =Inputs!J32 -> 8.6 | F33: =Inputs!E32 -> 0.45 | G33: =Inputs!F32 -> 0.85 | H33: =Inputs!H32 -> 0.85 | I33: =Inputs!G32 -> 0.4 | J33: =Parameters!$B$4 -> 0.3 | K33: =Parameters!$B$5 -> 1000 | L33: =C33*D33*E33*((F33+G33)/2)*H33/I33*K33 -> 1187.875 | M33: =C33*D33*E33*J33*H33/I33*K33 -> 548.25 | N33: =L33/M33 -> 2.1666667 | O33: =Portfolio!AM27 -> 214285.71 | P33: =Inputs!K32 -> 0.75 | Q33: =Inputs!L32 -> 0.7 | R33: =L33*P33*Q33 -> 623.63437 | S33: =L33-R33 -> 564.24063 | T33: =S33/M33 -> 1.0291667 | U33: =IF(T33<Parameters!$B$6,"Below tolerance",IF(T33<=Parameters!$B$7,"Approximately at tolerance","Above tolerance")) -> Approximately at tolerance | V33: =IF(O33=0,0,(L33-S33)/O33*1000) -> 2.9102938 | W33: =IF(AND(P33>=0,P33<=1,Q33>=0,Q33<=1),"OK","CHECK") -> OK
A34: =Inputs!A33 -> S30 | B34: =Inputs!B33 -> Criminals impersonate MediBec to defraud or phish patients | C34: =Inputs!C33 -> 0.7 | D34: =Inputs!D33 -> 0.5 | E34: =Inputs!J33 -> 5.1 | F34: =Inputs!E33 -> 0.3 | G34: =Inputs!F33 -> 0.55 | H34: =Inputs!H33 -> 0.55 | I34: =Inputs!G33 -> 0.45 | J34: =Parameters!$B$4 -> 0.3 | K34: =Parameters!$B$5 -> 1000 | L34: =C34*D34*E34*((F34+G34)/2)*H34/I34*K34 -> 927.20833 | M34: =C34*D34*E34*J34*H34/I34*K34 -> 654.5 | N34: =L34/M34 -> 1.4166667 | O34: =Portfolio!AN27 -> 93500 | P34: =Inputs!K33 -> 0.55 | Q34: =Inputs!L33 -> 0.6 | R34: =L34*P34*Q34 -> 305.97875 | S34: =L34-R34 -> 621.22958 | T34: =S34/M34 -> 0.94916667 | U34: =IF(T34<Parameters!$B$6,"Below tolerance",IF(T34<=Parameters!$B$7,"Approximately at tolerance","Above tolerance")) -> Approximately at tolerance | V34: =IF(O34=0,0,(L34-S34)/O34*1000) -> 3.2725 | W34: =IF(AND(P34>=0,P34<=1,Q34>=0,Q34<=1),"OK","CHECK") -> OK
B35: Portfolio totals | L35: =SUM(L5:L34) -> 84305.471 | M35: =SUM(M5:M34) -> 37123.257 | O35: =SUM(O5:O34) -> 5311000 | R35: =SUM(R5:R34) -> 43282.703 | S35: =SUM(S5:S34) -> 41022.768 | T35: =S35/M35 -> 1.1050423 | V35: =(L35-S35)/O35*1000 -> 8.1496335
B37: Interpretation: Residual/Tolerated simplifies to ((de+dm)/2) x (1 - P x Q) / Appetite - CVSS, probabilities, resilience and criticality scale magnitude (ranking) but cancel out of the tolerance test.

Sheet Parameters
A1: Global parameters
A3: Parameter | B3: Value | C3: Source / note
A4: Risk appetite (analytical estimate) | B4: 0.3 | C4: Analytical estimate — validation required. Case states 0.40 normalized tolerance; see report s.4.
A5: Multiplication factor | B5: 1000 | C5: Constant across all scenarios (Excel Guide worked example).
A6: Tolerance band - lower bound of 'approximately at' | B6: 0.9 | C6: Ratio < this = below tolerance
A7: Tolerance band - upper bound of 'approximately at' | B7: 1.1 | C7: Ratio > this = above tolerance
A8: Case appetite (for comparison) | B8: 0.4 | C8: Business case s.8
A9: Sensitivity delta | B9: 0.1 | C9: Shift applied in Sensitivity sheet
A10: Case escalation - executive review threshold | B10: 0.25 | C10: Business case s.8
A11: Case escalation - Board acceptance threshold | B11: 0.4 | C11: Business case s.8

Sheet Inputs
A1: Scenario inputs (0-1 scale unless stated) - Analytical estimate — validation required
A3: ID | B3: Scenario | C3: Pb(A) | D3: Pb(psi,A) | E3: de | F3: dm | G3: theta | H3: mu(E) | I3: CVSS v4.0 vector | J3: CVSS-B | K3: Prob. reduction | L3: Impact reduction | M3: Conf Pb(A) | N3: Conf Pb(psi,A) | O3: Conf de | P3: Conf dm | Q3: Conf theta | R3: Conf mu
A4: S1 | B4: Credential compromise of clinical administrator accounts through phishing and MFA fatigue | C4: 0.85 | D4: 0.55 | E4: 0.55 | F4: 0.85 | G4: 0.4 | H4: 0.85 | I4: CVSS:4.0/AV:N/AC:L/AT:N/PR:N/UI:A/VC:H/VI:H/VA:N/SC:H/SI:L/SA:L | J4: 9.3 | K4: 0.8 | L4: 0.75 | M4: Medium | N4: Low | O4: Medium | P4: Medium | Q4: Medium | R4: High
A5: S2 | B5: Ransomware disrupting EHR access and clinic operations across the network | C5: 0.75 | D5: 0.5 | E5: 0.7 | F5: 0.95 | G5: 0.35 | H5: 0.95 | I5: CVSS:4.0/AV:L/AC:L/AT:N/PR:N/UI:P/VC:H/VI:H/VA:H/SC:H/SI:H/SA:H | J5: 9.3 | K5: 0.75 | L5: 0.75 | M5: Medium | N5: Low | O5: Medium | P5: Medium | Q5: Medium | R5: High
A6: S3 | B6: Backup environment compromised, preventing recovery after a destructive attack | C6: 0.55 | D6: 0.5 | E6: 0.6 | F6: 0.9 | G6: 0.35 | H6: 0.9 | I6: CVSS:4.0/AV:N/AC:L/AT:N/PR:H/UI:N/VC:H/VI:H/VA:H/SC:N/SI:N/SA:H | J6: 9.2 | K6: 0.8 | L6: 0.85 | M6: Medium | N6: Low | O6: Medium | P6: Medium | Q6: Medium | R6: High
A7: S4 | B7: Cloud medical-image transfer storage exposed, enabling bulk health-data exfiltration | C7: 0.6 | D7: 0.45 | E7: 0.55 | F7: 0.8 | G7: 0.4 | H7: 0.75 | I7: CVSS:4.0/AV:N/AC:L/AT:N/PR:N/UI:N/VC:H/VI:N/VA:N/SC:N/SI:N/SA:N | J7: 8.7 | K7: 0.85 | L7: 0.7 | M7: Medium | N7: Low | O7: Medium | P7: Medium | Q7: Low | R7: Medium
A8: S5 | B8: Misuse of legitimate clinical, privileged or service-account access to extract patient records | C8: 0.6 | D8: 0.55 | E8: 0.45 | F8: 0.75 | G8: 0.4 | H8: 0.8 | I8: CVSS:4.0/AV:N/AC:L/AT:N/PR:L/UI:N/VC:H/VI:L/VA:N/SC:N/SI:N/SA:N | J8: 7.1 | K8: 0.6 | L8: 0.65 | M8: Medium | N8: Medium | O8: Medium | P8: Medium | Q8: Medium | R8: High
A9: S6 | B9: Exploitation of unpatched internet-facing or end-of-life systems | C9: 0.8 | D9: 0.5 | E9: 0.6 | F9: 0.9 | G9: 0.4 | H9: 0.85 | I9: CVSS:4.0/AV:N/AC:L/AT:N/PR:N/UI:N/VC:H/VI:H/VA:H/SC:H/SI:H/SA:H | J9: 10 | K9: 0.85 | L9: 0.7 | M9: Medium | N9: Low | O9: Medium | P9: Medium | Q9: Medium | R9: High
A10: S7 | B10: Connected medical device used as a foothold to disrupt clinical equipment and reach the EHR network | C10: 0.45 | D10: 0.5 | E10: 0.55 | F10: 0.95 | G10: 0.35 | H10: 0.9 | I10: CVSS:4.0/AV:A/AC:L/AT:N/PR:N/UI:N/VC:H/VI:H/VA:H/SC:L/SI:L/SA:L | J10: 8.7 | K10: 0.7 | L10: 0.6 | M10: Low | N10: Low | O10: Medium | P10: Medium | Q10: Medium | R10: High
A11: S8 | B11: Detection and response gaps allow an intrusion to persist and escalate | C11: 0.8 | D11: 0.6 | E11: 0.6 | F11: 0.9 | G11: 0.3 | H11: 0.85 | I11: CVSS:4.0/AV:L/AC:L/AT:N/PR:N/UI:P/VC:H/VI:H/VA:L/SC:H/SI:L/SA:L | J11: 9.2 | K11: 0.7 | L11: 0.8 | M11: Medium | N11: Medium | O11: Medium | P11: Medium | Q11: Medium | R11: High
A12: S9 | B12: Compromise of a critical vendor with remote access to MediBec systems | C12: 0.55 | D12: 0.45 | E12: 0.6 | F12: 0.9 | G12: 0.35 | H12: 0.85 | I12: CVSS:4.0/AV:N/AC:L/AT:P/PR:L/UI:N/VC:H/VI:H/VA:H/SC:H/SI:H/SA:H | J12: 9 | K12: 0.55 | L12: 0.7 | M12: Low | N12: Low | O12: Medium | P12: Medium | Q12: Low | R12: High
A13: S10 | B13: Manipulation of patient, medication or billing records undermining clinical decisions | C13: 0.3 | D13: 0.4 | E13: 0.55 | F13: 0.95 | G13: 0.4 | H13: 0.95 | I13: CVSS:4.0/AV:N/AC:L/AT:N/PR:L/UI:N/VC:L/VI:H/VA:N/SC:N/SI:H/SA:N | J13: 8.3 | K13: 0.7 | L13: 0.75 | M13: Low | N13: Low | O13: Medium | P13: Medium | Q13: Low | R13: High
A14: S11 | B14: API key or secret exposed in code, logs or configuration enables direct data access | C14: 0.45 | D14: 0.45 | E14: 0.5 | F14: 0.8 | G14: 0.4 | H14: 0.75 | I14: CVSS:4.0/AV:N/AC:L/AT:P/PR:N/UI:N/VC:H/VI:L/VA:N/SC:N/SI:N/SA:N | J14: 8.3 | K14: 0.85 | L14: 0.6 | M14: Low | N14: Low | O14: Medium | P14: Medium | Q14: Low | R14: Medium
A15: S12 | B15: Clinic Wi-Fi compromise or rogue access point gives access to the clinical network | C15: 0.4 | D15: 0.45 | E15: 0.4 | F15: 0.75 | G15: 0.4 | H15: 0.7 | I15: CVSS:4.0/AV:A/AC:L/AT:N/PR:N/UI:N/VC:L/VI:L/VA:N/SC:H/SI:L/SA:L | J15: 6.4 | K15: 0.8 | L15: 0.65 | M15: Low | N15: Low | O15: Medium | P15: Medium | Q15: Low | R15: Medium
... A33: S30 | B33: Criminals impersonate MediBec to defraud or phish patients | C33: 0.7 | D33: 0.5 | E33: 0.3 | F33: 0.55 | G33: 0.45 | H33: 0.55 | I33: CVSS:4.0/AV:N/AC:L/AT:N/PR:N/UI:A/VC:L/VI:L/VA:N/SC:N/SI:N/SA:N | J33: 5.1 | K33: 0.55 | L33: 0.6 | M33: Medium | N33: Low | O33: Low | P33: Low | Q33: Low | R33: Medium

Sheet Portfolio
A1: Recommended treatment portfolio (indicative CAD estimates - not quotations or approved budgets)
A3: ID | B3: Initiative | C3: Owner | D3: Priority | E3: Type | F3: Initial cost | G3: Recurring / yr | H3: Year-1 cost | I3: # scenarios | J3: Y1 per scenario | K3: S1 | L3: S2 | M3: S3 | N3: S4 | O3: S5 | P3: S6 | Q3: S7 | R3: S8 | S3: S9 | T3: S10 | U3: S11 | V3: S12 | W3: S13 | X3: S14 | Y3: S15 | Z3: S16 | AA3: S17 | AB3: S18 | AC3: S19 | AD3: S20 | AE3: S21 | AF3: S22 | AG3: S23 | AH3: S24 | AI3: S25 | AJ3: S26 | AK3: S27 | AL3: S28 | AM3: S29 | AN3: S30 | AO3: Start | AP3: End | AQ3: Success indicator
A4: I01 | B4: Phishing-resistant MFA and conditional access | C4: CIO / Cybersecurity lead | D4: Immediate | E4: Prevention | F4: 180000 | G4: 60000 | H4: =F4+G4 -> 240000 | I4: =SUM(K4:AN4) -> 7 | J4: =IF(I4=0,0,H4/I4) -> 34285.714 | K4: 1 | L4: 0 | M4: 0 | N4: 0 | O4: 0 | P4: 0 | Q4: 0 | R4: 1 | S4: 1 | T4: 1 | U4: 0 | V4: 0 | W4: 0 | X4: 0 | Y4: 0 | Z4: 0 | AA4: 0 | AB4: 0 | AC4: 0 | AD4: 1 | AE4: 0 | AF4: 0 | AG4: 1 | AH4: 0 | AI4: 0 | AJ4: 0 | AK4: 1 | AL4: 0 | AM4: 0 | AN4: 0 | AO4: Month 0 | AP4: Month 6 | AQ4: 100% privileged and remote-access accounts on phishing-resistant MFA
A5: I02 | B5: Privileged access and service-account management (PAM) | C5: Cybersecurity lead | D5: Near-term | E5: Prevention / Governance | F5: 250000 | G5: 80000 | H5: =F5+G5 -> 330000 | I5: =SUM(K5:AN5) -> 9 | J5: =IF(I5=0,0,H5/I5) -> 36666.667 | K5: 1 | L5: 1 | M5: 1 | N5: 0 | O5: 1 | P5: 0 | Q5: 0 | R5: 0 | S5: 1 | T5: 1 | U5: 0 | V5: 0 | W5: 0 | X5: 0 | Y5: 0 | Z5: 0 | AA5: 0 | AB5: 0 | AC5: 0 | AD5: 1 | AE5: 0 | AF5: 0 | AG5: 1 | AH5: 0 | AI5: 0 | AJ5: 0 | AK5: 0 | AL5: 1 | AM5: 0 | AN5: 0 | AO5: Month 2 | AP5: Month 12 | AQ5: 0 standing domain-admin accounts; 100% service accounts vaulted
A6: I03 | B6: 24/7 managed detection and response with centralized logging | C6: Cybersecurity lead | D6: Immediate | E6: Detection / Response | F6: 200000 | G6: 420000 | H6: =F6+G6 -> 620000 | I6: =SUM(K6:AN6) -> 17 | J6: =IF(I6=0,0,H6/I6) -> 36470.588 | K6: 1 | L6: 1 | M6: 1 | N6: 1 | O6: 1 | P6: 1 | Q6: 0 | R6: 1 | S6: 1 | T6: 1 | U6: 1 | V6: 1 | W6: 0 | X6: 0 | Y6: 0 | Z6: 0 | AA6: 0 | AB6: 1 | AC6: 1 | AD6: 1 | AE6: 0 | AF6: 0 | AG6: 1 | AH6: 1 | AI6: 0 | AJ6: 0 | AK6: 0 | AL6: 1 | AM6: 0 | AN6: 0 | AO6: Month 0 | AP6: Month 6 | AQ6: MTTD < 1 h, MTTC < 4 h for high-severity alerts; >95% critical log sources
A7: I04 | B7: Immutable and isolated backup with tested recovery | C7: CIO (Infrastructure) | D7: Immediate | E7: Recovery / Resilience | F7: 300000 | G7: 90000 | H7: =F7+G7 -> 390000 | I7: =SUM(K7:AN7) -> 4 | J7: =IF(I7=0,0,H7/I7) -> 97500 | K7: 0 | L7: 1 | M7: 1 | N7: 0 | O7: 0 | P7: 0 | Q7: 0 | R7: 0 | S7: 0 | T7: 1 | U7: 0 | V7: 0 | W7: 0 | X7: 0 | Y7: 0 | Z7: 0 | AA7: 0 | AB7: 0 | AC7: 0 | AD7: 0 | AE7: 0 | AF7: 0 | AG7: 0 | AH7: 0 | AI7: 0 | AJ7: 0 | AK7: 0 | AL7: 1 | AM7: 0 | AN7: 0 | AO7: Month 0 | AP7: Month 9 | AQ7: 100% crown-jewel restore tests pass within RTO
A8: I05 | B8: Risk-based vulnerability and patch management | C8: CIO / Cybersecurity lead | D8: Near-term | E8: Prevention | F8: 150000 | G8: 216000 | H8: =F8+G8 -> 366000 | I8: =SUM(K8:AN8) -> 5 | J8: =IF(I8=0,0,H8/I8) -> 73200 | K8: 0 | L8: 1 | M8: 0 | N8: 0 | O8: 0 | P8: 1 | Q8: 1 | R8: 0 | S8: 0 | T8: 0 | U8: 0 | V8: 0 | W8: 0 | X8: 0 | Y8: 0 | Z8: 0 | AA8: 0 | AB8: 1 | AC8: 0 | AD8: 0 | AE8: 0 | AF8: 0 | AG8: 1 | AH8: 0 | AI8: 0 | AJ8: 0 | AK8: 0 | AL8: 0 | AM8: 0 | AN8: 0 | AO8: Month 1 | AP8: Month 9 | AQ8: >95% critical vulns remediated within SLA; 0 unsupported internet-facing systems
A9: I06 | B9: Network segmentation and network access control | C9: CIO (Infrastructure) | D9: Planned | E9: Prevention / Resilience | F9: 450000 | G9: 70000 | H9: =F9+G9 -> 520000 | I9: =SUM(K9:AN9) -> 7 | J9: =IF(I9=0,0,H9/I9) -> 74285.714 | K9: 0 | L9: 1 | M9: 1 | N9: 0 | O9: 0 | P9: 1 | Q9: 1 | R9: 0 | S9: 0 | T9: 0 | U9: 0 | V9: 1 | W9: 0 | X9: 0 | Y9: 0 | Z9: 0 | AA9: 0 | AB9: 0 | AC9: 0 | AD9: 0 | AE9: 0 | AF9: 0 | AG9: 0 | AH9: 1 | AI9: 0 | AJ9: 0 | AK9: 0 | AL9: 0 | AM9: 1 | AN9: 0 | AO9: Month 6 | AP9: Month 24 | AQ9: 100% medical devices and guest Wi-Fi in isolated segments
A10: I07 | B10: Medical device security programme | C10: Biomedical engineering / Clinical Ops | D10: Near-term | E10: Identify / Detection | F10: 180000 | G10: 90000 | H10: =F10+G10 -> 270000 | I10: =SUM(K10:AN10) -> 2 | J10: =IF(I10=0,0,H10/I10) -> 135000 | K10: 0 | L10: 0 | M10: 0 | N10: 0 | O10: 0 | P10: 0 | Q10: 1 | R10: 0 | S10: 0 | T10: 0 | U10: 0 | V10: 0 | W10: 0 | X10: 0 | Y10: 0 | Z10: 0 | AA10: 0 | AB10: 0 | AC10: 0 | AD10: 0 | AE10: 0 | AF10: 0 | AG10: 0 | AH10: 1 | AI10: 0 | AJ10: 0 | AK10: 0 | AL10: 0 | AM10: 0 | AN10: 0 | AO10: Month 3 | AP10: Month 12 | AQ10: 100% networked devices inventoried and risk-rated
A11: I08 | B11: Cloud security posture and secure image transfer | C11: CIO / Radiology lead | D11: Immediate | E11: Prevention / Detection | F11: 120000 | G11: 60000 | H11: =F11+G11 -> 180000 | I11: =SUM(K11:AN11) -> 3 | J11: =IF(I11=0,0,H11/I11) -> 60000 | K11: 0 | L11: 0 | M11: 0 | N11: 1 | O11: 0 | P11: 0 | Q11: 0 | R11: 0 | S11: 0 | T11: 0 | U11: 1 | V11: 0 | W11: 0 | X11: 0 | Y11: 0 | Z11: 0 | AA11: 0 | AB11: 0 | AC11: 0 | AD11: 1 | AE11: 0 | AF11: 0 | AG11: 0 | AH11: 0 | AI11: 0 | AJ11: 0 | AK11: 0 | AL11: 0 | AM11: 0 | AN11: 0 | AO11: Month 0 | AP11: Month 6 | AQ11: 0 publicly accessible storage objects; 100% object access logged
A12: I09 | B12: Data access governance and EHR privacy monitoring | C12: Privacy officer / CIO | D12: Near-term | E12: Governance / Detection | F12: 200000 | G12: 90000 | H12: =F12+G12 -> 290000 | I12: =SUM(K12:AN12) -> 5 | J12: =IF(I12=0,0,H12/I12) -> 58000 | K12: 0 | L12: 0 | M12: 0 | N12: 1 | O12: 1 | P12: 0 | Q12: 0 | R12: 0 | S12: 0 | T12: 1 | U12: 0 | V12: 0 | W12: 0 | X12: 0 | Y12: 0 | Z12: 0 | AA12: 0 | AB12: 0 | AC12: 0 | AD12: 0 | AE12: 1 | AF12: 0 | AG12: 0 | AH12: 0 | AI12: 0 | AJ12: 1 | AK12: 0 | AL12: 0 | AM12: 0 | AN12: 0 | AO12: Month 3 | AP12: Month 12 | AQ12: 100% EHR roles recertified quarterly; bulk-access alerts reviewed within 24 h
A13: I10 | B13: Third-party cyber risk management | C13: Procurement / Cybersecurity lead | D13: Near-term | E13: Governance | F13: 90000 | G13: 70000 | H13: =F13+G13 -> 160000 | I13: =SUM(K13:AN13) -> 2 | J13: =IF(I13=0,0,H13/I13) -> 80000 | K13: 0 | L13: 0 | M13: 0 | N13: 0 | O13: 0 | P13: 0 | Q13: 0 | R13: 0 | S13: 1 | T13: 0 | U13: 0 | V13: 0 | W13: 0 | X13: 0 | Y13: 0 | Z13: 0 | AA13: 0 | AB13: 0 | AC13: 1 | AD13: 0 | AE13: 0 | AF13: 0 | AG13: 0 | AH13: 0 | AI13: 0 | AJ13: 0 | AK13: 0 | AL13: 0 | AM13: 0 | AN13: 0 | AO13: Month 2 | AP13: Month 12 | AQ13: 100% critical vendors assessed and under revised clauses
A14: I11 | B14: Incident response and clinical continuity readiness | C14: Cybersecurity lead / Clinical Ops | D14: Immediate | E14: Response / Resilience | F14: 120000 | G14: 80000 | H14: =F14+G14 -> 200000 | I14: =SUM(K14:AN14) -> 9 | J14: =IF(I14=0,0,H14/I14) -> 22222.222 | K14: 0 | L14: 1 | M14: 1 | N14: 0 | O14: 0 | P14: 0 | Q14: 0 | R14: 1 | S14: 1 | T14: 1 | U14: 0 | V14: 0 | W14: 1 | X14: 0 | Y14: 0 | Z14: 1 | AA14: 0 | AB14: 0 | AC14: 1 | AD14: 0 | AE14: 0 | AF14: 0 | AG14: 0 | AH14: 0 | AI14: 0 | AJ14: 0 | AK14: 0 | AL14: 1 | AM14: 0 | AN14: 0 | AO14: Month 0 | AP14: Month 6 | AQ14: 2 tabletops/year; all 10 clinics with tested downtime procedures
A15: I12 | B15: Governance, awareness and risk reporting | C15: Cybersecurity lead / Executive sponsor | D15: Immediate | E15: Governance | F15: 70000 | G15: 90000 | H15: =F15+G15 -> 160000 | I15: =SUM(K15:AN15) -> 10 | J15: =IF(I15=0,0,H15/I15) -> 16000 | K15: 1 | L15: 1 | M15: 0 | N15: 0 | O15: 1 | P15: 0 | Q15: 0 | R15: 1 | S15: 0 | T15: 0 | U15: 0 | V15: 0 | W15: 0 | X15: 1 | Y15: 0 | Z15: 0 | AA15: 0 | AB15: 0 | AC15: 0 | AD15: 0 | AE15: 1 | AF15: 0 | AG15: 0 | AH15: 1 | AI15: 0 | AJ15: 1 | AK15: 1 | AL15: 0 | AM15: 0 | AN15: 1 | AO15: Month 0 | AP15: Month 3 | AQ15: Quarterly KRI report delivered; phishing report rate > 70%
... A26: I23 | B26: Brand protection and patient anti-fraud communication | C26: Communications lead | D26: Immediate | E26: Detection / Response | F26: 25000 | G26: 30000 | H26: =F26+G26 -> 55000 | I26: =SUM(K26:AN26) -> 1 | J26: =IF(I26=0,0,H26/I26) -> 55000 | K26: 0 | L26: 0 | M26: 0 | N26: 0 | O26: 0 | P26: 0 | Q26: 0 | R26: 0 | S26: 0 | T26: 0 | U26: 0 | V26: 0 | W26: 0 | X26: 0 | Y26: 0 | Z26: 0 | AA26: 0 | AB26: 0 | AC26: 0 | AD26: 0 | AE26: 0 | AF26: 0 | AG26: 0 | AH26: 0 | AI26: 0 | AJ26: 0 | AK26: 0 | AL26: 0 | AM26: 0 | AN26: 1 | AO26: Month 0 | AP26: Month 3 | AQ26: Takedown within 48 h of detection; patient notice published
B27: TOTAL (each initiative counted once) | F27: =SUM(F4:F26) -> 3390000 | G27: =SUM(G4:G26) -> 1921000 | H27: =SUM(H4:H26) -> 5311000 | K27: =SUMPRODUCT(K4:K26,$J$4:$J$26) -> 123422.97 | L27: =SUMPRODUCT(L4:L26,$J$4:$J$26) -> 356345.19 | M27: =SUMPRODUCT(M4:M26,$J$4:$J$26) -> 267145.19 | N27: =SUMPRODUCT(N4:N26,$J$4:$J$26) -> 154470.59 | O27: =SUMPRODUCT(O4:O26,$J$4:$J$26) -> 147137.25 | P27: =SUMPRODUCT(P4:P26,$J$4:$J$26) -> 183956.3 | Q27: =SUMPRODUCT(Q4:Q26,$J$4:$J$26) -> 282485.71 | R27: =SUMPRODUCT(R4:R26,$J$4:$J$26) -> 108978.52 | ... AN27: =SUMPRODUCT(AN4:AN26,$J$4:$J$26) -> 93500
B28: Check: sum of scenario allocations - portfolio Year-1 total (should be 0) | H28: =SUM(K27:AN27)-H27 -> 0
B30: Allocation assumption: each initiative's Year-1 cost is split equally across the scenarios it addresses, so shared controls are never charged in full to several scenarios.
B31: Cyber-insurance premium is excluded (Information gap — organizational validation required: broker quotation required).

Sheet Sensitivity
A1: Sensitivity - lower / central / higher cases
A2: Lower case: Pb(A), Pb(psi,A), de, dm -delta; theta +delta; reductions +delta. Higher case: the reverse. Values clamped to [0.05, 0.99].
A4: ID | B4: Case | C4: Shift | D4: Pb(A) | E4: Pb(psi,A) | F4: de | G4: dm | H4: theta | I4: mu | J4: CVSS | K4: P red | L4: I red | M4: Estimated | N4: Tolerated | O4: Residual | P4: Ratio | Q4: Classification
A5: S2 | B5: Lower | C5: =-1*Parameters!$B$9 -> -0.1 | D5: =MAX(0.05,MIN(0.99,Inputs!C5+C5)) -> 0.65 | E5: =MAX(0.05,MIN(0.99,Inputs!D5+C5)) -> 0.4 | F5: =MAX(0.05,MIN(0.99,Inputs!E5+C5)) -> 0.6 | G5: =MAX(0.05,MIN(0.99,Inputs!F5+C5)) -> 0.85 | H5: =MAX(0.05,MIN(0.99,Inputs!G5-C5)) -> 0.45 | I5: =Inputs!H5 -> 0.95 | J5: =Inputs!J5 -> 9.3 | K5: =MAX(0.05,MIN(0.99,Inputs!K5-C5)) -> 0.85 | L5: =MAX(0.05,MIN(0.99,Inputs!L5-C5)) -> 0.85 | M5: =D5*E5*J5*((F5+G5)/2)*I5/H5*Parameters!$B$5 -> 3700.8833 | N5: =D5*E5*J5*Parameters!$B$4*I5/H5*Parameters!$B$5 -> 1531.4 | O5: =M5-M5*K5*L5 -> 1026.9951 | P5: =O5/N5 -> 0.670625 | Q5: =IF(P5<Parameters!$B$6,"Below tolerance",IF(P5<=Parameters!$B$7,"Approximately at tolerance","Above tolerance")) -> Below tolerance
A6: S2 | B6: Central | C6: =0*Parameters!$B$9 -> 0 | D6: =MAX(0.05,MIN(0.99,Inputs!C5+C6)) -> 0.75 | E6: =MAX(0.05,MIN(0.99,Inputs!D5+C6)) -> 0.5 | F6: =MAX(0.05,MIN(0.99,Inputs!E5+C6)) -> 0.7 | G6: =MAX(0.05,MIN(0.99,Inputs!F5+C6)) -> 0.95 | H6: =MAX(0.05,MIN(0.99,Inputs!G5-C6)) -> 0.35 | I6: =Inputs!H5 -> 0.95 | J6: =Inputs!J5 -> 9.3 | K6: =MAX(0.05,MIN(0.99,Inputs!K5-C6)) -> 0.75 | L6: =MAX(0.05,MIN(0.99,Inputs!L5-C6)) -> 0.75 | M6: =D6*E6*J6*((F6+G6)/2)*I6/H6*Parameters!$B$5 -> 7809.5089 | N6: =D6*E6*J6*Parameters!$B$4*I6/H6*Parameters!$B$5 -> 2839.8214 | O6: =M6-M6*K6*L6 -> 3416.6602 | P6: =O6/N6 -> 1.203125 | Q6: =IF(P6<Parameters!$B$6,"Below tolerance",IF(P6<=Parameters!$B$7,"Approximately at tolerance","Above tolerance")) -> Above tolerance
A7: S2 | B7: Higher | C7: =1*Parameters!$B$9 -> 0.1 | D7: =MAX(0.05,MIN(0.99,Inputs!C5+C7)) -> 0.85 | E7: =MAX(0.05,MIN(0.99,Inputs!D5+C7)) -> 0.6 | F7: =MAX(0.05,MIN(0.99,Inputs!E5+C7)) -> 0.8 | G7: =MAX(0.05,MIN(0.99,Inputs!F5+C7)) -> 0.99 | H7: =MAX(0.05,MIN(0.99,Inputs!G5-C7)) -> 0.25 | I7: =Inputs!H5 -> 0.95 | J7: =Inputs!J5 -> 9.3 | K7: =MAX(0.05,MIN(0.99,Inputs!K5-C7)) -> 0.65 | L7: =MAX(0.05,MIN(0.99,Inputs!L5-C7)) -> 0.65 | M7: =D7*E7*J7*((F7+G7)/2)*I7/H7*Parameters!$B$5 -> 16130.943 | N7: =D7*E7*J7*Parameters!$B$4*I7/H7*Parameters!$B$5 -> 5407.02 | O7: =M7-M7*K7*L7 -> 9315.6196 | P7: =O7/N7 -> 1.722875 | Q7: =IF(P7<Parameters!$B$6,"Below tolerance",IF(P7<=Parameters!$B$7,"Approximately at tolerance","Above tolerance")) -> Above tolerance
A8: S8 | B8: Lower | C8: =-1*Parameters!$B$9 -> -0.1 | D8: =MAX(0.05,MIN(0.99,Inputs!C11+C8)) -> 0.7 | E8: =MAX(0.05,MIN(0.99,Inputs!D11+C8)) -> 0.5 | F8: =MAX(0.05,MIN(0.99,Inputs!E11+C8)) -> 0.5 | G8: =MAX(0.05,MIN(0.99,Inputs!F11+C8)) -> 0.8 | H8: =MAX(0.05,MIN(0.99,Inputs!G11-C8)) -> 0.4 | I8: =Inputs!H11 -> 0.85 | J8: =Inputs!J11 -> 9.2 | K8: =MAX(0.05,MIN(0.99,Inputs!K11-C8)) -> 0.8 | L8: =MAX(0.05,MIN(0.99,Inputs!L11-C8)) -> 0.9 | M8: =D8*E8*J8*((F8+G8)/2)*I8/H8*Parameters!$B$5 -> 4447.625 | N8: =D8*E8*J8*Parameters!$B$4*I8/H8*Parameters!$B$5 -> 2052.75 | O8: =M8-M8*K8*L8 -> 1245.335 | P8: =O8/N8 -> 0.60666667 | Q8: =IF(P8<Parameters!$B$6,"Below tolerance",IF(P8<=Parameters!$B$7,"Approximately at tolerance","Above tolerance")) -> Below tolerance
A9: S8 | B9: Central | C9: =0*Parameters!$B$9 -> 0 | D9: =MAX(0.05,MIN(0.99,Inputs!C11+C9)) -> 0.8 | E9: =MAX(0.05,MIN(0.99,Inputs!D11+C9)) -> 0.6 | F9: =MAX(0.05,MIN(0.99,Inputs!E11+C9)) -> 0.6 | G9: =MAX(0.05,MIN(0.99,Inputs!F11+C9)) -> 0.9 | H9: =MAX(0.05,MIN(0.99,Inputs!G11-C9)) -> 0.3 | I9: =Inputs!H11 -> 0.85 | J9: =Inputs!J11 -> 9.2 | K9: =MAX(0.05,MIN(0.99,Inputs!K11-C9)) -> 0.7 | L9: =MAX(0.05,MIN(0.99,Inputs!L11-C9)) -> 0.8 | M9: =D9*E9*J9*((F9+G9)/2)*I9/H9*Parameters!$B$5 -> 9384 | N9: =D9*E9*J9*Parameters!$B$4*I9/H9*Parameters!$B$5 -> 3753.6 | O9: =M9-M9*K9*L9 -> 4128.96 | P9: =O9/N9 -> 1.1 | Q9: =IF(P9<Parameters!$B$6,"Below tolerance",IF(P9<=Parameters!$B$7,"Approximately at tolerance","Above tolerance")) -> Approximately at tolerance
A10: S8 | B10: Higher | C10: =1*Parameters!$B$9 -> 0.1 | D10: =MAX(0.05,MIN(0.99,Inputs!C11+C10)) -> 0.9 | E10: =MAX(0.05,MIN(0.99,Inputs!D11+C10)) -> 0.7 | F10: =MAX(0.05,MIN(0.99,Inputs!E11+C10)) -> 0.7 | G10: =MAX(0.05,MIN(0.99,Inputs!F11+C10)) -> 0.99 | H10: =MAX(0.05,MIN(0.99,Inputs!G11-C10)) -> 0.2 | I10: =Inputs!H11 -> 0.85 | J10: =Inputs!J11 -> 9.2 | K10: =MAX(0.05,MIN(0.99,Inputs!K11-C10)) -> 0.6 | L10: =MAX(0.05,MIN(0.99,Inputs!L11-C10)) -> 0.7 | M10: =D10*E10*J10*((F10+G10)/2)*I10/H10*Parameters!$B$5 -> 20814.885 | N10: =D10*E10*J10*Parameters!$B$4*I10/H10*Parameters!$B$5 -> 7389.9 | O10: =M10-M10*K10*L10 -> 12072.633 | P10: =O10/N10 -> 1.6336667 | Q10: =IF(P10<Parameters!$B$6,"Below tolerance",IF(P10<=Parameters!$B$7,"Approximately at tolerance","Above tolerance")) -> Above tolerance
A11: S1 | B11: Lower | C11: =-1*Parameters!$B$9 -> -0.1 | D11: =MAX(0.05,MIN(0.99,Inputs!C4+C11)) -> 0.75 | E11: =MAX(0.05,MIN(0.99,Inputs!D4+C11)) -> 0.45 | F11: =MAX(0.05,MIN(0.99,Inputs!E4+C11)) -> 0.45 | G11: =MAX(0.05,MIN(0.99,Inputs!F4+C11)) -> 0.75 | H11: =MAX(0.05,MIN(0.99,Inputs!G4-C11)) -> 0.5 | I11: =Inputs!H4 -> 0.85 | J11: =Inputs!J4 -> 9.3 | K11: =MAX(0.05,MIN(0.99,Inputs!K4-C11)) -> 0.9 | L11: =MAX(0.05,MIN(0.99,Inputs!L4-C11)) -> 0.85 | M11: =D11*E11*J11*((F11+G11)/2)*I11/H11*Parameters!$B$5 -> 3201.525 | N11: =D11*E11*J11*Parameters!$B$4*I11/H11*Parameters!$B$5 -> 1600.7625 | O11: =M11-M11*K11*L11 -> 752.35838 | P11: =O11/N11 -> 0.47 | Q11: =IF(P11<Parameters!$B$6,"Below tolerance",IF(P11<=Parameters!$B$7,"Approximately at tolerance","Above tolerance")) -> Below tolerance
A12: S1 | B12: Central | C12: =0*Parameters!$B$9 -> 0 | D12: =MAX(0.05,MIN(0.99,Inputs!C4+C12)) -> 0.85 | E12: =MAX(0.05,MIN(0.99,Inputs!D4+C12)) -> 0.55 | F12: =MAX(0.05,MIN(0.99,Inputs!E4+C12)) -> 0.55 | G12: =MAX(0.05,MIN(0.99,Inputs!F4+C12)) -> 0.85 | H12: =MAX(0.05,MIN(0.99,Inputs!G4-C12)) -> 0.4 | I12: =Inputs!H4 -> 0.85 | J12: =Inputs!J4 -> 9.3 | K12: =MAX(0.05,MIN(0.99,Inputs!K4-C12)) -> 0.8 | L12: =MAX(0.05,MIN(0.99,Inputs!L4-C12)) -> 0.75 | M12: =D12*E12*J12*((F12+G12)/2)*I12/H12*Parameters!$B$5 -> 6467.2781 | N12: =D12*E12*J12*Parameters!$B$4*I12/H12*Parameters!$B$5 -> 2771.6906 | O12: =M12-M12*K12*L12 -> 2586.9113 | P12: =O12/N12 -> 0.93333333 | Q12: =IF(P12<Parameters!$B$6,"Below tolerance",IF(P12<=Parameters!$B$7,"Approximately at tolerance","Above tolerance")) -> Approximately at tolerance
A13: S1 | B13: Higher | C13: =1*Parameters!$B$9 -> 0.1 | D13: =MAX(0.05,MIN(0.99,Inputs!C4+C13)) -> 0.95 | E13: =MAX(0.05,MIN(0.99,Inputs!D4+C13)) -> 0.65 | F13: =MAX(0.05,MIN(0.99,Inputs!E4+C13)) -> 0.65 | G13: =MAX(0.05,MIN(0.99,Inputs!F4+C13)) -> 0.95 | H13: =MAX(0.05,MIN(0.99,Inputs!G4-C13)) -> 0.3 | I13: =Inputs!H4 -> 0.85 | J13: =Inputs!J4 -> 9.3 | K13: =MAX(0.05,MIN(0.99,Inputs!K4-C13)) -> 0.7 | L13: =MAX(0.05,MIN(0.99,Inputs!L4-C13)) -> 0.65 | M13: =D13*E13*J13*((F13+G13)/2)*I13/H13*Parameters!$B$5 -> 13016.9 | N13: =D13*E13*J13*Parameters!$B$4*I13/H13*Parameters!$B$5 -> 4881.3375 | O13: =M13-M13*K13*L13 -> 7094.2105 | P13: =O13/N13 -> 1.4533333 | Q13: =IF(P13<Parameters!$B$6,"Below tolerance",IF(P13<=Parameters!$B$7,"Approximately at tolerance","Above tolerance")) -> Above tolerance
A14: S7 | B14: Lower | C14: =-1*Parameters!$B$9 -> -0.1 | D14: =MAX(0.05,MIN(0.99,Inputs!C10+C14)) -> 0.35 | E14: =MAX(0.05,MIN(0.99,Inputs!D10+C14)) -> 0.4 | F14: =MAX(0.05,MIN(0.99,Inputs!E10+C14)) -> 0.45 | G14: =MAX(0.05,MIN(0.99,Inputs!F10+C14)) -> 0.85 | H14: =MAX(0.05,MIN(0.99,Inputs!G10-C14)) -> 0.45 | I14: =Inputs!H10 -> 0.9 | J14: =Inputs!J10 -> 8.7 | K14: =MAX(0.05,MIN(0.99,Inputs!K10-C14)) -> 0.8 | L14: =MAX(0.05,MIN(0.99,Inputs!L10-C14)) -> 0.7 | M14: =D14*E14*J14*((F14+G14)/2)*I14/H14*Parameters!$B$5 -> 1583.4 | N14: =D14*E14*J14*Parameters!$B$4*I14/H14*Parameters!$B$5 -> 730.8 | O14: =M14-M14*K14*L14 -> 696.696 | P14: =O14/N14 -> 0.95333333 | Q14: =IF(P14<Parameters!$B$6,"Below tolerance",IF(P14<=Parameters!$B$7,"Approximately at tolerance","Above tolerance")) -> Approximately at tolerance
A15: S7 | B15: Central | C15: =0*Parameters!$B$9 -> 0 | D15: =MAX(0.05,MIN(0.99,Inputs!C10+C15)) -> 0.45 | E15: =MAX(0.05,MIN(0.99,Inputs!D10+C15)) -> 0.5 | F15: =MAX(0.05,MIN(0.99,Inputs!E10+C15)) -> 0.55 | G15: =MAX(0.05,MIN(0.99,Inputs!F10+C15)) -> 0.95 | H15: =MAX(0.05,MIN(0.99,Inputs!G10-C15)) -> 0.35 | I15: =Inputs!H10 -> 0.9 | J15: =Inputs!J10 -> 8.7 | K15: =MAX(0.05,MIN(0.99,Inputs!K10-C15)) -> 0.7 | L15: =MAX(0.05,MIN(0.99,Inputs!L10-C15)) -> 0.6 | M15: =D15*E15*J15*((F15+G15)/2)*I15/H15*Parameters!$B$5 -> 3775.1786 | N15: =D15*E15*J15*Parameters!$B$4*I15/H15*Parameters!$B$5 -> 1510.0714 | O15: =M15-M15*K15*L15 -> 2189.6036 | P15: =O15/N15 -> 1.45 | Q15: =IF(P15<Parameters!$B$6,"Below tolerance",IF(P15<=Parameters!$B$7,"Approximately at tolerance","Above tolerance")) -> Above tolerance
A16: S7 | B16: Higher | C16: =1*Parameters!$B$9 -> 0.1 | D16: =MAX(0.05,MIN(0.99,Inputs!C10+C16)) -> 0.55 | E16: =MAX(0.05,MIN(0.99,Inputs!D10+C16)) -> 0.6 | F16: =MAX(0.05,MIN(0.99,Inputs!E10+C16)) -> 0.65 | G16: =MAX(0.05,MIN(0.99,Inputs!F10+C16)) -> 0.99 | H16: =MAX(0.05,MIN(0.99,Inputs!G10-C16)) -> 0.25 | I16: =Inputs!H10 -> 0.9 | J16: =Inputs!J10 -> 8.7 | K16: =MAX(0.05,MIN(0.99,Inputs!K10-C16)) -> 0.6 | L16: =MAX(0.05,MIN(0.99,Inputs!L10-C16)) -> 0.5 | M16: =D16*E16*J16*((F16+G16)/2)*I16/H16*Parameters!$B$5 -> 8475.192 | N16: =D16*E16*J16*Parameters!$B$4*I16/H16*Parameters!$B$5 -> 3100.68 | O16: =M16-M16*K16*L16 -> 5932.6344 | P16: =O16/N16 -> 1.9133333 | Q16: =IF(P16<Parameters!$B$6,"Below tolerance",IF(P16<=Parameters!$B$7,"Approximately at tolerance","Above tolerance")) -> Above tolerance
A17: S9 | B17: Lower | C17: =-1*Parameters!$B$9 -> -0.1 | D17: =MAX(0.05,MIN(0.99,Inputs!C12+C17)) -> 0.45 | E17: =MAX(0.05,MIN(0.99,Inputs!D12+C17)) -> 0.35 | F17: =MAX(0.05,MIN(0.99,Inputs!E12+C17)) -> 0.5 | G17: =MAX(0.05,MIN(0.99,Inputs!F12+C17)) -> 0.8 | H17: =MAX(0.05,MIN(0.99,Inputs!G12-C17)) -> 0.45 | I17: =Inputs!H12 -> 0.85 | J17: =Inputs!J12 -> 9 | K17: =MAX(0.05,MIN(0.99,Inputs!K12-C17)) -> 0.65 | L17: =MAX(0.05,MIN(0.99,Inputs!L12-C17)) -> 0.8 | M17: =D17*E17*J17*((F17+G17)/2)*I17/H17*Parameters!$B$5 -> 1740.375 | N17: =D17*E17*J17*Parameters!$B$4*I17/H17*Parameters!$B$5 -> 803.25 | O17: =M17-M17*K17*L17 -> 835.38 | P17: =O17/N17 -> 1.04 | Q17: =IF(P17<Parameters!$B$6,"Below tolerance",IF(P17<=Parameters!$B$7,"Approximately at tolerance","Above tolerance")) -> Approximately at tolerance
A18: S9 | B18: Central | C18: =0*Parameters!$B$9 -> 0 | D18: =MAX(0.05,MIN(0.99,Inputs!C12+C18)) -> 0.55 | E18: =MAX(0.05,MIN(0.99,Inputs!D12+C18)) -> 0.45 | F18: =MAX(0.05,MIN(0.99,Inputs!E12+C18)) -> 0.6 | G18: =MAX(0.05,MIN(0.99,Inputs!F12+C18)) -> 0.9 | H18: =MAX(0.05,MIN(0.99,Inputs!G12-C18)) -> 0.35 | I18: =Inputs!H12 -> 0.85 | J18: =Inputs!J12 -> 9 | K18: =MAX(0.05,MIN(0.99,Inputs!K12-C18)) -> 0.55 | L18: =MAX(0.05,MIN(0.99,Inputs!L12-C18)) -> 0.7 | M18: =D18*E18*J18*((F18+G18)/2)*I18/H18*Parameters!$B$5 -> 4057.2321 | N18: =D18*E18*J18*Parameters!$B$4*I18/H18*Parameters!$B$5 -> 1622.8929 | O18: =M18-M18*K18*L18 -> 2495.1978 | P18: =O18/N18 -> 1.5375 | Q18: =IF(P18<Parameters!$B$6,"Below tolerance",IF(P18<=Parameters!$B$7,"Approximately at tolerance","Above tolerance")) -> Above tolerance
A19: S9 | B19: Higher | C19: =1*Parameters!$B$9 -> 0.1 | D19: =MAX(0.05,MIN(0.99,Inputs!C12+C19)) -> 0.65 | E19: =MAX(0.05,MIN(0.99,Inputs!D12+C19)) -> 0.55 | F19: =MAX(0.05,MIN(0.99,Inputs!E12+C19)) -> 0.7 | G19: =MAX(0.05,MIN(0.99,Inputs!F12+C19)) -> 0.99 | H19: =MAX(0.05,MIN(0.99,Inputs!G12-C19)) -> 0.25 | I19: =Inputs!H12 -> 0.85 | J19: =Inputs!J12 -> 9 | K19: =MAX(0.05,MIN(0.99,Inputs!K12-C19)) -> 0.45 | L19: =MAX(0.05,MIN(0.99,Inputs!L12-C19)) -> 0.6 | M19: =D19*E19*J19*((F19+G19)/2)*I19/H19*Parameters!$B$5 -> 9243.8775 | N19: =D19*E19*J19*Parameters!$B$4*I19/H19*Parameters!$B$5 -> 3281.85 | O19: =M19-M19*K19*L19 -> 6748.0306 | P19: =O19/N19 -> 2.0561667 | Q19: =IF(P19<Parameters!$B$6,"Below tolerance",IF(P19<=Parameters!$B$7,"Approximately at tolerance","Above tolerance")) -> Above tolerance
A20: S16 | B20: Lower | C20: =-1*Parameters!$B$9 -> -0.1 | D20: =MAX(0.05,MIN(0.99,Inputs!C19+C20)) -> 0.25 | E20: =MAX(0.05,MIN(0.99,Inputs!D19+C20)) -> 0.4 | F20: =MAX(0.05,MIN(0.99,Inputs!E19+C20)) -> 0.45 | G20: =MAX(0.05,MIN(0.99,Inputs!F19+C20)) -> 0.75 | H20: =MAX(0.05,MIN(0.99,Inputs!G19-C20)) -> 0.45 | I20: =Inputs!H19 -> 0.95 | J20: =Inputs!J19 -> 8.9 | K20: =MAX(0.05,MIN(0.99,Inputs!K19-C20)) -> 0.8 | L20: =MAX(0.05,MIN(0.99,Inputs!L19-C20)) -> 0.75 | M20: =D20*E20*J20*((F20+G20)/2)*I20/H20*Parameters!$B$5 -> 1127.3333 | N20: =D20*E20*J20*Parameters!$B$4*I20/H20*Parameters!$B$5 -> 563.66667 | O20: =M20-M20*K20*L20 -> 450.93333 | P20: =O20/N20 -> 0.8 | Q20: =IF(P20<Parameters!$B$6,"Below tolerance",IF(P20<=Parameters!$B$7,"Approximately at tolerance","Above tolerance")) -> Below tolerance
A21: S16 | B21: Central | C21: =0*Parameters!$B$9 -> 0 | D21: =MAX(0.05,MIN(0.99,Inputs!C19+C21)) -> 0.35 | E21: =MAX(0.05,MIN(0.99,Inputs!D19+C21)) -> 0.5 | F21: =MAX(0.05,MIN(0.99,Inputs!E19+C21)) -> 0.55 | G21: =MAX(0.05,MIN(0.99,Inputs!F19+C21)) -> 0.85 | H21: =MAX(0.05,MIN(0.99,Inputs!G19-C21)) -> 0.35 | I21: =Inputs!H19 -> 0.95 | J21: =Inputs!J19 -> 8.9 | K21: =MAX(0.05,MIN(0.99,Inputs!K19-C21)) -> 0.7 | L21: =MAX(0.05,MIN(0.99,Inputs!L19-C21)) -> 0.65 | M21: =D21*E21*J21*((F21+G21)/2)*I21/H21*Parameters!$B$5 -> 2959.25 | N21: =D21*E21*J21*Parameters!$B$4*I21/H21*Parameters!$B$5 -> 1268.25 | O21: =M21-M21*K21*L21 -> 1612.7912 | P21: =O21/N21 -> 1.2716667 | Q21: =IF(P21<Parameters!$B$6,"Below tolerance",IF(P21<=Parameters!$B$7,"Approximately at tolerance","Above tolerance")) -> Above tolerance
A22: S16 | B22: Higher | C22: =1*Parameters!$B$9 -> 0.1 | D22: =MAX(0.05,MIN(0.99,Inputs!C19+C22)) -> 0.45 | E22: =MAX(0.05,MIN(0.99,Inputs!D19+C22)) -> 0.6 | F22: =MAX(0.05,MIN(0.99,Inputs!E19+C22)) -> 0.65 | G22: =MAX(0.05,MIN(0.99,Inputs!F19+C22)) -> 0.95 | H22: =MAX(0.05,MIN(0.99,Inputs!G19-C22)) -> 0.25 | I22: =Inputs!H19 -> 0.95 | J22: =Inputs!J19 -> 8.9 | K22: =MAX(0.05,MIN(0.99,Inputs!K19-C22)) -> 0.6 | L22: =MAX(0.05,MIN(0.99,Inputs!L19-C22)) -> 0.55 | M22: =D22*E22*J22*((F22+G22)/2)*I22/H22*Parameters!$B$5 -> 7305.12 | N22: =D22*E22*J22*Parameters!$B$4*I22/H22*Parameters!$B$5 -> 2739.42 | O22: =M22-M22*K22*L22 -> 4894.4304 | P22: =O22/N22 -> 1.7866667 | Q22: =IF(P22<Parameters!$B$6,"Below tolerance",IF(P22<=Parameters!$B$7,"Approximately at tolerance","Above tolerance")) -> Above tolerance
A23: S19 | B23: Lower | C23: =-1*Parameters!$B$9 -> -0.1 | D23: =MAX(0.05,MIN(0.99,Inputs!C22+C23)) -> 0.15 | E23: =MAX(0.05,MIN(0.99,Inputs!D22+C23)) -> 0.4 | F23: =MAX(0.05,MIN(0.99,Inputs!E22+C23)) -> 0.5 | G23: =MAX(0.05,MIN(0.99,Inputs!F22+C23)) -> 0.85 | H23: =MAX(0.05,MIN(0.99,Inputs!G22-C23)) -> 0.45 | I23: =Inputs!H22 -> 0.85 | J23: =Inputs!J22 -> 9.5 | K23: =MAX(0.05,MIN(0.99,Inputs!K22-C23)) -> 0.5 | L23: =MAX(0.05,MIN(0.99,Inputs!L22-C23)) -> 0.75 | M23: =D23*E23*J23*((F23+G23)/2)*I23/H23*Parameters!$B$5 -> 726.75 | N23: =D23*E23*J23*Parameters!$B$4*I23/H23*Parameters!$B$5 -> 323 | O23: =M23-M23*K23*L23 -> 454.21875 | P23: =O23/N23 -> 1.40625 | Q23: =IF(P23<Parameters!$B$6,"Below tolerance",IF(P23<=Parameters!$B$7,"Approximately at tolerance","Above tolerance")) -> Above tolerance
A24: S19 | B24: Central | C24: =0*Parameters!$B$9 -> 0 | D24: =MAX(0.05,MIN(0.99,Inputs!C22+C24)) -> 0.25 | E24: =MAX(0.05,MIN(0.99,Inputs!D22+C24)) -> 0.5 | F24: =MAX(0.05,MIN(0.99,Inputs!E22+C24)) -> 0.6 | G24: =MAX(0.05,MIN(0.99,Inputs!F22+C24)) -> 0.95 | H24: =MAX(0.05,MIN(0.99,Inputs!G22-C24)) -> 0.35 | I24: =Inputs!H22 -> 0.85 | J24: =Inputs!J22 -> 9.5 | K24: =MAX(0.05,MIN(0.99,Inputs!K22-C24)) -> 0.4 | L24: =MAX(0.05,MIN(0.99,Inputs!L22-C24)) -> 0.65 | M24: =D24*E24*J24*((F24+G24)/2)*I24/H24*Parameters!$B$5 -> 2235.0446 | N24: =D24*E24*J24*Parameters!$B$4*I24/H24*Parameters!$B$5 -> 865.17857 | O24: =M24-M24*K24*L24 -> 1653.933 | P24: =O24/N24 -> 1.9116667 | Q24: =IF(P24<Parameters!$B$6,"Below tolerance",IF(P24<=Parameters!$B$7,"Approximately at tolerance","Above tolerance")) -> Above tolerance
A25: S19 | B25: Higher | C25: =1*Parameters!$B$9 -> 0.1 | D25: =MAX(0.05,MIN(0.99,Inputs!C22+C25)) -> 0.35 | E25: =MAX(0.05,MIN(0.99,Inputs!D22+C25)) -> 0.6 | F25: =MAX(0.05,MIN(0.99,Inputs!E22+C25)) -> 0.7 | G25: =MAX(0.05,MIN(0.99,Inputs!F22+C25)) -> 0.99 | H25: =MAX(0.05,MIN(0.99,Inputs!G22-C25)) -> 0.25 | I25: =Inputs!H22 -> 0.85 | J25: =Inputs!J22 -> 9.5 | K25: =MAX(0.05,MIN(0.99,Inputs!K22-C25)) -> 0.3 | L25: =MAX(0.05,MIN(0.99,Inputs!L22-C25)) -> 0.55 | M25: =D25*E25*J25*((F25+G25)/2)*I25/H25*Parameters!$B$5 -> 5731.635 | N25: =D25*E25*J25*Parameters!$B$4*I25/H25*Parameters!$B$5 -> 2034.9 | O25: =M25-M25*K25*L25 -> 4785.9152 | P25: =O25/N25 -> 2.3519167 | Q25: =IF(P25<Parameters!$B$6,"Below tolerance",IF(P25<=Parameters!$B$7,"Approximately at tolerance","Above tolerance")) -> Above tolerance
A26: S20 | B26: Lower | C26: =-1*Parameters!$B$9 -> -0.1 | D26: =MAX(0.05,MIN(0.99,Inputs!C23+C26)) -> 0.45 | E26: =MAX(0.05,MIN(0.99,Inputs!D23+C26)) -> 0.3 | F26: =MAX(0.05,MIN(0.99,Inputs!E23+C26)) -> 0.45 | G26: =MAX(0.05,MIN(0.99,Inputs!F23+C26)) -> 0.8 | H26: =MAX(0.05,MIN(0.99,Inputs!G23-C26)) -> 0.5 | I26: =Inputs!H23 -> 0.85 | J26: =Inputs!J23 -> 9.4 | K26: =MAX(0.05,MIN(0.99,Inputs!K23-C26)) -> 0.9 | L26: =MAX(0.05,MIN(0.99,Inputs!L23-C26)) -> 0.75 | M26: =D26*E26*J26*((F26+G26)/2)*I26/H26*Parameters!$B$5 -> 1348.3125 | N26: =D26*E26*J26*Parameters!$B$4*I26/H26*Parameters!$B$5 -> 647.19 | O26: =M26-M26*K26*L26 -> 438.20156 | P26: =O26/N26 -> 0.67708333 | Q26: =IF(P26<Parameters!$B$6,"Below tolerance",IF(P26<=Parameters!$B$7,"Approximately at tolerance","Above tolerance")) -> Below tolerance
A27: S20 | B27: Central | C27: =0*Parameters!$B$9 -> 0 | D27: =MAX(0.05,MIN(0.99,Inputs!C23+C27)) -> 0.55 | E27: =MAX(0.05,MIN(0.99,Inputs!D23+C27)) -> 0.4 | F27: =MAX(0.05,MIN(0.99,Inputs!E23+C27)) -> 0.55 | G27: =MAX(0.05,MIN(0.99,Inputs!F23+C27)) -> 0.9 | H27: =MAX(0.05,MIN(0.99,Inputs!G23-C27)) -> 0.4 | I27: =Inputs!H23 -> 0.85 | J27: =Inputs!J23 -> 9.4 | K27: =MAX(0.05,MIN(0.99,Inputs!K23-C27)) -> 0.8 | L27: =MAX(0.05,MIN(0.99,Inputs!L23-C27)) -> 0.65 | M27: =D27*E27*J27*((F27+G27)/2)*I27/H27*Parameters!$B$5 -> 3186.0125 | N27: =D27*E27*J27*Parameters!$B$4*I27/H27*Parameters!$B$5 -> 1318.35 | O27: =M27-M27*K27*L27 -> 1529.286 | P27: =O27/N27 -> 1.16 | Q27: =IF(P27<Parameters!$B$6,"Below tolerance",IF(P27<=Parameters!$B$7,"Approximately at tolerance","Above tolerance")) -> Above tolerance
A28: S20 | B28: Higher | C28: =1*Parameters!$B$9 -> 0.1 | D28: =MAX(0.05,MIN(0.99,Inputs!C23+C28)) -> 0.65 | E28: =MAX(0.05,MIN(0.99,Inputs!D23+C28)) -> 0.5 | F28: =MAX(0.05,MIN(0.99,Inputs!E23+C28)) -> 0.65 | G28: =MAX(0.05,MIN(0.99,Inputs!F23+C28)) -> 0.99 | H28: =MAX(0.05,MIN(0.99,Inputs!G23-C28)) -> 0.3 | I28: =Inputs!H23 -> 0.85 | J28: =Inputs!J23 -> 9.4 | K28: =MAX(0.05,MIN(0.99,Inputs!K23-C28)) -> 0.7 | L28: =MAX(0.05,MIN(0.99,Inputs!L23-C28)) -> 0.55 | M28: =D28*E28*J28*((F28+G28)/2)*I28/H28*Parameters!$B$5 -> 7097.7833 | N28: =D28*E28*J28*Parameters!$B$4*I28/H28*Parameters!$B$5 -> 2596.75 | O28: =M28-M28*K28*L28 -> 4365.1367 | P28: =O28/N28 -> 1.681 | Q28: =IF(P28<Parameters!$B$6,"Below tolerance",IF(P28<=Parameters!$B$7,"Approximately at tolerance","Above tolerance")) -> Above tolerance
A29: S27 | B29: Lower | C29: =-1*Parameters!$B$9 -> -0.1 | D29: =MAX(0.05,MIN(0.99,Inputs!C30+C29)) -> 0.45 | E29: =MAX(0.05,MIN(0.99,Inputs!D30+C29)) -> 0.4 | F29: =MAX(0.05,MIN(0.99,Inputs!E30+C29)) -> 0.45 | G29: =MAX(0.05,MIN(0.99,Inputs!F30+C29)) -> 0.8 | H29: =MAX(0.05,MIN(0.99,Inputs!G30-C29)) -> 0.5 | I29: =Inputs!H30 -> 0.85 | J29: =Inputs!J30 -> 9.3 | K29: =MAX(0.05,MIN(0.99,Inputs!K30-C29)) -> 0.9 | L29: =MAX(0.05,MIN(0.99,Inputs!L30-C29)) -> 0.7 | M29: =D29*E29*J29*((F29+G29)/2)*I29/H29*Parameters!$B$5 -> 1778.625 | N29: =D29*E29*J29*Parameters!$B$4*I29/H29*Parameters!$B$5 -> 853.74 | O29: =M29-M29*K29*L29 -> 658.09125 | P29: =O29/N29 -> 0.77083333 | Q29: =IF(P29<Parameters!$B$6,"Below tolerance",IF(P29<=Parameters!$B$7,"Approximately at tolerance","Above tolerance")) -> Below tolerance
A30: S27 | B30: Central | C30: =0*Parameters!$B$9 -> 0 | D30: =MAX(0.05,MIN(0.99,Inputs!C30+C30)) -> 0.55 | E30: =MAX(0.05,MIN(0.99,Inputs!D30+C30)) -> 0.5 | F30: =MAX(0.05,MIN(0.99,Inputs!E30+C30)) -> 0.55 | G30: =MAX(0.05,MIN(0.99,Inputs!F30+C30)) -> 0.9 | H30: =MAX(0.05,MIN(0.99,Inputs!G30-C30)) -> 0.4 | I30: =Inputs!H30 -> 0.85 | J30: =Inputs!J30 -> 9.3 | K30: =MAX(0.05,MIN(0.99,Inputs!K30-C30)) -> 0.8 | L30: =MAX(0.05,MIN(0.99,Inputs!L30-C30)) -> 0.6 | M30: =D30*E30*J30*((F30+G30)/2)*I30/H30*Parameters!$B$5 -> 3940.1484 | N30: =D30*E30*J30*Parameters!$B$4*I30/H30*Parameters!$B$5 -> 1630.4062 | O30: =M30-M30*K30*L30 -> 2048.8772 | P30: =O30/N30 -> 1.2566667 | Q30: =IF(P30<Parameters!$B$6,"Below tolerance",IF(P30<=Parameters!$B$7,"Approximately at tolerance","Above tolerance")) -> Above tolerance
A31: S27 | B31: Higher | C31: =1*Parameters!$B$9 -> 0.1 | D31: =MAX(0.05,MIN(0.99,Inputs!C30+C31)) -> 0.65 | E31: =MAX(0.05,MIN(0.99,Inputs!D30+C31)) -> 0.6 | F31: =MAX(0.05,MIN(0.99,Inputs!E30+C31)) -> 0.65 | G31: =MAX(0.05,MIN(0.99,Inputs!F30+C31)) -> 0.99 | H31: =MAX(0.05,MIN(0.99,Inputs!G30-C31)) -> 0.3 | I31: =Inputs!H30 -> 0.85 | J31: =Inputs!J30 -> 9.3 | K31: =MAX(0.05,MIN(0.99,Inputs!K30-C31)) -> 0.7 | L31: =MAX(0.05,MIN(0.99,Inputs!L30-C31)) -> 0.5 | M31: =D31*E31*J31*((F31+G31)/2)*I31/H31*Parameters!$B$5 -> 8426.73 | N31: =D31*E31*J31*Parameters!$B$4*I31/H31*Parameters!$B$5 -> 3082.95 | O31: =M31-M31*K31*L31 -> 5477.3745 | P31: =O31/N31 -> 1.7766667 | Q31: =IF(P31<Parameters!$B$6,"Below tolerance",IF(P31<=Parameters!$B$7,"Approximately at tolerance","Above tolerance")) -> Above tolerance
A32: S28 | B32: Lower | C32: =-1*Parameters!$B$9 -> -0.1 | D32: =MAX(0.05,MIN(0.99,Inputs!C31+C32)) -> 0.05 | E32: =MAX(0.05,MIN(0.99,Inputs!D31+C32)) -> 0.5 | F32: =MAX(0.05,MIN(0.99,Inputs!E31+C32)) -> 0.5 | G32: =MAX(0.05,MIN(0.99,Inputs!F31+C32)) -> 0.85 | H32: =MAX(0.05,MIN(0.99,Inputs!G31-C32)) -> 0.45 | I32: =Inputs!H31 -> 0.9 | J32: =Inputs!J31 -> 9.4 | K32: =MAX(0.05,MIN(0.99,Inputs!K31-C32)) -> 0.65 | L32: =MAX(0.05,MIN(0.99,Inputs!L31-C32)) -> 0.7 | M32: =D32*E32*J32*((F32+G32)/2)*I32/H32*Parameters!$B$5 -> 317.25 | N32: =D32*E32*J32*Parameters!$B$4*I32/H32*Parameters!$B$5 -> 141 | O32: =M32-M32*K32*L32 -> 172.90125 | P32: =O32/N32 -> 1.22625 | Q32: =IF(P32<Parameters!$B$6,"Below tolerance",IF(P32<=Parameters!$B$7,"Approximately at tolerance","Above tolerance")) -> Above tolerance
A33: S28 | B33: Central | C33: =0*Parameters!$B$9 -> 0 | D33: =MAX(0.05,MIN(0.99,Inputs!C31+C33)) -> 0.15 | E33: =MAX(0.05,MIN(0.99,Inputs!D31+C33)) -> 0.6 | F33: =MAX(0.05,MIN(0.99,Inputs!E31+C33)) -> 0.6 | G33: =MAX(0.05,MIN(0.99,Inputs!F31+C33)) -> 0.95 | H33: =MAX(0.05,MIN(0.99,Inputs!G31-C33)) -> 0.35 | I33: =Inputs!H31 -> 0.9 | J33: =Inputs!J31 -> 9.4 | K33: =MAX(0.05,MIN(0.99,Inputs!K31-C33)) -> 0.55 | L33: =MAX(0.05,MIN(0.99,Inputs!L31-C33)) -> 0.6 | M33: =D33*E33*J33*((F33+G33)/2)*I33/H33*Parameters!$B$5 -> 1685.9571 | N33: =D33*E33*J33*Parameters!$B$4*I33/H33*Parameters!$B$5 -> 652.62857 | O33: =M33-M33*K33*L33 -> 1129.5913 | P33: =O33/N33 -> 1.7308333 | Q33: =IF(P33<Parameters!$B$6,"Below tolerance",IF(P33<=Parameters!$B$7,"Approximately at tolerance","Above tolerance")) -> Above tolerance
A34: S28 | B34: Higher | C34: =1*Parameters!$B$9 -> 0.1 | D34: =MAX(0.05,MIN(0.99,Inputs!C31+C34)) -> 0.25 | E34: =MAX(0.05,MIN(0.99,Inputs!D31+C34)) -> 0.7 | F34: =MAX(0.05,MIN(0.99,Inputs!E31+C34)) -> 0.7 | G34: =MAX(0.05,MIN(0.99,Inputs!F31+C34)) -> 0.99 | H34: =MAX(0.05,MIN(0.99,Inputs!G31-C34)) -> 0.25 | I34: =Inputs!H31 -> 0.9 | J34: =Inputs!J31 -> 9.4 | K34: =MAX(0.05,MIN(0.99,Inputs!K31-C34)) -> 0.45 | L34: =MAX(0.05,MIN(0.99,Inputs!L31-C34)) -> 0.5 | M34: =D34*E34*J34*((F34+G34)/2)*I34/H34*Parameters!$B$5 -> 5004.09 | N34: =D34*E34*J34*Parameters!$B$4*I34/H34*Parameters!$B$5 -> 1776.6 | O34: =M34-M34*K34*L34 -> 3878.1698 | P34: =O34/N34 -> 2.1829167 | Q34: =IF(P34<Parameters!$B$6,"Below tolerance",IF(P34<=Parameters!$B$7,"Approximately at tolerance","Above tolerance")) -> Above tolerance
A36: Appetite sensitivity (central parameters): ratio at alternative appetite values
A37: ID | B37: Appetite 0.20 | C37: Appetite 0.30 | D37: Appetite 0.40
A38: S1 | B38: =Analyse!S5/(Analyse!M5/Analyse!J5*0.2) -> 1.4 | C38: =Analyse!S5/(Analyse!M5/Analyse!J5*0.3) -> 0.93333333 | D38: =Analyse!S5/(Analyse!M5/Analyse!J5*0.4) -> 0.7
A39: S2 | B39: =Analyse!S6/(Analyse!M6/Analyse!J6*0.2) -> 1.8046875 | C39: =Analyse!S6/(Analyse!M6/Analyse!J6*0.3) -> 1.203125 | D39: =Analyse!S6/(Analyse!M6/Analyse!J6*0.4) -> 0.90234375
A40: S3 | B40: =Analyse!S7/(Analyse!M7/Analyse!J7*0.2) -> 1.2 | C40: =Analyse!S7/(Analyse!M7/Analyse!J7*0.3) -> 0.8 | D40: =Analyse!S7/(Analyse!M7/Analyse!J7*0.4) -> 0.6
A41: S4 | B41: =Analyse!S8/(Analyse!M8/Analyse!J8*0.2) -> 1.366875 | C41: =Analyse!S8/(Analyse!M8/Analyse!J8*0.3) -> 0.91125 | D41: =Analyse!S8/(Analyse!M8/Analyse!J8*0.4) -> 0.6834375
A42: S5 | B42: =Analyse!S9/(Analyse!M9/Analyse!J9*0.2) -> 1.83 | C42: =Analyse!S9/(Analyse!M9/Analyse!J9*0.3) -> 1.22 | D42: =Analyse!S9/(Analyse!M9/Analyse!J9*0.4) -> 0.915
A43: S6 | B43: =Analyse!S10/(Analyse!M10/Analyse!J10*0.2) -> 1.51875 | C43: =Analyse!S10/(Analyse!M10/Analyse!J10*0.3) -> 1.0125 | D43: =Analyse!S10/(Analyse!M10/Analyse!J10*0.4) -> 0.759375
A44: S7 | B44: =Analyse!S11/(Analyse!M11/Analyse!J11*0.2) -> 2.175 | C44: =Analyse!S11/(Analyse!M11/Analyse!J11*0.3) -> 1.45 | D44: =Analyse!S11/(Analyse!M11/Analyse!J11*0.4) -> 1.0875
A45: S8 | B45: =Analyse!S12/(Analyse!M12/Analyse!J12*0.2) -> 1.65 | C45: =Analyse!S12/(Analyse!M12/Analyse!J12*0.3) -> 1.1 | D45: =Analyse!S12/(Analyse!M12/Analyse!J12*0.4) -> 0.825
A46: S9 | B46: =Analyse!S13/(Analyse!M13/Analyse!J13*0.2) -> 2.30625 | C46: =Analyse!S13/(Analyse!M13/Analyse!J13*0.3) -> 1.5375 | D46: =Analyse!S13/(Analyse!M13/Analyse!J13*0.4) -> 1.153125
A47: S10 | B47: =Analyse!S14/(Analyse!M14/Analyse!J14*0.2) -> 1.78125 | C47: =Analyse!S14/(Analyse!M14/Analyse!J14*0.3) -> 1.1875 | D47: =Analyse!S14/(Analyse!M14/Analyse!J14*0.4) -> 0.890625
A48: S11 | B48: =Analyse!S15/(Analyse!M15/Analyse!J15*0.2) -> 1.5925 | C48: =Analyse!S15/(Analyse!M15/Analyse!J15*0.3) -> 1.0616667 | D48: =Analyse!S15/(Analyse!M15/Analyse!J15*0.4) -> 0.79625
A49: S12 | B49: =Analyse!S16/(Analyse!M16/Analyse!J16*0.2) -> 1.38 | C49: =Analyse!S16/(Analyse!M16/Analyse!J16*0.3) -> 0.92 | D49: =Analyse!S16/(Analyse!M16/Analyse!J16*0.4) -> 0.69
... A67: S30 | B67: =Analyse!S34/(Analyse!M34/Analyse!J34*0.2) -> 1.42375 | C67: =Analyse!S34/(Analyse!M34/Analyse!J34*0.3) -> 0.94916667 | D67: =Analyse!S34/(Analyse!M34/Analyse!J34*0.4) -> 0.711875

Sheet Case_View
A1: Case-native escalation view (Business case s.8) - secondary cross-check
A2: Normalized residual = T x E x I x (1 - C), with T = Pb(A), E = Pb(psi,A), I = (de+dm)/2, C (control maturity) proxied by theta. Post-treatment = current x (1 - P x Q). Analyst mapping - validate.
A4: ID | B4: T | C4: E | D4: I | E4: C (theta) | F4: Current residual | G4: Level | H4: Post-treatment residual | I4: Level | J4: Acceptance authority (post)
A5: S1 | B5: =Inputs!C4 -> 0.85 | C5: =Inputs!D4 -> 0.55 | D5: =(Inputs!E4+Inputs!F4)/2 -> 0.7 | E5: =Inputs!G4 -> 0.4 | F5: =B5*C5*D5*(1-E5) -> 0.19635 | G5: =IF(F5<=0.07,"Low",IF(F5<=0.15,"Moderate",IF(F5<=0.25,"High","Critical"))) -> High | H5: =F5*(1-Inputs!K4*Inputs!L4) -> 0.07854 | I5: =IF(H5<=0.07,"Low",IF(H5<=0.15,"Moderate",IF(H5<=0.25,"High","Critical"))) -> Moderate | J5: =IF(H5>Parameters!$B$11,"Board / ownership group",IF(H5>Parameters!$B$10,"Executive leadership","CIO / Cybersecurity lead")) -> CIO / Cybersecurity lead
A6: S2 | B6: =Inputs!C5 -> 0.75 | C6: =Inputs!D5 -> 0.5 | D6: =(Inputs!E5+Inputs!F5)/2 -> 0.825 | E6: =Inputs!G5 -> 0.35 | F6: =B6*C6*D6*(1-E6) -> 0.20109375 | G6: =IF(F6<=0.07,"Low",IF(F6<=0.15,"Moderate",IF(F6<=0.25,"High","Critical"))) -> High | H6: =F6*(1-Inputs!K5*Inputs!L5) -> 0.087978516 | I6: =IF(H6<=0.07,"Low",IF(H6<=0.15,"Moderate",IF(H6<=0.25,"High","Critical"))) -> Moderate | J6: =IF(H6>Parameters!$B$11,"Board / ownership group",IF(H6>Parameters!$B$10,"Executive leadership","CIO / Cybersecurity lead")) -> CIO / Cybersecurity lead
A7: S3 | B7: =Inputs!C6 -> 0.55 | C7: =Inputs!D6 -> 0.5 | D7: =(Inputs!E6+Inputs!F6)/2 -> 0.75 | E7: =Inputs!G6 -> 0.35 | F7: =B7*C7*D7*(1-E7) -> 0.1340625 | G7: =IF(F7<=0.07,"Low",IF(F7<=0.15,"Moderate",IF(F7<=0.25,"High","Critical"))) -> Moderate | H7: =F7*(1-Inputs!K6*Inputs!L6) -> 0.0429 | I7: =IF(H7<=0.07,"Low",IF(H7<=0.15,"Moderate",IF(H7<=0.25,"High","Critical"))) -> Low | J7: =IF(H7>Parameters!$B$11,"Board / ownership group",IF(H7>Parameters!$B$10,"Executive leadership","CIO / Cybersecurity lead")) -> CIO / Cybersecurity lead
A8: S4 | B8: =Inputs!C7 -> 0.6 | C8: =Inputs!D7 -> 0.45 | D8: =(Inputs!E7+Inputs!F7)/2 -> 0.675 | E8: =Inputs!G7 -> 0.4 | F8: =B8*C8*D8*(1-E8) -> 0.10935 | G8: =IF(F8<=0.07,"Low",IF(F8<=0.15,"Moderate",IF(F8<=0.25,"High","Critical"))) -> Moderate | H8: =F8*(1-Inputs!K7*Inputs!L7) -> 0.04428675 | I8: =IF(H8<=0.07,"Low",IF(H8<=0.15,"Moderate",IF(H8<=0.25,"High","Critical"))) -> Low | J8: =IF(H8>Parameters!$B$11,"Board / ownership group",IF(H8>Parameters!$B$10,"Executive leadership","CIO / Cybersecurity lead")) -> CIO / Cybersecurity lead
A9: S5 | B9: =Inputs!C8 -> 0.6 | C9: =Inputs!D8 -> 0.55 | D9: =(Inputs!E8+Inputs!F8)/2 -> 0.6 | E9: =Inputs!G8 -> 0.4 | F9: =B9*C9*D9*(1-E9) -> 0.1188 | G9: =IF(F9<=0.07,"Low",IF(F9<=0.15,"Moderate",IF(F9<=0.25,"High","Critical"))) -> Moderate | H9: =F9*(1-Inputs!K8*Inputs!L8) -> 0.072468 | I9: =IF(H9<=0.07,"Low",IF(H9<=0.15,"Moderate",IF(H9<=0.25,"High","Critical"))) -> Moderate | J9: =IF(H9>Parameters!$B$11,"Board / ownership group",IF(H9>Parameters!$B$10,"Executive leadership","CIO / Cybersecurity lead")) -> CIO / Cybersecurity lead
A10: S6 | B10: =Inputs!C9 -> 0.8 | C10: =Inputs!D9 -> 0.5 | D10: =(Inputs!E9+Inputs!F9)/2 -> 0.75 | E10: =Inputs!G9 -> 0.4 | F10: =B10*C10*D10*(1-E10) -> 0.18 | G10: =IF(F10<=0.07,"Low",IF(F10<=0.15,"Moderate",IF(F10<=0.25,"High","Critical"))) -> High | H10: =F10*(1-Inputs!K9*Inputs!L9) -> 0.0729 | I10: =IF(H10<=0.07,"Low",IF(H10<=0.15,"Moderate",IF(H10<=0.25,"High","Critical"))) -> Moderate | J10: =IF(H10>Parameters!$B$11,"Board / ownership group",IF(H10>Parameters!$B$10,"Executive leadership","CIO / Cybersecurity lead")) -> CIO / Cybersecurity lead
A11: S7 | B11: =Inputs!C10 -> 0.45 | C11: =Inputs!D10 -> 0.5 | D11: =(Inputs!E10+Inputs!F10)/2 -> 0.75 | E11: =Inputs!G10 -> 0.35 | F11: =B11*C11*D11*(1-E11) -> 0.1096875 | G11: =IF(F11<=0.07,"Low",IF(F11<=0.15,"Moderate",IF(F11<=0.25,"High","Critical"))) -> Moderate | H11: =F11*(1-Inputs!K10*Inputs!L10) -> 0.06361875 | I11: =IF(H11<=0.07,"Low",IF(H11<=0.15,"Moderate",IF(H11<=0.25,"High","Critical"))) -> Low | J11: =IF(H11>Parameters!$B$11,"Board / ownership group",IF(H11>Parameters!$B$10,"Executive leadership","CIO / Cybersecurity lead")) -> CIO / Cybersecurity lead
A12: S8 | B12: =Inputs!C11 -> 0.8 | C12: =Inputs!D11 -> 0.6 | D12: =(Inputs!E11+Inputs!F11)/2 -> 0.75 | E12: =Inputs!G11 -> 0.3 | F12: =B12*C12*D12*(1-E12) -> 0.252 | G12: =IF(F12<=0.07,"Low",IF(F12<=0.15,"Moderate",IF(F12<=0.25,"High","Critical"))) -> Critical | H12: =F12*(1-Inputs!K11*Inputs!L11) -> 0.11088 | I12: =IF(H12<=0.07,"Low",IF(H12<=0.15,"Moderate",IF(H12<=0.25,"High","Critical"))) -> Moderate | J12: =IF(H12>Parameters!$B$11,"Board / ownership group",IF(H12>Parameters!$B$10,"Executive leadership","CIO / Cybersecurity lead")) -> CIO / Cybersecurity lead
A13: S9 | B13: =Inputs!C12 -> 0.55 | C13: =Inputs!D12 -> 0.45 | D13: =(Inputs!E12+Inputs!F12)/2 -> 0.75 | E13: =Inputs!G12 -> 0.35 | F13: =B13*C13*D13*(1-E13) -> 0.12065625 | G13: =IF(F13<=0.07,"Low",IF(F13<=0.15,"Moderate",IF(F13<=0.25,"High","Critical"))) -> Moderate | H13: =F13*(1-Inputs!K12*Inputs!L12) -> 0.074203594 | I13: =IF(H13<=0.07,"Low",IF(H13<=0.15,"Moderate",IF(H13<=0.25,"High","Critical"))) -> Moderate | J13: =IF(H13>Parameters!$B$11,"Board / ownership group",IF(H13>Parameters!$B$10,"Executive leadership","CIO / Cybersecurity lead")) -> CIO / Cybersecurity lead
A14: S10 | B14: =Inputs!C13 -> 0.3 | C14: =Inputs!D13 -> 0.4 | D14: =(Inputs!E13+Inputs!F13)/2 -> 0.75 | E14: =Inputs!G13 -> 0.4 | F14: =B14*C14*D14*(1-E14) -> 0.054 | G14: =IF(F14<=0.07,"Low",IF(F14<=0.15,"Moderate",IF(F14<=0.25,"High","Critical"))) -> Low | H14: =F14*(1-Inputs!K13*Inputs!L13) -> 0.02565 | I14: =IF(H14<=0.07,"Low",IF(H14<=0.15,"Moderate",IF(H14<=0.25,"High","Critical"))) -> Low | J14: =IF(H14>Parameters!$B$11,"Board / ownership group",IF(H14>Parameters!$B$10,"Executive leadership","CIO / Cybersecurity lead")) -> CIO / Cybersecurity lead
A15: S11 | B15: =Inputs!C14 -> 0.45 | C15: =Inputs!D14 -> 0.45 | D15: =(Inputs!E14+Inputs!F14)/2 -> 0.65 | E15: =Inputs!G14 -> 0.4 | F15: =B15*C15*D15*(1-E15) -> 0.078975 | G15: =IF(F15<=0.07,"Low",IF(F15<=0.15,"Moderate",IF(F15<=0.25,"High","Critical"))) -> Moderate | H15: =F15*(1-Inputs!K14*Inputs!L14) -> 0.03869775 | I15: =IF(H15<=0.07,"Low",IF(H15<=0.15,"Moderate",IF(H15<=0.25,"High","Critical"))) -> Low | J15: =IF(H15>Parameters!$B$11,"Board / ownership group",IF(H15>Parameters!$B$10,"Executive leadership","CIO / Cybersecurity lead")) -> CIO / Cybersecurity lead
A16: S12 | B16: =Inputs!C15 -> 0.4 | C16: =Inputs!D15 -> 0.45 | D16: =(Inputs!E15+Inputs!F15)/2 -> 0.575 | E16: =Inputs!G15 -> 0.4 | F16: =B16*C16*D16*(1-E16) -> 0.0621 | G16: =IF(F16<=0.07,"Low",IF(F16<=0.15,"Moderate",IF(F16<=0.25,"High","Critical"))) -> Low | H16: =F16*(1-Inputs!K15*Inputs!L15) -> 0.029808 | I16: =IF(H16<=0.07,"Low",IF(H16<=0.15,"Moderate",IF(H16<=0.25,"High","Critical"))) -> Low | J16: =IF(H16>Parameters!$B$11,"Board / ownership group",IF(H16>Parameters!$B$10,"Executive leadership","CIO / Cybersecurity lead")) -> CIO / Cybersecurity lead
... A34: S30 | B34: =Inputs!C33 -> 0.7 | C34: =Inputs!D33 -> 0.5 | D34: =(Inputs!E33+Inputs!F33)/2 -> 0.425 | E34: =Inputs!G33 -> 0.45 | F34: =B34*C34*D34*(1-E34) -> 0.0818125 | G34: =IF(F34<=0.07,"Low",IF(F34<=0.15,"Moderate",IF(F34<=0.25,"High","Critical"))) -> Moderate | H34: =F34*(1-Inputs!K33*Inputs!L33) -> 0.054814375 | I34: =IF(H34<=0.07,"Low",IF(H34<=0.15,"Moderate",IF(H34<=0.25,"High","Critical"))) -> Low | J34: =IF(H34>Parameters!$B$11,"Board / ownership group",IF(H34>Parameters!$B$10,"Executive leadership","CIO / Cybersecurity lead")) -> CIO / Cybersecurity lead

Sheet Scenarios
A1: ID | B1: Library ref | C1: Scenario | D1: Statement | E1: Threat source | F1: Vulnerabilities / conditions | G1: Existing controls (evidence) | H1: Treatment package | I1: Initiatives | J1: Risk owner | K1: Horizon | L1: CVSS rationale
A2: S1 | B2: MED-CYR-01 / 12 | C2: Credential compromise of clinical administrator accounts through phishing and MFA fatigue | D2: A financially motivated external actor phishes clinic administrators and billing staff with an EHR-themed lure, captures credentials and obtains approval of an MFA push prompt, gaining remote access to the EHR, billing and administrative systems, enabling unauthorized access to patient records and follow-on intrusion. | E2: Cybercriminal (initial-access broker or ransomware affiliate). | F2: Push-based MFA without number matching or phishing resistance (E6 - validate); No evidence of conditional access (geo/device) policies; Internet-sourced macro documents reach users (E6); Awareness programme maturity unknown (Information gap) | G2: Email filtering / antimalware (E2 - effectiveness unknown); MFA push on remote access (E6); EDR alerting (E6 - triage weak) | H2: Phishing-resistant MFA and conditional access (I01) is the primary lever; PAM (I02) limits blast radius; MDR (I03) shortens dwell time; awareness and reporting (I12). | I2: I01, I02, I03, I12 | J2: CIO | K2: 0-6 months | L2: Representative weakness: remote-access authentication accepting MFA push approval (CWE-308-type single-channel weakness). AV:N internet-reachable gateway; AC:L no special conditions; AT:N; PR:N attacker starts unauthenticated; UI:A user must actively approve; VC/VI:H full session on gateway; VA:N; SC:H EHR data behind the gateway; SI:L/SA:L limited downstream change/disruption. Applicability: moderate - human factor dominates.
A3: S2 | B3: MED-CYR-02 | C3: Ransomware disrupting EHR access and clinic operations across the network | D3: A ransomware group gains a foothold through a macro-enabled phishing attachment or exposed service, moves laterally across an insufficiently segmented network, exfiltrates health data and encrypts EHR support servers, shared folders and scheduling systems, halting clinical and administrative operations at multiple clinics. | E3: Ransomware-as-a-service affiliate (double extortion). | F3: Macro execution and weak alert triage (E6); Segmentation between clinics, servers and backups not evidenced (E2, E7); Privileged credential hygiene unknown (Information gap); Clinic downtime procedures untested (E7) | G3: Firewalls, IDS/IPS, antimalware (E2); EDR (E6); On-site and off-site backups (E2 - isolation and testing unknown); Incident command structure defined (E6 - untested) | H3: Layered: MDR/EDR (I03), PAM (I02), segmentation (I06), immutable backup (I04), patching (I05), IR and downtime procedures (I11), awareness (I12). Residual remains material - consider cyber-insurance transfer. | I3: I02, I03, I04, I05, I06, I11, I12 | J3: Executive leadership (COO) with CIO | K3: 0-24 months | L3: Representative weakness: malicious macro document leading to code execution (initial vector in E6). AV:L: the document is delivered by e-mail but opened and executed locally on the workstation (FIRST CVSS v4.0 user guide scores malicious documents as Local whatever the delivery channel); AC:L; AT:N; PR:N; UI:P user opens the document; VC/VI/VA:H on the workstation; SC/SI/SA:H because EHR and clinic systems are subsequently affected. CVSS describes the entry weakness only, not the enterprise impact.
A4: S3 | B4: MED-CYR-07 | C4: Backup environment compromised, preventing recovery after a destructive attack | D4: An attacker holding administrative credentials reaches backup servers that share the production identity domain and network, deletes or encrypts backup sets and clinic storage copies, so that MediBec cannot restore EHR and clinic systems within clinically acceptable time after a destructive event. | E4: Ransomware operator or other attacker with administrative access. | F4: Backup consoles authenticated through production directory (Analyst assumption - validate); No immutable or offline copy evidenced; Restore testing and RTO/RPO not evidenced (E7); Backup failure alerts not escalated (E6) | G4: On-site and off-site backups (E2); Encrypted storage (E2) | H4: Immutable/offline copies with separate backup identity (I04), segmentation (I06), PAM (I02), backup-alert monitoring (I03), quarterly restore tests and IR integration (I11). | I4: I02, I03, I04, I06, I11 | J4: CIO | K4: 0-9 months | L4: Representative weakness: backup management console reachable from production network and trusting production administrator accounts. PR:H attacker already holds admin credentials; VC/VI/VA:H on the backup system; SA:H because recovery of all subsequent systems is lost.
A5: S4 | B5: MED-CYR-03 | C5: Cloud medical-image transfer storage exposed, enabling bulk health-data exfiltration | D5: An opportunistic or targeted actor discovers a cloud storage location used for medical-image transfer and exports that is shared through long-lived public or weakly authenticated links, downloads large volumes of images and associated patient identifiers, and causes a large-scale health-data breach. | E5: Opportunistic scanner or cybercriminal data broker. | F5: Permissive or long-lived sharing links (Analyst assumption); No cloud posture management evidenced; Object-level access logging unknown (E4); Exports contain identifiers alongside images | G5: Encrypted storage (E2 - at-rest only, not access control); Cloud access via identity (E2) | H5: Block public access and enforce expiring authenticated links (I08); DLP and data minimization in exports (I09); object-access logging to MDR (I03). | I5: I03, I08, I09 | J5: CIO with Privacy officer | K5: 0-6 months | L5: Representative weakness: storage object accessible without authentication (CWE-284 misconfiguration). AV:N, AC:L, AT:N, PR:N, UI:N; confidentiality only (VC:H).
A6: S5 | B6: MED-CYR-11 (+ service-account evidence) | C6: Misuse of legitimate clinical, privileged or service-account access to extract patient records | D6: A malicious or curious insider, or an attacker who has taken over the over-privileged ehr-sync-svc service account, uses legitimate but excessive EHR access to query and export large volumes of patient or billing records without triggering review, resulting in a privacy breach and loss of trust. | E6: Malicious or negligent insider; external actor using a service account. | F6: Broad role-based access in EHR (Analyst assumption); Over-privileged service account without vaulting (E6); No EHR access analytics or periodic recertification evidenced (E7); No DLP evidenced | G6: EHR audit log exists (E6); Encrypted storage (E2) | H6: Least-privilege redesign and access recertification plus EHR access analytics and DLP (I09); vault and restrict service accounts (I02); MDR use-cases (I03); HR/awareness (I12). | I6: I02, I03, I09, I12 | J6: Privacy officer | K6: 3-12 months | L6: Limited applicability: insider misuse is not a software vulnerability. Representative weakness used for the workbook: excessive privileges on an authenticated account (CWE-269). PR:L legitimate low-privilege access; VC:H bulk read; VI:L. Interpret with caution.
A7: S6 | B7: MED-CYR-06 | C7: Exploitation of unpatched internet-facing or end-of-life systems | D7: A cybercriminal or state-linked actor mass-exploits a known vulnerability in an internet-facing remote access gateway, firewall or web application that MediBec has not patched because of uptime concerns, vendor constraints or limited staff, obtaining remote code execution and a foothold for data theft or ransomware. | E7: Cybercriminal / state-linked actor using public exploits. | F7: Patch SLAs and exception governance not evidenced (E7); Incomplete asset inventory (E4); Possible end-of-life systems (Information gap) | G7: Firewalls, IDS/IPS (E2); Antimalware (E2) | H7: Risk-based vulnerability and patch management with KEV SLAs and EOL retirement (I05); segmentation behind the edge (I06); MDR threat hunting (I03). | I7: I03, I05, I06 | J7: CIO | K7: 1-9 months | L7: Representative weakness: unauthenticated remote code execution in an internet-facing gateway (typical of known-exploited edge vulnerabilities). All impacts High because the gateway fronts the internal network. Replace with the actual CVE vector once scan data is available.
A8: S7 | B8: MED-CYR-09 (+ Wi-Fi path MED-CYR-05) | C8: Connected medical device used as a foothold to disrupt clinical equipment and reach the EHR network | D8: An attacker reaching a clinic network (through malware, a compromised clinic Wi-Fi or vendor access) exploits an unpatched or default-credential medical device on a network shared with EHR workstations, disrupting device operation and using it as a persistent foothold, with potential consequences for patient care. | E8: Cybercriminal (opportunistic or during ransomware operation). | F8: Incomplete device inventory (E4); Embedded OS patching restricted by certification (E3); Devices and guest/clinical Wi-Fi not segmented (E4, E7 - validate); Default credentials (Analyst assumption) | G8: Firewalls and IDS/IPS at hub (E2 - east-west coverage unknown) | H8: Medical device security programme (I07), segmentation and NAC including guest Wi-Fi isolation (I06), patch/compensating controls (I05). Residual depends on manufacturers. | I8: I05, I06, I07 | J8: Clinical Ops with Biomedical engineering | K8: 3-24 months | L8: Representative weakness: unpatched embedded service or default credential on a networked device. AV:A reachable from the clinic LAN/Wi-Fi only; PR:N; full device impact; SC/SI/SA:L onward effects. CVSS supplemental metric Safety (S:P) would apply but is not part of the base score.
A9: S8 | B9: MED-CYR-08 / 15 | C9: Detection and response gaps allow an intrusion to persist and escalate | D9: An intrusion by any external actor goes unnoticed or is misclassified because alert triage, log coverage and after-hours monitoring are insufficient for a two-person cybersecurity team, and the untested incident response plan leads to slow, uncoordinated containment, turning a contained event into a major privacy and operational incident. | E9: Any external actor (amplifier scenario). | F9: No 24/7 monitoring (E3 - inferred); Alert triage criteria weak (E6); Log coverage and retention unknown (E4); IR plan untested; decision rights unclear (E8) | G9: IDS/IPS (E2); EDR (E6); Incident command roles defined (E6) | H9: 24/7 MDR with centralized logging and escalation criteria (I03); IR plan, playbooks, retainer and tabletop exercises across clinics (I11); governance reporting (I12). | I9: I01, I03, I11, I12 | J9: Cybersecurity lead | K9: 0-6 months | L9: Limited applicability: a detection gap is a control weakness, not a vulnerability. Representative weakness for the workbook: the undetected initial code-execution vector (macro/PowerShell, E6), scored AV:L because the e-mailed document is opened and executed locally (FIRST CVSS v4.0 user guide). Do not interpret the score as the severity of the detection gap.
A10: S9 | B10: MED-CYR-14 | C10: Compromise of a critical vendor with remote access to MediBec systems | D10: A threat actor compromises an EHR, diagnostic, device or IT support vendor and uses the vendor's standing remote access or software update channel to enter MediBec's environment, bypassing perimeter controls to access health data or deploy malware. | E10: Supply-chain attacker (cybercriminal or state-linked). | F10: Standing vendor remote access (Analyst assumption); No vendor tiering or assessments evidenced (E7); Incident-notification clauses unknown (E5); Vendor sessions not brokered or recorded | G10: Firewalls (E2); Vendor coordination role defined for incidents (E6) | H10: Third-party risk programme and contract clauses (I10); vendor access only through PAM with MFA and recording (I01/I02); MDR monitoring of vendor sessions (I03); joint IR (I11). Residual largely outside MediBec's control - consider contractual and insurance transfer. | I10: I01, I02, I03, I10, I11 | J10: Procurement with CIO | K10: 2-12 months | L10: Limited applicability: supplier concentration is not a single vulnerability. Representative weakness: standing authenticated remote-access channel. AT:P the vendor must first be compromised; PR:L vendor account; full impacts. Validate against actual vendor access design.
A11: S10 | B11: MED-CYR-13 | C11: Manipulation of patient, medication or billing records undermining clinical decisions | D11: An attacker with compromised clinical credentials, or a malicious insider, alters medication, allergy, laboratory or billing records in the EHR or pharmacy system without detection, leading to incorrect clinical decisions, patient harm and loss of confidence in the record. | E11: External attacker (extortion or sabotage) or malicious insider. | F11: No integrity monitoring or reconciliation evidenced (E8); Broad write privileges (Analyst assumption); Audit trail review not evidenced; Post-restore integrity verification absent | G11: EHR audit logging (E6); Encrypted storage (E2 - no integrity protection) | H11: Integrity monitoring and reconciliation (I13), least-privilege write access (I09/I02), strong authentication (I01), backup-based verification (I04), MDR (I03), clinical playbook (I11). | I11: I01, I02, I03, I04, I09, I11, I13 | J11: Clinical Ops (CMO) | K11: 3-15 months | L11: Representative weakness: authenticated user able to modify records beyond need (improper authorization, CWE-285). PR:L; VI:H; SI:H because pharmacy/lab downstream systems consume the altered data.
A12: S11 | B12: MED-CYR-04 | C12: API key or secret exposed in code, logs or configuration enables direct data access | D12: An opportunistic actor finds an API key, database connection string or cloud access token that a developer committed to a code repository, left in a log or embedded in a configuration file, and uses it to call MediBec's EHR integration or cloud storage APIs directly, extracting patient data without passing through user authentication. | E12: Opportunistic actor scanning public repositories and paste sites; cybercriminal. | F12: No secret scanning or vault evidenced (E7); Long-lived API keys without rotation (Analyst assumption); API calls not monitored for anomalous volume (E7); Development practices and repository visibility unknown (Information gap) | G12: Encrypted storage (E2 - does not protect against valid-key access) | H12: Secret scanning in repositories and pipelines, central vault with short-lived tokens and rotation (I14); API anomaly monitoring (I03); scoped cloud keys (I08). | I12: I03, I08, I14 | J12: CIO (Application development) | K12: 3-9 months | L12: Representative weakness: hard-coded credential (CWE-798). AT:P the attacker must first obtain the leaked secret; PR:N once held, no further privileges needed; VC:H data access; VI:L limited write scope.
... A31: S30 | B31: Appendix A domain; Annex B #65, #71 | C31: Criminals impersonate MediBec to defraud or phish patients | D31: Fraudsters register look-alike domains and send SMS or e-mail messages posing as MediBec (appointment confirmations, billing notices, results available) to harvest patients' credentials, health-card details or payments, harming patients and eroding trust even though MediBec's systems are not breached. | E31: Fraud group. | F31: No look-alike domain monitoring or takedown (E6); DMARC enforcement unknown; No published patient communication standard (e.g. 'we never ask for...') | G31: None evidenced | H31: Look-alike domain monitoring and takedown, verified sender channels, patient communication standard and awareness notices (I23), DMARC enforcement (I16), staff reporting (I12). | I31: I12, I16, I23 | J31: Communications lead | K31: 0-6 months | L31: Limited applicability: impersonation outside MediBec's systems. Representative weakness: sender domain spoofable without enforced DMARC. Business impact is captured by damage estimates, not CVSS.

Sheet Candidates
A1: ID | B1: Candidate scenario | C1: Threat source | D1: Vulnerability / condition | E1: Primary asset | F1: Undesired outcome | G1: Library ref | H1: Decision | I1: Screening rationale
A2: C01 | B2: Phishing-led compromise of clinic administrator credentials | C2: Cybercriminal | D2: Push-based MFA susceptible to fatigue; macro attachments delivered | E2: CJ5 / CJ1 | F2: Unauthorized EHR and remote access | G2: MED-CYR-01, 12 | H2: Selected (S1) | I2: Most frequent initial-access path; directly evidenced by injects E6.
A3: C02 | B3: Ransomware encrypting EHR support systems, shared folders and scheduling | C3: Ransomware group | D3: Flat internal network; weak alert triage; backups reachable | E3: CJ1 / CJ3 / CJ6 | F3: Multi-clinic disruption and data theft | G3: MED-CYR-02 | H3: Selected (S2) | I3: Highest combined clinical, privacy and operational consequence.
A4: C03 | B4: Backup environment compromised before encryption, recovery fails | C4: Ransomware group / privileged attacker | D4: Backups in same admin domain; restore testing not evidenced | E4: CJ6 | F4: Prolonged outage, loss of recoverability | G4: MED-CYR-07 | H4: Selected (S3) | I4: Determines whether S2 is survivable; backup failures in E6.
A5: C04 | B5: Cloud medical-image transfer storage exposed or accessed externally | C5: Opportunistic actor / cybercriminal | D5: Permissive sharing, weak cloud logging and posture management | E5: CJ7 | F5: Bulk health-data exposure | G5: MED-CYR-03 | H5: Selected (S4) | I5: Large-volume PHI exposure; evidenced by unusual downloads (E6).
A6: C05 | B6: API key committed to a code repository enables data access | C6: Opportunistic actor | D6: No secret scanning or vault evidenced | E6: CJ1 / CJ7 | F6: Direct API data extraction | G6: MED-CYR-04 | H6: Selected (S11) | I6: Now retained: portfolio of 30 allows coverage of development-related exposure.
A7: C06 | B7: Clinic Wi-Fi compromise or rogue access point | C7: Local attacker | D7: Guest/clinical Wi-Fi segmentation not evidenced | E7: Clinic LAN | F7: Internal network foothold | G7: MED-CYR-05 | H7: Selected (S12) | I7: Now retained as a distinct wireless entry path (S7 remains the device-safety scenario).
A8: C07 | B8: Exploitation of unpatched internet-facing or end-of-life systems | C8: Cybercriminal / state-linked actor | D8: Patch delays from uptime and vendor constraints | E8: CJ5 / CJ6 | F8: Remote code execution and intrusion | G8: MED-CYR-06 | H8: Selected (S6) | I8: Mass exploitation of edge devices is a leading entry vector; patching constraints documented (E3).
A9: C08 | B9: Intrusion goes undetected because monitoring and triage are insufficient | C9: Any external actor | D9: 2-person team, alert closed as low severity, log coverage unknown | E9: All | F9: Extended dwell time, amplified harm | G9: MED-CYR-08 | H9: Selected (S8) | I9: Systemic amplifier; directly evidenced (E3, E6).
A10: C09 | B10: Connected medical device used as network foothold | C10: Cybercriminal | D10: Unpatched embedded OS, incomplete inventory, weak segmentation | E10: CJ8 | F10: Device disruption, lateral movement | G10: MED-CYR-09 | H10: Selected (S7) | I10: Only scenario with direct patient-safety pathway through equipment.
A11: C10 | B11: DDoS against patient-facing online services | C11: Hacktivist / extortionist | D11: No DDoS protection evidenced | E11: CJ3 | F11: Online booking unavailable | G11: MED-CYR-10 | H11: Selected (S13) | I11: Now retained: availability of patient-facing services.
A12: C11 | B12: Staff member exports health or billing records for unauthorized purposes | C12: Malicious or curious insider | D12: Broad EHR roles, limited access analytics | E12: CJ1 / CJ4 | F12: Privacy breach | G12: MED-CYR-11 | H12: Selected (S5, merged with C15) | I12: Common in healthcare; high regulatory significance.
... A46: C45 | B46: Firewall single point of failure | C46: Accidental / attacker | D46: No redundancy | E46: CJ6 | F46: Outage | G46: Annex B #5 | H46: Merged into S16 | I46: Same resilience treatment (I18).

Sheet KRIs
A1: ID | B1: KRI | C1: Scenarios | D1: Measurement | E1: Data source | F1: Owner | G1: Frequency | H1: Target | I1: Warning | J1: Critical
A2: KRI-01 | B2: % privileged and remote-access accounts on phishing-resistant MFA | C2: S1, S8, S9 | D2: Accounts with FIDO2 / total in-scope accounts | E2: IdP / directory report | F2: Cybersecurity lead | G2: Monthly | H2: 100% | I2: < 95% | J2: < 85%
A3: KRI-02 | B3: Phishing simulation report rate / click rate | C3: S1, S2 | D3: Reported vs clicked in simulations | E3: Awareness platform | F3: Cybersecurity lead | G3: Quarterly | H3: > 70% / < 5% | I3: < 50% / > 8% | J3: < 30% / > 15%
A4: KRI-03 | B4: % critical/known-exploited vulnerabilities remediated within SLA | C4: S6, S2 | D4: Closed within SLA / total | E4: Vulnerability scanner | F4: CIO | G4: Monthly | H4: > 95% | I4: < 90% | J4: < 75%
A5: KRI-04 | B5: Number of unsupported (end-of-life) systems on patient-data or internet-facing networks | C5: S6, S7 | D5: Count from inventory | E5: CMDB / scanner | F5: CIO | G5: Monthly | H5: 0 | I5: >= 1 | J5: >= 5
A6: KRI-05 | B6: Crown-jewel backup restore-test success rate within RTO | C6: S2, S3, S10 | D6: Successful tests / tests run | E6: Backup platform, DR test records | F6: CIO (Infrastructure) | G6: Quarterly | H6: 100% | I6: < 95% | J6: < 80%
A7: KRI-06 | B7: EDR and log coverage of critical assets | C7: S2, S8 | D7: Assets reporting / inventory | E7: EDR console, SIEM | F7: Cybersecurity lead | G7: Monthly | H7: > 98% | I7: < 95% | J7: < 90%
A8: KRI-07 | B8: Mean time to detect / contain high-severity incidents | C8: S8, S2 | D8: Median hours from first signal to detection / containment | E8: MDR reports | F8: Cybersecurity lead | G8: Monthly | H8: < 1 h / < 4 h | I8: > 4 h / > 24 h | J8: > 24 h / > 72 h
A9: KRI-08 | B9: Publicly accessible cloud storage objects containing health data | C9: S4 | D9: Count from CSPM | E9: CSPM | F9: CIO | G9: Weekly | H9: 0 | I9: >= 1 | J9: >= 1 with PHI
A10: KRI-09 | B10: % EHR roles recertified and bulk-access alerts reviewed within 24 h | C10: S5, S10 | D10: Recertified / total; reviewed / raised | E10: EHR access analytics, IAM | F10: Privacy officer | G10: Quarterly | H10: 100% | I10: < 95% | J10: < 85%
A11: KRI-10 | B11: % networked medical devices inventoried and in isolated segments | C11: S7 | D11: Segmented devices / inventoried | E11: IoMT monitoring, NAC | F11: Biomedical engineering | G11: Quarterly | H11: 100% | I11: < 90% | J11: < 70%
A12: KRI-11 | B12: % critical vendors assessed with current notification clauses | C12: S9 | D12: Assessed / critical vendors | E12: TPRM register | F12: Procurement | G12: Quarterly | H12: 100% | I12: < 90% | J12: < 70%
... A21: KRI-20 | B21: Internet-exposed management interfaces | C21: S23, S6 | D21: Count from attack-surface monitoring | E21: EASM tool | F21: CIO (Infra) | G21: Weekly | H21: 0 | I21: >= 1 | J21: >= 1 without MFA

Sheet Evidence
A1: ID | B1: Source | C1: Basis | D1: Content used
A2: E1 | B2: MediBec business case v2.0b, s.3 - Background and healthcare profile | C2: Documented (case) | D2: HQ Montreal; 10 clinics (Montreal, Quebec City, Gatineau, Saguenay); EHR, radiology, lab, pharmacy, billing, communications; sensitive health data.
A3: E2 | B3: Business case s.4 - Technology environment table | C3: Documented (case) | D3: Central network hub in Montreal, WAN fibre to clinics, firewalls, IDS/IPS, antivirus/antimalware; Montreal data centre, local clinic storage, on-site and off-site backups, encrypted storage; cloud-based remote access; interconnected medical equipment.
A4: E3 | B4: Business case s.4 - Operating model and budget context | C4: Documented (case) | D4: 15-person IT department, 2 dedicated cybersecurity staff; stated IT budget CAD 100M incl. salaries; 2024-2030 roadmap; medical-device certification and clinical change constraints.
A5: E4 | B5: Business case s.5 - Threat context | C5: Documented (case) | D5: Multiple unsuccessful attack attempts since 2020, increasing recently; no confirmed successful breach; open questions on log sufficiency, device inventories, cloud configuration.
A6: E5 | B6: Business case s.8 - Risk appetite statement | C6: Documented (case) | D6: Low appetite for patient safety, health-data confidentiality, compliance, public trust; moderate for governed innovation; normalized tolerance 0.40; residual >0.25 executive review, >0.40 Board acceptance.
A7: E6 | B7: Business case s.6 and Appendices A-B - Incident injects and technical evidence | C7: Exercise evidence (illustrative - validate) | D7: Phishing with .docm macro; EDR PowerShell alert closed as low severity; remote login from unusual geography with MFA push approved; cloud medical_image_export.zip downloaded from unknown IP; ehr-sync-svc service account unusual query volume; clinic backup failures.
A8: E7 | B8: Business case s.7 - Audit universe | C8: Documented (case) | D8: Auditable areas incl. EHR access/IAM, cloud/remote access, backup, medical device/IoT, Wi-Fi, patching, IDS/SIEM, privacy, third parties, API keys, awareness, remediation governance.
A9: E8 | B9: Business case s.9 - Scenario library MED-CYR-01 to 15 | C9: Documented (case) | D9: Fifteen candidate scenario themes with suggested control families.
A10: E9 | B10: Business case Instructor Annex A - Detailed scenarios | C10: Illustrative values (calibration only) | D10: Illustrative probabilities, damages, resilience, CVSS v3.1 and budgets. Used only as a calibration cross-check; not adopted as evidence.
A11: E10 | B11: Project KB - Cybersecurity Risk Assessment Excel Guide v1.0c | C11: Methodology | D11: Authoritative risk-index formulas; CVSS v4.0; multiplication factor 1,000 in worked example; reductions must stay within 0-1.
A12: E11 | B12: Project KB - Master task specification / Scenario development guide | C12: Methodology | D12: Scenario construction standard, 20-to-10 screening, reporting structure, QC checklist.
A13: E12 | B13: FIRST CVSS v4.0 specification (computed with the 'cvss' Python library) | C13: External reference | D13: Base scores (CVSS-B) computed from the documented vectors.
