Workbook

Sheet Analyse
C1: Scenario | D1: Description | E1: Pb(A) | F1: Pb(ψ,A) | G1: CVSS | H1: CVSS v4.0 vector Vecteur CVSS | I1: δe(ψ,A) | J1: δm(ψ,A) | K1: θ(ψ,A) | L1: μ(E) | M1: Estimated Re | N1: Tolerated Rt | P1: Cost | Q1: Pb reduction rp Réduction Pb | R1: Impact reduction ri Réduction impact | S1: Mitigated Re×rp×ri Mitigé | T1: Residual | U1: Tolerated Rt | W1: Recommendation (1/0) Recommandation | Y1: Pre-treatment ratio Re÷Rt | Z1: Risk-to-tolerance ratio Residual÷Rt | AA1: Tolerance verdict | AB1: Cost-effectiveness (per $1,000) | AC1: Checks | AD1: Transfer: share of loss covered (0-1, informational) | AE1: Transfer approver
C2: Scénario | D2: Description | M2: R estimé Re | N2: R toléré Rt | P2: Coût | T2: R résiduel | U2: R toléré Rt | Y2: Ratio avant traitement | Z2: Ratio risque/tolérance | AA2: Verdict de tolérance | AB2: Coût-efficacité (par 1 000 $) | AC2: Contrôles de validité | AD2: Transfert : part de la perte couverte (0-1, information) | AE2: Approbateur du transfert
C3: ='S1'!$B$2 | D3: ='S1'!$B$3 | E3: ='S1'!$B$6 | F3: ='S1'!$B$7 | I3: ='S1'!$B$8 | J3: ='S1'!$B$9 | K3: ='S1'!$B$10 | L3: ='S1'!$B$11 | M3: =IF(NOT(ISNUMBER(G3)),"CVSS required",IF(N(K3)<=0,"θ required",E3*F3*G3*((I3+J3)/2)*L3/K3*$E$15)) | N3: =IF(NOT(ISNUMBER(G3)),"CVSS required",IF(N(K3)<=0,"θ required",IF(NOT(AND(ISNUMBER($E$14),$E$14>0,$E$14<1)),"Appetite required",E3*F3*G3*$E$14*L3/K3*$E$15))) | P3: ='M1'!N265 | Q3: ='M1'!Q266 | R3: ='M1'!P266 | S3: =IF(ISNUMBER(M3),M3*Q3*R3,"") | T3: =IF(ISNUMBER(M3),MAX(0,M3-S3),"") | U3: =N3 | W3: 0 | Y3: =IF(AND(ISNUMBER(M3),ISNUMBER(N3)),IF(N3>0,M3/N3,""),"") | Z3: =IF(AND(ISNUMBER(T3),ISNUMBER(U3)),IF(U3>0,T3/U3,""),"") | AA3: =IF(Z3="","",IF(OR(COUNTIF('M1'!$K$2:$L$263,">1")>0,COUNTIF('M1'!$K$2:$L$263,"<0")>0),"Review M1: coefficient outside 0-1 / Revoir M1",IF(Z3<0.9,"Below tolerance / Sous la tolérance",IF(Z3<=1.1,"Approximately at tolerance / Environ à la tolérance","Above tolerance / Au-dessus de la tolérance")))) | AB3: =IF(AND(ISNUMBER(T3),N(P3)>0),(M3-T3)/P3*1000,"") | AC3: =IF(NOT(ISNUMBER(G3)),"CVSS required: score with the NVD or FIRST CVSS v4.0 calculator / CVSS requis",IF(H3="","CVSS vector missing: keep the vector next to the score / Vecteur CVSS manquant",IF(NOT(AND(LEFT(H3,9)="CVSS:4.0/",ISNUMBER(SEARCH("/AV:",H3)),ISNUMBER(SEARCH("/AC:",H3)),ISNUMBER(SEARCH("/AT:",H3)),ISNUMBER(SEARCH("/PR:",H3)),ISNUMBER(SEARCH("/UI:",H3)),ISNUMBER(SEARCH("/VC:",H3)),ISNUMBER(SEARCH("/VI:",H3)),ISNUMBER(SEARCH("/VA:",H3)),ISNUMBER(SEARCH("/SC:",H3)),ISNUMBER(SEARCH("/SI:",H3)),ISNUMBER(SEARCH("/SA:",H3)))),"CVSS vector invalid: CVSS:4.0/ with all 11 base metrics / Vecteur CVSS invalide",IF(NOT(AND(ISNUMBER($E$14),$E$14>0,$E$14<1)),"Appetite (E14) must be > 0 and < 1 / Appétence requise",IF(NOT(ISNUMBER(M3)),"θ required (> 0) on sheet S1 / θ requis",IF(OR(COUNTIF('M1'!$K$2:$L$263,">1")>0,COUNTIF('M1'!$K$2:$L$263,"<0")>0),"A coefficient on M1 is outside 0-1: correct it / Un coefficient de M1 est hors de 0-1",IF(OR(S3>M3,S3<0),"Mitigated > Estimated: reduction estimates are wrong / Mitigé > Estimé : estimations erronées",IF(AND(ISNUMBER(AD3),OR(AD3<0,AD3>1)),"Transfer share must be 0-1 / Part transférée : 0 à 1","OK - verify the score against the vector with the calculator / vérifier le score avec le calculateur"))))))))
C4: ='S2'!$B$2 | D4: ='S2'!$B$3 | E4: ='S2'!$B$6 | F4: ='S2'!$B$7 | I4: ='S2'!$B$8 | J4: ='S2'!$B$9 | K4: ='S2'!$B$10 | L4: ='S2'!$B$11 | M4: =IF(NOT(ISNUMBER(G4)),"CVSS required",IF(N(K4)<=0,"θ required",E4*F4*G4*((I4+J4)/2)*L4/K4*$E$15)) | N4: =IF(NOT(ISNUMBER(G4)),"CVSS required",IF(N(K4)<=0,"θ required",IF(NOT(AND(ISNUMBER($E$14),$E$14>0,$E$14<1)),"Appetite required",E4*F4*G4*$E$14*L4/K4*$E$15))) | P4: ='M2'!N265 | Q4: ='M2'!Q266 | R4: ='M2'!P266 | S4: =IF(ISNUMBER(M4),M4*Q4*R4,"") | T4: =IF(ISNUMBER(M4),MAX(0,M4-S4),"") | U4: =N4 | W4: 0 | Y4: =IF(AND(ISNUMBER(M4),ISNUMBER(N4)),IF(N4>0,M4/N4,""),"") | Z4: =IF(AND(ISNUMBER(T4),ISNUMBER(U4)),IF(U4>0,T4/U4,""),"") | AA4: =IF(Z4="","",IF(OR(COUNTIF('M2'!$K$2:$L$263,">1")>0,COUNTIF('M2'!$K$2:$L$263,"<0")>0),"Review M2: coefficient outside 0-1 / Revoir M2",IF(Z4<0.9,"Below tolerance / Sous la tolérance",IF(Z4<=1.1,"Approximately at tolerance / Environ à la tolérance","Above tolerance / Au-dessus de la tolérance")))) | AB4: =IF(AND(ISNUMBER(T4),N(P4)>0),(M4-T4)/P4*1000,"") | AC4: =IF(NOT(ISNUMBER(G4)),"CVSS required: score with the NVD or FIRST CVSS v4.0 calculator / CVSS requis",IF(H4="","CVSS vector missing: keep the vector next to the score / Vecteur CVSS manquant",IF(NOT(AND(LEFT(H4,9)="CVSS:4.0/",ISNUMBER(SEARCH("/AV:",H4)),ISNUMBER(SEARCH("/AC:",H4)),ISNUMBER(SEARCH("/AT:",H4)),ISNUMBER(SEARCH("/PR:",H4)),ISNUMBER(SEARCH("/UI:",H4)),ISNUMBER(SEARCH("/VC:",H4)),ISNUMBER(SEARCH("/VI:",H4)),ISNUMBER(SEARCH("/VA:",H4)),ISNUMBER(SEARCH("/SC:",H4)),ISNUMBER(SEARCH("/SI:",H4)),ISNUMBER(SEARCH("/SA:",H4)))),"CVSS vector invalid: CVSS:4.0/ with all 11 base metrics / Vecteur CVSS invalide",IF(NOT(AND(ISNUMBER($E$14),$E$14>0,$E$14<1)),"Appetite (E14) must be > 0 and < 1 / Appétence requise",IF(NOT(ISNUMBER(M4)),"θ required (> 0) on sheet S2 / θ requis",IF(OR(COUNTIF('M2'!$K$2:$L$263,">1")>0,COUNTIF('M2'!$K$2:$L$263,"<0")>0),"A coefficient on M2 is outside 0-1: correct it / Un coefficient de M2 est hors de 0-1",IF(OR(S4>M4,S4<0),"Mitigated > Estimated: reduction estimates are wrong / Mitigé > Estimé : estimations erronées",IF(AND(ISNUMBER(AD4),OR(AD4<0,AD4>1)),"Transfer share must be 0-1 / Part transférée : 0 à 1","OK - verify the score against the vector with the calculator / vérifier le score avec le calculateur"))))))))
C5: ='S3'!$B$2 | D5: ='S3'!$B$3 | E5: ='S3'!$B$6 | F5: ='S3'!$B$7 | I5: ='S3'!$B$8 | J5: ='S3'!$B$9 | K5: ='S3'!$B$10 | L5: ='S3'!$B$11 | M5: =IF(NOT(ISNUMBER(G5)),"CVSS required",IF(N(K5)<=0,"θ required",E5*F5*G5*((I5+J5)/2)*L5/K5*$E$15)) | N5: =IF(NOT(ISNUMBER(G5)),"CVSS required",IF(N(K5)<=0,"θ required",IF(NOT(AND(ISNUMBER($E$14),$E$14>0,$E$14<1)),"Appetite required",E5*F5*G5*$E$14*L5/K5*$E$15))) | P5: ='M3'!N265 | Q5: ='M3'!Q266 | R5: ='M3'!P266 | S5: =IF(ISNUMBER(M5),M5*Q5*R5,"") | T5: =IF(ISNUMBER(M5),MAX(0,M5-S5),"") | U5: =N5 | W5: 0 | Y5: =IF(AND(ISNUMBER(M5),ISNUMBER(N5)),IF(N5>0,M5/N5,""),"") | Z5: =IF(AND(ISNUMBER(T5),ISNUMBER(U5)),IF(U5>0,T5/U5,""),"") | AA5: =IF(Z5="","",IF(OR(COUNTIF('M3'!$K$2:$L$263,">1")>0,COUNTIF('M3'!$K$2:$L$263,"<0")>0),"Review M3: coefficient outside 0-1 / Revoir M3",IF(Z5<0.9,"Below tolerance / Sous la tolérance",IF(Z5<=1.1,"Approximately at tolerance / Environ à la tolérance","Above tolerance / Au-dessus de la tolérance")))) | AB5: =IF(AND(ISNUMBER(T5),N(P5)>0),(M5-T5)/P5*1000,"") | AC5: =IF(NOT(ISNUMBER(G5)),"CVSS required: score with the NVD or FIRST CVSS v4.0 calculator / CVSS requis",IF(H5="","CVSS vector missing: keep the vector next to the score / Vecteur CVSS manquant",IF(NOT(AND(LEFT(H5,9)="CVSS:4.0/",ISNUMBER(SEARCH("/AV:",H5)),ISNUMBER(SEARCH("/AC:",H5)),ISNUMBER(SEARCH("/AT:",H5)),ISNUMBER(SEARCH("/PR:",H5)),ISNUMBER(SEARCH("/UI:",H5)),ISNUMBER(SEARCH("/VC:",H5)),ISNUMBER(SEARCH("/VI:",H5)),ISNUMBER(SEARCH("/VA:",H5)),ISNUMBER(SEARCH("/SC:",H5)),ISNUMBER(SEARCH("/SI:",H5)),ISNUMBER(SEARCH("/SA:",H5)))),"CVSS vector invalid: CVSS:4.0/ with all 11 base metrics / Vecteur CVSS invalide",IF(NOT(AND(ISNUMBER($E$14),$E$14>0,$E$14<1)),"Appetite (E14) must be > 0 and < 1 / Appétence requise",IF(NOT(ISNUMBER(M5)),"θ required (> 0) on sheet S3 / θ requis",IF(OR(COUNTIF('M3'!$K$2:$L$263,">1")>0,COUNTIF('M3'!$K$2:$L$263,"<0")>0),"A coefficient on M3 is outside 0-1: correct it / Un coefficient de M3 est hors de 0-1",IF(OR(S5>M5,S5<0),"Mitigated > Estimated: reduction estimates are wrong / Mitigé > Estimé : estimations erronées",IF(AND(ISNUMBER(AD5),OR(AD5<0,AD5>1)),"Transfer share must be 0-1 / Part transférée : 0 à 1","OK - verify the score against the vector with the calculator / vérifier le score avec le calculateur"))))))))
C6: ='S4'!$B$2 | D6: ='S4'!$B$3 | E6: ='S4'!$B$6 | F6: ='S4'!$B$7 | I6: ='S4'!$B$8 | J6: ='S4'!$B$9 | K6: ='S4'!$B$10 | L6: ='S4'!$B$11 | M6: =IF(NOT(ISNUMBER(G6)),"CVSS required",IF(N(K6)<=0,"θ required",E6*F6*G6*((I6+J6)/2)*L6/K6*$E$15)) | N6: =IF(NOT(ISNUMBER(G6)),"CVSS required",IF(N(K6)<=0,"θ required",IF(NOT(AND(ISNUMBER($E$14),$E$14>0,$E$14<1)),"Appetite required",E6*F6*G6*$E$14*L6/K6*$E$15))) | P6: ='M4'!N265 | Q6: ='M4'!Q266 | R6: ='M4'!P266 | S6: =IF(ISNUMBER(M6),M6*Q6*R6,"") | T6: =IF(ISNUMBER(M6),MAX(0,M6-S6),"") | U6: =N6 | W6: 0 | Y6: =IF(AND(ISNUMBER(M6),ISNUMBER(N6)),IF(N6>0,M6/N6,""),"") | Z6: =IF(AND(ISNUMBER(T6),ISNUMBER(U6)),IF(U6>0,T6/U6,""),"") | AA6: =IF(Z6="","",IF(OR(COUNTIF('M4'!$K$2:$L$263,">1")>0,COUNTIF('M4'!$K$2:$L$263,"<0")>0),"Review M4: coefficient outside 0-1 / Revoir M4",IF(Z6<0.9,"Below tolerance / Sous la tolérance",IF(Z6<=1.1,"Approximately at tolerance / Environ à la tolérance","Above tolerance / Au-dessus de la tolérance")))) | AB6: =IF(AND(ISNUMBER(T6),N(P6)>0),(M6-T6)/P6*1000,"") | AC6: =IF(NOT(ISNUMBER(G6)),"CVSS required: score with the NVD or FIRST CVSS v4.0 calculator / CVSS requis",IF(H6="","CVSS vector missing: keep the vector next to the score / Vecteur CVSS manquant",IF(NOT(AND(LEFT(H6,9)="CVSS:4.0/",ISNUMBER(SEARCH("/AV:",H6)),ISNUMBER(SEARCH("/AC:",H6)),ISNUMBER(SEARCH("/AT:",H6)),ISNUMBER(SEARCH("/PR:",H6)),ISNUMBER(SEARCH("/UI:",H6)),ISNUMBER(SEARCH("/VC:",H6)),ISNUMBER(SEARCH("/VI:",H6)),ISNUMBER(SEARCH("/VA:",H6)),ISNUMBER(SEARCH("/SC:",H6)),ISNUMBER(SEARCH("/SI:",H6)),ISNUMBER(SEARCH("/SA:",H6)))),"CVSS vector invalid: CVSS:4.0/ with all 11 base metrics / Vecteur CVSS invalide",IF(NOT(AND(ISNUMBER($E$14),$E$14>0,$E$14<1)),"Appetite (E14) must be > 0 and < 1 / Appétence requise",IF(NOT(ISNUMBER(M6)),"θ required (> 0) on sheet S4 / θ requis",IF(OR(COUNTIF('M4'!$K$2:$L$263,">1")>0,COUNTIF('M4'!$K$2:$L$263,"<0")>0),"A coefficient on M4 is outside 0-1: correct it / Un coefficient de M4 est hors de 0-1",IF(OR(S6>M6,S6<0),"Mitigated > Estimated: reduction estimates are wrong / Mitigé > Estimé : estimations erronées",IF(AND(ISNUMBER(AD6),OR(AD6<0,AD6>1)),"Transfer share must be 0-1 / Part transférée : 0 à 1","OK - verify the score against the vector with the calculator / vérifier le score avec le calculateur"))))))))
C7: ='S5'!$B$2 | D7: ='S5'!$B$3 | E7: ='S5'!$B$6 | F7: ='S5'!$B$7 | I7: ='S5'!$B$8 | J7: ='S5'!$B$9 | K7: ='S5'!$B$10 | L7: ='S5'!$B$11 | M7: =IF(NOT(ISNUMBER(G7)),"CVSS required",IF(N(K7)<=0,"θ required",E7*F7*G7*((I7+J7)/2)*L7/K7*$E$15)) | N7: =IF(NOT(ISNUMBER(G7)),"CVSS required",IF(N(K7)<=0,"θ required",IF(NOT(AND(ISNUMBER($E$14),$E$14>0,$E$14<1)),"Appetite required",E7*F7*G7*$E$14*L7/K7*$E$15))) | P7: ='M5'!N265 | Q7: ='M5'!Q266 | R7: ='M5'!P266 | S7: =IF(ISNUMBER(M7),M7*Q7*R7,"") | T7: =IF(ISNUMBER(M7),MAX(0,M7-S7),"") | U7: =N7 | W7: 0 | Y7: =IF(AND(ISNUMBER(M7),ISNUMBER(N7)),IF(N7>0,M7/N7,""),"") | Z7: =IF(AND(ISNUMBER(T7),ISNUMBER(U7)),IF(U7>0,T7/U7,""),"") | AA7: =IF(Z7="","",IF(OR(COUNTIF('M5'!$K$2:$L$263,">1")>0,COUNTIF('M5'!$K$2:$L$263,"<0")>0),"Review M5: coefficient outside 0-1 / Revoir M5",IF(Z7<0.9,"Below tolerance / Sous la tolérance",IF(Z7<=1.1,"Approximately at tolerance / Environ à la tolérance","Above tolerance / Au-dessus de la tolérance")))) | AB7: =IF(AND(ISNUMBER(T7),N(P7)>0),(M7-T7)/P7*1000,"") | AC7: =IF(NOT(ISNUMBER(G7)),"CVSS required: score with the NVD or FIRST CVSS v4.0 calculator / CVSS requis",IF(H7="","CVSS vector missing: keep the vector next to the score / Vecteur CVSS manquant",IF(NOT(AND(LEFT(H7,9)="CVSS:4.0/",ISNUMBER(SEARCH("/AV:",H7)),ISNUMBER(SEARCH("/AC:",H7)),ISNUMBER(SEARCH("/AT:",H7)),ISNUMBER(SEARCH("/PR:",H7)),ISNUMBER(SEARCH("/UI:",H7)),ISNUMBER(SEARCH("/VC:",H7)),ISNUMBER(SEARCH("/VI:",H7)),ISNUMBER(SEARCH("/VA:",H7)),ISNUMBER(SEARCH("/SC:",H7)),ISNUMBER(SEARCH("/SI:",H7)),ISNUMBER(SEARCH("/SA:",H7)))),"CVSS vector invalid: CVSS:4.0/ with all 11 base metrics / Vecteur CVSS invalide",IF(NOT(AND(ISNUMBER($E$14),$E$14>0,$E$14<1)),"Appetite (E14) must be > 0 and < 1 / Appétence requise",IF(NOT(ISNUMBER(M7)),"θ required (> 0) on sheet S5 / θ requis",IF(OR(COUNTIF('M5'!$K$2:$L$263,">1")>0,COUNTIF('M5'!$K$2:$L$263,"<0")>0),"A coefficient on M5 is outside 0-1: correct it / Un coefficient de M5 est hors de 0-1",IF(OR(S7>M7,S7<0),"Mitigated > Estimated: reduction estimates are wrong / Mitigé > Estimé : estimations erronées",IF(AND(ISNUMBER(AD7),OR(AD7<0,AD7>1)),"Transfer share must be 0-1 / Part transférée : 0 à 1","OK - verify the score against the vector with the calculator / vérifier le score avec le calculateur"))))))))
C8: ='S6'!$B$2 | D8: ='S6'!$B$3 | E8: ='S6'!$B$6 | F8: ='S6'!$B$7 | I8: ='S6'!$B$8 | J8: ='S6'!$B$9 | K8: ='S6'!$B$10 | L8: ='S6'!$B$11 | M8: =IF(NOT(ISNUMBER(G8)),"CVSS required",IF(N(K8)<=0,"θ required",E8*F8*G8*((I8+J8)/2)*L8/K8*$E$15)) | N8: =IF(NOT(ISNUMBER(G8)),"CVSS required",IF(N(K8)<=0,"θ required",IF(NOT(AND(ISNUMBER($E$14),$E$14>0,$E$14<1)),"Appetite required",E8*F8*G8*$E$14*L8/K8*$E$15))) | P8: ='M6'!N265 | Q8: ='M6'!Q266 | R8: ='M6'!P266 | S8: =IF(ISNUMBER(M8),M8*Q8*R8,"") | T8: =IF(ISNUMBER(M8),MAX(0,M8-S8),"") | U8: =N8 | W8: 0 | Y8: =IF(AND(ISNUMBER(M8),ISNUMBER(N8)),IF(N8>0,M8/N8,""),"") | Z8: =IF(AND(ISNUMBER(T8),ISNUMBER(U8)),IF(U8>0,T8/U8,""),"") | AA8: =IF(Z8="","",IF(OR(COUNTIF('M6'!$K$2:$L$263,">1")>0,COUNTIF('M6'!$K$2:$L$263,"<0")>0),"Review M6: coefficient outside 0-1 / Revoir M6",IF(Z8<0.9,"Below tolerance / Sous la tolérance",IF(Z8<=1.1,"Approximately at tolerance / Environ à la tolérance","Above tolerance / Au-dessus de la tolérance")))) | AB8: =IF(AND(ISNUMBER(T8),N(P8)>0),(M8-T8)/P8*1000,"") | AC8: =IF(NOT(ISNUMBER(G8)),"CVSS required: score with the NVD or FIRST CVSS v4.0 calculator / CVSS requis",IF(H8="","CVSS vector missing: keep the vector next to the score / Vecteur CVSS manquant",IF(NOT(AND(LEFT(H8,9)="CVSS:4.0/",ISNUMBER(SEARCH("/AV:",H8)),ISNUMBER(SEARCH("/AC:",H8)),ISNUMBER(SEARCH("/AT:",H8)),ISNUMBER(SEARCH("/PR:",H8)),ISNUMBER(SEARCH("/UI:",H8)),ISNUMBER(SEARCH("/VC:",H8)),ISNUMBER(SEARCH("/VI:",H8)),ISNUMBER(SEARCH("/VA:",H8)),ISNUMBER(SEARCH("/SC:",H8)),ISNUMBER(SEARCH("/SI:",H8)),ISNUMBER(SEARCH("/SA:",H8)))),"CVSS vector invalid: CVSS:4.0/ with all 11 base metrics / Vecteur CVSS invalide",IF(NOT(AND(ISNUMBER($E$14),$E$14>0,$E$14<1)),"Appetite (E14) must be > 0 and < 1 / Appétence requise",IF(NOT(ISNUMBER(M8)),"θ required (> 0) on sheet S6 / θ requis",IF(OR(COUNTIF('M6'!$K$2:$L$263,">1")>0,COUNTIF('M6'!$K$2:$L$263,"<0")>0),"A coefficient on M6 is outside 0-1: correct it / Un coefficient de M6 est hors de 0-1",IF(OR(S8>M8,S8<0),"Mitigated > Estimated: reduction estimates are wrong / Mitigé > Estimé : estimations erronées",IF(AND(ISNUMBER(AD8),OR(AD8<0,AD8>1)),"Transfer share must be 0-1 / Part transférée : 0 à 1","OK - verify the score against the vector with the calculator / vérifier le score avec le calculateur"))))))))
C9: ='S7'!$B$2 | D9: ='S7'!$B$3 | E9: ='S7'!$B$6 | F9: ='S7'!$B$7 | I9: ='S7'!$B$8 | J9: ='S7'!$B$9 | K9: ='S7'!$B$10 | L9: ='S7'!$B$11 | M9: =IF(NOT(ISNUMBER(G9)),"CVSS required",IF(N(K9)<=0,"θ required",E9*F9*G9*((I9+J9)/2)*L9/K9*$E$15)) | N9: =IF(NOT(ISNUMBER(G9)),"CVSS required",IF(N(K9)<=0,"θ required",IF(NOT(AND(ISNUMBER($E$14),$E$14>0,$E$14<1)),"Appetite required",E9*F9*G9*$E$14*L9/K9*$E$15))) | P9: ='M7'!N265 | Q9: ='M7'!Q266 | R9: ='M7'!P266 | S9: =IF(ISNUMBER(M9),M9*Q9*R9,"") | T9: =IF(ISNUMBER(M9),MAX(0,M9-S9),"") | U9: =N9 | W9: 0 | Y9: =IF(AND(ISNUMBER(M9),ISNUMBER(N9)),IF(N9>0,M9/N9,""),"") | Z9: =IF(AND(ISNUMBER(T9),ISNUMBER(U9)),IF(U9>0,T9/U9,""),"") | AA9: =IF(Z9="","",IF(OR(COUNTIF('M7'!$K$2:$L$263,">1")>0,COUNTIF('M7'!$K$2:$L$263,"<0")>0),"Review M7: coefficient outside 0-1 / Revoir M7",IF(Z9<0.9,"Below tolerance / Sous la tolérance",IF(Z9<=1.1,"Approximately at tolerance / Environ à la tolérance","Above tolerance / Au-dessus de la tolérance")))) | AB9: =IF(AND(ISNUMBER(T9),N(P9)>0),(M9-T9)/P9*1000,"") | AC9: =IF(NOT(ISNUMBER(G9)),"CVSS required: score with the NVD or FIRST CVSS v4.0 calculator / CVSS requis",IF(H9="","CVSS vector missing: keep the vector next to the score / Vecteur CVSS manquant",IF(NOT(AND(LEFT(H9,9)="CVSS:4.0/",ISNUMBER(SEARCH("/AV:",H9)),ISNUMBER(SEARCH("/AC:",H9)),ISNUMBER(SEARCH("/AT:",H9)),ISNUMBER(SEARCH("/PR:",H9)),ISNUMBER(SEARCH("/UI:",H9)),ISNUMBER(SEARCH("/VC:",H9)),ISNUMBER(SEARCH("/VI:",H9)),ISNUMBER(SEARCH("/VA:",H9)),ISNUMBER(SEARCH("/SC:",H9)),ISNUMBER(SEARCH("/SI:",H9)),ISNUMBER(SEARCH("/SA:",H9)))),"CVSS vector invalid: CVSS:4.0/ with all 11 base metrics / Vecteur CVSS invalide",IF(NOT(AND(ISNUMBER($E$14),$E$14>0,$E$14<1)),"Appetite (E14) must be > 0 and < 1 / Appétence requise",IF(NOT(ISNUMBER(M9)),"θ required (> 0) on sheet S7 / θ requis",IF(OR(COUNTIF('M7'!$K$2:$L$263,">1")>0,COUNTIF('M7'!$K$2:$L$263,"<0")>0),"A coefficient on M7 is outside 0-1: correct it / Un coefficient de M7 est hors de 0-1",IF(OR(S9>M9,S9<0),"Mitigated > Estimated: reduction estimates are wrong / Mitigé > Estimé : estimations erronées",IF(AND(ISNUMBER(AD9),OR(AD9<0,AD9>1)),"Transfer share must be 0-1 / Part transférée : 0 à 1","OK - verify the score against the vector with the calculator / vérifier le score avec le calculateur"))))))))
C10: ='S8'!$B$2 | D10: ='S8'!$B$3 | E10: ='S8'!$B$6 | F10: ='S8'!$B$7 | I10: ='S8'!$B$8 | J10: ='S8'!$B$9 | K10: ='S8'!$B$10 | L10: ='S8'!$B$11 | M10: =IF(NOT(ISNUMBER(G10)),"CVSS required",IF(N(K10)<=0,"θ required",E10*F10*G10*((I10+J10)/2)*L10/K10*$E$15)) | N10: =IF(NOT(ISNUMBER(G10)),"CVSS required",IF(N(K10)<=0,"θ required",IF(NOT(AND(ISNUMBER($E$14),$E$14>0,$E$14<1)),"Appetite required",E10*F10*G10*$E$14*L10/K10*$E$15))) | P10: ='M8'!N265 | Q10: ='M8'!Q266 | R10: ='M8'!P266 | S10: =IF(ISNUMBER(M10),M10*Q10*R10,"") | T10: =IF(ISNUMBER(M10),MAX(0,M10-S10),"") | U10: =N10 | W10: 0 | Y10: =IF(AND(ISNUMBER(M10),ISNUMBER(N10)),IF(N10>0,M10/N10,""),"") | Z10: =IF(AND(ISNUMBER(T10),ISNUMBER(U10)),IF(U10>0,T10/U10,""),"") | AA10: =IF(Z10="","",IF(OR(COUNTIF('M8'!$K$2:$L$263,">1")>0,COUNTIF('M8'!$K$2:$L$263,"<0")>0),"Review M8: coefficient outside 0-1 / Revoir M8",IF(Z10<0.9,"Below tolerance / Sous la tolérance",IF(Z10<=1.1,"Approximately at tolerance / Environ à la tolérance","Above tolerance / Au-dessus de la tolérance")))) | AB10: =IF(AND(ISNUMBER(T10),N(P10)>0),(M10-T10)/P10*1000,"") | AC10: =IF(NOT(ISNUMBER(G10)),"CVSS required: score with the NVD or FIRST CVSS v4.0 calculator / CVSS requis",IF(H10="","CVSS vector missing: keep the vector next to the score / Vecteur CVSS manquant",IF(NOT(AND(LEFT(H10,9)="CVSS:4.0/",ISNUMBER(SEARCH("/AV:",H10)),ISNUMBER(SEARCH("/AC:",H10)),ISNUMBER(SEARCH("/AT:",H10)),ISNUMBER(SEARCH("/PR:",H10)),ISNUMBER(SEARCH("/UI:",H10)),ISNUMBER(SEARCH("/VC:",H10)),ISNUMBER(SEARCH("/VI:",H10)),ISNUMBER(SEARCH("/VA:",H10)),ISNUMBER(SEARCH("/SC:",H10)),ISNUMBER(SEARCH("/SI:",H10)),ISNUMBER(SEARCH("/SA:",H10)))),"CVSS vector invalid: CVSS:4.0/ with all 11 base metrics / Vecteur CVSS invalide",IF(NOT(AND(ISNUMBER($E$14),$E$14>0,$E$14<1)),"Appetite (E14) must be > 0 and < 1 / Appétence requise",IF(NOT(ISNUMBER(M10)),"θ required (> 0) on sheet S8 / θ requis",IF(OR(COUNTIF('M8'!$K$2:$L$263,">1")>0,COUNTIF('M8'!$K$2:$L$263,"<0")>0),"A coefficient on M8 is outside 0-1: correct it / Un coefficient de M8 est hors de 0-1",IF(OR(S10>M10,S10<0),"Mitigated > Estimated: reduction estimates are wrong / Mitigé > Estimé : estimations erronées",IF(AND(ISNUMBER(AD10),OR(AD10<0,AD10>1)),"Transfer share must be 0-1 / Part transférée : 0 à 1","OK - verify the score against the vector with the calculator / vérifier le score avec le calculateur"))))))))
C11: ='S9'!$B$2 | D11: ='S9'!$B$3 | E11: ='S9'!$B$6 | F11: ='S9'!$B$7 | I11: ='S9'!$B$8 | J11: ='S9'!$B$9 | K11: ='S9'!$B$10 | L11: ='S9'!$B$11 | M11: =IF(NOT(ISNUMBER(G11)),"CVSS required",IF(N(K11)<=0,"θ required",E11*F11*G11*((I11+J11)/2)*L11/K11*$E$15)) | N11: =IF(NOT(ISNUMBER(G11)),"CVSS required",IF(N(K11)<=0,"θ required",IF(NOT(AND(ISNUMBER($E$14),$E$14>0,$E$14<1)),"Appetite required",E11*F11*G11*$E$14*L11/K11*$E$15))) | P11: ='M9'!N265 | Q11: ='M9'!Q266 | R11: ='M9'!P266 | S11: =IF(ISNUMBER(M11),M11*Q11*R11,"") | T11: =IF(ISNUMBER(M11),MAX(0,M11-S11),"") | U11: =N11 | W11: 0 | Y11: =IF(AND(ISNUMBER(M11),ISNUMBER(N11)),IF(N11>0,M11/N11,""),"") | Z11: =IF(AND(ISNUMBER(T11),ISNUMBER(U11)),IF(U11>0,T11/U11,""),"") | AA11: =IF(Z11="","",IF(OR(COUNTIF('M9'!$K$2:$L$263,">1")>0,COUNTIF('M9'!$K$2:$L$263,"<0")>0),"Review M9: coefficient outside 0-1 / Revoir M9",IF(Z11<0.9,"Below tolerance / Sous la tolérance",IF(Z11<=1.1,"Approximately at tolerance / Environ à la tolérance","Above tolerance / Au-dessus de la tolérance")))) | AB11: =IF(AND(ISNUMBER(T11),N(P11)>0),(M11-T11)/P11*1000,"") | AC11: =IF(NOT(ISNUMBER(G11)),"CVSS required: score with the NVD or FIRST CVSS v4.0 calculator / CVSS requis",IF(H11="","CVSS vector missing: keep the vector next to the score / Vecteur CVSS manquant",IF(NOT(AND(LEFT(H11,9)="CVSS:4.0/",ISNUMBER(SEARCH("/AV:",H11)),ISNUMBER(SEARCH("/AC:",H11)),ISNUMBER(SEARCH("/AT:",H11)),ISNUMBER(SEARCH("/PR:",H11)),ISNUMBER(SEARCH("/UI:",H11)),ISNUMBER(SEARCH("/VC:",H11)),ISNUMBER(SEARCH("/VI:",H11)),ISNUMBER(SEARCH("/VA:",H11)),ISNUMBER(SEARCH("/SC:",H11)),ISNUMBER(SEARCH("/SI:",H11)),ISNUMBER(SEARCH("/SA:",H11)))),"CVSS vector invalid: CVSS:4.0/ with all 11 base metrics / Vecteur CVSS invalide",IF(NOT(AND(ISNUMBER($E$14),$E$14>0,$E$14<1)),"Appetite (E14) must be > 0 and < 1 / Appétence requise",IF(NOT(ISNUMBER(M11)),"θ required (> 0) on sheet S9 / θ requis",IF(OR(COUNTIF('M9'!$K$2:$L$263,">1")>0,COUNTIF('M9'!$K$2:$L$263,"<0")>0),"A coefficient on M9 is outside 0-1: correct it / Un coefficient de M9 est hors de 0-1",IF(OR(S11>M11,S11<0),"Mitigated > Estimated: reduction estimates are wrong / Mitigé > Estimé : estimations erronées",IF(AND(ISNUMBER(AD11),OR(AD11<0,AD11>1)),"Transfer share must be 0-1 / Part transférée : 0 à 1","OK - verify the score against the vector with the calculator / vérifier le score avec le calculateur"))))))))
C12: ='S10'!$B$2 | D12: ='S10'!$B$3 | E12: ='S10'!$B$6 | F12: ='S10'!$B$7 | I12: ='S10'!$B$8 | J12: ='S10'!$B$9 | K12: ='S10'!$B$10 | L12: ='S10'!$B$11 | M12: =IF(NOT(ISNUMBER(G12)),"CVSS required",IF(N(K12)<=0,"θ required",E12*F12*G12*((I12+J12)/2)*L12/K12*$E$15)) | N12: =IF(NOT(ISNUMBER(G12)),"CVSS required",IF(N(K12)<=0,"θ required",IF(NOT(AND(ISNUMBER($E$14),$E$14>0,$E$14<1)),"Appetite required",E12*F12*G12*$E$14*L12/K12*$E$15))) | P12: ='M10'!N265 | Q12: ='M10'!Q266 | R12: ='M10'!P266 | S12: =IF(ISNUMBER(M12),M12*Q12*R12,"") | T12: =IF(ISNUMBER(M12),MAX(0,M12-S12),"") | U12: =N12 | W12: 0 | Y12: =IF(AND(ISNUMBER(M12),ISNUMBER(N12)),IF(N12>0,M12/N12,""),"") | Z12: =IF(AND(ISNUMBER(T12),ISNUMBER(U12)),IF(U12>0,T12/U12,""),"") | AA12: =IF(Z12="","",IF(OR(COUNTIF('M10'!$K$2:$L$263,">1")>0,COUNTIF('M10'!$K$2:$L$263,"<0")>0),"Review M10: coefficient outside 0-1 / Revoir M10",IF(Z12<0.9,"Below tolerance / Sous la tolérance",IF(Z12<=1.1,"Approximately at tolerance / Environ à la tolérance","Above tolerance / Au-dessus de la tolérance")))) | AB12: =IF(AND(ISNUMBER(T12),N(P12)>0),(M12-T12)/P12*1000,"") | AC12: =IF(NOT(ISNUMBER(G12)),"CVSS required: score with the NVD or FIRST CVSS v4.0 calculator / CVSS requis",IF(H12="","CVSS vector missing: keep the vector next to the score / Vecteur CVSS manquant",IF(NOT(AND(LEFT(H12,9)="CVSS:4.0/",ISNUMBER(SEARCH("/AV:",H12)),ISNUMBER(SEARCH("/AC:",H12)),ISNUMBER(SEARCH("/AT:",H12)),ISNUMBER(SEARCH("/PR:",H12)),ISNUMBER(SEARCH("/UI:",H12)),ISNUMBER(SEARCH("/VC:",H12)),ISNUMBER(SEARCH("/VI:",H12)),ISNUMBER(SEARCH("/VA:",H12)),ISNUMBER(SEARCH("/SC:",H12)),ISNUMBER(SEARCH("/SI:",H12)),ISNUMBER(SEARCH("/SA:",H12)))),"CVSS vector invalid: CVSS:4.0/ with all 11 base metrics / Vecteur CVSS invalide",IF(NOT(AND(ISNUMBER($E$14),$E$14>0,$E$14<1)),"Appetite (E14) must be > 0 and < 1 / Appétence requise",IF(NOT(ISNUMBER(M12)),"θ required (> 0) on sheet S10 / θ requis",IF(OR(COUNTIF('M10'!$K$2:$L$263,">1")>0,COUNTIF('M10'!$K$2:$L$263,"<0")>0),"A coefficient on M10 is outside 0-1: correct it / Un coefficient de M10 est hors de 0-1",IF(OR(S12>M12,S12<0),"Mitigated > Estimated: reduction estimates are wrong / Mitigé > Estimé : estimations erronées",IF(AND(ISNUMBER(AD12),OR(AD12<0,AD12>1)),"Transfer share must be 0-1 / Part transférée : 0 à 1","OK - verify the score against the vector with the calculator / vérifier le score avec le calculateur"))))))))
U13: Cost / Coût : | W13: =(W3*P3)+(W4*P4)+(W5*P5)+(W6*P6)+(W7*P7)+(W8*P8)+(W9*P9)+(W10*P10)+(W11*P11)+(W12*P12)
D14: Risk appetite - Appétence au risque : | E14: 0.5 | F14: =IF(AND(ISNUMBER(E14),E14>0,E14<1),IF(OR(E14<0.1,E14>0.9),"Outside recommended 0.1-0.9 / hors plage recommandée",""),"Appetite must be > 0 and < 1 / doit être > 0 et < 1") | N14: Total cost / Coût total : | P14: =SUM(P3:P12) | Y14: Cybersecurity budget — best-practice benchmark / Budget de cybersécurité — référence de bonnes pratiques
D15: Multiplication factor - Facteur : | E15: 1000 | F15: =IF(E15<>1000,"CRG convention is 1,000 / convention CRG : 1 000","") | Y15: Total IT budget incl. salaries / Budget TI total ($)
J16: 4. Saisir le score CVSS v4.0 (G3:G12) et le vecteur (H3:H12) | Y16: Benchmark % at appetite E14 / % de référence | AB16: =IF(AND(ISNUMBER(E14),E14>0,E14<1),IF(E14<=0.3,0.12,IF(E14<=0.5,0.12+(E14-0.3)/0.2*(0.078-0.12),IF(E14<=0.7,0.078+(E14-0.5)/0.2*(0.04-0.078),0.04))),"")
D17: 2. Indiquer l'appétence au risque de l'organisation (E14) | J17: 4. Enter the CVSS v4.0 score (G3:G12) and vector (H3:H12) | Y17: Benchmark cyber budget / Budget de référence ($) | AB17: =IF(AND(N(AB15)>0,ISNUMBER(AB16)),AB15*AB16,"")
D18: 2. Set the organization's risk appetite (E14) | Y18: Recommended cost W13 ÷ IT budget / Coût recommandé ÷ budget TI | AB18: =IF(N(AB15)>0,W13/AB15,"")
D19: Very low / Très faible = 0.1 | F19: Procédure en 8 étapes (chapitre 6) / 8-step procedure (chapter 6) | Y19: Rule: appetite ≤ 0.30 → 12%; 0.50 → 7.8%; ≥ 0.70 → 4%; linear in between; % of the total IT budget, salaries included. / Règle : ≤ 0,30 → 12 %; 0,50 → 7,8 %; ≥ 0,70 → 4 %; interpolation linéaire.
D20: Risk averse / Aversion au risque = 0.3 | F20: 1. Préparer le classeur et vérifier le moteur : saisir l'exemple du chapitre 6 en S1 (CVSS 9,3), Calculer maintenant, confirmer Re 3 554,46 et résiduel 1 937,18 | Y20: Current cybersecurity spending ($) / Dépenses actuelles de cybersécurité ($)
D21: Risk neutral / Neutre = 0.5 | F21: 2. Indiquer l'appétence approuvée ou estimée (E14, strictement entre 0 et 1, jamais la valeur provisoire 0,5) et garder le facteur à 1 000 (E15) | S21: 8. Recommander le portefeuille : 1 dans la colonne W | Y21: Planned = current + recommended (W13) ($) / Prévu = actuel + recommandé ($) | AB21: =IF(ISNUMBER(AB20),AB20+W13,"")
D22: Risk seeking / Propension au risque = 0.7 | F22: 3. Renseigner les scénarios (feuilles S1 à S10) : Pb(A), Pb(ψ,A), δe, δm (≥ δe), θ (> 0), μ(E), avec justification, preuve et confiance | S22: 8. Recommend the portfolio: enter 1 in column W | Y22: Planned % of IT budget / % prévu du budget TI | AB22: =IF(AND(N(AB15)>0,ISNUMBER(AB21)),AB21/AB15,"")
D23: Very high / Très élevée = 0.9 | F23: 4. Saisir le score CVSS v4.0 (G3:G12) et son vecteur (H3:H12) : calculateur NVD https://nvd.nist.gov/vuln-metrics/cvss/v4-calculator ou FIRST | Y23: Gap to target ($; positive = below target) / Écart à la cible ($) | AB23: =IF(AND(ISNUMBER(AB17),ISNUMBER(AB21)),AB17-AB21,"")
D24: Strictly > 0 and < 1 / strictement > 0 et < 1 | F24: 5. Calculer et lire le risque estimé et toléré : mode manuel - Formules > Calculer maintenant (F9); ratio avant traitement = dommage moyen ÷ appétence | Y24: Implied appetite of the planned spending / Appétence implicite | AB24: =IF(ISNUMBER(AB22),IF(AB22>=0.12,0.3,IF(AB22>=0.078,0.3+(0.12-AB22)/(0.12-0.078)*0.2,IF(AB22>=0.04,0.5+(0.078-AB22)/(0.078-0.04)*0.2,0.7))),"")
F25: 6. Définir le traitement (feuilles M1 à M10) : 1 dans la colonne A; réductions combinées par la règle du produit 1 − ∏(1 − rᵢ) | Y25: Report the gap; closing it or revising the appetite is a Management decision required. Count shared controls once (split their cost across scenarios). / L'écart est signalé; le combler ou réviser l'appétence : Décision de la direction requise.
F26: 7. Recalculer et lire le résiduel, le ratio risque/tolérance et le coût-efficacité; transfert, évitement, acceptation = décisions
F27: 8. Recommander le portefeuille (colonne W = 1) et calibrer le budget (Y14:AC25) - Décision de la direction requise
F28: 1. Prepare the workbook and verify the engine: enter the chapter 6 worked example in S1 (CVSS 9.3), Calculate Now, confirm Re 3,554.46 and residual 1,937.18
F29: 2. Enter the approved or estimated appetite (E14, strictly between 0 and 1, never the 0.5 placeholder) and keep the factor at 1,000 (E15)
F30: 3. Populate the scenario sheets (S1 to S10): Pb(A), Pb(ψ,A), δe, δm (≥ δe), θ (> 0), μ(E), with rationale, evidence and confidence
F31: 4. Enter each CVSS v4.0 score (G3:G12) and its vector (H3:H12): NVD calculator https://nvd.nist.gov/vuln-metrics/cvss/v4-calculator or FIRST
F32: 5. Calculate and read estimated and tolerated risk: manual mode - Formulas > Calculate Now (F9); pre-treatment ratio = average damage ÷ appetite
F33: 6. Define the treatment (sheets M1 to M10): 1 in column A; reductions combine with the product rule 1 − ∏(1 − rᵢ)
F34: 7. Recalculate and read residual risk, the risk-to-tolerance ratio and cost-effectiveness; transfer, avoidance, acceptance are decisions
F35: 8. Recommend the portfolio (column W = 1) and calibrate the budget (Y14:AC25) - Management decision required
F37: Formulas and rules (CyberRiskGuardian) / Formules et règles
F38: Estimated risk Re = Pb(A) × Pb(ψ,A) × CVSS × ((δe + δm) / 2) × μ(E) ÷ θ(ψ,A) × Factor
... F51: CyberRiskGuardian Excel model v2-6 (October 2026), aligned with Introduction to Cybersecurity Governance, 3rd ed., v2.51, ch06. CC BY-NC 4.0, © Marc-André Léger.

Sheet S1
A1: Risk scenario number 1 / Scénario de risque 1
A2: Scenario number / Numéro : | B2: 1
A3: Scenario name / Nom du scénario :
A4: Date of creation / Date de création du scénario :
A6: Probability that the threat will be present = Probabilité de réalisation : Pb(A)
A7: Probability of exploitation = Probabilité d’exploitation: Pb(ψ,A)
A8: Estimated expected damages = Dommage estimé: δe(ψ,A)
A9: Maximal damages = Dommage maximal: δm(ψ,A) | C9: =IF(AND(ISNUMBER(B8),ISNUMBER(B9),B9<B8),"δm should be ≥ δe / δm devrait être ≥ δe","")
A10: Level of organizational resilience = Niveau de résilience: θ(ψ,A) | C10: =IF(AND(B10<>"",OR(NOT(ISNUMBER(B10)),B10<=0,B10>1)),"θ must be in (0, 1] / θ doit être dans ]0, 1]","")
A11: Organizational criticality (expected utility) = Criticité organisationnelle (utilité espérée) : μ(E)
A14: 3. Renseigner les scénarios de risque (feuilles S1 à S10)
A15: 3. Populate the risk scenarios (Sheets S1 to S10)
A16: Values 0-1; θ > 0 and ≤ 1; δm ≥ δe. Horizon: 12 months. Each value: rationale, evidence (E-number), confidence — Analytical estimate — validation required.
A17: Valeurs 0-1; θ > 0 et ≤ 1; δm ≥ δe. Horizon : 12 mois. Chaque valeur : justification, preuve (n° E), confiance — Estimation analytique — validation requise.

Sheet M1
A1: Other / autre | C1: Proposed risk mitigation measure / mesure de mitigation des risques proposés | D1: Source | F1: Immobilisations | G1: Logiciels | H1: Mise en œuvre | I1: Exploitation | J1: ÉTC | K1: Réduc impacts | L1: Réduction Pb | N1: Coût | O1: ETC | P1: Impact | Q1: Pb | R1: 1 − impact | S1: 1 − Pb
N2: =A2*((SUM(F2:I2))+(J2*1950*80)) | O2: =A2*J2 | P2: =A2*K2 | Q2: =A2*L2 | R2: =1-P2 | S2: =1-Q2
N3: =A3*((SUM(F3:I3))+(J3*1950*80)) | O3: =A3*J3 | P3: =A3*K3 | Q3: =A3*L3 | R3: =1-P3 | S3: =1-Q3
N4: =A4*((SUM(F4:I4))+(J4*1950*80)) | O4: =A4*J4 | P4: =A4*K4 | Q4: =A4*L4 | R4: =1-P4 | S4: =1-Q4
N5: =A5*((SUM(F5:I5))+(J5*1950*80)) | O5: =A5*J5 | P5: =A5*K5 | Q5: =A5*L5 | R5: =1-P5 | S5: =1-Q5
N6: =A6*((SUM(F6:I6))+(J6*1950*80)) | O6: =A6*J6 | P6: =A6*K6 | Q6: =A6*L6 | R6: =1-P6 | S6: =1-Q6
N7: =SUM(N2:N6) | O7: =SUM(O2:O6) | P7: =1-PRODUCT(R2:R6) | Q7: =1-PRODUCT(S2:S6)
A8: Include | C8: Control / Contrôle | D8: Source | F8: Immobilisations | G8: Logiciels | H8: Mise en œuvre | I8: Exploitation | J8: ÉTC | K8: Réduc impacts | L8: Réduction Pb | N8: Coût | O8: ETC | P8: Impact | Q8: Pb | R8: 1 − impact | S8: 1 − Pb
A9: Inclure | C9: ISO/IEC 27002:2022 — information security controls (93) / mesures de sécurité de l'information | F9: CAPEX | G9: Software | H9: Implementation | I9: Exploitation | J9: FTE | K9: Reduce impacts | L9: Reduce Pb | N9: Cost | O9: FTE | P9: Impact | Q9: Pb
C10: 5 Organizational controls / Mesures organisationnelles
C11: 5.1 Policies for information security | D11: ISO/IEC 27002:2022 | E11: 1 | H11: 25000 | I11: 3000 | J11: 0.01 | K11: 0.06 | L11: 0.06 | N11: =A11*((SUM(F11:I11))+(J11*1950*80)) | O11: =A11*J11 | P11: =A11*K11 | Q11: =A11*L11 | R11: =1-P11 | S11: =1-Q11 | U11: 6. Définir les mesures de mitigation (feuilles M1 à M10)
C12: 5.2 Information security roles and responsibilities | D12: ISO/IEC 27002:2022 | E12: 2 | H12: 5000 | I12: 500 | J12: 0.01 | K12: 0.01 | L12: 0.01 | N12: =A12*((SUM(F12:I12))+(J12*1950*80)) | O12: =A12*J12 | P12: =A12*K12 | Q12: =A12*L12 | R12: =1-P12 | S12: =1-Q12 | U12: dans la colonne A Inclure Mesure
C13: 5.3 Segregation of duties | D13: ISO/IEC 27002:2022 | E13: 3 | H13: 5000 | I13: 500 | J13: 0.01 | K13: 0.01 | L13: 0.01 | N13: =A13*((SUM(F13:I13))+(J13*1950*80)) | O13: =A13*J13 | P13: =A13*K13 | Q13: =A13*L13 | R13: =1-P13 | S13: =1-Q13 | U13: 0 ou vide = non sélectionné
C14: 5.4 Management responsibilities | D14: ISO/IEC 27002:2022 | E14: 4 | H14: 5000 | I14: 500 | J14: 0.01 | K14: 0.01 | L14: 0.01 | N14: =A14*((SUM(F14:I14))+(J14*1950*80)) | O14: =A14*J14 | P14: =A14*K14 | Q14: =A14*L14 | R14: =1-P14 | S14: =1-Q14 | U14: 1 = Inclure ce contrôle dans les mesures de mitigation.
C15: 5.5 Contact with authorities | D15: ISO/IEC 27002:2022 | E15: 5 | H15: 5000 | J15: =1/50 | K15: 0.01 | L15: 0.01 | N15: =A15*((SUM(F15:I15))+(J15*1950*80)) | O15: =A15*J15 | P15: =A15*K15 | Q15: =A15*L15 | R15: =1-P15 | S15: =1-Q15
C16: 5.6 Contact with special interest groups | D16: ISO/IEC 27002:2022 | E16: 6 | H16: 5000 | J16: =3/50 | K16: 0.01 | L16: 0.01 | N16: =A16*((SUM(F16:I16))+(J16*1950*80)) | O16: =A16*J16 | P16: =A16*K16 | Q16: =A16*L16 | R16: =1-P16 | S16: =1-Q16 | U16: 6. Define the risk mitigation measures (Sheets M1 to M10)
C17: 5.7 Threat intelligence | D17: ISO/IEC 27002:2022 | E17: 7 | H17: 10000 | I17: 1000 | J17: 0.02 | K17: 0.01 | L17: 0.01 | N17: =A17*((SUM(F17:I17))+(J17*1950*80)) | O17: =A17*J17 | P17: =A17*K17 | Q17: =A17*L17 | R17: =1-P17 | S17: =1-Q17 | U17: indicate the selected mitigation measures or controls in Column A
C18: 5.8 Information security in project management | D18: ISO/IEC 27002:2022 | E18: 8 | H18: 5000 | J18: 0.06 | K18: 0.06 | L18: 0.06 | N18: =A18*((SUM(F18:I18))+(J18*1950*80)) | O18: =A18*J18 | P18: =A18*K18 | Q18: =A18*L18 | R18: =1-P18 | S18: =1-Q18 | U18: 0 or empty = not selected
C19: 5.9 Inventory of information and other associated assets | D19: ISO/IEC 27002:2022 | E19: 9 | G19: 10000 | H19: 50000 | I19: 100 | J19: 0.04 | K19: 0.06 | L19: 0.06 | N19: =A19*((SUM(F19:I19))+(J19*1950*80)) | O19: =A19*J19 | P19: =A19*K19 | Q19: =A19*L19 | R19: =1-P19 | S19: =1-Q19 | U19: 1 = include this control in the mitigation measures for the scenario
C20: 5.10 Acceptable use of information and other associated assets | D20: ISO/IEC 27002:2022 | E20: 10 | H20: 10000 | I20: 100 | J20: 0.02 | K20: 0.03 | L20: 0.03 | N20: =A20*((SUM(F20:I20))+(J20*1950*80)) | O20: =A20*J20 | P20: =A20*K20 | Q20: =A20*L20 | R20: =1-P20 | S20: =1-Q20
C21: 5.11 Return of assets | D21: ISO/IEC 27002:2022 | E21: 11 | H21: 20000 | I21: 100 | J21: 0.02 | K21: 0.01 | L21: 0.01 | N21: =A21*((SUM(F21:I21))+(J21*1950*80)) | O21: =A21*J21 | P21: =A21*K21 | Q21: =A21*L21 | R21: =1-P21 | S21: =1-Q21 | U21: Combination rule / Règle de combinaison :
C22: 5.12 Classification of information | D22: ISO/IEC 27002:2022 | E22: 12 | G22: 5000 | H22: 50000 | I22: 100 | J22: 0.02 | K22: 0.06 | L22: 0.06 | N22: =A22*((SUM(F22:I22))+(J22*1950*80)) | O22: =A22*J22 | P22: =A22*K22 | Q22: =A22*L22 | R22: =1-P22 | S22: =1-Q22 | U22: Selected coefficients combine per column (K impact, L probability) with the product rule:
C23: 5.13 Labelling of information | D23: ISO/IEC 27002:2022 | E23: 13 | H23: 10000 | I23: 50 | J23: 0.02 | K23: 0.01 | L23: 0.01 | N23: =A23*((SUM(F23:I23))+(J23*1950*80)) | O23: =A23*J23 | P23: =A23*K23 | Q23: =A23*L23 | R23: =1-P23 | S23: =1-Q23 | U23: package reduction = 1 − ∏(1 − rᵢ). Each rᵢ must be 0-1, so the package can never exceed 1;
C24: 5.14 Information transfer | D24: ISO/IEC 27002:2022 | E24: 14 | H24: 20000 | I24: 1000 | J24: 0.02 | K24: 0.02 | L24: 0.02 | N24: =A24*((SUM(F24:I24))+(J24*1950*80)) | O24: =A24*J24 | P24: =A24*K24 | Q24: =A24*L24 | R24: =1-P24 | S24: =1-Q24 | U24: the 'Other' rows count as additional factors. A warning appears under the TOTAL row if a coefficient is outside 0-1.
C25: 5.15 Access control | D25: ISO/IEC 27002:2022 | E25: 15 | G25: 5000 | H25: 5000 | I25: 100 | J25: 0.02 | K25: 0.06 | L25: 0.06 | N25: =A25*((SUM(F25:I25))+(J25*1950*80)) | O25: =A25*J25 | P25: =A25*K25 | Q25: =A25*L25 | R25: =1-P25 | S25: =1-Q25 | U25: Prefer a few well-justified controls, or enter ONE package-level
C26: 5.16 Identity management | D26: ISO/IEC 27002:2022 | E26: 16 | G26: 5000 | H26: 5000 | I26: 100 | J26: 0.01 | K26: 0.01 | L26: 0.01 | N26: =A26*((SUM(F26:I26))+(J26*1950*80)) | O26: =A26*J26 | P26: =A26*K26 | Q26: =A26*L26 | R26: =1-P26 | S26: =1-Q26 | U26: estimate (cost, impact and Pb reduction) in an 'Other' row, with its rationale.
C27: 5.17 Authentication information | D27: ISO/IEC 27002:2022 | E27: 17 | G27: 5000 | H27: 5000 | I27: 100 | J27: 0.01 | K27: 0.01 | L27: 0.01 | N27: =A27*((SUM(F27:I27))+(J27*1950*80)) | O27: =A27*J27 | P27: =A27*K27 | Q27: =A27*L27 | R27: =1-P27 | S27: =1-Q27 | U27: Les coefficients retenus se combinent par colonne selon la règle du produit :
C28: 5.18 Access rights | D28: ISO/IEC 27002:2022 | E28: 18 | G28: 5000 | H28: 5000 | I28: 100 | J28: 0.01 | K28: 0.01 | L28: 0.01 | N28: =A28*((SUM(F28:I28))+(J28*1950*80)) | O28: =A28*J28 | P28: =A28*K28 | Q28: =A28*L28 | R28: =1-P28 | S28: =1-Q28 | U28: réduction du bouquet = 1 − ∏(1 − rᵢ); chaque rᵢ entre 0 et 1, donc jamais plus de 1;
C29: 5.19 Information security in supplier relationships | D29: ISO/IEC 27002:2022 | E29: 19 | H29: 20000 | I29: 1000 | J29: 0.02 | K29: 0.06 | L29: 0.06 | N29: =A29*((SUM(F29:I29))+(J29*1950*80)) | O29: =A29*J29 | P29: =A29*K29 | Q29: =A29*L29 | R29: =1-P29 | S29: =1-Q29 | U29: les lignes « Other / autre » comptent comme facteurs. Privilégier peu de mesures bien justifiées,
C30: 5.20 Addressing information security within supplier agreements | D30: ISO/IEC 27002:2022 | E30: 20 | H30: 20000 | I30: 1000 | J30: 0.02 | K30: 0.06 | L30: 0.06 | N30: =A30*((SUM(F30:I30))+(J30*1950*80)) | O30: =A30*J30 | P30: =A30*K30 | Q30: =A30*L30 | R30: =1-P30 | S30: =1-Q30 | U30: ou saisir une estimation globale du bouquet dans une ligne « Other / autre ».
C31: 5.21 Managing information security in the ICT supply chain | D31: ISO/IEC 27002:2022 | E31: 21 | H31: 20000 | I31: 1000 | J31: 0.02 | K31: 0.01 | L31: 0.01 | N31: =A31*((SUM(F31:I31))+(J31*1950*80)) | O31: =A31*J31 | P31: =A31*K31 | Q31: =A31*L31 | R31: =1-P31 | S31: =1-Q31
C32: 5.22 Monitoring, review and change management of supplier services | D32: ISO/IEC 27002:2022 | E32: 22 | H32: 20000 | I32: 1000 | J32: 0.02 | K32: 0.06 | L32: 0.06 | N32: =A32*((SUM(F32:I32))+(J32*1950*80)) | O32: =A32*J32 | P32: =A32*K32 | Q32: =A32*L32 | R32: =1-P32 | S32: =1-Q32 | U32: Catalogues: ISO/IEC 27002:2022 (93), NIST CSF 2.0 (106), CIS Controls v8.1 (18).
C33: 5.23 Information security for use of cloud services | D33: ISO/IEC 27002:2022 | E33: 23 | H33: 10000 | I33: 1000 | J33: 0.02 | K33: 0.01 | L33: 0.01 | N33: =A33*((SUM(F33:I33))+(J33*1950*80)) | O33: =A33*J33 | P33: =A33*K33 | Q33: =A33*L33 | R33: =1-P33 | S33: =1-Q33 | U33: Default costs and coefficients are generic placeholders: recalibrate them.
C34: 5.24 Information security incident management planning and preparation | D34: ISO/IEC 27002:2022 | E34: 24 | H34: 10000 | I34: 1000 | J34: 0.02 | K34: 0.01 | L34: 0.01 | N34: =A34*((SUM(F34:I34))+(J34*1950*80)) | O34: =A34*J34 | P34: =A34*K34 | Q34: =A34*L34 | R34: =1-P34 | S34: =1-Q34 | U34: Coûts et coefficients par défaut génériques : à recalibrer.
C35: 5.25 Assessment and decision on information security events | D35: ISO/IEC 27002:2022 | E35: 25 | H35: 10000 | I35: 1000 | J35: 0.02 | K35: 0.01 | L35: 0.01 | N35: =A35*((SUM(F35:I35))+(J35*1950*80)) | O35: =A35*J35 | P35: =A35*K35 | Q35: =A35*L35 | R35: =1-P35 | S35: =1-Q35
C36: 5.26 Response to information security incidents | D36: ISO/IEC 27002:2022 | E36: 26 | H36: 10000 | I36: 1000 | J36: 0.02 | K36: 0.06 | L36: 0.06 | N36: =A36*((SUM(F36:I36))+(J36*1950*80)) | O36: =A36*J36 | P36: =A36*K36 | Q36: =A36*L36 | R36: =1-P36 | S36: =1-Q36
C37: 5.27 Learning from information security incidents | D37: ISO/IEC 27002:2022 | E37: 27 | H37: 10000 | I37: 1000 | J37: 0.02 | K37: 0.01 | L37: 0.01 | N37: =A37*((SUM(F37:I37))+(J37*1950*80)) | O37: =A37*J37 | P37: =A37*K37 | Q37: =A37*L37 | R37: =1-P37 | S37: =1-Q37
C38: 5.28 Collection of evidence | D38: ISO/IEC 27002:2022 | E38: 28 | H38: 10000 | I38: 10000 | J38: 0.02 | K38: 0.01 | L38: 0.01 | N38: =A38*((SUM(F38:I38))+(J38*1950*80)) | O38: =A38*J38 | P38: =A38*K38 | Q38: =A38*L38 | R38: =1-P38 | S38: =1-Q38
C39: 5.29 Information security during disruption | D39: ISO/IEC 27002:2022 | E39: 29 | H39: 20000 | I39: 1000 | J39: 0.02 | K39: 0.01 | L39: 0.01 | N39: =A39*((SUM(F39:I39))+(J39*1950*80)) | O39: =A39*J39 | P39: =A39*K39 | Q39: =A39*L39 | R39: =1-P39 | S39: =1-Q39
C40: 5.30 ICT readiness for business continuity | D40: ISO/IEC 27002:2022 | E40: 30 | H40: 10000 | I40: 1000 | J40: 0.02 | K40: 0.01 | L40: 0.01 | N40: =A40*((SUM(F40:I40))+(J40*1950*80)) | O40: =A40*J40 | P40: =A40*K40 | Q40: =A40*L40 | R40: =1-P40 | S40: =1-Q40
C41: 5.31 Legal, statutory, regulatory and contractual requirements | D41: ISO/IEC 27002:2022 | E41: 31 | H41: 10000 | I41: 1000 | J41: 0.02 | K41: 0.01 | L41: 0.01 | N41: =A41*((SUM(F41:I41))+(J41*1950*80)) | O41: =A41*J41 | P41: =A41*K41 | Q41: =A41*L41 | R41: =1-P41 | S41: =1-Q41
C42: 5.32 Intellectual property rights | D42: ISO/IEC 27002:2022 | E42: 32 | H42: 10000 | I42: 1000 | J42: 0.02 | K42: 0.01 | L42: 0.01 | N42: =A42*((SUM(F42:I42))+(J42*1950*80)) | O42: =A42*J42 | P42: =A42*K42 | Q42: =A42*L42 | R42: =1-P42 | S42: =1-Q42
C43: 5.33 Protection of records | D43: ISO/IEC 27002:2022 | E43: 33 | H43: 10000 | I43: 1000 | J43: 0.02 | K43: 0.01 | L43: 0.01 | N43: =A43*((SUM(F43:I43))+(J43*1950*80)) | O43: =A43*J43 | P43: =A43*K43 | Q43: =A43*L43 | R43: =1-P43 | S43: =1-Q43
C44: 5.34 Privacy and protection of PII | D44: ISO/IEC 27002:2022 | E44: 34 | H44: 10000 | I44: 1000 | J44: 0.02 | K44: 0.01 | L44: 0.01 | N44: =A44*((SUM(F44:I44))+(J44*1950*80)) | O44: =A44*J44 | P44: =A44*K44 | Q44: =A44*L44 | R44: =1-P44 | S44: =1-Q44
C45: 5.35 Independent review of information security | D45: ISO/IEC 27002:2022 | E45: 35 | H45: 10000 | I45: 10000 | J45: 0.02 | K45: 0.01 | L45: 0.01 | N45: =A45*((SUM(F45:I45))+(J45*1950*80)) | O45: =A45*J45 | P45: =A45*K45 | Q45: =A45*L45 | R45: =1-P45 | S45: =1-Q45
C46: 5.36 Compliance with policies, rules and standards for information security | D46: ISO/IEC 27002:2022 | E46: 36 | H46: 10000 | I46: 10000 | J46: 0.02 | K46: 0.01 | L46: 0.01 | N46: =A46*((SUM(F46:I46))+(J46*1950*80)) | O46: =A46*J46 | P46: =A46*K46 | Q46: =A46*L46 | R46: =1-P46 | S46: =1-Q46
C47: 5.37 Documented operating procedures | D47: ISO/IEC 27002:2022 | E47: 37 | H47: 50000 | I47: 100 | J47: 0.01 | K47: 0.06 | L47: 0.06 | N47: =A47*((SUM(F47:I47))+(J47*1950*80)) | O47: =A47*J47 | P47: =A47*K47 | Q47: =A47*L47 | R47: =1-P47 | S47: =1-Q47
C48: 6 People controls / Mesures liées aux personnes
C49: 6.1 Screening | D49: ISO/IEC 27002:2022 | E49: 38 | H49: 5000 | I49: 500 | J49: 0.01 | K49: 0.01 | L49: 0.01 | N49: =A49*((SUM(F49:I49))+(J49*1950*80)) | O49: =A49*J49 | P49: =A49*K49 | Q49: =A49*L49 | R49: =1-P49 | S49: =1-Q49
C50: 6.2 Terms and conditions of employment | D50: ISO/IEC 27002:2022 | E50: 39 | H50: 5000 | J50: 0.01 | K50: 0.01 | L50: 0.01 | N50: =A50*((SUM(F50:I50))+(J50*1950*80)) | O50: =A50*J50 | P50: =A50*K50 | Q50: =A50*L50 | R50: =1-P50 | S50: =1-Q50
C51: 6.3 Information security awareness, education and training | D51: ISO/IEC 27002:2022 | E51: 40 | H51: 30000 | I51: 500 | J51: 0.01 | K51: 0.06 | L51: 0.06 | N51: =A51*((SUM(F51:I51))+(J51*1950*80)) | O51: =A51*J51 | P51: =A51*K51 | Q51: =A51*L51 | R51: =1-P51 | S51: =1-Q51
C52: 6.4 Disciplinary process | D52: ISO/IEC 27002:2022 | E52: 41 | H52: 10000 | I52: 500 | J52: 0.01 | K52: 0.01 | L52: 0.01 | N52: =A52*((SUM(F52:I52))+(J52*1950*80)) | O52: =A52*J52 | P52: =A52*K52 | Q52: =A52*L52 | R52: =1-P52 | S52: =1-Q52
C53: 6.5 Responsibilities after termination or change of employment | D53: ISO/IEC 27002:2022 | E53: 42 | H53: 5000 | I53: 500 | J53: 0.01 | K53: 0.05 | L53: 0.02 | N53: =A53*((SUM(F53:I53))+(J53*1950*80)) | O53: =A53*J53 | P53: =A53*K53 | Q53: =A53*L53 | R53: =1-P53 | S53: =1-Q53
C54: 6.6 Confidentiality or non-disclosure agreements | D54: ISO/IEC 27002:2022 | E54: 43 | H54: 20000 | I54: 1000 | J54: 0.02 | K54: 0.02 | L54: 0.02 | N54: =A54*((SUM(F54:I54))+(J54*1950*80)) | O54: =A54*J54 | P54: =A54*K54 | Q54: =A54*L54 | R54: =1-P54 | S54: =1-Q54
C55: 6.7 Remote working | D55: ISO/IEC 27002:2022 | E55: 44 | H55: 5000 | I55: 2000 | J55: 0.05 | K55: 0.01 | L55: 0.01 | N55: =A55*((SUM(F55:I55))+(J55*1950*80)) | O55: =A55*J55 | P55: =A55*K55 | Q55: =A55*L55 | R55: =1-P55 | S55: =1-Q55
C56: 6.8 Information security event reporting | D56: ISO/IEC 27002:2022 | E56: 45 | H56: 10000 | I56: 1000 | J56: 0.02 | K56: 0.01 | L56: 0.01 | N56: =A56*((SUM(F56:I56))+(J56*1950*80)) | O56: =A56*J56 | P56: =A56*K56 | Q56: =A56*L56 | R56: =1-P56 | S56: =1-Q56
C57: 7 Physical controls / Mesures physiques
C58: 7.1 Physical security perimeters | D58: ISO/IEC 27002:2022 | E58: 46 | F58: 10000 | G58: 50000 | H58: 10000 | I58: 500 | J58: 0.02 | K58: 0.06 | L58: 0.06 | N58: =A58*((SUM(F58:I58))+(J58*1950*80)) | O58: =A58*J58 | P58: =A58*K58 | Q58: =A58*L58 | R58: =1-P58 | S58: =1-Q58
C59: 7.2 Physical entry | D59: ISO/IEC 27002:2022 | E59: 47 | F59: 10000 | G59: 50000 | H59: 10000 | I59: 500 | J59: 0.02 | K59: 0.06 | L59: 0.06 | N59: =A59*((SUM(F59:I59))+(J59*1950*80)) | O59: =A59*J59 | P59: =A59*K59 | Q59: =A59*L59 | R59: =1-P59 | S59: =1-Q59
C60: 7.3 Securing offices, rooms and facilities | D60: ISO/IEC 27002:2022 | E60: 48 | F60: 10000 | G60: 50000 | H60: 10000 | I60: 500 | J60: 0.02 | K60: 0.01 | L60: 0.01 | N60: =A60*((SUM(F60:I60))+(J60*1950*80)) | O60: =A60*J60 | P60: =A60*K60 | Q60: =A60*L60 | R60: =1-P60 | S60: =1-Q60
C61: 7.4 Physical security monitoring | D61: ISO/IEC 27002:2022 | E61: 49 | H61: 10000 | I61: 1000 | J61: 0.02 | K61: 0.01 | L61: 0.01 | N61: =A61*((SUM(F61:I61))+(J61*1950*80)) | O61: =A61*J61 | P61: =A61*K61 | Q61: =A61*L61 | R61: =1-P61 | S61: =1-Q61
C62: 7.5 Protecting against physical and environmental threats | D62: ISO/IEC 27002:2022 | E62: 50 | F62: 10000 | G62: 50000 | H62: 10000 | I62: 100 | J62: 0.02 | K62: 0.06 | L62: 0.06 | N62: =A62*((SUM(F62:I62))+(J62*1950*80)) | O62: =A62*J62 | P62: =A62*K62 | Q62: =A62*L62 | R62: =1-P62 | S62: =1-Q62
C63: 7.6 Working in secure areas | D63: ISO/IEC 27002:2022 | E63: 51 | F63: 10000 | G63: 50000 | H63: 10000 | I63: 100 | J63: 0.02 | K63: 0.01 | L63: 0.01 | N63: =A63*((SUM(F63:I63))+(J63*1950*80)) | O63: =A63*J63 | P63: =A63*K63 | Q63: =A63*L63 | R63: =1-P63 | S63: =1-Q63
C64: 7.7 Clear desk and clear screen | D64: ISO/IEC 27002:2022 | E64: 52 | H64: 5000 | I64: 100 | J64: 0.01 | K64: 0.01 | L64: 0.01 | N64: =A64*((SUM(F64:I64))+(J64*1950*80)) | O64: =A64*J64 | P64: =A64*K64 | Q64: =A64*L64 | R64: =1-P64 | S64: =1-Q64
C65: 7.8 Equipment siting and protection | D65: ISO/IEC 27002:2022 | E65: 53 | F65: 10000 | H65: 10000 | I65: 500 | J65: 0.02 | K65: 0.06 | L65: 0.06 | N65: =A65*((SUM(F65:I65))+(J65*1950*80)) | O65: =A65*J65 | P65: =A65*K65 | Q65: =A65*L65 | R65: =1-P65 | S65: =1-Q65
C66: 7.9 Security of assets off-premises | D66: ISO/IEC 27002:2022 | E66: 54 | G66: 50000 | H66: 10000 | I66: 100 | J66: 0.01 | K66: 0.01 | L66: 0.01 | N66: =A66*((SUM(F66:I66))+(J66*1950*80)) | O66: =A66*J66 | P66: =A66*K66 | Q66: =A66*L66 | R66: =1-P66 | S66: =1-Q66
C67: 7.10 Storage media | D67: ISO/IEC 27002:2022 | E67: 55 | G67: 5000 | H67: 5000 | I67: 100 | J67: 0.02 | K67: 0.01 | L67: 0.01 | N67: =A67*((SUM(F67:I67))+(J67*1950*80)) | O67: =A67*J67 | P67: =A67*K67 | Q67: =A67*L67 | R67: =1-P67 | S67: =1-Q67
C68: 7.11 Supporting utilities | D68: ISO/IEC 27002:2022 | E68: 56 | F68: 10000 | G68: 50000 | H68: 10000 | I68: 100 | J68: 0.01 | K68: 0.01 | L68: 0.01 | N68: =A68*((SUM(F68:I68))+(J68*1950*80)) | O68: =A68*J68 | P68: =A68*K68 | Q68: =A68*L68 | R68: =1-P68 | S68: =1-Q68
C69: 7.12 Cabling security | D69: ISO/IEC 27002:2022 | E69: 57 | F69: 10000 | G69: 50000 | H69: 10000 | I69: 100 | J69: 0.01 | K69: 0.01 | L69: 0.01 | N69: =A69*((SUM(F69:I69))+(J69*1950*80)) | O69: =A69*J69 | P69: =A69*K69 | Q69: =A69*L69 | R69: =1-P69 | S69: =1-Q69
C70: 7.13 Equipment maintenance | D70: ISO/IEC 27002:2022 | E70: 58 | F70: 10000 | G70: 50000 | H70: 10000 | I70: 500 | J70: 0.01 | K70: 0.01 | L70: 0.01 | N70: =A70*((SUM(F70:I70))+(J70*1950*80)) | O70: =A70*J70 | P70: =A70*K70 | Q70: =A70*L70 | R70: =1-P70 | S70: =1-Q70
C71: 7.14 Secure disposal or re-use of equipment | D71: ISO/IEC 27002:2022 | E71: 59 | G71: 50000 | H71: 10000 | I71: 100 | J71: 0.01 | K71: 0.01 | L71: 0.01 | N71: =A71*((SUM(F71:I71))+(J71*1950*80)) | O71: =A71*J71 | P71: =A71*K71 | Q71: =A71*L71 | R71: =1-P71 | S71: =1-Q71
C72: 8 Technological controls / Mesures technologiques
C73: 8.1 User end point devices | D73: ISO/IEC 27002:2022 | E73: 60 | H73: 5000 | I73: 500 | J73: 0.01 | K73: 0.01 | L73: 0.01 | N73: =A73*((SUM(F73:I73))+(J73*1950*80)) | O73: =A73*J73 | P73: =A73*K73 | Q73: =A73*L73 | R73: =1-P73 | S73: =1-Q73
C74: 8.2 Privileged access rights | D74: ISO/IEC 27002:2022 | E74: 61 | G74: 5000 | H74: 5000 | I74: 100 | J74: 0.01 | K74: 0.06 | L74: 0.06 | N74: =A74*((SUM(F74:I74))+(J74*1950*80)) | O74: =A74*J74 | P74: =A74*K74 | Q74: =A74*L74 | R74: =1-P74 | S74: =1-Q74
C75: 8.3 Information access restriction | D75: ISO/IEC 27002:2022 | E75: 62 | G75: 5000 | H75: 5000 | I75: 100 | J75: 0.01 | K75: 0.065 | L75: 0.06 | N75: =A75*((SUM(F75:I75))+(J75*1950*80)) | O75: =A75*J75 | P75: =A75*K75 | Q75: =A75*L75 | R75: =1-P75 | S75: =1-Q75
C76: 8.4 Access to source code | D76: ISO/IEC 27002:2022 | E76: 63 | G76: 5000 | H76: 5000 | I76: 100 | J76: 0.01 | K76: 0.01 | L76: 0.01 | N76: =A76*((SUM(F76:I76))+(J76*1950*80)) | O76: =A76*J76 | P76: =A76*K76 | Q76: =A76*L76 | R76: =1-P76 | S76: =1-Q76
C77: 8.5 Secure authentication | D77: ISO/IEC 27002:2022 | E77: 64 | G77: 5000 | H77: 5000 | I77: 100 | J77: 0.01 | K77: 0.01 | L77: 0.01 | N77: =A77*((SUM(F77:I77))+(J77*1950*80)) | O77: =A77*J77 | P77: =A77*K77 | Q77: =A77*L77 | R77: =1-P77 | S77: =1-Q77
C78: 8.6 Capacity management | D78: ISO/IEC 27002:2022 | E78: 65 | H78: 50000 | I78: 100 | J78: 0.01 | K78: 0.01 | L78: 0.01 | N78: =A78*((SUM(F78:I78))+(J78*1950*80)) | O78: =A78*J78 | P78: =A78*K78 | Q78: =A78*L78 | R78: =1-P78 | S78: =1-Q78
C79: 8.7 Protection against malware | D79: ISO/IEC 27002:2022 | E79: 66 | G79: 5000 | H79: 25000 | I79: 200 | J79: 0.06 | K79: 0.08 | L79: 0.08 | N79: =A79*((SUM(F79:I79))+(J79*1950*80)) | O79: =A79*J79 | P79: =A79*K79 | Q79: =A79*L79 | R79: =1-P79 | S79: =1-Q79
C80: 8.8 Management of technical vulnerabilities | D80: ISO/IEC 27002:2022 | E80: 67 | F80: 5000 | G80: 25000 | H80: 50000 | I80: 10000 | J80: 0.06 | K80: 0.065 | L80: 0.065 | N80: =A80*((SUM(F80:I80))+(J80*1950*80)) | O80: =A80*J80 | P80: =A80*K80 | Q80: =A80*L80 | R80: =1-P80 | S80: =1-Q80
C81: 8.9 Configuration management | D81: ISO/IEC 27002:2022 | E81: 68 | H81: 10000 | I81: 1000 | J81: 0.02 | K81: 0.01 | L81: 0.01 | N81: =A81*((SUM(F81:I81))+(J81*1950*80)) | O81: =A81*J81 | P81: =A81*K81 | Q81: =A81*L81 | R81: =1-P81 | S81: =1-Q81
C82: 8.10 Information deletion | D82: ISO/IEC 27002:2022 | E82: 69 | H82: 10000 | I82: 1000 | J82: 0.02 | K82: 0.01 | L82: 0.01 | N82: =A82*((SUM(F82:I82))+(J82*1950*80)) | O82: =A82*J82 | P82: =A82*K82 | Q82: =A82*L82 | R82: =1-P82 | S82: =1-Q82
C83: 8.11 Data masking | D83: ISO/IEC 27002:2022 | E83: 70 | H83: 10000 | I83: 1000 | J83: 0.02 | K83: 0.01 | L83: 0.01 | N83: =A83*((SUM(F83:I83))+(J83*1950*80)) | O83: =A83*J83 | P83: =A83*K83 | Q83: =A83*L83 | R83: =1-P83 | S83: =1-Q83
C84: 8.12 Data leakage prevention | D84: ISO/IEC 27002:2022 | E84: 71 | H84: 10000 | I84: 1000 | J84: 0.02 | K84: 0.01 | L84: 0.01 | N84: =A84*((SUM(F84:I84))+(J84*1950*80)) | O84: =A84*J84 | P84: =A84*K84 | Q84: =A84*L84 | R84: =1-P84 | S84: =1-Q84
C85: 8.13 Information backup | D85: ISO/IEC 27002:2022 | E85: 72 | F85: 50000 | G85: 10000 | H85: 50000 | I85: 10000 | J85: 0.06 | K85: 0.065 | L85: 0.06 | N85: =A85*((SUM(F85:I85))+(J85*1950*80)) | O85: =A85*J85 | P85: =A85*K85 | Q85: =A85*L85 | R85: =1-P85 | S85: =1-Q85
C86: 8.14 Redundancy of information processing facilities | D86: ISO/IEC 27002:2022 | E86: 73 | H86: 20000 | I86: 50000 | J86: 0.02 | K86: 0.065 | L86: 0.065 | N86: =A86*((SUM(F86:I86))+(J86*1950*80)) | O86: =A86*J86 | P86: =A86*K86 | Q86: =A86*L86 | R86: =1-P86 | S86: =1-Q86
C87: 8.15 Logging | D87: ISO/IEC 27002:2022 | E87: 74 | F87: 10000 | G87: 5000 | H87: 50000 | I87: 10000 | J87: 0.01 | K87: 0.06 | L87: 0.06 | N87: =A87*((SUM(F87:I87))+(J87*1950*80)) | O87: =A87*J87 | P87: =A87*K87 | Q87: =A87*L87 | R87: =1-P87 | S87: =1-Q87
C88: 8.16 Monitoring activities | D88: ISO/IEC 27002:2022 | E88: 75 | H88: 10000 | I88: 1000 | J88: 0.02 | K88: 0.01 | L88: 0.01 | N88: =A88*((SUM(F88:I88))+(J88*1950*80)) | O88: =A88*J88 | P88: =A88*K88 | Q88: =A88*L88 | R88: =1-P88 | S88: =1-Q88
C89: 8.17 Clock synchronization | D89: ISO/IEC 27002:2022 | E89: 76 | H89: 10000 | I89: 1000 | J89: 0.02 | K89: 0.01 | L89: 0.01 | N89: =A89*((SUM(F89:I89))+(J89*1950*80)) | O89: =A89*J89 | P89: =A89*K89 | Q89: =A89*L89 | R89: =1-P89 | S89: =1-Q89
C90: 8.18 Use of privileged utility programs | D90: ISO/IEC 27002:2022 | E90: 77 | G90: 5000 | H90: 5000 | I90: 100 | J90: 0.01 | K90: 0.01 | L90: 0.01 | N90: =A90*((SUM(F90:I90))+(J90*1950*80)) | O90: =A90*J90 | P90: =A90*K90 | Q90: =A90*L90 | R90: =1-P90 | S90: =1-Q90
C91: 8.19 Installation of software on operational systems | D91: ISO/IEC 27002:2022 | E91: 78 | F91: 10000 | G91: 5000 | I91: 500 | J91: 0.02 | K91: 0.06 | L91: 0.06 | N91: =A91*((SUM(F91:I91))+(J91*1950*80)) | O91: =A91*J91 | P91: =A91*K91 | Q91: =A91*L91 | R91: =1-P91 | S91: =1-Q91
C92: 8.20 Networks security | D92: ISO/IEC 27002:2022 | E92: 79 | F92: 5000 | G92: 25000 | H92: 50000 | I92: 10000 | J92: 0.06 | K92: 0.02 | L92: 0.02 | N92: =A92*((SUM(F92:I92))+(J92*1950*80)) | O92: =A92*J92 | P92: =A92*K92 | Q92: =A92*L92 | R92: =1-P92 | S92: =1-Q92
C93: 8.21 Security of network services | D93: ISO/IEC 27002:2022 | E93: 80 | F93: 5000 | G93: 25000 | H93: 50000 | I93: 10000 | J93: 0.06 | K93: 0.02 | L93: 0.02 | N93: =A93*((SUM(F93:I93))+(J93*1950*80)) | O93: =A93*J93 | P93: =A93*K93 | Q93: =A93*L93 | R93: =1-P93 | S93: =1-Q93
C94: 8.22 Segregation of networks | D94: ISO/IEC 27002:2022 | E94: 81 | F94: 5000 | G94: 25000 | H94: 50000 | I94: 10000 | J94: 0.06 | K94: 0.02 | L94: 0.02 | N94: =A94*((SUM(F94:I94))+(J94*1950*80)) | O94: =A94*J94 | P94: =A94*K94 | Q94: =A94*L94 | R94: =1-P94 | S94: =1-Q94
C95: 8.23 Web filtering | D95: ISO/IEC 27002:2022 | E95: 82 | H95: 10000 | I95: 1000 | J95: 0.02 | K95: 0.01 | L95: 0.01 | N95: =A95*((SUM(F95:I95))+(J95*1950*80)) | O95: =A95*J95 | P95: =A95*K95 | Q95: =A95*L95 | R95: =1-P95 | S95: =1-Q95
C96: 8.24 Use of cryptography | D96: ISO/IEC 27002:2022 | E96: 83 | G96: 5000 | H96: 5000 | I96: 100 | J96: 0.01 | K96: 0.01 | L96: 0.01 | N96: =A96*((SUM(F96:I96))+(J96*1950*80)) | O96: =A96*J96 | P96: =A96*K96 | Q96: =A96*L96 | R96: =1-P96 | S96: =1-Q96
C97: 8.25 Secure development life cycle | D97: ISO/IEC 27002:2022 | E97: 84 | H97: 20000 | I97: 1000 | J97: 0.02 | K97: 0.01 | L97: 0.01 | N97: =A97*((SUM(F97:I97))+(J97*1950*80)) | O97: =A97*J97 | P97: =A97*K97 | Q97: =A97*L97 | R97: =1-P97 | S97: =1-Q97
C98: 8.26 Application security requirements | D98: ISO/IEC 27002:2022 | E98: 85 | H98: 20000 | I98: 1000 | J98: 0.02 | K98: 0.02 | L98: 0.02 | N98: =A98*((SUM(F98:I98))+(J98*1950*80)) | O98: =A98*J98 | P98: =A98*K98 | Q98: =A98*L98 | R98: =1-P98 | S98: =1-Q98
C99: 8.27 Secure system architecture and engineering principles | D99: ISO/IEC 27002:2022 | E99: 86 | H99: 20000 | I99: 1000 | J99: 0.02 | K99: 0.01 | L99: 0.01 | N99: =A99*((SUM(F99:I99))+(J99*1950*80)) | O99: =A99*J99 | P99: =A99*K99 | Q99: =A99*L99 | R99: =1-P99 | S99: =1-Q99
C100: 8.28 Secure coding | D100: ISO/IEC 27002:2022 | E100: 87 | H100: 10000 | I100: 1000 | J100: 0.02 | K100: 0.01 | L100: 0.01 | N100: =A100*((SUM(F100:I100))+(J100*1950*80)) | O100: =A100*J100 | P100: =A100*K100 | Q100: =A100*L100 | R100: =1-P100 | S100: =1-Q100
...

Sheet S2
A1: Risk scenario number 2 / Scénario de risque 2
A2: Scenario number / Numéro : | B2: 2
A3: Scenario name / Nom du scénario :
A4: Date of creation / Date de création du scénario :
A6: Probability that the threat will be present = Probabilité de réalisation : Pb(A)
A7: Probability of exploitation = Probabilité d’exploitation: Pb(ψ,A)
A8: Estimated expected damages = Dommage estimé: δe(ψ,A)
A9: Maximal damages = Dommage maximal: δm(ψ,A) | C9: =IF(AND(ISNUMBER(B8),ISNUMBER(B9),B9<B8),"δm should be ≥ δe / δm devrait être ≥ δe","")
A10: Level of organizational resilience = Niveau de résilience: θ(ψ,A) | C10: =IF(AND(B10<>"",OR(NOT(ISNUMBER(B10)),B10<=0,B10>1)),"θ must be in (0, 1] / θ doit être dans ]0, 1]","")
A11: Organizational criticality (expected utility) = Criticité organisationnelle (utilité espérée) : μ(E)
A14: 3. Renseigner les scénarios de risque (feuilles S1 à S10)
A15: 3. Populate the risk scenarios (Sheets S1 to S10)
A16: Values 0-1; θ > 0 and ≤ 1; δm ≥ δe. Horizon: 12 months. Each value: rationale, evidence (E-number), confidence — Analytical estimate — validation required.
A17: Valeurs 0-1; θ > 0 et ≤ 1; δm ≥ δe. Horizon : 12 mois. Chaque valeur : justification, preuve (n° E), confiance — Estimation analytique — validation requise.

Sheet M2
A1: Other / autre | C1: Proposed risk mitigation measure / mesure de mitigation des risques proposés | D1: Source | F1: Immobilisations | G1: Logiciels | H1: Mise en œuvre | I1: Exploitation | J1: ÉTC | K1: Réduc impacts | L1: Réduction Pb | N1: Coût | O1: ETC | P1: Impact | Q1: Pb | R1: 1 − impact | S1: 1 − Pb
N2: =A2*((SUM(F2:I2))+(J2*1950*80)) | O2: =A2*J2 | P2: =A2*K2 | Q2: =A2*L2 | R2: =1-P2 | S2: =1-Q2
N3: =A3*((SUM(F3:I3))+(J3*1950*80)) | O3: =A3*J3 | P3: =A3*K3 | Q3: =A3*L3 | R3: =1-P3 | S3: =1-Q3
N4: =A4*((SUM(F4:I4))+(J4*1950*80)) | O4: =A4*J4 | P4: =A4*K4 | Q4: =A4*L4 | R4: =1-P4 | S4: =1-Q4
N5: =A5*((SUM(F5:I5))+(J5*1950*80)) | O5: =A5*J5 | P5: =A5*K5 | Q5: =A5*L5 | R5: =1-P5 | S5: =1-Q5
N6: =A6*((SUM(F6:I6))+(J6*1950*80)) | O6: =A6*J6 | P6: =A6*K6 | Q6: =A6*L6 | R6: =1-P6 | S6: =1-Q6
N7: =SUM(N2:N6) | O7: =SUM(O2:O6) | P7: =1-PRODUCT(R2:R6) | Q7: =1-PRODUCT(S2:S6)
A8: Include | C8: Control / Contrôle | D8: Source | F8: Immobilisations | G8: Logiciels | H8: Mise en œuvre | I8: Exploitation | J8: ÉTC | K8: Réduc impacts | L8: Réduction Pb | N8: Coût | O8: ETC | P8: Impact | Q8: Pb | R8: 1 − impact | S8: 1 − Pb
A9: Inclure | C9: ISO/IEC 27002:2022 — information security controls (93) / mesures de sécurité de l'information | F9: CAPEX | G9: Software | H9: Implementation | I9: Exploitation | J9: FTE | K9: Reduce impacts | L9: Reduce Pb | N9: Cost | O9: FTE | P9: Impact | Q9: Pb
C10: 5 Organizational controls / Mesures organisationnelles
C11: 5.1 Policies for information security | D11: ISO/IEC 27002:2022 | E11: 1 | H11: 25000 | I11: 3000 | J11: 0.01 | K11: 0.06 | L11: 0.06 | N11: =A11*((SUM(F11:I11))+(J11*1950*80)) | O11: =A11*J11 | P11: =A11*K11 | Q11: =A11*L11 | R11: =1-P11 | S11: =1-Q11
C12: 5.2 Information security roles and responsibilities | D12: ISO/IEC 27002:2022 | E12: 2 | H12: 5000 | I12: 500 | J12: 0.01 | K12: 0.01 | L12: 0.01 | N12: =A12*((SUM(F12:I12))+(J12*1950*80)) | O12: =A12*J12 | P12: =A12*K12 | Q12: =A12*L12 | R12: =1-P12 | S12: =1-Q12 | U12: 4. Définir les mesures de mitigation (feuilles M1 à M10)
C13: 5.3 Segregation of duties | D13: ISO/IEC 27002:2022 | E13: 3 | H13: 5000 | I13: 500 | J13: 0.01 | K13: 0.01 | L13: 0.01 | N13: =A13*((SUM(F13:I13))+(J13*1950*80)) | O13: =A13*J13 | P13: =A13*K13 | Q13: =A13*L13 | R13: =1-P13 | S13: =1-Q13 | U13: dans la colonne A Inclure Mesure
C14: 5.4 Management responsibilities | D14: ISO/IEC 27002:2022 | E14: 4 | H14: 5000 | I14: 500 | J14: 0.01 | K14: 0.01 | L14: 0.01 | N14: =A14*((SUM(F14:I14))+(J14*1950*80)) | O14: =A14*J14 | P14: =A14*K14 | Q14: =A14*L14 | R14: =1-P14 | S14: =1-Q14 | U14: 0 ou vide = non sélectionné
C15: 5.5 Contact with authorities | D15: ISO/IEC 27002:2022 | E15: 5 | H15: 5000 | J15: =1/50 | K15: 0.01 | L15: 0.01 | N15: =A15*((SUM(F15:I15))+(J15*1950*80)) | O15: =A15*J15 | P15: =A15*K15 | Q15: =A15*L15 | R15: =1-P15 | S15: =1-Q15 | U15: 1 = Inclure ce contrôle dans les mesures de mitigation.
C16: 5.6 Contact with special interest groups | D16: ISO/IEC 27002:2022 | E16: 6 | H16: 5000 | J16: =3/50 | K16: 0.01 | L16: 0.01 | N16: =A16*((SUM(F16:I16))+(J16*1950*80)) | O16: =A16*J16 | P16: =A16*K16 | Q16: =A16*L16 | R16: =1-P16 | S16: =1-Q16
C17: 5.7 Threat intelligence | D17: ISO/IEC 27002:2022 | E17: 7 | H17: 10000 | I17: 1000 | J17: 0.02 | K17: 0.01 | L17: 0.01 | N17: =A17*((SUM(F17:I17))+(J17*1950*80)) | O17: =A17*J17 | P17: =A17*K17 | Q17: =A17*L17 | R17: =1-P17 | S17: =1-Q17 | U17: 4. Define the risk mitigation measures (Sheets M1 to M10)
C18: 5.8 Information security in project management | D18: ISO/IEC 27002:2022 | E18: 8 | H18: 5000 | J18: 0.06 | K18: 0.06 | L18: 0.06 | N18: =A18*((SUM(F18:I18))+(J18*1950*80)) | O18: =A18*J18 | P18: =A18*K18 | Q18: =A18*L18 | R18: =1-P18 | S18: =1-Q18 | U18: indicate the selected mitigation measures or controls in Column A
C19: 5.9 Inventory of information and other associated assets | D19: ISO/IEC 27002:2022 | E19: 9 | G19: 10000 | H19: 50000 | I19: 100 | J19: 0.04 | K19: 0.06 | L19: 0.06 | N19: =A19*((SUM(F19:I19))+(J19*1950*80)) | O19: =A19*J19 | P19: =A19*K19 | Q19: =A19*L19 | R19: =1-P19 | S19: =1-Q19 | U19: 0 or empty = not selected
C20: 5.10 Acceptable use of information and other associated assets | D20: ISO/IEC 27002:2022 | E20: 10 | H20: 10000 | I20: 100 | J20: 0.02 | K20: 0.03 | L20: 0.03 | N20: =A20*((SUM(F20:I20))+(J20*1950*80)) | O20: =A20*J20 | P20: =A20*K20 | Q20: =A20*L20 | R20: =1-P20 | S20: =1-Q20 | U20: 1 = include this control in the mitigation measures for the scenario
C21: 5.11 Return of assets | D21: ISO/IEC 27002:2022 | E21: 11 | H21: 20000 | I21: 100 | J21: 0.02 | K21: 0.01 | L21: 0.01 | N21: =A21*((SUM(F21:I21))+(J21*1950*80)) | O21: =A21*J21 | P21: =A21*K21 | Q21: =A21*L21 | R21: =1-P21 | S21: =1-Q21 | U21: Combination rule / Règle de combinaison :
C22: 5.12 Classification of information | D22: ISO/IEC 27002:2022 | E22: 12 | G22: 5000 | H22: 50000 | I22: 100 | J22: 0.02 | K22: 0.06 | L22: 0.06 | N22: =A22*((SUM(F22:I22))+(J22*1950*80)) | O22: =A22*J22 | P22: =A22*K22 | Q22: =A22*L22 | R22: =1-P22 | S22: =1-Q22 | U22: Selected coefficients combine per column (K impact, L probability) with the product rule:
C23: 5.13 Labelling of information | D23: ISO/IEC 27002:2022 | E23: 13 | H23: 10000 | I23: 50 | J23: 0.02 | K23: 0.01 | L23: 0.01 | N23: =A23*((SUM(F23:I23))+(J23*1950*80)) | O23: =A23*J23 | P23: =A23*K23 | Q23: =A23*L23 | R23: =1-P23 | S23: =1-Q23 | U23: package reduction = 1 − ∏(1 − rᵢ). Each rᵢ must be 0-1, so the package can never exceed 1;
C24: 5.14 Information transfer | D24: ISO/IEC 27002:2022 | E24: 14 | H24: 20000 | I24: 1000 | J24: 0.02 | K24: 0.02 | L24: 0.02 | N24: =A24*((SUM(F24:I24))+(J24*1950*80)) | O24: =A24*J24 | P24: =A24*K24 | Q24: =A24*L24 | R24: =1-P24 | S24: =1-Q24 | U24: the 'Other' rows count as additional factors. A warning appears under the TOTAL row if a coefficient is outside 0-1.
C25: 5.15 Access control | D25: ISO/IEC 27002:2022 | E25: 15 | G25: 5000 | H25: 5000 | I25: 100 | J25: 0.02 | K25: 0.06 | L25: 0.06 | N25: =A25*((SUM(F25:I25))+(J25*1950*80)) | O25: =A25*J25 | P25: =A25*K25 | Q25: =A25*L25 | R25: =1-P25 | S25: =1-Q25 | U25: Prefer a few well-justified controls, or enter ONE package-level
C26: 5.16 Identity management | D26: ISO/IEC 27002:2022 | E26: 16 | G26: 5000 | H26: 5000 | I26: 100 | J26: 0.01 | K26: 0.01 | L26: 0.01 | N26: =A26*((SUM(F26:I26))+(J26*1950*80)) | O26: =A26*J26 | P26: =A26*K26 | Q26: =A26*L26 | R26: =1-P26 | S26: =1-Q26 | U26: estimate (cost, impact and Pb reduction) in an 'Other' row, with its rationale.
C27: 5.17 Authentication information | D27: ISO/IEC 27002:2022 | E27: 17 | G27: 5000 | H27: 5000 | I27: 100 | J27: 0.01 | K27: 0.01 | L27: 0.01 | N27: =A27*((SUM(F27:I27))+(J27*1950*80)) | O27: =A27*J27 | P27: =A27*K27 | Q27: =A27*L27 | R27: =1-P27 | S27: =1-Q27 | U27: Les coefficients retenus se combinent par colonne selon la règle du produit :
C28: 5.18 Access rights | D28: ISO/IEC 27002:2022 | E28: 18 | G28: 5000 | H28: 5000 | I28: 100 | J28: 0.01 | K28: 0.01 | L28: 0.01 | N28: =A28*((SUM(F28:I28))+(J28*1950*80)) | O28: =A28*J28 | P28: =A28*K28 | Q28: =A28*L28 | R28: =1-P28 | S28: =1-Q28 | U28: réduction du bouquet = 1 − ∏(1 − rᵢ); chaque rᵢ entre 0 et 1, donc jamais plus de 1;
C29: 5.19 Information security in supplier relationships | D29: ISO/IEC 27002:2022 | E29: 19 | H29: 20000 | I29: 1000 | J29: 0.02 | K29: 0.06 | L29: 0.06 | N29: =A29*((SUM(F29:I29))+(J29*1950*80)) | O29: =A29*J29 | P29: =A29*K29 | Q29: =A29*L29 | R29: =1-P29 | S29: =1-Q29 | U29: les lignes « Other / autre » comptent comme facteurs. Privilégier peu de mesures bien justifiées,
C30: 5.20 Addressing information security within supplier agreements | D30: ISO/IEC 27002:2022 | E30: 20 | H30: 20000 | I30: 1000 | J30: 0.02 | K30: 0.06 | L30: 0.06 | N30: =A30*((SUM(F30:I30))+(J30*1950*80)) | O30: =A30*J30 | P30: =A30*K30 | Q30: =A30*L30 | R30: =1-P30 | S30: =1-Q30 | U30: ou saisir une estimation globale du bouquet dans une ligne « Other / autre ».
C31: 5.21 Managing information security in the ICT supply chain | D31: ISO/IEC 27002:2022 | E31: 21 | H31: 20000 | I31: 1000 | J31: 0.02 | K31: 0.01 | L31: 0.01 | N31: =A31*((SUM(F31:I31))+(J31*1950*80)) | O31: =A31*J31 | P31: =A31*K31 | Q31: =A31*L31 | R31: =1-P31 | S31: =1-Q31 | U31: estimation globale du bouquet dans une ligne « Other / autre ».
C32: 5.22 Monitoring, review and change management of supplier services | D32: ISO/IEC 27002:2022 | E32: 22 | H32: 20000 | I32: 1000 | J32: 0.02 | K32: 0.06 | L32: 0.06 | N32: =A32*((SUM(F32:I32))+(J32*1950*80)) | O32: =A32*J32 | P32: =A32*K32 | Q32: =A32*L32 | R32: =1-P32 | S32: =1-Q32
C33: 5.23 Information security for use of cloud services | D33: ISO/IEC 27002:2022 | E33: 23 | H33: 10000 | I33: 1000 | J33: 0.02 | K33: 0.01 | L33: 0.01 | N33: =A33*((SUM(F33:I33))+(J33*1950*80)) | O33: =A33*J33 | P33: =A33*K33 | Q33: =A33*L33 | R33: =1-P33 | S33: =1-Q33 | U33: Catalogues: ISO/IEC 27002:2022 (93), NIST CSF 2.0 (106), CIS Controls v8.1 (18).
C34: 5.24 Information security incident management planning and preparation | D34: ISO/IEC 27002:2022 | E34: 24 | H34: 10000 | I34: 1000 | J34: 0.02 | K34: 0.01 | L34: 0.01 | N34: =A34*((SUM(F34:I34))+(J34*1950*80)) | O34: =A34*J34 | P34: =A34*K34 | Q34: =A34*L34 | R34: =1-P34 | S34: =1-Q34 | U34: Default costs and coefficients are generic placeholders: recalibrate them.
C35: 5.25 Assessment and decision on information security events | D35: ISO/IEC 27002:2022 | E35: 25 | H35: 10000 | I35: 1000 | J35: 0.02 | K35: 0.01 | L35: 0.01 | N35: =A35*((SUM(F35:I35))+(J35*1950*80)) | O35: =A35*J35 | P35: =A35*K35 | Q35: =A35*L35 | R35: =1-P35 | S35: =1-Q35 | U35: Coûts et coefficients par défaut génériques : à recalibrer.
C36: 5.26 Response to information security incidents | D36: ISO/IEC 27002:2022 | E36: 26 | H36: 10000 | I36: 1000 | J36: 0.02 | K36: 0.06 | L36: 0.06 | N36: =A36*((SUM(F36:I36))+(J36*1950*80)) | O36: =A36*J36 | P36: =A36*K36 | Q36: =A36*L36 | R36: =1-P36 | S36: =1-Q36
C37: 5.27 Learning from information security incidents | D37: ISO/IEC 27002:2022 | E37: 27 | H37: 10000 | I37: 1000 | J37: 0.02 | K37: 0.01 | L37: 0.01 | N37: =A37*((SUM(F37:I37))+(J37*1950*80)) | O37: =A37*J37 | P37: =A37*K37 | Q37: =A37*L37 | R37: =1-P37 | S37: =1-Q37
C38: 5.28 Collection of evidence | D38: ISO/IEC 27002:2022 | E38: 28 | H38: 10000 | I38: 10000 | J38: 0.02 | K38: 0.01 | L38: 0.01 | N38: =A38*((SUM(F38:I38))+(J38*1950*80)) | O38: =A38*J38 | P38: =A38*K38 | Q38: =A38*L38 | R38: =1-P38 | S38: =1-Q38
C39: 5.29 Information security during disruption | D39: ISO/IEC 27002:2022 | E39: 29 | H39: 20000 | I39: 1000 | J39: 0.02 | K39: 0.01 | L39: 0.01 | N39: =A39*((SUM(F39:I39))+(J39*1950*80)) | O39: =A39*J39 | P39: =A39*K39 | Q39: =A39*L39 | R39: =1-P39 | S39: =1-Q39
C40: 5.30 ICT readiness for business continuity | D40: ISO/IEC 27002:2022 | E40: 30 | H40: 10000 | I40: 1000 | J40: 0.02 | K40: 0.01 | L40: 0.01 | N40: =A40*((SUM(F40:I40))+(J40*1950*80)) | O40: =A40*J40 | P40: =A40*K40 | Q40: =A40*L40 | R40: =1-P40 | S40: =1-Q40
C41: 5.31 Legal, statutory, regulatory and contractual requirements | D41: ISO/IEC 27002:2022 | E41: 31 | H41: 10000 | I41: 1000 | J41: 0.02 | K41: 0.01 | L41: 0.01 | N41: =A41*((SUM(F41:I41))+(J41*1950*80)) | O41: =A41*J41 | P41: =A41*K41 | Q41: =A41*L41 | R41: =1-P41 | S41: =1-Q41
C42: 5.32 Intellectual property rights | D42: ISO/IEC 27002:2022 | E42: 32 | H42: 10000 | I42: 1000 | J42: 0.02 | K42: 0.01 | L42: 0.01 | N42: =A42*((SUM(F42:I42))+(J42*1950*80)) | O42: =A42*J42 | P42: =A42*K42 | Q42: =A42*L42 | R42: =1-P42 | S42: =1-Q42
C43: 5.33 Protection of records | D43: ISO/IEC 27002:2022 | E43: 33 | H43: 10000 | I43: 1000 | J43: 0.02 | K43: 0.01 | L43: 0.01 | N43: =A43*((SUM(F43:I43))+(J43*1950*80)) | O43: =A43*J43 | P43: =A43*K43 | Q43: =A43*L43 | R43: =1-P43 | S43: =1-Q43
C44: 5.34 Privacy and protection of PII | D44: ISO/IEC 27002:2022 | E44: 34 | H44: 10000 | I44: 1000 | J44: 0.02 | K44: 0.01 | L44: 0.01 | N44: =A44*((SUM(F44:I44))+(J44*1950*80)) | O44: =A44*J44 | P44: =A44*K44 | Q44: =A44*L44 | R44: =1-P44 | S44: =1-Q44
C45: 5.35 Independent review of information security | D45: ISO/IEC 27002:2022 | E45: 35 | H45: 10000 | I45: 10000 | J45: 0.02 | K45: 0.01 | L45: 0.01 | N45: =A45*((SUM(F45:I45))+(J45*1950*80)) | O45: =A45*J45 | P45: =A45*K45 | Q45: =A45*L45 | R45: =1-P45 | S45: =1-Q45
C46: 5.36 Compliance with policies, rules and standards for information security | D46: ISO/IEC 27002:2022 | E46: 36 | H46: 10000 | I46: 10000 | J46: 0.02 | K46: 0.01 | L46: 0.01 | N46: =A46*((SUM(F46:I46))+(J46*1950*80)) | O46: =A46*J46 | P46: =A46*K46 | Q46: =A46*L46 | R46: =1-P46 | S46: =1-Q46
C47: 5.37 Documented operating procedures | D47: ISO/IEC 27002:2022 | E47: 37 | H47: 50000 | I47: 100 | J47: 0.01 | K47: 0.06 | L47: 0.06 | N47: =A47*((SUM(F47:I47))+(J47*1950*80)) | O47: =A47*J47 | P47: =A47*K47 | Q47: =A47*L47 | R47: =1-P47 | S47: =1-Q47
C48: 6 People controls / Mesures liées aux personnes
C49: 6.1 Screening | D49: ISO/IEC 27002:2022 | E49: 38 | H49: 5000 | I49: 500 | J49: 0.01 | K49: 0.01 | L49: 0.01 | N49: =A49*((SUM(F49:I49))+(J49*1950*80)) | O49: =A49*J49 | P49: =A49*K49 | Q49: =A49*L49 | R49: =1-P49 | S49: =1-Q49
C50: 6.2 Terms and conditions of employment | D50: ISO/IEC 27002:2022 | E50: 39 | H50: 5000 | J50: 0.01 | K50: 0.01 | L50: 0.01 | N50: =A50*((SUM(F50:I50))+(J50*1950*80)) | O50: =A50*J50 | P50: =A50*K50 | Q50: =A50*L50 | R50: =1-P50 | S50: =1-Q50
C51: 6.3 Information security awareness, education and training | D51: ISO/IEC 27002:2022 | E51: 40 | H51: 30000 | I51: 500 | J51: 0.01 | K51: 0.06 | L51: 0.06 | N51: =A51*((SUM(F51:I51))+(J51*1950*80)) | O51: =A51*J51 | P51: =A51*K51 | Q51: =A51*L51 | R51: =1-P51 | S51: =1-Q51
C52: 6.4 Disciplinary process | D52: ISO/IEC 27002:2022 | E52: 41 | H52: 10000 | I52: 500 | J52: 0.01 | K52: 0.01 | L52: 0.01 | N52: =A52*((SUM(F52:I52))+(J52*1950*80)) | O52: =A52*J52 | P52: =A52*K52 | Q52: =A52*L52 | R52: =1-P52 | S52: =1-Q52
C53: 6.5 Responsibilities after termination or change of employment | D53: ISO/IEC 27002:2022 | E53: 42 | H53: 5000 | I53: 500 | J53: 0.01 | K53: 0.05 | L53: 0.02 | N53: =A53*((SUM(F53:I53))+(J53*1950*80)) | O53: =A53*J53 | P53: =A53*K53 | Q53: =A53*L53 | R53: =1-P53 | S53: =1-Q53
C54: 6.6 Confidentiality or non-disclosure agreements | D54: ISO/IEC 27002:2022 | E54: 43 | H54: 20000 | I54: 1000 | J54: 0.02 | K54: 0.02 | L54: 0.02 | N54: =A54*((SUM(F54:I54))+(J54*1950*80)) | O54: =A54*J54 | P54: =A54*K54 | Q54: =A54*L54 | R54: =1-P54 | S54: =1-Q54
C55: 6.7 Remote working | D55: ISO/IEC 27002:2022 | E55: 44 | H55: 5000 | I55: 2000 | J55: 0.05 | K55: 0.01 | L55: 0.01 | N55: =A55*((SUM(F55:I55))+(J55*1950*80)) | O55: =A55*J55 | P55: =A55*K55 | Q55: =A55*L55 | R55: =1-P55 | S55: =1-Q55
C56: 6.8 Information security event reporting | D56: ISO/IEC 27002:2022 | E56: 45 | H56: 10000 | I56: 1000 | J56: 0.02 | K56: 0.01 | L56: 0.01 | N56: =A56*((SUM(F56:I56))+(J56*1950*80)) | O56: =A56*J56 | P56: =A56*K56 | Q56: =A56*L56 | R56: =1-P56 | S56: =1-Q56
C57: 7 Physical controls / Mesures physiques
C58: 7.1 Physical security perimeters | D58: ISO/IEC 27002:2022 | E58: 46 | F58: 10000 | G58: 50000 | H58: 10000 | I58: 500 | J58: 0.02 | K58: 0.06 | L58: 0.06 | N58: =A58*((SUM(F58:I58))+(J58*1950*80)) | O58: =A58*J58 | P58: =A58*K58 | Q58: =A58*L58 | R58: =1-P58 | S58: =1-Q58
C59: 7.2 Physical entry | D59: ISO/IEC 27002:2022 | E59: 47 | F59: 10000 | G59: 50000 | H59: 10000 | I59: 500 | J59: 0.02 | K59: 0.06 | L59: 0.06 | N59: =A59*((SUM(F59:I59))+(J59*1950*80)) | O59: =A59*J59 | P59: =A59*K59 | Q59: =A59*L59 | R59: =1-P59 | S59: =1-Q59
C60: 7.3 Securing offices, rooms and facilities | D60: ISO/IEC 27002:2022 | E60: 48 | F60: 10000 | G60: 50000 | H60: 10000 | I60: 500 | J60: 0.02 | K60: 0.01 | L60: 0.01 | N60: =A60*((SUM(F60:I60))+(J60*1950*80)) | O60: =A60*J60 | P60: =A60*K60 | Q60: =A60*L60 | R60: =1-P60 | S60: =1-Q60
C61: 7.4 Physical security monitoring | D61: ISO/IEC 27002:2022 | E61: 49 | H61: 10000 | I61: 1000 | J61: 0.02 | K61: 0.01 | L61: 0.01 | N61: =A61*((SUM(F61:I61))+(J61*1950*80)) | O61: =A61*J61 | P61: =A61*K61 | Q61: =A61*L61 | R61: =1-P61 | S61: =1-Q61
C62: 7.5 Protecting against physical and environmental threats | D62: ISO/IEC 27002:2022 | E62: 50 | F62: 10000 | G62: 50000 | H62: 10000 | I62: 100 | J62: 0.02 | K62: 0.06 | L62: 0.06 | N62: =A62*((SUM(F62:I62))+(J62*1950*80)) | O62: =A62*J62 | P62: =A62*K62 | Q62: =A62*L62 | R62: =1-P62 | S62: =1-Q62
C63: 7.6 Working in secure areas | D63: ISO/IEC 27002:2022 | E63: 51 | F63: 10000 | G63: 50000 | H63: 10000 | I63: 100 | J63: 0.02 | K63: 0.01 | L63: 0.01 | N63: =A63*((SUM(F63:I63))+(J63*1950*80)) | O63: =A63*J63 | P63: =A63*K63 | Q63: =A63*L63 | R63: =1-P63 | S63: =1-Q63
C64: 7.7 Clear desk and clear screen | D64: ISO/IEC 27002:2022 | E64: 52 | H64: 5000 | I64: 100 | J64: 0.01 | K64: 0.01 | L64: 0.01 | N64: =A64*((SUM(F64:I64))+(J64*1950*80)) | O64: =A64*J64 | P64: =A64*K64 | Q64: =A64*L64 | R64: =1-P64 | S64: =1-Q64
C65: 7.8 Equipment siting and protection | D65: ISO/IEC 27002:2022 | E65: 53 | F65: 10000 | H65: 10000 | I65: 500 | J65: 0.02 | K65: 0.06 | L65: 0.06 | N65: =A65*((SUM(F65:I65))+(J65*1950*80)) | O65: =A65*J65 | P65: =A65*K65 | Q65: =A65*L65 | R65: =1-P65 | S65: =1-Q65
C66: 7.9 Security of assets off-premises | D66: ISO/IEC 27002:2022 | E66: 54 | G66: 50000 | H66: 10000 | I66: 100 | J66: 0.01 | K66: 0.01 | L66: 0.01 | N66: =A66*((SUM(F66:I66))+(J66*1950*80)) | O66: =A66*J66 | P66: =A66*K66 | Q66: =A66*L66 | R66: =1-P66 | S66: =1-Q66
C67: 7.10 Storage media | D67: ISO/IEC 27002:2022 | E67: 55 | G67: 5000 | H67: 5000 | I67: 100 | J67: 0.02 | K67: 0.01 | L67: 0.01 | N67: =A67*((SUM(F67:I67))+(J67*1950*80)) | O67: =A67*J67 | P67: =A67*K67 | Q67: =A67*L67 | R67: =1-P67 | S67: =1-Q67
C68: 7.11 Supporting utilities | D68: ISO/IEC 27002:2022 | E68: 56 | F68: 10000 | G68: 50000 | H68: 10000 | I68: 100 | J68: 0.01 | K68: 0.01 | L68: 0.01 | N68: =A68*((SUM(F68:I68))+(J68*1950*80)) | O68: =A68*J68 | P68: =A68*K68 | Q68: =A68*L68 | R68: =1-P68 | S68: =1-Q68
C69: 7.12 Cabling security | D69: ISO/IEC 27002:2022 | E69: 57 | F69: 10000 | G69: 50000 | H69: 10000 | I69: 100 | J69: 0.01 | K69: 0.01 | L69: 0.01 | N69: =A69*((SUM(F69:I69))+(J69*1950*80)) | O69: =A69*J69 | P69: =A69*K69 | Q69: =A69*L69 | R69: =1-P69 | S69: =1-Q69
C70: 7.13 Equipment maintenance | D70: ISO/IEC 27002:2022 | E70: 58 | F70: 10000 | G70: 50000 | H70: 10000 | I70: 500 | J70: 0.01 | K70: 0.01 | L70: 0.01 | N70: =A70*((SUM(F70:I70))+(J70*1950*80)) | O70: =A70*J70 | P70: =A70*K70 | Q70: =A70*L70 | R70: =1-P70 | S70: =1-Q70
C71: 7.14 Secure disposal or re-use of equipment | D71: ISO/IEC 27002:2022 | E71: 59 | G71: 50000 | H71: 10000 | I71: 100 | J71: 0.01 | K71: 0.01 | L71: 0.01 | N71: =A71*((SUM(F71:I71))+(J71*1950*80)) | O71: =A71*J71 | P71: =A71*K71 | Q71: =A71*L71 | R71: =1-P71 | S71: =1-Q71
C72: 8 Technological controls / Mesures technologiques
C73: 8.1 User end point devices | D73: ISO/IEC 27002:2022 | E73: 60 | H73: 5000 | I73: 500 | J73: 0.01 | K73: 0.01 | L73: 0.01 | N73: =A73*((SUM(F73:I73))+(J73*1950*80)) | O73: =A73*J73 | P73: =A73*K73 | Q73: =A73*L73 | R73: =1-P73 | S73: =1-Q73
C74: 8.2 Privileged access rights | D74: ISO/IEC 27002:2022 | E74: 61 | G74: 5000 | H74: 5000 | I74: 100 | J74: 0.01 | K74: 0.06 | L74: 0.06 | N74: =A74*((SUM(F74:I74))+(J74*1950*80)) | O74: =A74*J74 | P74: =A74*K74 | Q74: =A74*L74 | R74: =1-P74 | S74: =1-Q74
C75: 8.3 Information access restriction | D75: ISO/IEC 27002:2022 | E75: 62 | G75: 5000 | H75: 5000 | I75: 100 | J75: 0.01 | K75: 0.065 | L75: 0.06 | N75: =A75*((SUM(F75:I75))+(J75*1950*80)) | O75: =A75*J75 | P75: =A75*K75 | Q75: =A75*L75 | R75: =1-P75 | S75: =1-Q75
C76: 8.4 Access to source code | D76: ISO/IEC 27002:2022 | E76: 63 | G76: 5000 | H76: 5000 | I76: 100 | J76: 0.01 | K76: 0.01 | L76: 0.01 | N76: =A76*((SUM(F76:I76))+(J76*1950*80)) | O76: =A76*J76 | P76: =A76*K76 | Q76: =A76*L76 | R76: =1-P76 | S76: =1-Q76
C77: 8.5 Secure authentication | D77: ISO/IEC 27002:2022 | E77: 64 | G77: 5000 | H77: 5000 | I77: 100 | J77: 0.01 | K77: 0.01 | L77: 0.01 | N77: =A77*((SUM(F77:I77))+(J77*1950*80)) | O77: =A77*J77 | P77: =A77*K77 | Q77: =A77*L77 | R77: =1-P77 | S77: =1-Q77
C78: 8.6 Capacity management | D78: ISO/IEC 27002:2022 | E78: 65 | H78: 50000 | I78: 100 | J78: 0.01 | K78: 0.01 | L78: 0.01 | N78: =A78*((SUM(F78:I78))+(J78*1950*80)) | O78: =A78*J78 | P78: =A78*K78 | Q78: =A78*L78 | R78: =1-P78 | S78: =1-Q78
C79: 8.7 Protection against malware | D79: ISO/IEC 27002:2022 | E79: 66 | G79: 5000 | H79: 25000 | I79: 200 | J79: 0.06 | K79: 0.08 | L79: 0.08 | N79: =A79*((SUM(F79:I79))+(J79*1950*80)) | O79: =A79*J79 | P79: =A79*K79 | Q79: =A79*L79 | R79: =1-P79 | S79: =1-Q79
C80: 8.8 Management of technical vulnerabilities | D80: ISO/IEC 27002:2022 | E80: 67 | F80: 5000 | G80: 25000 | H80: 50000 | I80: 10000 | J80: 0.06 | K80: 0.065 | L80: 0.065 | N80: =A80*((SUM(F80:I80))+(J80*1950*80)) | O80: =A80*J80 | P80: =A80*K80 | Q80: =A80*L80 | R80: =1-P80 | S80: =1-Q80
C81: 8.9 Configuration management | D81: ISO/IEC 27002:2022 | E81: 68 | H81: 10000 | I81: 1000 | J81: 0.02 | K81: 0.01 | L81: 0.01 | N81: =A81*((SUM(F81:I81))+(J81*1950*80)) | O81: =A81*J81 | P81: =A81*K81 | Q81: =A81*L81 | R81: =1-P81 | S81: =1-Q81
C82: 8.10 Information deletion | D82: ISO/IEC 27002:2022 | E82: 69 | H82: 10000 | I82: 1000 | J82: 0.02 | K82: 0.01 | L82: 0.01 | N82: =A82*((SUM(F82:I82))+(J82*1950*80)) | O82: =A82*J82 | P82: =A82*K82 | Q82: =A82*L82 | R82: =1-P82 | S82: =1-Q82
C83: 8.11 Data masking | D83: ISO/IEC 27002:2022 | E83: 70 | H83: 10000 | I83: 1000 | J83: 0.02 | K83: 0.01 | L83: 0.01 | N83: =A83*((SUM(F83:I83))+(J83*1950*80)) | O83: =A83*J83 | P83: =A83*K83 | Q83: =A83*L83 | R83: =1-P83 | S83: =1-Q83
C84: 8.12 Data leakage prevention | D84: ISO/IEC 27002:2022 | E84: 71 | H84: 10000 | I84: 1000 | J84: 0.02 | K84: 0.01 | L84: 0.01 | N84: =A84*((SUM(F84:I84))+(J84*1950*80)) | O84: =A84*J84 | P84: =A84*K84 | Q84: =A84*L84 | R84: =1-P84 | S84: =1-Q84
C85: 8.13 Information backup | D85: ISO/IEC 27002:2022 | E85: 72 | F85: 50000 | G85: 10000 | H85: 50000 | I85: 10000 | J85: 0.06 | K85: 0.065 | L85: 0.06 | N85: =A85*((SUM(F85:I85))+(J85*1950*80)) | O85: =A85*J85 | P85: =A85*K85 | Q85: =A85*L85 | R85: =1-P85 | S85: =1-Q85
C86: 8.14 Redundancy of information processing facilities | D86: ISO/IEC 27002:2022 | E86: 73 | H86: 20000 | I86: 50000 | J86: 0.02 | K86: 0.065 | L86: 0.065 | N86: =A86*((SUM(F86:I86))+(J86*1950*80)) | O86: =A86*J86 | P86: =A86*K86 | Q86: =A86*L86 | R86: =1-P86 | S86: =1-Q86
C87: 8.15 Logging | D87: ISO/IEC 27002:2022 | E87: 74 | F87: 10000 | G87: 5000 | H87: 50000 | I87: 10000 | J87: 0.01 | K87: 0.06 | L87: 0.06 | N87: =A87*((SUM(F87:I87))+(J87*1950*80)) | O87: =A87*J87 | P87: =A87*K87 | Q87: =A87*L87 | R87: =1-P87 | S87: =1-Q87
C88: 8.16 Monitoring activities | D88: ISO/IEC 27002:2022 | E88: 75 | H88: 10000 | I88: 1000 | J88: 0.02 | K88: 0.01 | L88: 0.01 | N88: =A88*((SUM(F88:I88))+(J88*1950*80)) | O88: =A88*J88 | P88: =A88*K88 | Q88: =A88*L88 | R88: =1-P88 | S88: =1-Q88
C89: 8.17 Clock synchronization | D89: ISO/IEC 27002:2022 | E89: 76 | H89: 10000 | I89: 1000 | J89: 0.02 | K89: 0.01 | L89: 0.01 | N89: =A89*((SUM(F89:I89))+(J89*1950*80)) | O89: =A89*J89 | P89: =A89*K89 | Q89: =A89*L89 | R89: =1-P89 | S89: =1-Q89
C90: 8.18 Use of privileged utility programs | D90: ISO/IEC 27002:2022 | E90: 77 | G90: 5000 | H90: 5000 | I90: 100 | J90: 0.01 | K90: 0.01 | L90: 0.01 | N90: =A90*((SUM(F90:I90))+(J90*1950*80)) | O90: =A90*J90 | P90: =A90*K90 | Q90: =A90*L90 | R90: =1-P90 | S90: =1-Q90
C91: 8.19 Installation of software on operational systems | D91: ISO/IEC 27002:2022 | E91: 78 | F91: 10000 | G91: 5000 | I91: 500 | J91: 0.02 | K91: 0.06 | L91: 0.06 | N91: =A91*((SUM(F91:I91))+(J91*1950*80)) | O91: =A91*J91 | P91: =A91*K91 | Q91: =A91*L91 | R91: =1-P91 | S91: =1-Q91
C92: 8.20 Networks security | D92: ISO/IEC 27002:2022 | E92: 79 | F92: 5000 | G92: 25000 | H92: 50000 | I92: 10000 | J92: 0.06 | K92: 0.02 | L92: 0.02 | N92: =A92*((SUM(F92:I92))+(J92*1950*80)) | O92: =A92*J92 | P92: =A92*K92 | Q92: =A92*L92 | R92: =1-P92 | S92: =1-Q92
C93: 8.21 Security of network services | D93: ISO/IEC 27002:2022 | E93: 80 | F93: 5000 | G93: 25000 | H93: 50000 | I93: 10000 | J93: 0.06 | K93: 0.02 | L93: 0.02 | N93: =A93*((SUM(F93:I93))+(J93*1950*80)) | O93: =A93*J93 | P93: =A93*K93 | Q93: =A93*L93 | R93: =1-P93 | S93: =1-Q93
C94: 8.22 Segregation of networks | D94: ISO/IEC 27002:2022 | E94: 81 | F94: 5000 | G94: 25000 | H94: 50000 | I94: 10000 | J94: 0.06 | K94: 0.02 | L94: 0.02 | N94: =A94*((SUM(F94:I94))+(J94*1950*80)) | O94: =A94*J94 | P94: =A94*K94 | Q94: =A94*L94 | R94: =1-P94 | S94: =1-Q94
C95: 8.23 Web filtering | D95: ISO/IEC 27002:2022 | E95: 82 | H95: 10000 | I95: 1000 | J95: 0.02 | K95: 0.01 | L95: 0.01 | N95: =A95*((SUM(F95:I95))+(J95*1950*80)) | O95: =A95*J95 | P95: =A95*K95 | Q95: =A95*L95 | R95: =1-P95 | S95: =1-Q95
C96: 8.24 Use of cryptography | D96: ISO/IEC 27002:2022 | E96: 83 | G96: 5000 | H96: 5000 | I96: 100 | J96: 0.01 | K96: 0.01 | L96: 0.01 | N96: =A96*((SUM(F96:I96))+(J96*1950*80)) | O96: =A96*J96 | P96: =A96*K96 | Q96: =A96*L96 | R96: =1-P96 | S96: =1-Q96
C97: 8.25 Secure development life cycle | D97: ISO/IEC 27002:2022 | E97: 84 | H97: 20000 | I97: 1000 | J97: 0.02 | K97: 0.01 | L97: 0.01 | N97: =A97*((SUM(F97:I97))+(J97*1950*80)) | O97: =A97*J97 | P97: =A97*K97 | Q97: =A97*L97 | R97: =1-P97 | S97: =1-Q97
C98: 8.26 Application security requirements | D98: ISO/IEC 27002:2022 | E98: 85 | H98: 20000 | I98: 1000 | J98: 0.02 | K98: 0.02 | L98: 0.02 | N98: =A98*((SUM(F98:I98))+(J98*1950*80)) | O98: =A98*J98 | P98: =A98*K98 | Q98: =A98*L98 | R98: =1-P98 | S98: =1-Q98
C99: 8.27 Secure system architecture and engineering principles | D99: ISO/IEC 27002:2022 | E99: 86 | H99: 20000 | I99: 1000 | J99: 0.02 | K99: 0.01 | L99: 0.01 | N99: =A99*((SUM(F99:I99))+(J99*1950*80)) | O99: =A99*J99 | P99: =A99*K99 | Q99: =A99*L99 | R99: =1-P99 | S99: =1-Q99
C100: 8.28 Secure coding | D100: ISO/IEC 27002:2022 | E100: 87 | H100: 10000 | I100: 1000 | J100: 0.02 | K100: 0.01 | L100: 0.01 | N100: =A100*((SUM(F100:I100))+(J100*1950*80)) | O100: =A100*J100 | P100: =A100*K100 | Q100: =A100*L100 | R100: =1-P100 | S100: =1-Q100
...

Sheet S3
A1: Risk scenario number 3 / Scénario de risque 3
A2: Scenario number / Numéro : | B2: 3
A3: Scenario name / Nom du scénario :
A4: Date of creation / Date de création du scénario :
A6: Probability that the threat will be present = Probabilité de réalisation : Pb(A)
A7: Probability of exploitation = Probabilité d’exploitation: Pb(ψ,A)
A8: Estimated expected damages = Dommage estimé: δe(ψ,A)
A9: Maximal damages = Dommage maximal: δm(ψ,A) | C9: =IF(AND(ISNUMBER(B8),ISNUMBER(B9),B9<B8),"δm should be ≥ δe / δm devrait être ≥ δe","")
A10: Level of organizational resilience = Niveau de résilience: θ(ψ,A) | C10: =IF(AND(B10<>"",OR(NOT(ISNUMBER(B10)),B10<=0,B10>1)),"θ must be in (0, 1] / θ doit être dans ]0, 1]","")
A11: Organizational criticality (expected utility) = Criticité organisationnelle (utilité espérée) : μ(E)
A14: 3. Renseigner les scénarios de risque (feuilles S1 à S10)
A15: 3. Populate the risk scenarios (Sheets S1 to S10)
A16: Values 0-1; θ > 0 and ≤ 1; δm ≥ δe. Horizon: 12 months. Each value: rationale, evidence (E-number), confidence — Analytical estimate — validation required.
A17: Valeurs 0-1; θ > 0 et ≤ 1; δm ≥ δe. Horizon : 12 mois. Chaque valeur : justification, preuve (n° E), confiance — Estimation analytique — validation requise.

Sheet M3
A1: Other / autre | C1: Proposed risk mitigation measure / mesure de mitigation des risques proposés | D1: Source | F1: Immobilisations | G1: Logiciels | H1: Mise en œuvre | I1: Exploitation | J1: ÉTC | K1: Réduc impacts | L1: Réduction Pb | N1: Coût | O1: ETC | P1: Impact | Q1: Pb | R1: 1 − impact | S1: 1 − Pb
N2: =A2*((SUM(F2:I2))+(J2*1950*80)) | O2: =A2*J2 | P2: =A2*K2 | Q2: =A2*L2 | R2: =1-P2 | S2: =1-Q2
N3: =A3*((SUM(F3:I3))+(J3*1950*80)) | O3: =A3*J3 | P3: =A3*K3 | Q3: =A3*L3 | R3: =1-P3 | S3: =1-Q3
N4: =A4*((SUM(F4:I4))+(J4*1950*80)) | O4: =A4*J4 | P4: =A4*K4 | Q4: =A4*L4 | R4: =1-P4 | S4: =1-Q4
N5: =A5*((SUM(F5:I5))+(J5*1950*80)) | O5: =A5*J5 | P5: =A5*K5 | Q5: =A5*L5 | R5: =1-P5 | S5: =1-Q5
N6: =A6*((SUM(F6:I6))+(J6*1950*80)) | O6: =A6*J6 | P6: =A6*K6 | Q6: =A6*L6 | R6: =1-P6 | S6: =1-Q6
N7: =SUM(N2:N6) | O7: =SUM(O2:O6) | P7: =1-PRODUCT(R2:R6) | Q7: =1-PRODUCT(S2:S6)
A8: Include | C8: Control / Contrôle | D8: Source | F8: Immobilisations | G8: Logiciels | H8: Mise en œuvre | I8: Exploitation | J8: ÉTC | K8: Réduc impacts | L8: Réduction Pb | N8: Coût | O8: ETC | P8: Impact | Q8: Pb | R8: 1 − impact | S8: 1 − Pb
A9: Inclure | C9: ISO/IEC 27002:2022 — information security controls (93) / mesures de sécurité de l'information | F9: CAPEX | G9: Software | H9: Implementation | I9: Exploitation | J9: FTE | K9: Reduce impacts | L9: Reduce Pb | N9: Cost | O9: FTE | P9: Impact | Q9: Pb
C10: 5 Organizational controls / Mesures organisationnelles
C11: 5.1 Policies for information security | D11: ISO/IEC 27002:2022 | E11: 1 | H11: 25000 | I11: 3000 | J11: 0.01 | K11: 0.06 | L11: 0.06 | N11: =A11*((SUM(F11:I11))+(J11*1950*80)) | O11: =A11*J11 | P11: =A11*K11 | Q11: =A11*L11 | R11: =1-P11 | S11: =1-Q11
C12: 5.2 Information security roles and responsibilities | D12: ISO/IEC 27002:2022 | E12: 2 | H12: 5000 | I12: 500 | J12: 0.01 | K12: 0.01 | L12: 0.01 | N12: =A12*((SUM(F12:I12))+(J12*1950*80)) | O12: =A12*J12 | P12: =A12*K12 | Q12: =A12*L12 | R12: =1-P12 | S12: =1-Q12
C13: 5.3 Segregation of duties | D13: ISO/IEC 27002:2022 | E13: 3 | H13: 5000 | I13: 500 | J13: 0.01 | K13: 0.01 | L13: 0.01 | N13: =A13*((SUM(F13:I13))+(J13*1950*80)) | O13: =A13*J13 | P13: =A13*K13 | Q13: =A13*L13 | R13: =1-P13 | S13: =1-Q13 | U13: 4. Définir les mesures de mitigation (feuilles M1 à M10)
C14: 5.4 Management responsibilities | D14: ISO/IEC 27002:2022 | E14: 4 | H14: 5000 | I14: 500 | J14: 0.01 | K14: 0.01 | L14: 0.01 | N14: =A14*((SUM(F14:I14))+(J14*1950*80)) | O14: =A14*J14 | P14: =A14*K14 | Q14: =A14*L14 | R14: =1-P14 | S14: =1-Q14 | U14: dans la colonne A Inclure Mesure
C15: 5.5 Contact with authorities | D15: ISO/IEC 27002:2022 | E15: 5 | H15: 5000 | J15: =1/50 | K15: 0.01 | L15: 0.01 | N15: =A15*((SUM(F15:I15))+(J15*1950*80)) | O15: =A15*J15 | P15: =A15*K15 | Q15: =A15*L15 | R15: =1-P15 | S15: =1-Q15 | U15: 0 ou vide = non sélectionné
C16: 5.6 Contact with special interest groups | D16: ISO/IEC 27002:2022 | E16: 6 | H16: 5000 | J16: =3/50 | K16: 0.01 | L16: 0.01 | N16: =A16*((SUM(F16:I16))+(J16*1950*80)) | O16: =A16*J16 | P16: =A16*K16 | Q16: =A16*L16 | R16: =1-P16 | S16: =1-Q16 | U16: 6. Define the risk mitigation measures (Sheets M1 to M10)
C17: 5.7 Threat intelligence | D17: ISO/IEC 27002:2022 | E17: 7 | H17: 10000 | I17: 1000 | J17: 0.02 | K17: 0.01 | L17: 0.01 | N17: =A17*((SUM(F17:I17))+(J17*1950*80)) | O17: =A17*J17 | P17: =A17*K17 | Q17: =A17*L17 | R17: =1-P17 | S17: =1-Q17
C18: 5.8 Information security in project management | D18: ISO/IEC 27002:2022 | E18: 8 | H18: 5000 | J18: 0.06 | K18: 0.06 | L18: 0.06 | N18: =A18*((SUM(F18:I18))+(J18*1950*80)) | O18: =A18*J18 | P18: =A18*K18 | Q18: =A18*L18 | R18: =1-P18 | S18: =1-Q18 | U18: 4. Define the risk mitigation measures (Sheets M1 to M10)
C19: 5.9 Inventory of information and other associated assets | D19: ISO/IEC 27002:2022 | E19: 9 | G19: 10000 | H19: 50000 | I19: 100 | J19: 0.04 | K19: 0.06 | L19: 0.06 | N19: =A19*((SUM(F19:I19))+(J19*1950*80)) | O19: =A19*J19 | P19: =A19*K19 | Q19: =A19*L19 | R19: =1-P19 | S19: =1-Q19 | U19: indicate the selected mitigation measures or controls in Column A
C20: 5.10 Acceptable use of information and other associated assets | D20: ISO/IEC 27002:2022 | E20: 10 | H20: 10000 | I20: 100 | J20: 0.02 | K20: 0.03 | L20: 0.03 | N20: =A20*((SUM(F20:I20))+(J20*1950*80)) | O20: =A20*J20 | P20: =A20*K20 | Q20: =A20*L20 | R20: =1-P20 | S20: =1-Q20 | U20: 0 or empty = not selected
C21: 5.11 Return of assets | D21: ISO/IEC 27002:2022 | E21: 11 | H21: 20000 | I21: 100 | J21: 0.02 | K21: 0.01 | L21: 0.01 | N21: =A21*((SUM(F21:I21))+(J21*1950*80)) | O21: =A21*J21 | P21: =A21*K21 | Q21: =A21*L21 | R21: =1-P21 | S21: =1-Q21 | U21: Combination rule / Règle de combinaison :
C22: 5.12 Classification of information | D22: ISO/IEC 27002:2022 | E22: 12 | G22: 5000 | H22: 50000 | I22: 100 | J22: 0.02 | K22: 0.06 | L22: 0.06 | N22: =A22*((SUM(F22:I22))+(J22*1950*80)) | O22: =A22*J22 | P22: =A22*K22 | Q22: =A22*L22 | R22: =1-P22 | S22: =1-Q22 | U22: Selected coefficients combine per column (K impact, L probability) with the product rule:
C23: 5.13 Labelling of information | D23: ISO/IEC 27002:2022 | E23: 13 | H23: 10000 | I23: 50 | J23: 0.02 | K23: 0.01 | L23: 0.01 | N23: =A23*((SUM(F23:I23))+(J23*1950*80)) | O23: =A23*J23 | P23: =A23*K23 | Q23: =A23*L23 | R23: =1-P23 | S23: =1-Q23 | U23: package reduction = 1 − ∏(1 − rᵢ). Each rᵢ must be 0-1, so the package can never exceed 1;
C24: 5.14 Information transfer | D24: ISO/IEC 27002:2022 | E24: 14 | H24: 20000 | I24: 1000 | J24: 0.02 | K24: 0.02 | L24: 0.02 | N24: =A24*((SUM(F24:I24))+(J24*1950*80)) | O24: =A24*J24 | P24: =A24*K24 | Q24: =A24*L24 | R24: =1-P24 | S24: =1-Q24 | U24: the 'Other' rows count as additional factors. A warning appears under the TOTAL row if a coefficient is outside 0-1.
C25: 5.15 Access control | D25: ISO/IEC 27002:2022 | E25: 15 | G25: 5000 | H25: 5000 | I25: 100 | J25: 0.02 | K25: 0.06 | L25: 0.06 | N25: =A25*((SUM(F25:I25))+(J25*1950*80)) | O25: =A25*J25 | P25: =A25*K25 | Q25: =A25*L25 | R25: =1-P25 | S25: =1-Q25 | U25: Prefer a few well-justified controls, or enter ONE package-level
C26: 5.16 Identity management | D26: ISO/IEC 27002:2022 | E26: 16 | G26: 5000 | H26: 5000 | I26: 100 | J26: 0.01 | K26: 0.01 | L26: 0.01 | N26: =A26*((SUM(F26:I26))+(J26*1950*80)) | O26: =A26*J26 | P26: =A26*K26 | Q26: =A26*L26 | R26: =1-P26 | S26: =1-Q26 | U26: estimate (cost, impact and Pb reduction) in an 'Other' row, with its rationale.
C27: 5.17 Authentication information | D27: ISO/IEC 27002:2022 | E27: 17 | G27: 5000 | H27: 5000 | I27: 100 | J27: 0.01 | K27: 0.01 | L27: 0.01 | N27: =A27*((SUM(F27:I27))+(J27*1950*80)) | O27: =A27*J27 | P27: =A27*K27 | Q27: =A27*L27 | R27: =1-P27 | S27: =1-Q27 | U27: Les coefficients retenus se combinent par colonne selon la règle du produit :
C28: 5.18 Access rights | D28: ISO/IEC 27002:2022 | E28: 18 | G28: 5000 | H28: 5000 | I28: 100 | J28: 0.01 | K28: 0.01 | L28: 0.01 | N28: =A28*((SUM(F28:I28))+(J28*1950*80)) | O28: =A28*J28 | P28: =A28*K28 | Q28: =A28*L28 | R28: =1-P28 | S28: =1-Q28 | U28: réduction du bouquet = 1 − ∏(1 − rᵢ); chaque rᵢ entre 0 et 1, donc jamais plus de 1;
C29: 5.19 Information security in supplier relationships | D29: ISO/IEC 27002:2022 | E29: 19 | H29: 20000 | I29: 1000 | J29: 0.02 | K29: 0.06 | L29: 0.06 | N29: =A29*((SUM(F29:I29))+(J29*1950*80)) | O29: =A29*J29 | P29: =A29*K29 | Q29: =A29*L29 | R29: =1-P29 | S29: =1-Q29 | U29: les lignes « Other / autre » comptent comme facteurs. Privilégier peu de mesures bien justifiées,
C30: 5.20 Addressing information security within supplier agreements | D30: ISO/IEC 27002:2022 | E30: 20 | H30: 20000 | I30: 1000 | J30: 0.02 | K30: 0.06 | L30: 0.06 | N30: =A30*((SUM(F30:I30))+(J30*1950*80)) | O30: =A30*J30 | P30: =A30*K30 | Q30: =A30*L30 | R30: =1-P30 | S30: =1-Q30 | U30: ou saisir une estimation globale du bouquet dans une ligne « Other / autre ».
C31: 5.21 Managing information security in the ICT supply chain | D31: ISO/IEC 27002:2022 | E31: 21 | H31: 20000 | I31: 1000 | J31: 0.02 | K31: 0.01 | L31: 0.01 | N31: =A31*((SUM(F31:I31))+(J31*1950*80)) | O31: =A31*J31 | P31: =A31*K31 | Q31: =A31*L31 | R31: =1-P31 | S31: =1-Q31 | U31: dépasse 1. Privilégier peu de mesures bien justifiées, ou saisir une
C32: 5.22 Monitoring, review and change management of supplier services | D32: ISO/IEC 27002:2022 | E32: 22 | H32: 20000 | I32: 1000 | J32: 0.02 | K32: 0.06 | L32: 0.06 | N32: =A32*((SUM(F32:I32))+(J32*1950*80)) | O32: =A32*J32 | P32: =A32*K32 | Q32: =A32*L32 | R32: =1-P32 | S32: =1-Q32 | U32: estimation globale du bouquet dans une ligne « Other / autre ».
C33: 5.23 Information security for use of cloud services | D33: ISO/IEC 27002:2022 | E33: 23 | H33: 10000 | I33: 1000 | J33: 0.02 | K33: 0.01 | L33: 0.01 | N33: =A33*((SUM(F33:I33))+(J33*1950*80)) | O33: =A33*J33 | P33: =A33*K33 | Q33: =A33*L33 | R33: =1-P33 | S33: =1-Q33
C34: 5.24 Information security incident management planning and preparation | D34: ISO/IEC 27002:2022 | E34: 24 | H34: 10000 | I34: 1000 | J34: 0.02 | K34: 0.01 | L34: 0.01 | N34: =A34*((SUM(F34:I34))+(J34*1950*80)) | O34: =A34*J34 | P34: =A34*K34 | Q34: =A34*L34 | R34: =1-P34 | S34: =1-Q34 | U34: Catalogues: ISO/IEC 27002:2022 (93), NIST CSF 2.0 (106), CIS Controls v8.1 (18).
C35: 5.25 Assessment and decision on information security events | D35: ISO/IEC 27002:2022 | E35: 25 | H35: 10000 | I35: 1000 | J35: 0.02 | K35: 0.01 | L35: 0.01 | N35: =A35*((SUM(F35:I35))+(J35*1950*80)) | O35: =A35*J35 | P35: =A35*K35 | Q35: =A35*L35 | R35: =1-P35 | S35: =1-Q35 | U35: Default costs and coefficients are generic placeholders: recalibrate them.
C36: 5.26 Response to information security incidents | D36: ISO/IEC 27002:2022 | E36: 26 | H36: 10000 | I36: 1000 | J36: 0.02 | K36: 0.06 | L36: 0.06 | N36: =A36*((SUM(F36:I36))+(J36*1950*80)) | O36: =A36*J36 | P36: =A36*K36 | Q36: =A36*L36 | R36: =1-P36 | S36: =1-Q36 | U36: Coûts et coefficients par défaut génériques : à recalibrer.
C37: 5.27 Learning from information security incidents | D37: ISO/IEC 27002:2022 | E37: 27 | H37: 10000 | I37: 1000 | J37: 0.02 | K37: 0.01 | L37: 0.01 | N37: =A37*((SUM(F37:I37))+(J37*1950*80)) | O37: =A37*J37 | P37: =A37*K37 | Q37: =A37*L37 | R37: =1-P37 | S37: =1-Q37
C38: 5.28 Collection of evidence | D38: ISO/IEC 27002:2022 | E38: 28 | H38: 10000 | I38: 10000 | J38: 0.02 | K38: 0.01 | L38: 0.01 | N38: =A38*((SUM(F38:I38))+(J38*1950*80)) | O38: =A38*J38 | P38: =A38*K38 | Q38: =A38*L38 | R38: =1-P38 | S38: =1-Q38
C39: 5.29 Information security during disruption | D39: ISO/IEC 27002:2022 | E39: 29 | H39: 20000 | I39: 1000 | J39: 0.02 | K39: 0.01 | L39: 0.01 | N39: =A39*((SUM(F39:I39))+(J39*1950*80)) | O39: =A39*J39 | P39: =A39*K39 | Q39: =A39*L39 | R39: =1-P39 | S39: =1-Q39
C40: 5.30 ICT readiness for business continuity | D40: ISO/IEC 27002:2022 | E40: 30 | H40: 10000 | I40: 1000 | J40: 0.02 | K40: 0.01 | L40: 0.01 | N40: =A40*((SUM(F40:I40))+(J40*1950*80)) | O40: =A40*J40 | P40: =A40*K40 | Q40: =A40*L40 | R40: =1-P40 | S40: =1-Q40
C41: 5.31 Legal, statutory, regulatory and contractual requirements | D41: ISO/IEC 27002:2022 | E41: 31 | H41: 10000 | I41: 1000 | J41: 0.02 | K41: 0.01 | L41: 0.01 | N41: =A41*((SUM(F41:I41))+(J41*1950*80)) | O41: =A41*J41 | P41: =A41*K41 | Q41: =A41*L41 | R41: =1-P41 | S41: =1-Q41
C42: 5.32 Intellectual property rights | D42: ISO/IEC 27002:2022 | E42: 32 | H42: 10000 | I42: 1000 | J42: 0.02 | K42: 0.01 | L42: 0.01 | N42: =A42*((SUM(F42:I42))+(J42*1950*80)) | O42: =A42*J42 | P42: =A42*K42 | Q42: =A42*L42 | R42: =1-P42 | S42: =1-Q42
C43: 5.33 Protection of records | D43: ISO/IEC 27002:2022 | E43: 33 | H43: 10000 | I43: 1000 | J43: 0.02 | K43: 0.01 | L43: 0.01 | N43: =A43*((SUM(F43:I43))+(J43*1950*80)) | O43: =A43*J43 | P43: =A43*K43 | Q43: =A43*L43 | R43: =1-P43 | S43: =1-Q43
C44: 5.34 Privacy and protection of PII | D44: ISO/IEC 27002:2022 | E44: 34 | H44: 10000 | I44: 1000 | J44: 0.02 | K44: 0.01 | L44: 0.01 | N44: =A44*((SUM(F44:I44))+(J44*1950*80)) | O44: =A44*J44 | P44: =A44*K44 | Q44: =A44*L44 | R44: =1-P44 | S44: =1-Q44
C45: 5.35 Independent review of information security | D45: ISO/IEC 27002:2022 | E45: 35 | H45: 10000 | I45: 10000 | J45: 0.02 | K45: 0.01 | L45: 0.01 | N45: =A45*((SUM(F45:I45))+(J45*1950*80)) | O45: =A45*J45 | P45: =A45*K45 | Q45: =A45*L45 | R45: =1-P45 | S45: =1-Q45
C46: 5.36 Compliance with policies, rules and standards for information security | D46: ISO/IEC 27002:2022 | E46: 36 | H46: 10000 | I46: 10000 | J46: 0.02 | K46: 0.01 | L46: 0.01 | N46: =A46*((SUM(F46:I46))+(J46*1950*80)) | O46: =A46*J46 | P46: =A46*K46 | Q46: =A46*L46 | R46: =1-P46 | S46: =1-Q46
C47: 5.37 Documented operating procedures | D47: ISO/IEC 27002:2022 | E47: 37 | H47: 50000 | I47: 100 | J47: 0.01 | K47: 0.06 | L47: 0.06 | N47: =A47*((SUM(F47:I47))+(J47*1950*80)) | O47: =A47*J47 | P47: =A47*K47 | Q47: =A47*L47 | R47: =1-P47 | S47: =1-Q47
C48: 6 People controls / Mesures liées aux personnes
C49: 6.1 Screening | D49: ISO/IEC 27002:2022 | E49: 38 | H49: 5000 | I49: 500 | J49: 0.01 | K49: 0.01 | L49: 0.01 | N49: =A49*((SUM(F49:I49))+(J49*1950*80)) | O49: =A49*J49 | P49: =A49*K49 | Q49: =A49*L49 | R49: =1-P49 | S49: =1-Q49
C50: 6.2 Terms and conditions of employment | D50: ISO/IEC 27002:2022 | E50: 39 | H50: 5000 | J50: 0.01 | K50: 0.01 | L50: 0.01 | N50: =A50*((SUM(F50:I50))+(J50*1950*80)) | O50: =A50*J50 | P50: =A50*K50 | Q50: =A50*L50 | R50: =1-P50 | S50: =1-Q50
C51: 6.3 Information security awareness, education and training | D51: ISO/IEC 27002:2022 | E51: 40 | H51: 30000 | I51: 500 | J51: 0.01 | K51: 0.06 | L51: 0.06 | N51: =A51*((SUM(F51:I51))+(J51*1950*80)) | O51: =A51*J51 | P51: =A51*K51 | Q51: =A51*L51 | R51: =1-P51 | S51: =1-Q51
C52: 6.4 Disciplinary process | D52: ISO/IEC 27002:2022 | E52: 41 | H52: 10000 | I52: 500 | J52: 0.01 | K52: 0.01 | L52: 0.01 | N52: =A52*((SUM(F52:I52))+(J52*1950*80)) | O52: =A52*J52 | P52: =A52*K52 | Q52: =A52*L52 | R52: =1-P52 | S52: =1-Q52
C53: 6.5 Responsibilities after termination or change of employment | D53: ISO/IEC 27002:2022 | E53: 42 | H53: 5000 | I53: 500 | J53: 0.01 | K53: 0.05 | L53: 0.02 | N53: =A53*((SUM(F53:I53))+(J53*1950*80)) | O53: =A53*J53 | P53: =A53*K53 | Q53: =A53*L53 | R53: =1-P53 | S53: =1-Q53
C54: 6.6 Confidentiality or non-disclosure agreements | D54: ISO/IEC 27002:2022 | E54: 43 | H54: 20000 | I54: 1000 | J54: 0.02 | K54: 0.02 | L54: 0.02 | N54: =A54*((SUM(F54:I54))+(J54*1950*80)) | O54: =A54*J54 | P54: =A54*K54 | Q54: =A54*L54 | R54: =1-P54 | S54: =1-Q54
C55: 6.7 Remote working | D55: ISO/IEC 27002:2022 | E55: 44 | H55: 5000 | I55: 2000 | J55: 0.05 | K55: 0.01 | L55: 0.01 | N55: =A55*((SUM(F55:I55))+(J55*1950*80)) | O55: =A55*J55 | P55: =A55*K55 | Q55: =A55*L55 | R55: =1-P55 | S55: =1-Q55
C56: 6.8 Information security event reporting | D56: ISO/IEC 27002:2022 | E56: 45 | H56: 10000 | I56: 1000 | J56: 0.02 | K56: 0.01 | L56: 0.01 | N56: =A56*((SUM(F56:I56))+(J56*1950*80)) | O56: =A56*J56 | P56: =A56*K56 | Q56: =A56*L56 | R56: =1-P56 | S56: =1-Q56
C57: 7 Physical controls / Mesures physiques
C58: 7.1 Physical security perimeters | D58: ISO/IEC 27002:2022 | E58: 46 | F58: 10000 | G58: 50000 | H58: 10000 | I58: 500 | J58: 0.02 | K58: 0.06 | L58: 0.06 | N58: =A58*((SUM(F58:I58))+(J58*1950*80)) | O58: =A58*J58 | P58: =A58*K58 | Q58: =A58*L58 | R58: =1-P58 | S58: =1-Q58
C59: 7.2 Physical entry | D59: ISO/IEC 27002:2022 | E59: 47 | F59: 10000 | G59: 50000 | H59: 10000 | I59: 500 | J59: 0.02 | K59: 0.06 | L59: 0.06 | N59: =A59*((SUM(F59:I59))+(J59*1950*80)) | O59: =A59*J59 | P59: =A59*K59 | Q59: =A59*L59 | R59: =1-P59 | S59: =1-Q59
C60: 7.3 Securing offices, rooms and facilities | D60: ISO/IEC 27002:2022 | E60: 48 | F60: 10000 | G60: 50000 | H60: 10000 | I60: 500 | J60: 0.02 | K60: 0.01 | L60: 0.01 | N60: =A60*((SUM(F60:I60))+(J60*1950*80)) | O60: =A60*J60 | P60: =A60*K60 | Q60: =A60*L60 | R60: =1-P60 | S60: =1-Q60
C61: 7.4 Physical security monitoring | D61: ISO/IEC 27002:2022 | E61: 49 | H61: 10000 | I61: 1000 | J61: 0.02 | K61: 0.01 | L61: 0.01 | N61: =A61*((SUM(F61:I61))+(J61*1950*80)) | O61: =A61*J61 | P61: =A61*K61 | Q61: =A61*L61 | R61: =1-P61 | S61: =1-Q61
C62: 7.5 Protecting against physical and environmental threats | D62: ISO/IEC 27002:2022 | E62: 50 | F62: 10000 | G62: 50000 | H62: 10000 | I62: 100 | J62: 0.02 | K62: 0.06 | L62: 0.06 | N62: =A62*((SUM(F62:I62))+(J62*1950*80)) | O62: =A62*J62 | P62: =A62*K62 | Q62: =A62*L62 | R62: =1-P62 | S62: =1-Q62
C63: 7.6 Working in secure areas | D63: ISO/IEC 27002:2022 | E63: 51 | F63: 10000 | G63: 50000 | H63: 10000 | I63: 100 | J63: 0.02 | K63: 0.01 | L63: 0.01 | N63: =A63*((SUM(F63:I63))+(J63*1950*80)) | O63: =A63*J63 | P63: =A63*K63 | Q63: =A63*L63 | R63: =1-P63 | S63: =1-Q63
C64: 7.7 Clear desk and clear screen | D64: ISO/IEC 27002:2022 | E64: 52 | H64: 5000 | I64: 100 | J64: 0.01 | K64: 0.01 | L64: 0.01 | N64: =A64*((SUM(F64:I64))+(J64*1950*80)) | O64: =A64*J64 | P64: =A64*K64 | Q64: =A64*L64 | R64: =1-P64 | S64: =1-Q64
C65: 7.8 Equipment siting and protection | D65: ISO/IEC 27002:2022 | E65: 53 | F65: 10000 | H65: 10000 | I65: 500 | J65: 0.02 | K65: 0.06 | L65: 0.06 | N65: =A65*((SUM(F65:I65))+(J65*1950*80)) | O65: =A65*J65 | P65: =A65*K65 | Q65: =A65*L65 | R65: =1-P65 | S65: =1-Q65
C66: 7.9 Security of assets off-premises | D66: ISO/IEC 27002:2022 | E66: 54 | G66: 50000 | H66: 10000 | I66: 100 | J66: 0.01 | K66: 0.01 | L66: 0.01 | N66: =A66*((SUM(F66:I66))+(J66*1950*80)) | O66: =A66*J66 | P66: =A66*K66 | Q66: =A66*L66 | R66: =1-P66 | S66: =1-Q66
C67: 7.10 Storage media | D67: ISO/IEC 27002:2022 | E67: 55 | G67: 5000 | H67: 5000 | I67: 100 | J67: 0.02 | K67: 0.01 | L67: 0.01 | N67: =A67*((SUM(F67:I67))+(J67*1950*80)) | O67: =A67*J67 | P67: =A67*K67 | Q67: =A67*L67 | R67: =1-P67 | S67: =1-Q67
C68: 7.11 Supporting utilities | D68: ISO/IEC 27002:2022 | E68: 56 | F68: 10000 | G68: 50000 | H68: 10000 | I68: 100 | J68: 0.01 | K68: 0.01 | L68: 0.01 | N68: =A68*((SUM(F68:I68))+(J68*1950*80)) | O68: =A68*J68 | P68: =A68*K68 | Q68: =A68*L68 | R68: =1-P68 | S68: =1-Q68
C69: 7.12 Cabling security | D69: ISO/IEC 27002:2022 | E69: 57 | F69: 10000 | G69: 50000 | H69: 10000 | I69: 100 | J69: 0.01 | K69: 0.01 | L69: 0.01 | N69: =A69*((SUM(F69:I69))+(J69*1950*80)) | O69: =A69*J69 | P69: =A69*K69 | Q69: =A69*L69 | R69: =1-P69 | S69: =1-Q69
C70: 7.13 Equipment maintenance | D70: ISO/IEC 27002:2022 | E70: 58 | F70: 10000 | G70: 50000 | H70: 10000 | I70: 500 | J70: 0.01 | K70: 0.01 | L70: 0.01 | N70: =A70*((SUM(F70:I70))+(J70*1950*80)) | O70: =A70*J70 | P70: =A70*K70 | Q70: =A70*L70 | R70: =1-P70 | S70: =1-Q70
C71: 7.14 Secure disposal or re-use of equipment | D71: ISO/IEC 27002:2022 | E71: 59 | G71: 50000 | H71: 10000 | I71: 100 | J71: 0.01 | K71: 0.01 | L71: 0.01 | N71: =A71*((SUM(F71:I71))+(J71*1950*80)) | O71: =A71*J71 | P71: =A71*K71 | Q71: =A71*L71 | R71: =1-P71 | S71: =1-Q71
C72: 8 Technological controls / Mesures technologiques
C73: 8.1 User end point devices | D73: ISO/IEC 27002:2022 | E73: 60 | H73: 5000 | I73: 500 | J73: 0.01 | K73: 0.01 | L73: 0.01 | N73: =A73*((SUM(F73:I73))+(J73*1950*80)) | O73: =A73*J73 | P73: =A73*K73 | Q73: =A73*L73 | R73: =1-P73 | S73: =1-Q73
C74: 8.2 Privileged access rights | D74: ISO/IEC 27002:2022 | E74: 61 | G74: 5000 | H74: 5000 | I74: 100 | J74: 0.01 | K74: 0.06 | L74: 0.06 | N74: =A74*((SUM(F74:I74))+(J74*1950*80)) | O74: =A74*J74 | P74: =A74*K74 | Q74: =A74*L74 | R74: =1-P74 | S74: =1-Q74
C75: 8.3 Information access restriction | D75: ISO/IEC 27002:2022 | E75: 62 | G75: 5000 | H75: 5000 | I75: 100 | J75: 0.01 | K75: 0.065 | L75: 0.06 | N75: =A75*((SUM(F75:I75))+(J75*1950*80)) | O75: =A75*J75 | P75: =A75*K75 | Q75: =A75*L75 | R75: =1-P75 | S75: =1-Q75
C76: 8.4 Access to source code | D76: ISO/IEC 27002:2022 | E76: 63 | G76: 5000 | H76: 5000 | I76: 100 | J76: 0.01 | K76: 0.01 | L76: 0.01 | N76: =A76*((SUM(F76:I76))+(J76*1950*80)) | O76: =A76*J76 | P76: =A76*K76 | Q76: =A76*L76 | R76: =1-P76 | S76: =1-Q76
C77: 8.5 Secure authentication | D77: ISO/IEC 27002:2022 | E77: 64 | G77: 5000 | H77: 5000 | I77: 100 | J77: 0.01 | K77: 0.01 | L77: 0.01 | N77: =A77*((SUM(F77:I77))+(J77*1950*80)) | O77: =A77*J77 | P77: =A77*K77 | Q77: =A77*L77 | R77: =1-P77 | S77: =1-Q77
C78: 8.6 Capacity management | D78: ISO/IEC 27002:2022 | E78: 65 | H78: 50000 | I78: 100 | J78: 0.01 | K78: 0.01 | L78: 0.01 | N78: =A78*((SUM(F78:I78))+(J78*1950*80)) | O78: =A78*J78 | P78: =A78*K78 | Q78: =A78*L78 | R78: =1-P78 | S78: =1-Q78
C79: 8.7 Protection against malware | D79: ISO/IEC 27002:2022 | E79: 66 | G79: 5000 | H79: 25000 | I79: 200 | J79: 0.06 | K79: 0.08 | L79: 0.08 | N79: =A79*((SUM(F79:I79))+(J79*1950*80)) | O79: =A79*J79 | P79: =A79*K79 | Q79: =A79*L79 | R79: =1-P79 | S79: =1-Q79
C80: 8.8 Management of technical vulnerabilities | D80: ISO/IEC 27002:2022 | E80: 67 | F80: 5000 | G80: 25000 | H80: 50000 | I80: 10000 | J80: 0.06 | K80: 0.065 | L80: 0.065 | N80: =A80*((SUM(F80:I80))+(J80*1950*80)) | O80: =A80*J80 | P80: =A80*K80 | Q80: =A80*L80 | R80: =1-P80 | S80: =1-Q80
C81: 8.9 Configuration management | D81: ISO/IEC 27002:2022 | E81: 68 | H81: 10000 | I81: 1000 | J81: 0.02 | K81: 0.01 | L81: 0.01 | N81: =A81*((SUM(F81:I81))+(J81*1950*80)) | O81: =A81*J81 | P81: =A81*K81 | Q81: =A81*L81 | R81: =1-P81 | S81: =1-Q81
C82: 8.10 Information deletion | D82: ISO/IEC 27002:2022 | E82: 69 | H82: 10000 | I82: 1000 | J82: 0.02 | K82: 0.01 | L82: 0.01 | N82: =A82*((SUM(F82:I82))+(J82*1950*80)) | O82: =A82*J82 | P82: =A82*K82 | Q82: =A82*L82 | R82: =1-P82 | S82: =1-Q82
C83: 8.11 Data masking | D83: ISO/IEC 27002:2022 | E83: 70 | H83: 10000 | I83: 1000 | J83: 0.02 | K83: 0.01 | L83: 0.01 | N83: =A83*((SUM(F83:I83))+(J83*1950*80)) | O83: =A83*J83 | P83: =A83*K83 | Q83: =A83*L83 | R83: =1-P83 | S83: =1-Q83
C84: 8.12 Data leakage prevention | D84: ISO/IEC 27002:2022 | E84: 71 | H84: 10000 | I84: 1000 | J84: 0.02 | K84: 0.01 | L84: 0.01 | N84: =A84*((SUM(F84:I84))+(J84*1950*80)) | O84: =A84*J84 | P84: =A84*K84 | Q84: =A84*L84 | R84: =1-P84 | S84: =1-Q84
C85: 8.13 Information backup | D85: ISO/IEC 27002:2022 | E85: 72 | F85: 50000 | G85: 10000 | H85: 50000 | I85: 10000 | J85: 0.06 | K85: 0.065 | L85: 0.06 | N85: =A85*((SUM(F85:I85))+(J85*1950*80)) | O85: =A85*J85 | P85: =A85*K85 | Q85: =A85*L85 | R85: =1-P85 | S85: =1-Q85
C86: 8.14 Redundancy of information processing facilities | D86: ISO/IEC 27002:2022 | E86: 73 | H86: 20000 | I86: 50000 | J86: 0.02 | K86: 0.065 | L86: 0.065 | N86: =A86*((SUM(F86:I86))+(J86*1950*80)) | O86: =A86*J86 | P86: =A86*K86 | Q86: =A86*L86 | R86: =1-P86 | S86: =1-Q86
C87: 8.15 Logging | D87: ISO/IEC 27002:2022 | E87: 74 | F87: 10000 | G87: 5000 | H87: 50000 | I87: 10000 | J87: 0.01 | K87: 0.06 | L87: 0.06 | N87: =A87*((SUM(F87:I87))+(J87*1950*80)) | O87: =A87*J87 | P87: =A87*K87 | Q87: =A87*L87 | R87: =1-P87 | S87: =1-Q87
C88: 8.16 Monitoring activities | D88: ISO/IEC 27002:2022 | E88: 75 | H88: 10000 | I88: 1000 | J88: 0.02 | K88: 0.01 | L88: 0.01 | N88: =A88*((SUM(F88:I88))+(J88*1950*80)) | O88: =A88*J88 | P88: =A88*K88 | Q88: =A88*L88 | R88: =1-P88 | S88: =1-Q88
C89: 8.17 Clock synchronization | D89: ISO/IEC 27002:2022 | E89: 76 | H89: 10000 | I89: 1000 | J89: 0.02 | K89: 0.01 | L89: 0.01 | N89: =A89*((SUM(F89:I89))+(J89*1950*80)) | O89: =A89*J89 | P89: =A89*K89 | Q89: =A89*L89 | R89: =1-P89 | S89: =1-Q89
C90: 8.18 Use of privileged utility programs | D90: ISO/IEC 27002:2022 | E90: 77 | G90: 5000 | H90: 5000 | I90: 100 | J90: 0.01 | K90: 0.01 | L90: 0.01 | N90: =A90*((SUM(F90:I90))+(J90*1950*80)) | O90: =A90*J90 | P90: =A90*K90 | Q90: =A90*L90 | R90: =1-P90 | S90: =1-Q90
C91: 8.19 Installation of software on operational systems | D91: ISO/IEC 27002:2022 | E91: 78 | F91: 10000 | G91: 5000 | I91: 500 | J91: 0.02 | K91: 0.06 | L91: 0.06 | N91: =A91*((SUM(F91:I91))+(J91*1950*80)) | O91: =A91*J91 | P91: =A91*K91 | Q91: =A91*L91 | R91: =1-P91 | S91: =1-Q91
C92: 8.20 Networks security | D92: ISO/IEC 27002:2022 | E92: 79 | F92: 5000 | G92: 25000 | H92: 50000 | I92: 10000 | J92: 0.06 | K92: 0.02 | L92: 0.02 | N92: =A92*((SUM(F92:I92))+(J92*1950*80)) | O92: =A92*J92 | P92: =A92*K92 | Q92: =A92*L92 | R92: =1-P92 | S92: =1-Q92
C93: 8.21 Security of network services | D93: ISO/IEC 27002:2022 | E93: 80 | F93: 5000 | G93: 25000 | H93: 50000 | I93: 10000 | J93: 0.06 | K93: 0.02 | L93: 0.02 | N93: =A93*((SUM(F93:I93))+(J93*1950*80)) | O93: =A93*J93 | P93: =A93*K93 | Q93: =A93*L93 | R93: =1-P93 | S93: =1-Q93
C94: 8.22 Segregation of networks | D94: ISO/IEC 27002:2022 | E94: 81 | F94: 5000 | G94: 25000 | H94: 50000 | I94: 10000 | J94: 0.06 | K94: 0.02 | L94: 0.02 | N94: =A94*((SUM(F94:I94))+(J94*1950*80)) | O94: =A94*J94 | P94: =A94*K94 | Q94: =A94*L94 | R94: =1-P94 | S94: =1-Q94
C95: 8.23 Web filtering | D95: ISO/IEC 27002:2022 | E95: 82 | H95: 10000 | I95: 1000 | J95: 0.02 | K95: 0.01 | L95: 0.01 | N95: =A95*((SUM(F95:I95))+(J95*1950*80)) | O95: =A95*J95 | P95: =A95*K95 | Q95: =A95*L95 | R95: =1-P95 | S95: =1-Q95
C96: 8.24 Use of cryptography | D96: ISO/IEC 27002:2022 | E96: 83 | G96: 5000 | H96: 5000 | I96: 100 | J96: 0.01 | K96: 0.01 | L96: 0.01 | N96: =A96*((SUM(F96:I96))+(J96*1950*80)) | O96: =A96*J96 | P96: =A96*K96 | Q96: =A96*L96 | R96: =1-P96 | S96: =1-Q96
C97: 8.25 Secure development life cycle | D97: ISO/IEC 27002:2022 | E97: 84 | H97: 20000 | I97: 1000 | J97: 0.02 | K97: 0.01 | L97: 0.01 | N97: =A97*((SUM(F97:I97))+(J97*1950*80)) | O97: =A97*J97 | P97: =A97*K97 | Q97: =A97*L97 | R97: =1-P97 | S97: =1-Q97
C98: 8.26 Application security requirements | D98: ISO/IEC 27002:2022 | E98: 85 | H98: 20000 | I98: 1000 | J98: 0.02 | K98: 0.02 | L98: 0.02 | N98: =A98*((SUM(F98:I98))+(J98*1950*80)) | O98: =A98*J98 | P98: =A98*K98 | Q98: =A98*L98 | R98: =1-P98 | S98: =1-Q98
C99: 8.27 Secure system architecture and engineering principles | D99: ISO/IEC 27002:2022 | E99: 86 | H99: 20000 | I99: 1000 | J99: 0.02 | K99: 0.01 | L99: 0.01 | N99: =A99*((SUM(F99:I99))+(J99*1950*80)) | O99: =A99*J99 | P99: =A99*K99 | Q99: =A99*L99 | R99: =1-P99 | S99: =1-Q99
C100: 8.28 Secure coding | D100: ISO/IEC 27002:2022 | E100: 87 | H100: 10000 | I100: 1000 | J100: 0.02 | K100: 0.01 | L100: 0.01 | N100: =A100*((SUM(F100:I100))+(J100*1950*80)) | O100: =A100*J100 | P100: =A100*K100 | Q100: =A100*L100 | R100: =1-P100 | S100: =1-Q100
...

Sheet S4
A1: Risk scenario number 4 / Scénario de risque 4
A2: Scenario number / Numéro : | B2: 4
A3: Scenario name / Nom du scénario :
A4: Date of creation / Date de création du scénario :
A6: Probability that the threat will be present = Probabilité de réalisation : Pb(A)
A7: Probability of exploitation = Probabilité d’exploitation: Pb(ψ,A)
A8: Estimated expected damages = Dommage estimé: δe(ψ,A)
A9: Maximal damages = Dommage maximal: δm(ψ,A) | C9: =IF(AND(ISNUMBER(B8),ISNUMBER(B9),B9<B8),"δm should be ≥ δe / δm devrait être ≥ δe","")
A10: Level of organizational resilience = Niveau de résilience: θ(ψ,A) | C10: =IF(AND(B10<>"",OR(NOT(ISNUMBER(B10)),B10<=0,B10>1)),"θ must be in (0, 1] / θ doit être dans ]0, 1]","")
A11: Organizational criticality (expected utility) = Criticité organisationnelle (utilité espérée) : μ(E)
A14: 3. Renseigner les scénarios de risque (feuilles S1 à S10)
A15: 3. Populate the risk scenarios (Sheets S1 to S10)
A16: Values 0-1; θ > 0 and ≤ 1; δm ≥ δe. Horizon: 12 months. Each value: rationale, evidence (E-number), confidence — Analytical estimate — validation required.
A17: Valeurs 0-1; θ > 0 et ≤ 1; δm ≥ δe. Horizon : 12 mois. Chaque valeur : justification, preuve (n° E), confiance — Estimation analytique — validation requise.

Sheet M4
A1: Other / autre | C1: Proposed risk mitigation measure / mesure de mitigation des risques proposés | D1: Source | F1: Immobilisations | G1: Logiciels | H1: Mise en œuvre | I1: Exploitation | J1: ÉTC | K1: Réduc impacts | L1: Réduction Pb | N1: Coût | O1: ETC | P1: Impact | Q1: Pb | R1: 1 − impact | S1: 1 − Pb
N2: =A2*((SUM(F2:I2))+(J2*1950*80)) | O2: =A2*J2 | P2: =A2*K2 | Q2: =A2*L2 | R2: =1-P2 | S2: =1-Q2
N3: =A3*((SUM(F3:I3))+(J3*1950*80)) | O3: =A3*J3 | P3: =A3*K3 | Q3: =A3*L3 | R3: =1-P3 | S3: =1-Q3
N4: =A4*((SUM(F4:I4))+(J4*1950*80)) | O4: =A4*J4 | P4: =A4*K4 | Q4: =A4*L4 | R4: =1-P4 | S4: =1-Q4
N5: =A5*((SUM(F5:I5))+(J5*1950*80)) | O5: =A5*J5 | P5: =A5*K5 | Q5: =A5*L5 | R5: =1-P5 | S5: =1-Q5
N6: =A6*((SUM(F6:I6))+(J6*1950*80)) | O6: =A6*J6 | P6: =A6*K6 | Q6: =A6*L6 | R6: =1-P6 | S6: =1-Q6
N7: =SUM(N2:N6) | O7: =SUM(O2:O6) | P7: =1-PRODUCT(R2:R6) | Q7: =1-PRODUCT(S2:S6)
A8: Include | C8: Control / Contrôle | D8: Source | F8: Immobilisations | G8: Logiciels | H8: Mise en œuvre | I8: Exploitation | J8: ÉTC | K8: Réduc impacts | L8: Réduction Pb | N8: Coût | O8: ETC | P8: Impact | Q8: Pb | R8: 1 − impact | S8: 1 − Pb
A9: Inclure | C9: ISO/IEC 27002:2022 — information security controls (93) / mesures de sécurité de l'information | F9: CAPEX | G9: Software | H9: Implementation | I9: Exploitation | J9: FTE | K9: Reduce impacts | L9: Reduce Pb | N9: Cost | O9: FTE | P9: Impact | Q9: Pb
C10: 5 Organizational controls / Mesures organisationnelles
C11: 5.1 Policies for information security | D11: ISO/IEC 27002:2022 | E11: 1 | H11: 25000 | I11: 3000 | J11: 0.01 | K11: 0.06 | L11: 0.06 | N11: =A11*((SUM(F11:I11))+(J11*1950*80)) | O11: =A11*J11 | P11: =A11*K11 | Q11: =A11*L11 | R11: =1-P11 | S11: =1-Q11
C12: 5.2 Information security roles and responsibilities | D12: ISO/IEC 27002:2022 | E12: 2 | H12: 5000 | I12: 500 | J12: 0.01 | K12: 0.01 | L12: 0.01 | N12: =A12*((SUM(F12:I12))+(J12*1950*80)) | O12: =A12*J12 | P12: =A12*K12 | Q12: =A12*L12 | R12: =1-P12 | S12: =1-Q12
C13: 5.3 Segregation of duties | D13: ISO/IEC 27002:2022 | E13: 3 | H13: 5000 | I13: 500 | J13: 0.01 | K13: 0.01 | L13: 0.01 | N13: =A13*((SUM(F13:I13))+(J13*1950*80)) | O13: =A13*J13 | P13: =A13*K13 | Q13: =A13*L13 | R13: =1-P13 | S13: =1-Q13 | U13: 4. Définir les mesures de mitigation (feuilles M1 à M10)
C14: 5.4 Management responsibilities | D14: ISO/IEC 27002:2022 | E14: 4 | H14: 5000 | I14: 500 | J14: 0.01 | K14: 0.01 | L14: 0.01 | N14: =A14*((SUM(F14:I14))+(J14*1950*80)) | O14: =A14*J14 | P14: =A14*K14 | Q14: =A14*L14 | R14: =1-P14 | S14: =1-Q14 | U14: dans la colonne A Inclure Mesure
C15: 5.5 Contact with authorities | D15: ISO/IEC 27002:2022 | E15: 5 | H15: 5000 | J15: =1/50 | K15: 0.01 | L15: 0.01 | N15: =A15*((SUM(F15:I15))+(J15*1950*80)) | O15: =A15*J15 | P15: =A15*K15 | Q15: =A15*L15 | R15: =1-P15 | S15: =1-Q15 | U15: 0 ou vide = non sélectionné
C16: 5.6 Contact with special interest groups | D16: ISO/IEC 27002:2022 | E16: 6 | H16: 5000 | J16: =3/50 | K16: 0.01 | L16: 0.01 | N16: =A16*((SUM(F16:I16))+(J16*1950*80)) | O16: =A16*J16 | P16: =A16*K16 | Q16: =A16*L16 | R16: =1-P16 | S16: =1-Q16 | U16: 6. Define the risk mitigation measures (Sheets M1 to M10)
C17: 5.7 Threat intelligence | D17: ISO/IEC 27002:2022 | E17: 7 | H17: 10000 | I17: 1000 | J17: 0.02 | K17: 0.01 | L17: 0.01 | N17: =A17*((SUM(F17:I17))+(J17*1950*80)) | O17: =A17*J17 | P17: =A17*K17 | Q17: =A17*L17 | R17: =1-P17 | S17: =1-Q17
C18: 5.8 Information security in project management | D18: ISO/IEC 27002:2022 | E18: 8 | H18: 5000 | J18: 0.06 | K18: 0.06 | L18: 0.06 | N18: =A18*((SUM(F18:I18))+(J18*1950*80)) | O18: =A18*J18 | P18: =A18*K18 | Q18: =A18*L18 | R18: =1-P18 | S18: =1-Q18 | U18: 4. Define the risk mitigation measures (Sheets M1 to M10)
C19: 5.9 Inventory of information and other associated assets | D19: ISO/IEC 27002:2022 | E19: 9 | G19: 10000 | H19: 50000 | I19: 100 | J19: 0.04 | K19: 0.06 | L19: 0.06 | N19: =A19*((SUM(F19:I19))+(J19*1950*80)) | O19: =A19*J19 | P19: =A19*K19 | Q19: =A19*L19 | R19: =1-P19 | S19: =1-Q19 | U19: indicate the selected mitigation measures or controls in Column A
C20: 5.10 Acceptable use of information and other associated assets | D20: ISO/IEC 27002:2022 | E20: 10 | H20: 10000 | I20: 100 | J20: 0.02 | K20: 0.03 | L20: 0.03 | N20: =A20*((SUM(F20:I20))+(J20*1950*80)) | O20: =A20*J20 | P20: =A20*K20 | Q20: =A20*L20 | R20: =1-P20 | S20: =1-Q20 | U20: 0 or empty = not selected
C21: 5.11 Return of assets | D21: ISO/IEC 27002:2022 | E21: 11 | H21: 20000 | I21: 100 | J21: 0.02 | K21: 0.01 | L21: 0.01 | N21: =A21*((SUM(F21:I21))+(J21*1950*80)) | O21: =A21*J21 | P21: =A21*K21 | Q21: =A21*L21 | R21: =1-P21 | S21: =1-Q21 | U21: Combination rule / Règle de combinaison :
C22: 5.12 Classification of information | D22: ISO/IEC 27002:2022 | E22: 12 | G22: 5000 | H22: 50000 | I22: 100 | J22: 0.02 | K22: 0.06 | L22: 0.06 | N22: =A22*((SUM(F22:I22))+(J22*1950*80)) | O22: =A22*J22 | P22: =A22*K22 | Q22: =A22*L22 | R22: =1-P22 | S22: =1-Q22 | U22: Selected coefficients combine per column (K impact, L probability) with the product rule:
C23: 5.13 Labelling of information | D23: ISO/IEC 27002:2022 | E23: 13 | H23: 10000 | I23: 50 | J23: 0.02 | K23: 0.01 | L23: 0.01 | N23: =A23*((SUM(F23:I23))+(J23*1950*80)) | O23: =A23*J23 | P23: =A23*K23 | Q23: =A23*L23 | R23: =1-P23 | S23: =1-Q23 | U23: package reduction = 1 − ∏(1 − rᵢ). Each rᵢ must be 0-1, so the package can never exceed 1;
C24: 5.14 Information transfer | D24: ISO/IEC 27002:2022 | E24: 14 | H24: 20000 | I24: 1000 | J24: 0.02 | K24: 0.02 | L24: 0.02 | N24: =A24*((SUM(F24:I24))+(J24*1950*80)) | O24: =A24*J24 | P24: =A24*K24 | Q24: =A24*L24 | R24: =1-P24 | S24: =1-Q24 | U24: the 'Other' rows count as additional factors. A warning appears under the TOTAL row if a coefficient is outside 0-1.
C25: 5.15 Access control | D25: ISO/IEC 27002:2022 | E25: 15 | G25: 5000 | H25: 5000 | I25: 100 | J25: 0.02 | K25: 0.06 | L25: 0.06 | N25: =A25*((SUM(F25:I25))+(J25*1950*80)) | O25: =A25*J25 | P25: =A25*K25 | Q25: =A25*L25 | R25: =1-P25 | S25: =1-Q25 | U25: Prefer a few well-justified controls, or enter ONE package-level
C26: 5.16 Identity management | D26: ISO/IEC 27002:2022 | E26: 16 | G26: 5000 | H26: 5000 | I26: 100 | J26: 0.01 | K26: 0.01 | L26: 0.01 | N26: =A26*((SUM(F26:I26))+(J26*1950*80)) | O26: =A26*J26 | P26: =A26*K26 | Q26: =A26*L26 | R26: =1-P26 | S26: =1-Q26 | U26: estimate (cost, impact and Pb reduction) in an 'Other' row, with its rationale.
C27: 5.17 Authentication information | D27: ISO/IEC 27002:2022 | E27: 17 | G27: 5000 | H27: 5000 | I27: 100 | J27: 0.01 | K27: 0.01 | L27: 0.01 | N27: =A27*((SUM(F27:I27))+(J27*1950*80)) | O27: =A27*J27 | P27: =A27*K27 | Q27: =A27*L27 | R27: =1-P27 | S27: =1-Q27 | U27: Les coefficients retenus se combinent par colonne selon la règle du produit :
C28: 5.18 Access rights | D28: ISO/IEC 27002:2022 | E28: 18 | G28: 5000 | H28: 5000 | I28: 100 | J28: 0.01 | K28: 0.01 | L28: 0.01 | N28: =A28*((SUM(F28:I28))+(J28*1950*80)) | O28: =A28*J28 | P28: =A28*K28 | Q28: =A28*L28 | R28: =1-P28 | S28: =1-Q28 | U28: réduction du bouquet = 1 − ∏(1 − rᵢ); chaque rᵢ entre 0 et 1, donc jamais plus de 1;
C29: 5.19 Information security in supplier relationships | D29: ISO/IEC 27002:2022 | E29: 19 | H29: 20000 | I29: 1000 | J29: 0.02 | K29: 0.06 | L29: 0.06 | N29: =A29*((SUM(F29:I29))+(J29*1950*80)) | O29: =A29*J29 | P29: =A29*K29 | Q29: =A29*L29 | R29: =1-P29 | S29: =1-Q29 | U29: les lignes « Other / autre » comptent comme facteurs. Privilégier peu de mesures bien justifiées,
C30: 5.20 Addressing information security within supplier agreements | D30: ISO/IEC 27002:2022 | E30: 20 | H30: 20000 | I30: 1000 | J30: 0.02 | K30: 0.06 | L30: 0.06 | N30: =A30*((SUM(F30:I30))+(J30*1950*80)) | O30: =A30*J30 | P30: =A30*K30 | Q30: =A30*L30 | R30: =1-P30 | S30: =1-Q30 | U30: ou saisir une estimation globale du bouquet dans une ligne « Other / autre ».
C31: 5.21 Managing information security in the ICT supply chain | D31: ISO/IEC 27002:2022 | E31: 21 | H31: 20000 | I31: 1000 | J31: 0.02 | K31: 0.01 | L31: 0.01 | N31: =A31*((SUM(F31:I31))+(J31*1950*80)) | O31: =A31*J31 | P31: =A31*K31 | Q31: =A31*L31 | R31: =1-P31 | S31: =1-Q31 | U31: dépasse 1. Privilégier peu de mesures bien justifiées, ou saisir une
C32: 5.22 Monitoring, review and change management of supplier services | D32: ISO/IEC 27002:2022 | E32: 22 | H32: 20000 | I32: 1000 | J32: 0.02 | K32: 0.06 | L32: 0.06 | N32: =A32*((SUM(F32:I32))+(J32*1950*80)) | O32: =A32*J32 | P32: =A32*K32 | Q32: =A32*L32 | R32: =1-P32 | S32: =1-Q32 | U32: estimation globale du bouquet dans une ligne « Other / autre ».
C33: 5.23 Information security for use of cloud services | D33: ISO/IEC 27002:2022 | E33: 23 | H33: 10000 | I33: 1000 | J33: 0.02 | K33: 0.01 | L33: 0.01 | N33: =A33*((SUM(F33:I33))+(J33*1950*80)) | O33: =A33*J33 | P33: =A33*K33 | Q33: =A33*L33 | R33: =1-P33 | S33: =1-Q33
C34: 5.24 Information security incident management planning and preparation | D34: ISO/IEC 27002:2022 | E34: 24 | H34: 10000 | I34: 1000 | J34: 0.02 | K34: 0.01 | L34: 0.01 | N34: =A34*((SUM(F34:I34))+(J34*1950*80)) | O34: =A34*J34 | P34: =A34*K34 | Q34: =A34*L34 | R34: =1-P34 | S34: =1-Q34 | U34: Catalogues: ISO/IEC 27002:2022 (93), NIST CSF 2.0 (106), CIS Controls v8.1 (18).
C35: 5.25 Assessment and decision on information security events | D35: ISO/IEC 27002:2022 | E35: 25 | H35: 10000 | I35: 1000 | J35: 0.02 | K35: 0.01 | L35: 0.01 | N35: =A35*((SUM(F35:I35))+(J35*1950*80)) | O35: =A35*J35 | P35: =A35*K35 | Q35: =A35*L35 | R35: =1-P35 | S35: =1-Q35 | U35: Default costs and coefficients are generic placeholders: recalibrate them.
C36: 5.26 Response to information security incidents | D36: ISO/IEC 27002:2022 | E36: 26 | H36: 10000 | I36: 1000 | J36: 0.02 | K36: 0.06 | L36: 0.06 | N36: =A36*((SUM(F36:I36))+(J36*1950*80)) | O36: =A36*J36 | P36: =A36*K36 | Q36: =A36*L36 | R36: =1-P36 | S36: =1-Q36 | U36: Coûts et coefficients par défaut génériques : à recalibrer.
C37: 5.27 Learning from information security incidents | D37: ISO/IEC 27002:2022 | E37: 27 | H37: 10000 | I37: 1000 | J37: 0.02 | K37: 0.01 | L37: 0.01 | N37: =A37*((SUM(F37:I37))+(J37*1950*80)) | O37: =A37*J37 | P37: =A37*K37 | Q37: =A37*L37 | R37: =1-P37 | S37: =1-Q37
C38: 5.28 Collection of evidence | D38: ISO/IEC 27002:2022 | E38: 28 | H38: 10000 | I38: 10000 | J38: 0.02 | K38: 0.01 | L38: 0.01 | N38: =A38*((SUM(F38:I38))+(J38*1950*80)) | O38: =A38*J38 | P38: =A38*K38 | Q38: =A38*L38 | R38: =1-P38 | S38: =1-Q38
C39: 5.29 Information security during disruption | D39: ISO/IEC 27002:2022 | E39: 29 | H39: 20000 | I39: 1000 | J39: 0.02 | K39: 0.01 | L39: 0.01 | N39: =A39*((SUM(F39:I39))+(J39*1950*80)) | O39: =A39*J39 | P39: =A39*K39 | Q39: =A39*L39 | R39: =1-P39 | S39: =1-Q39
C40: 5.30 ICT readiness for business continuity | D40: ISO/IEC 27002:2022 | E40: 30 | H40: 10000 | I40: 1000 | J40: 0.02 | K40: 0.01 | L40: 0.01 | N40: =A40*((SUM(F40:I40))+(J40*1950*80)) | O40: =A40*J40 | P40: =A40*K40 | Q40: =A40*L40 | R40: =1-P40 | S40: =1-Q40
C41: 5.31 Legal, statutory, regulatory and contractual requirements | D41: ISO/IEC 27002:2022 | E41: 31 | H41: 10000 | I41: 1000 | J41: 0.02 | K41: 0.01 | L41: 0.01 | N41: =A41*((SUM(F41:I41))+(J41*1950*80)) | O41: =A41*J41 | P41: =A41*K41 | Q41: =A41*L41 | R41: =1-P41 | S41: =1-Q41
C42: 5.32 Intellectual property rights | D42: ISO/IEC 27002:2022 | E42: 32 | H42: 10000 | I42: 1000 | J42: 0.02 | K42: 0.01 | L42: 0.01 | N42: =A42*((SUM(F42:I42))+(J42*1950*80)) | O42: =A42*J42 | P42: =A42*K42 | Q42: =A42*L42 | R42: =1-P42 | S42: =1-Q42
C43: 5.33 Protection of records | D43: ISO/IEC 27002:2022 | E43: 33 | H43: 10000 | I43: 1000 | J43: 0.02 | K43: 0.01 | L43: 0.01 | N43: =A43*((SUM(F43:I43))+(J43*1950*80)) | O43: =A43*J43 | P43: =A43*K43 | Q43: =A43*L43 | R43: =1-P43 | S43: =1-Q43
C44: 5.34 Privacy and protection of PII | D44: ISO/IEC 27002:2022 | E44: 34 | H44: 10000 | I44: 1000 | J44: 0.02 | K44: 0.01 | L44: 0.01 | N44: =A44*((SUM(F44:I44))+(J44*1950*80)) | O44: =A44*J44 | P44: =A44*K44 | Q44: =A44*L44 | R44: =1-P44 | S44: =1-Q44
C45: 5.35 Independent review of information security | D45: ISO/IEC 27002:2022 | E45: 35 | H45: 10000 | I45: 10000 | J45: 0.02 | K45: 0.01 | L45: 0.01 | N45: =A45*((SUM(F45:I45))+(J45*1950*80)) | O45: =A45*J45 | P45: =A45*K45 | Q45: =A45*L45 | R45: =1-P45 | S45: =1-Q45
C46: 5.36 Compliance with policies, rules and standards for information security | D46: ISO/IEC 27002:2022 | E46: 36 | H46: 10000 | I46: 10000 | J46: 0.02 | K46: 0.01 | L46: 0.01 | N46: =A46*((SUM(F46:I46))+(J46*1950*80)) | O46: =A46*J46 | P46: =A46*K46 | Q46: =A46*L46 | R46: =1-P46 | S46: =1-Q46
C47: 5.37 Documented operating procedures | D47: ISO/IEC 27002:2022 | E47: 37 | H47: 50000 | I47: 100 | J47: 0.01 | K47: 0.06 | L47: 0.06 | N47: =A47*((SUM(F47:I47))+(J47*1950*80)) | O47: =A47*J47 | P47: =A47*K47 | Q47: =A47*L47 | R47: =1-P47 | S47: =1-Q47
C48: 6 People controls / Mesures liées aux personnes
C49: 6.1 Screening | D49: ISO/IEC 27002:2022 | E49: 38 | H49: 5000 | I49: 500 | J49: 0.01 | K49: 0.01 | L49: 0.01 | N49: =A49*((SUM(F49:I49))+(J49*1950*80)) | O49: =A49*J49 | P49: =A49*K49 | Q49: =A49*L49 | R49: =1-P49 | S49: =1-Q49
C50: 6.2 Terms and conditions of employment | D50: ISO/IEC 27002:2022 | E50: 39 | H50: 5000 | J50: 0.01 | K50: 0.01 | L50: 0.01 | N50: =A50*((SUM(F50:I50))+(J50*1950*80)) | O50: =A50*J50 | P50: =A50*K50 | Q50: =A50*L50 | R50: =1-P50 | S50: =1-Q50
C51: 6.3 Information security awareness, education and training | D51: ISO/IEC 27002:2022 | E51: 40 | H51: 30000 | I51: 500 | J51: 0.01 | K51: 0.06 | L51: 0.06 | N51: =A51*((SUM(F51:I51))+(J51*1950*80)) | O51: =A51*J51 | P51: =A51*K51 | Q51: =A51*L51 | R51: =1-P51 | S51: =1-Q51
C52: 6.4 Disciplinary process | D52: ISO/IEC 27002:2022 | E52: 41 | H52: 10000 | I52: 500 | J52: 0.01 | K52: 0.01 | L52: 0.01 | N52: =A52*((SUM(F52:I52))+(J52*1950*80)) | O52: =A52*J52 | P52: =A52*K52 | Q52: =A52*L52 | R52: =1-P52 | S52: =1-Q52
C53: 6.5 Responsibilities after termination or change of employment | D53: ISO/IEC 27002:2022 | E53: 42 | H53: 5000 | I53: 500 | J53: 0.01 | K53: 0.05 | L53: 0.02 | N53: =A53*((SUM(F53:I53))+(J53*1950*80)) | O53: =A53*J53 | P53: =A53*K53 | Q53: =A53*L53 | R53: =1-P53 | S53: =1-Q53
C54: 6.6 Confidentiality or non-disclosure agreements | D54: ISO/IEC 27002:2022 | E54: 43 | H54: 20000 | I54: 1000 | J54: 0.02 | K54: 0.02 | L54: 0.02 | N54: =A54*((SUM(F54:I54))+(J54*1950*80)) | O54: =A54*J54 | P54: =A54*K54 | Q54: =A54*L54 | R54: =1-P54 | S54: =1-Q54
C55: 6.7 Remote working | D55: ISO/IEC 27002:2022 | E55: 44 | H55: 5000 | I55: 2000 | J55: 0.05 | K55: 0.01 | L55: 0.01 | N55: =A55*((SUM(F55:I55))+(J55*1950*80)) | O55: =A55*J55 | P55: =A55*K55 | Q55: =A55*L55 | R55: =1-P55 | S55: =1-Q55
C56: 6.8 Information security event reporting | D56: ISO/IEC 27002:2022 | E56: 45 | H56: 10000 | I56: 1000 | J56: 0.02 | K56: 0.01 | L56: 0.01 | N56: =A56*((SUM(F56:I56))+(J56*1950*80)) | O56: =A56*J56 | P56: =A56*K56 | Q56: =A56*L56 | R56: =1-P56 | S56: =1-Q56
C57: 7 Physical controls / Mesures physiques
C58: 7.1 Physical security perimeters | D58: ISO/IEC 27002:2022 | E58: 46 | F58: 10000 | G58: 50000 | H58: 10000 | I58: 500 | J58: 0.02 | K58: 0.06 | L58: 0.06 | N58: =A58*((SUM(F58:I58))+(J58*1950*80)) | O58: =A58*J58 | P58: =A58*K58 | Q58: =A58*L58 | R58: =1-P58 | S58: =1-Q58
C59: 7.2 Physical entry | D59: ISO/IEC 27002:2022 | E59: 47 | F59: 10000 | G59: 50000 | H59: 10000 | I59: 500 | J59: 0.02 | K59: 0.06 | L59: 0.06 | N59: =A59*((SUM(F59:I59))+(J59*1950*80)) | O59: =A59*J59 | P59: =A59*K59 | Q59: =A59*L59 | R59: =1-P59 | S59: =1-Q59
C60: 7.3 Securing offices, rooms and facilities | D60: ISO/IEC 27002:2022 | E60: 48 | F60: 10000 | G60: 50000 | H60: 10000 | I60: 500 | J60: 0.02 | K60: 0.01 | L60: 0.01 | N60: =A60*((SUM(F60:I60))+(J60*1950*80)) | O60: =A60*J60 | P60: =A60*K60 | Q60: =A60*L60 | R60: =1-P60 | S60: =1-Q60
C61: 7.4 Physical security monitoring | D61: ISO/IEC 27002:2022 | E61: 49 | H61: 10000 | I61: 1000 | J61: 0.02 | K61: 0.01 | L61: 0.01 | N61: =A61*((SUM(F61:I61))+(J61*1950*80)) | O61: =A61*J61 | P61: =A61*K61 | Q61: =A61*L61 | R61: =1-P61 | S61: =1-Q61
C62: 7.5 Protecting against physical and environmental threats | D62: ISO/IEC 27002:2022 | E62: 50 | F62: 10000 | G62: 50000 | H62: 10000 | I62: 100 | J62: 0.02 | K62: 0.06 | L62: 0.06 | N62: =A62*((SUM(F62:I62))+(J62*1950*80)) | O62: =A62*J62 | P62: =A62*K62 | Q62: =A62*L62 | R62: =1-P62 | S62: =1-Q62
C63: 7.6 Working in secure areas | D63: ISO/IEC 27002:2022 | E63: 51 | F63: 10000 | G63: 50000 | H63: 10000 | I63: 100 | J63: 0.02 | K63: 0.01 | L63: 0.01 | N63: =A63*((SUM(F63:I63))+(J63*1950*80)) | O63: =A63*J63 | P63: =A63*K63 | Q63: =A63*L63 | R63: =1-P63 | S63: =1-Q63
C64: 7.7 Clear desk and clear screen | D64: ISO/IEC 27002:2022 | E64: 52 | H64: 5000 | I64: 100 | J64: 0.01 | K64: 0.01 | L64: 0.01 | N64: =A64*((SUM(F64:I64))+(J64*1950*80)) | O64: =A64*J64 | P64: =A64*K64 | Q64: =A64*L64 | R64: =1-P64 | S64: =1-Q64
C65: 7.8 Equipment siting and protection | D65: ISO/IEC 27002:2022 | E65: 53 | F65: 10000 | H65: 10000 | I65: 500 | J65: 0.02 | K65: 0.06 | L65: 0.06 | N65: =A65*((SUM(F65:I65))+(J65*1950*80)) | O65: =A65*J65 | P65: =A65*K65 | Q65: =A65*L65 | R65: =1-P65 | S65: =1-Q65
C66: 7.9 Security of assets off-premises | D66: ISO/IEC 27002:2022 | E66: 54 | G66: 50000 | H66: 10000 | I66: 100 | J66: 0.01 | K66: 0.01 | L66: 0.01 | N66: =A66*((SUM(F66:I66))+(J66*1950*80)) | O66: =A66*J66 | P66: =A66*K66 | Q66: =A66*L66 | R66: =1-P66 | S66: =1-Q66
C67: 7.10 Storage media | D67: ISO/IEC 27002:2022 | E67: 55 | G67: 5000 | H67: 5000 | I67: 100 | J67: 0.02 | K67: 0.01 | L67: 0.01 | N67: =A67*((SUM(F67:I67))+(J67*1950*80)) | O67: =A67*J67 | P67: =A67*K67 | Q67: =A67*L67 | R67: =1-P67 | S67: =1-Q67
C68: 7.11 Supporting utilities | D68: ISO/IEC 27002:2022 | E68: 56 | F68: 10000 | G68: 50000 | H68: 10000 | I68: 100 | J68: 0.01 | K68: 0.01 | L68: 0.01 | N68: =A68*((SUM(F68:I68))+(J68*1950*80)) | O68: =A68*J68 | P68: =A68*K68 | Q68: =A68*L68 | R68: =1-P68 | S68: =1-Q68
C69: 7.12 Cabling security | D69: ISO/IEC 27002:2022 | E69: 57 | F69: 10000 | G69: 50000 | H69: 10000 | I69: 100 | J69: 0.01 | K69: 0.01 | L69: 0.01 | N69: =A69*((SUM(F69:I69))+(J69*1950*80)) | O69: =A69*J69 | P69: =A69*K69 | Q69: =A69*L69 | R69: =1-P69 | S69: =1-Q69
C70: 7.13 Equipment maintenance | D70: ISO/IEC 27002:2022 | E70: 58 | F70: 10000 | G70: 50000 | H70: 10000 | I70: 500 | J70: 0.01 | K70: 0.01 | L70: 0.01 | N70: =A70*((SUM(F70:I70))+(J70*1950*80)) | O70: =A70*J70 | P70: =A70*K70 | Q70: =A70*L70 | R70: =1-P70 | S70: =1-Q70
C71: 7.14 Secure disposal or re-use of equipment | D71: ISO/IEC 27002:2022 | E71: 59 | G71: 50000 | H71: 10000 | I71: 100 | J71: 0.01 | K71: 0.01 | L71: 0.01 | N71: =A71*((SUM(F71:I71))+(J71*1950*80)) | O71: =A71*J71 | P71: =A71*K71 | Q71: =A71*L71 | R71: =1-P71 | S71: =1-Q71
C72: 8 Technological controls / Mesures technologiques
C73: 8.1 User end point devices | D73: ISO/IEC 27002:2022 | E73: 60 | H73: 5000 | I73: 500 | J73: 0.01 | K73: 0.01 | L73: 0.01 | N73: =A73*((SUM(F73:I73))+(J73*1950*80)) | O73: =A73*J73 | P73: =A73*K73 | Q73: =A73*L73 | R73: =1-P73 | S73: =1-Q73
C74: 8.2 Privileged access rights | D74: ISO/IEC 27002:2022 | E74: 61 | G74: 5000 | H74: 5000 | I74: 100 | J74: 0.01 | K74: 0.06 | L74: 0.06 | N74: =A74*((SUM(F74:I74))+(J74*1950*80)) | O74: =A74*J74 | P74: =A74*K74 | Q74: =A74*L74 | R74: =1-P74 | S74: =1-Q74
C75: 8.3 Information access restriction | D75: ISO/IEC 27002:2022 | E75: 62 | G75: 5000 | H75: 5000 | I75: 100 | J75: 0.01 | K75: 0.065 | L75: 0.06 | N75: =A75*((SUM(F75:I75))+(J75*1950*80)) | O75: =A75*J75 | P75: =A75*K75 | Q75: =A75*L75 | R75: =1-P75 | S75: =1-Q75
C76: 8.4 Access to source code | D76: ISO/IEC 27002:2022 | E76: 63 | G76: 5000 | H76: 5000 | I76: 100 | J76: 0.01 | K76: 0.01 | L76: 0.01 | N76: =A76*((SUM(F76:I76))+(J76*1950*80)) | O76: =A76*J76 | P76: =A76*K76 | Q76: =A76*L76 | R76: =1-P76 | S76: =1-Q76
C77: 8.5 Secure authentication | D77: ISO/IEC 27002:2022 | E77: 64 | G77: 5000 | H77: 5000 | I77: 100 | J77: 0.01 | K77: 0.01 | L77: 0.01 | N77: =A77*((SUM(F77:I77))+(J77*1950*80)) | O77: =A77*J77 | P77: =A77*K77 | Q77: =A77*L77 | R77: =1-P77 | S77: =1-Q77
C78: 8.6 Capacity management | D78: ISO/IEC 27002:2022 | E78: 65 | H78: 50000 | I78: 100 | J78: 0.01 | K78: 0.01 | L78: 0.01 | N78: =A78*((SUM(F78:I78))+(J78*1950*80)) | O78: =A78*J78 | P78: =A78*K78 | Q78: =A78*L78 | R78: =1-P78 | S78: =1-Q78
C79: 8.7 Protection against malware | D79: ISO/IEC 27002:2022 | E79: 66 | G79: 5000 | H79: 25000 | I79: 200 | J79: 0.06 | K79: 0.08 | L79: 0.08 | N79: =A79*((SUM(F79:I79))+(J79*1950*80)) | O79: =A79*J79 | P79: =A79*K79 | Q79: =A79*L79 | R79: =1-P79 | S79: =1-Q79
C80: 8.8 Management of technical vulnerabilities | D80: ISO/IEC 27002:2022 | E80: 67 | F80: 5000 | G80: 25000 | H80: 50000 | I80: 10000 | J80: 0.06 | K80: 0.065 | L80: 0.065 | N80: =A80*((SUM(F80:I80))+(J80*1950*80)) | O80: =A80*J80 | P80: =A80*K80 | Q80: =A80*L80 | R80: =1-P80 | S80: =1-Q80
C81: 8.9 Configuration management | D81: ISO/IEC 27002:2022 | E81: 68 | H81: 10000 | I81: 1000 | J81: 0.02 | K81: 0.01 | L81: 0.01 | N81: =A81*((SUM(F81:I81))+(J81*1950*80)) | O81: =A81*J81 | P81: =A81*K81 | Q81: =A81*L81 | R81: =1-P81 | S81: =1-Q81
C82: 8.10 Information deletion | D82: ISO/IEC 27002:2022 | E82: 69 | H82: 10000 | I82: 1000 | J82: 0.02 | K82: 0.01 | L82: 0.01 | N82: =A82*((SUM(F82:I82))+(J82*1950*80)) | O82: =A82*J82 | P82: =A82*K82 | Q82: =A82*L82 | R82: =1-P82 | S82: =1-Q82
C83: 8.11 Data masking | D83: ISO/IEC 27002:2022 | E83: 70 | H83: 10000 | I83: 1000 | J83: 0.02 | K83: 0.01 | L83: 0.01 | N83: =A83*((SUM(F83:I83))+(J83*1950*80)) | O83: =A83*J83 | P83: =A83*K83 | Q83: =A83*L83 | R83: =1-P83 | S83: =1-Q83
C84: 8.12 Data leakage prevention | D84: ISO/IEC 27002:2022 | E84: 71 | H84: 10000 | I84: 1000 | J84: 0.02 | K84: 0.01 | L84: 0.01 | N84: =A84*((SUM(F84:I84))+(J84*1950*80)) | O84: =A84*J84 | P84: =A84*K84 | Q84: =A84*L84 | R84: =1-P84 | S84: =1-Q84
C85: 8.13 Information backup | D85: ISO/IEC 27002:2022 | E85: 72 | F85: 50000 | G85: 10000 | H85: 50000 | I85: 10000 | J85: 0.06 | K85: 0.065 | L85: 0.06 | N85: =A85*((SUM(F85:I85))+(J85*1950*80)) | O85: =A85*J85 | P85: =A85*K85 | Q85: =A85*L85 | R85: =1-P85 | S85: =1-Q85
C86: 8.14 Redundancy of information processing facilities | D86: ISO/IEC 27002:2022 | E86: 73 | H86: 20000 | I86: 50000 | J86: 0.02 | K86: 0.065 | L86: 0.065 | N86: =A86*((SUM(F86:I86))+(J86*1950*80)) | O86: =A86*J86 | P86: =A86*K86 | Q86: =A86*L86 | R86: =1-P86 | S86: =1-Q86
C87: 8.15 Logging | D87: ISO/IEC 27002:2022 | E87: 74 | F87: 10000 | G87: 5000 | H87: 50000 | I87: 10000 | J87: 0.01 | K87: 0.06 | L87: 0.06 | N87: =A87*((SUM(F87:I87))+(J87*1950*80)) | O87: =A87*J87 | P87: =A87*K87 | Q87: =A87*L87 | R87: =1-P87 | S87: =1-Q87
C88: 8.16 Monitoring activities | D88: ISO/IEC 27002:2022 | E88: 75 | H88: 10000 | I88: 1000 | J88: 0.02 | K88: 0.01 | L88: 0.01 | N88: =A88*((SUM(F88:I88))+(J88*1950*80)) | O88: =A88*J88 | P88: =A88*K88 | Q88: =A88*L88 | R88: =1-P88 | S88: =1-Q88
C89: 8.17 Clock synchronization | D89: ISO/IEC 27002:2022 | E89: 76 | H89: 10000 | I89: 1000 | J89: 0.02 | K89: 0.01 | L89: 0.01 | N89: =A89*((SUM(F89:I89))+(J89*1950*80)) | O89: =A89*J89 | P89: =A89*K89 | Q89: =A89*L89 | R89: =1-P89 | S89: =1-Q89
C90: 8.18 Use of privileged utility programs | D90: ISO/IEC 27002:2022 | E90: 77 | G90: 5000 | H90: 5000 | I90: 100 | J90: 0.01 | K90: 0.01 | L90: 0.01 | N90: =A90*((SUM(F90:I90))+(J90*1950*80)) | O90: =A90*J90 | P90: =A90*K90 | Q90: =A90*L90 | R90: =1-P90 | S90: =1-Q90
C91: 8.19 Installation of software on operational systems | D91: ISO/IEC 27002:2022 | E91: 78 | F91: 10000 | G91: 5000 | I91: 500 | J91: 0.02 | K91: 0.06 | L91: 0.06 | N91: =A91*((SUM(F91:I91))+(J91*1950*80)) | O91: =A91*J91 | P91: =A91*K91 | Q91: =A91*L91 | R91: =1-P91 | S91: =1-Q91
C92: 8.20 Networks security | D92: ISO/IEC 27002:2022 | E92: 79 | F92: 5000 | G92: 25000 | H92: 50000 | I92: 10000 | J92: 0.06 | K92: 0.02 | L92: 0.02 | N92: =A92*((SUM(F92:I92))+(J92*1950*80)) | O92: =A92*J92 | P92: =A92*K92 | Q92: =A92*L92 | R92: =1-P92 | S92: =1-Q92
C93: 8.21 Security of network services | D93: ISO/IEC 27002:2022 | E93: 80 | F93: 5000 | G93: 25000 | H93: 50000 | I93: 10000 | J93: 0.06 | K93: 0.02 | L93: 0.02 | N93: =A93*((SUM(F93:I93))+(J93*1950*80)) | O93: =A93*J93 | P93: =A93*K93 | Q93: =A93*L93 | R93: =1-P93 | S93: =1-Q93
C94: 8.22 Segregation of networks | D94: ISO/IEC 27002:2022 | E94: 81 | F94: 5000 | G94: 25000 | H94: 50000 | I94: 10000 | J94: 0.06 | K94: 0.02 | L94: 0.02 | N94: =A94*((SUM(F94:I94))+(J94*1950*80)) | O94: =A94*J94 | P94: =A94*K94 | Q94: =A94*L94 | R94: =1-P94 | S94: =1-Q94
C95: 8.23 Web filtering | D95: ISO/IEC 27002:2022 | E95: 82 | H95: 10000 | I95: 1000 | J95: 0.02 | K95: 0.01 | L95: 0.01 | N95: =A95*((SUM(F95:I95))+(J95*1950*80)) | O95: =A95*J95 | P95: =A95*K95 | Q95: =A95*L95 | R95: =1-P95 | S95: =1-Q95
C96: 8.24 Use of cryptography | D96: ISO/IEC 27002:2022 | E96: 83 | G96: 5000 | H96: 5000 | I96: 100 | J96: 0.01 | K96: 0.01 | L96: 0.01 | N96: =A96*((SUM(F96:I96))+(J96*1950*80)) | O96: =A96*J96 | P96: =A96*K96 | Q96: =A96*L96 | R96: =1-P96 | S96: =1-Q96
C97: 8.25 Secure development life cycle | D97: ISO/IEC 27002:2022 | E97: 84 | H97: 20000 | I97: 1000 | J97: 0.02 | K97: 0.01 | L97: 0.01 | N97: =A97*((SUM(F97:I97))+(J97*1950*80)) | O97: =A97*J97 | P97: =A97*K97 | Q97: =A97*L97 | R97: =1-P97 | S97: =1-Q97
C98: 8.26 Application security requirements | D98: ISO/IEC 27002:2022 | E98: 85 | H98: 20000 | I98: 1000 | J98: 0.02 | K98: 0.02 | L98: 0.02 | N98: =A98*((SUM(F98:I98))+(J98*1950*80)) | O98: =A98*J98 | P98: =A98*K98 | Q98: =A98*L98 | R98: =1-P98 | S98: =1-Q98
C99: 8.27 Secure system architecture and engineering principles | D99: ISO/IEC 27002:2022 | E99: 86 | H99: 20000 | I99: 1000 | J99: 0.02 | K99: 0.01 | L99: 0.01 | N99: =A99*((SUM(F99:I99))+(J99*1950*80)) | O99: =A99*J99 | P99: =A99*K99 | Q99: =A99*L99 | R99: =1-P99 | S99: =1-Q99
C100: 8.28 Secure coding | D100: ISO/IEC 27002:2022 | E100: 87 | H100: 10000 | I100: 1000 | J100: 0.02 | K100: 0.01 | L100: 0.01 | N100: =A100*((SUM(F100:I100))+(J100*1950*80)) | O100: =A100*J100 | P100: =A100*K100 | Q100: =A100*L100 | R100: =1-P100 | S100: =1-Q100
...

Sheet S5
A1: Risk scenario number 5 / Scénario de risque 5
A2: Scenario number / Numéro : | B2: 5
A3: Scenario name / Nom du scénario :
A4: Date of creation / Date de création du scénario :
A6: Probability that the threat will be present = Probabilité de réalisation : Pb(A)
A7: Probability of exploitation = Probabilité d’exploitation: Pb(ψ,A)
A8: Estimated expected damages = Dommage estimé: δe(ψ,A)
A9: Maximal damages = Dommage maximal: δm(ψ,A) | C9: =IF(AND(ISNUMBER(B8),ISNUMBER(B9),B9<B8),"δm should be ≥ δe / δm devrait être ≥ δe","")
A10: Level of organizational resilience = Niveau de résilience: θ(ψ,A) | C10: =IF(AND(B10<>"",OR(NOT(ISNUMBER(B10)),B10<=0,B10>1)),"θ must be in (0, 1] / θ doit être dans ]0, 1]","")
A11: Organizational criticality (expected utility) = Criticité organisationnelle (utilité espérée) : μ(E)
A14: 3. Renseigner les scénarios de risque (feuilles S1 à S10)
A15: 3. Populate the risk scenarios (Sheets S1 to S10)
A16: Values 0-1; θ > 0 and ≤ 1; δm ≥ δe. Horizon: 12 months. Each value: rationale, evidence (E-number), confidence — Analytical estimate — validation required.
A17: Valeurs 0-1; θ > 0 et ≤ 1; δm ≥ δe. Horizon : 12 mois. Chaque valeur : justification, preuve (n° E), confiance — Estimation analytique — validation requise.

Sheet M5
A1: Other / autre | C1: Proposed risk mitigation measure / mesure de mitigation des risques proposés | D1: Source | F1: Immobilisations | G1: Logiciels | H1: Mise en œuvre | I1: Exploitation | J1: ÉTC | K1: Réduc impacts | L1: Réduction Pb | N1: Coût | O1: ETC | P1: Impact | Q1: Pb | R1: 1 − impact | S1: 1 − Pb
N2: =A2*((SUM(F2:I2))+(J2*1950*80)) | O2: =A2*J2 | P2: =A2*K2 | Q2: =A2*L2 | R2: =1-P2 | S2: =1-Q2
N3: =A3*((SUM(F3:I3))+(J3*1950*80)) | O3: =A3*J3 | P3: =A3*K3 | Q3: =A3*L3 | R3: =1-P3 | S3: =1-Q3
N4: =A4*((SUM(F4:I4))+(J4*1950*80)) | O4: =A4*J4 | P4: =A4*K4 | Q4: =A4*L4 | R4: =1-P4 | S4: =1-Q4
N5: =A5*((SUM(F5:I5))+(J5*1950*80)) | O5: =A5*J5 | P5: =A5*K5 | Q5: =A5*L5 | R5: =1-P5 | S5: =1-Q5
N6: =A6*((SUM(F6:I6))+(J6*1950*80)) | O6: =A6*J6 | P6: =A6*K6 | Q6: =A6*L6 | R6: =1-P6 | S6: =1-Q6
N7: =SUM(N2:N6) | O7: =SUM(O2:O6) | P7: =1-PRODUCT(R2:R6) | Q7: =1-PRODUCT(S2:S6)
A8: Include | C8: Control / Contrôle | D8: Source | F8: Immobilisations | G8: Logiciels | H8: Mise en œuvre | I8: Exploitation | J8: ÉTC | K8: Réduc impacts | L8: Réduction Pb | N8: Coût | O8: ETC | P8: Impact | Q8: Pb | R8: 1 − impact | S8: 1 − Pb
A9: Inclure | C9: ISO/IEC 27002:2022 — information security controls (93) / mesures de sécurité de l'information | F9: CAPEX | G9: Software | H9: Implementation | I9: Exploitation | J9: FTE | K9: Reduce impacts | L9: Reduce Pb | N9: Cost | O9: FTE | P9: Impact | Q9: Pb
C10: 5 Organizational controls / Mesures organisationnelles
C11: 5.1 Policies for information security | D11: ISO/IEC 27002:2022 | E11: 1 | H11: 25000 | I11: 3000 | J11: 0.01 | K11: 0.06 | L11: 0.06 | N11: =A11*((SUM(F11:I11))+(J11*1950*80)) | O11: =A11*J11 | P11: =A11*K11 | Q11: =A11*L11 | R11: =1-P11 | S11: =1-Q11
C12: 5.2 Information security roles and responsibilities | D12: ISO/IEC 27002:2022 | E12: 2 | H12: 5000 | I12: 500 | J12: 0.01 | K12: 0.01 | L12: 0.01 | N12: =A12*((SUM(F12:I12))+(J12*1950*80)) | O12: =A12*J12 | P12: =A12*K12 | Q12: =A12*L12 | R12: =1-P12 | S12: =1-Q12
C13: 5.3 Segregation of duties | D13: ISO/IEC 27002:2022 | E13: 3 | H13: 5000 | I13: 500 | J13: 0.01 | K13: 0.01 | L13: 0.01 | N13: =A13*((SUM(F13:I13))+(J13*1950*80)) | O13: =A13*J13 | P13: =A13*K13 | Q13: =A13*L13 | R13: =1-P13 | S13: =1-Q13 | U13: 4. Définir les mesures de mitigation (feuilles M1 à M10)
C14: 5.4 Management responsibilities | D14: ISO/IEC 27002:2022 | E14: 4 | H14: 5000 | I14: 500 | J14: 0.01 | K14: 0.01 | L14: 0.01 | N14: =A14*((SUM(F14:I14))+(J14*1950*80)) | O14: =A14*J14 | P14: =A14*K14 | Q14: =A14*L14 | R14: =1-P14 | S14: =1-Q14 | U14: dans la colonne A Inclure Mesure
C15: 5.5 Contact with authorities | D15: ISO/IEC 27002:2022 | E15: 5 | H15: 5000 | J15: =1/50 | K15: 0.01 | L15: 0.01 | N15: =A15*((SUM(F15:I15))+(J15*1950*80)) | O15: =A15*J15 | P15: =A15*K15 | Q15: =A15*L15 | R15: =1-P15 | S15: =1-Q15 | U15: 0 ou vide = non sélectionné
C16: 5.6 Contact with special interest groups | D16: ISO/IEC 27002:2022 | E16: 6 | H16: 5000 | J16: =3/50 | K16: 0.01 | L16: 0.01 | N16: =A16*((SUM(F16:I16))+(J16*1950*80)) | O16: =A16*J16 | P16: =A16*K16 | Q16: =A16*L16 | R16: =1-P16 | S16: =1-Q16 | U16: 6. Define the risk mitigation measures (Sheets M1 to M10)
C17: 5.7 Threat intelligence | D17: ISO/IEC 27002:2022 | E17: 7 | H17: 10000 | I17: 1000 | J17: 0.02 | K17: 0.01 | L17: 0.01 | N17: =A17*((SUM(F17:I17))+(J17*1950*80)) | O17: =A17*J17 | P17: =A17*K17 | Q17: =A17*L17 | R17: =1-P17 | S17: =1-Q17
C18: 5.8 Information security in project management | D18: ISO/IEC 27002:2022 | E18: 8 | H18: 5000 | J18: 0.06 | K18: 0.06 | L18: 0.06 | N18: =A18*((SUM(F18:I18))+(J18*1950*80)) | O18: =A18*J18 | P18: =A18*K18 | Q18: =A18*L18 | R18: =1-P18 | S18: =1-Q18 | U18: 4. Define the risk mitigation measures (Sheets M1 to M10)
C19: 5.9 Inventory of information and other associated assets | D19: ISO/IEC 27002:2022 | E19: 9 | G19: 10000 | H19: 50000 | I19: 100 | J19: 0.04 | K19: 0.06 | L19: 0.06 | N19: =A19*((SUM(F19:I19))+(J19*1950*80)) | O19: =A19*J19 | P19: =A19*K19 | Q19: =A19*L19 | R19: =1-P19 | S19: =1-Q19 | U19: indicate the selected mitigation measures or controls in Column A
C20: 5.10 Acceptable use of information and other associated assets | D20: ISO/IEC 27002:2022 | E20: 10 | H20: 10000 | I20: 100 | J20: 0.02 | K20: 0.03 | L20: 0.03 | N20: =A20*((SUM(F20:I20))+(J20*1950*80)) | O20: =A20*J20 | P20: =A20*K20 | Q20: =A20*L20 | R20: =1-P20 | S20: =1-Q20 | U20: 0 or empty = not selected
C21: 5.11 Return of assets | D21: ISO/IEC 27002:2022 | E21: 11 | H21: 20000 | I21: 100 | J21: 0.02 | K21: 0.01 | L21: 0.01 | N21: =A21*((SUM(F21:I21))+(J21*1950*80)) | O21: =A21*J21 | P21: =A21*K21 | Q21: =A21*L21 | R21: =1-P21 | S21: =1-Q21 | U21: Combination rule / Règle de combinaison :
C22: 5.12 Classification of information | D22: ISO/IEC 27002:2022 | E22: 12 | G22: 5000 | H22: 50000 | I22: 100 | J22: 0.02 | K22: 0.06 | L22: 0.06 | N22: =A22*((SUM(F22:I22))+(J22*1950*80)) | O22: =A22*J22 | P22: =A22*K22 | Q22: =A22*L22 | R22: =1-P22 | S22: =1-Q22 | U22: Selected coefficients combine per column (K impact, L probability) with the product rule:
C23: 5.13 Labelling of information | D23: ISO/IEC 27002:2022 | E23: 13 | H23: 10000 | I23: 50 | J23: 0.02 | K23: 0.01 | L23: 0.01 | N23: =A23*((SUM(F23:I23))+(J23*1950*80)) | O23: =A23*J23 | P23: =A23*K23 | Q23: =A23*L23 | R23: =1-P23 | S23: =1-Q23 | U23: package reduction = 1 − ∏(1 − rᵢ). Each rᵢ must be 0-1, so the package can never exceed 1;
C24: 5.14 Information transfer | D24: ISO/IEC 27002:2022 | E24: 14 | H24: 20000 | I24: 1000 | J24: 0.02 | K24: 0.02 | L24: 0.02 | N24: =A24*((SUM(F24:I24))+(J24*1950*80)) | O24: =A24*J24 | P24: =A24*K24 | Q24: =A24*L24 | R24: =1-P24 | S24: =1-Q24 | U24: the 'Other' rows count as additional factors. A warning appears under the TOTAL row if a coefficient is outside 0-1.
C25: 5.15 Access control | D25: ISO/IEC 27002:2022 | E25: 15 | G25: 5000 | H25: 5000 | I25: 100 | J25: 0.02 | K25: 0.06 | L25: 0.06 | N25: =A25*((SUM(F25:I25))+(J25*1950*80)) | O25: =A25*J25 | P25: =A25*K25 | Q25: =A25*L25 | R25: =1-P25 | S25: =1-Q25 | U25: Prefer a few well-justified controls, or enter ONE package-level
C26: 5.16 Identity management | D26: ISO/IEC 27002:2022 | E26: 16 | G26: 5000 | H26: 5000 | I26: 100 | J26: 0.01 | K26: 0.01 | L26: 0.01 | N26: =A26*((SUM(F26:I26))+(J26*1950*80)) | O26: =A26*J26 | P26: =A26*K26 | Q26: =A26*L26 | R26: =1-P26 | S26: =1-Q26 | U26: estimate (cost, impact and Pb reduction) in an 'Other' row, with its rationale.
C27: 5.17 Authentication information | D27: ISO/IEC 27002:2022 | E27: 17 | G27: 5000 | H27: 5000 | I27: 100 | J27: 0.01 | K27: 0.01 | L27: 0.01 | N27: =A27*((SUM(F27:I27))+(J27*1950*80)) | O27: =A27*J27 | P27: =A27*K27 | Q27: =A27*L27 | R27: =1-P27 | S27: =1-Q27 | U27: Les coefficients retenus se combinent par colonne selon la règle du produit :
C28: 5.18 Access rights | D28: ISO/IEC 27002:2022 | E28: 18 | G28: 5000 | H28: 5000 | I28: 100 | J28: 0.01 | K28: 0.01 | L28: 0.01 | N28: =A28*((SUM(F28:I28))+(J28*1950*80)) | O28: =A28*J28 | P28: =A28*K28 | Q28: =A28*L28 | R28: =1-P28 | S28: =1-Q28 | U28: réduction du bouquet = 1 − ∏(1 − rᵢ); chaque rᵢ entre 0 et 1, donc jamais plus de 1;
C29: 5.19 Information security in supplier relationships | D29: ISO/IEC 27002:2022 | E29: 19 | H29: 20000 | I29: 1000 | J29: 0.02 | K29: 0.06 | L29: 0.06 | N29: =A29*((SUM(F29:I29))+(J29*1950*80)) | O29: =A29*J29 | P29: =A29*K29 | Q29: =A29*L29 | R29: =1-P29 | S29: =1-Q29 | U29: les lignes « Other / autre » comptent comme facteurs. Privilégier peu de mesures bien justifiées,
C30: 5.20 Addressing information security within supplier agreements | D30: ISO/IEC 27002:2022 | E30: 20 | H30: 20000 | I30: 1000 | J30: 0.02 | K30: 0.06 | L30: 0.06 | N30: =A30*((SUM(F30:I30))+(J30*1950*80)) | O30: =A30*J30 | P30: =A30*K30 | Q30: =A30*L30 | R30: =1-P30 | S30: =1-Q30 | U30: ou saisir une estimation globale du bouquet dans une ligne « Other / autre ».
C31: 5.21 Managing information security in the ICT supply chain | D31: ISO/IEC 27002:2022 | E31: 21 | H31: 20000 | I31: 1000 | J31: 0.02 | K31: 0.01 | L31: 0.01 | N31: =A31*((SUM(F31:I31))+(J31*1950*80)) | O31: =A31*J31 | P31: =A31*K31 | Q31: =A31*L31 | R31: =1-P31 | S31: =1-Q31 | U31: dépasse 1. Privilégier peu de mesures bien justifiées, ou saisir une
C32: 5.22 Monitoring, review and change management of supplier services | D32: ISO/IEC 27002:2022 | E32: 22 | H32: 20000 | I32: 1000 | J32: 0.02 | K32: 0.06 | L32: 0.06 | N32: =A32*((SUM(F32:I32))+(J32*1950*80)) | O32: =A32*J32 | P32: =A32*K32 | Q32: =A32*L32 | R32: =1-P32 | S32: =1-Q32 | U32: estimation globale du bouquet dans une ligne « Other / autre ».
C33: 5.23 Information security for use of cloud services | D33: ISO/IEC 27002:2022 | E33: 23 | H33: 10000 | I33: 1000 | J33: 0.02 | K33: 0.01 | L33: 0.01 | N33: =A33*((SUM(F33:I33))+(J33*1950*80)) | O33: =A33*J33 | P33: =A33*K33 | Q33: =A33*L33 | R33: =1-P33 | S33: =1-Q33
C34: 5.24 Information security incident management planning and preparation | D34: ISO/IEC 27002:2022 | E34: 24 | H34: 10000 | I34: 1000 | J34: 0.02 | K34: 0.01 | L34: 0.01 | N34: =A34*((SUM(F34:I34))+(J34*1950*80)) | O34: =A34*J34 | P34: =A34*K34 | Q34: =A34*L34 | R34: =1-P34 | S34: =1-Q34 | U34: Catalogues: ISO/IEC 27002:2022 (93), NIST CSF 2.0 (106), CIS Controls v8.1 (18).
C35: 5.25 Assessment and decision on information security events | D35: ISO/IEC 27002:2022 | E35: 25 | H35: 10000 | I35: 1000 | J35: 0.02 | K35: 0.01 | L35: 0.01 | N35: =A35*((SUM(F35:I35))+(J35*1950*80)) | O35: =A35*J35 | P35: =A35*K35 | Q35: =A35*L35 | R35: =1-P35 | S35: =1-Q35 | U35: Default costs and coefficients are generic placeholders: recalibrate them.
C36: 5.26 Response to information security incidents | D36: ISO/IEC 27002:2022 | E36: 26 | H36: 10000 | I36: 1000 | J36: 0.02 | K36: 0.06 | L36: 0.06 | N36: =A36*((SUM(F36:I36))+(J36*1950*80)) | O36: =A36*J36 | P36: =A36*K36 | Q36: =A36*L36 | R36: =1-P36 | S36: =1-Q36 | U36: Coûts et coefficients par défaut génériques : à recalibrer.
C37: 5.27 Learning from information security incidents | D37: ISO/IEC 27002:2022 | E37: 27 | H37: 10000 | I37: 1000 | J37: 0.02 | K37: 0.01 | L37: 0.01 | N37: =A37*((SUM(F37:I37))+(J37*1950*80)) | O37: =A37*J37 | P37: =A37*K37 | Q37: =A37*L37 | R37: =1-P37 | S37: =1-Q37
C38: 5.28 Collection of evidence | D38: ISO/IEC 27002:2022 | E38: 28 | H38: 10000 | I38: 10000 | J38: 0.02 | K38: 0.01 | L38: 0.01 | N38: =A38*((SUM(F38:I38))+(J38*1950*80)) | O38: =A38*J38 | P38: =A38*K38 | Q38: =A38*L38 | R38: =1-P38 | S38: =1-Q38
C39: 5.29 Information security during disruption | D39: ISO/IEC 27002:2022 | E39: 29 | H39: 20000 | I39: 1000 | J39: 0.02 | K39: 0.01 | L39: 0.01 | N39: =A39*((SUM(F39:I39))+(J39*1950*80)) | O39: =A39*J39 | P39: =A39*K39 | Q39: =A39*L39 | R39: =1-P39 | S39: =1-Q39
C40: 5.30 ICT readiness for business continuity | D40: ISO/IEC 27002:2022 | E40: 30 | H40: 10000 | I40: 1000 | J40: 0.02 | K40: 0.01 | L40: 0.01 | N40: =A40*((SUM(F40:I40))+(J40*1950*80)) | O40: =A40*J40 | P40: =A40*K40 | Q40: =A40*L40 | R40: =1-P40 | S40: =1-Q40
C41: 5.31 Legal, statutory, regulatory and contractual requirements | D41: ISO/IEC 27002:2022 | E41: 31 | H41: 10000 | I41: 1000 | J41: 0.02 | K41: 0.01 | L41: 0.01 | N41: =A41*((SUM(F41:I41))+(J41*1950*80)) | O41: =A41*J41 | P41: =A41*K41 | Q41: =A41*L41 | R41: =1-P41 | S41: =1-Q41
C42: 5.32 Intellectual property rights | D42: ISO/IEC 27002:2022 | E42: 32 | H42: 10000 | I42: 1000 | J42: 0.02 | K42: 0.01 | L42: 0.01 | N42: =A42*((SUM(F42:I42))+(J42*1950*80)) | O42: =A42*J42 | P42: =A42*K42 | Q42: =A42*L42 | R42: =1-P42 | S42: =1-Q42
C43: 5.33 Protection of records | D43: ISO/IEC 27002:2022 | E43: 33 | H43: 10000 | I43: 1000 | J43: 0.02 | K43: 0.01 | L43: 0.01 | N43: =A43*((SUM(F43:I43))+(J43*1950*80)) | O43: =A43*J43 | P43: =A43*K43 | Q43: =A43*L43 | R43: =1-P43 | S43: =1-Q43
C44: 5.34 Privacy and protection of PII | D44: ISO/IEC 27002:2022 | E44: 34 | H44: 10000 | I44: 1000 | J44: 0.02 | K44: 0.01 | L44: 0.01 | N44: =A44*((SUM(F44:I44))+(J44*1950*80)) | O44: =A44*J44 | P44: =A44*K44 | Q44: =A44*L44 | R44: =1-P44 | S44: =1-Q44
C45: 5.35 Independent review of information security | D45: ISO/IEC 27002:2022 | E45: 35 | H45: 10000 | I45: 10000 | J45: 0.02 | K45: 0.01 | L45: 0.01 | N45: =A45*((SUM(F45:I45))+(J45*1950*80)) | O45: =A45*J45 | P45: =A45*K45 | Q45: =A45*L45 | R45: =1-P45 | S45: =1-Q45
C46: 5.36 Compliance with policies, rules and standards for information security | D46: ISO/IEC 27002:2022 | E46: 36 | H46: 10000 | I46: 10000 | J46: 0.02 | K46: 0.01 | L46: 0.01 | N46: =A46*((SUM(F46:I46))+(J46*1950*80)) | O46: =A46*J46 | P46: =A46*K46 | Q46: =A46*L46 | R46: =1-P46 | S46: =1-Q46
C47: 5.37 Documented operating procedures | D47: ISO/IEC 27002:2022 | E47: 37 | H47: 50000 | I47: 100 | J47: 0.01 | K47: 0.06 | L47: 0.06 | N47: =A47*((SUM(F47:I47))+(J47*1950*80)) | O47: =A47*J47 | P47: =A47*K47 | Q47: =A47*L47 | R47: =1-P47 | S47: =1-Q47
C48: 6 People controls / Mesures liées aux personnes
C49: 6.1 Screening | D49: ISO/IEC 27002:2022 | E49: 38 | H49: 5000 | I49: 500 | J49: 0.01 | K49: 0.01 | L49: 0.01 | N49: =A49*((SUM(F49:I49))+(J49*1950*80)) | O49: =A49*J49 | P49: =A49*K49 | Q49: =A49*L49 | R49: =1-P49 | S49: =1-Q49
C50: 6.2 Terms and conditions of employment | D50: ISO/IEC 27002:2022 | E50: 39 | H50: 5000 | J50: 0.01 | K50: 0.01 | L50: 0.01 | N50: =A50*((SUM(F50:I50))+(J50*1950*80)) | O50: =A50*J50 | P50: =A50*K50 | Q50: =A50*L50 | R50: =1-P50 | S50: =1-Q50
C51: 6.3 Information security awareness, education and training | D51: ISO/IEC 27002:2022 | E51: 40 | H51: 30000 | I51: 500 | J51: 0.01 | K51: 0.06 | L51: 0.06 | N51: =A51*((SUM(F51:I51))+(J51*1950*80)) | O51: =A51*J51 | P51: =A51*K51 | Q51: =A51*L51 | R51: =1-P51 | S51: =1-Q51
C52: 6.4 Disciplinary process | D52: ISO/IEC 27002:2022 | E52: 41 | H52: 10000 | I52: 500 | J52: 0.01 | K52: 0.01 | L52: 0.01 | N52: =A52*((SUM(F52:I52))+(J52*1950*80)) | O52: =A52*J52 | P52: =A52*K52 | Q52: =A52*L52 | R52: =1-P52 | S52: =1-Q52
C53: 6.5 Responsibilities after termination or change of employment | D53: ISO/IEC 27002:2022 | E53: 42 | H53: 5000 | I53: 500 | J53: 0.01 | K53: 0.05 | L53: 0.02 | N53: =A53*((SUM(F53:I53))+(J53*1950*80)) | O53: =A53*J53 | P53: =A53*K53 | Q53: =A53*L53 | R53: =1-P53 | S53: =1-Q53
C54: 6.6 Confidentiality or non-disclosure agreements | D54: ISO/IEC 27002:2022 | E54: 43 | H54: 20000 | I54: 1000 | J54: 0.02 | K54: 0.02 | L54: 0.02 | N54: =A54*((SUM(F54:I54))+(J54*1950*80)) | O54: =A54*J54 | P54: =A54*K54 | Q54: =A54*L54 | R54: =1-P54 | S54: =1-Q54
C55: 6.7 Remote working | D55: ISO/IEC 27002:2022 | E55: 44 | H55: 5000 | I55: 2000 | J55: 0.05 | K55: 0.01 | L55: 0.01 | N55: =A55*((SUM(F55:I55))+(J55*1950*80)) | O55: =A55*J55 | P55: =A55*K55 | Q55: =A55*L55 | R55: =1-P55 | S55: =1-Q55
C56: 6.8 Information security event reporting | D56: ISO/IEC 27002:2022 | E56: 45 | H56: 10000 | I56: 1000 | J56: 0.02 | K56: 0.01 | L56: 0.01 | N56: =A56*((SUM(F56:I56))+(J56*1950*80)) | O56: =A56*J56 | P56: =A56*K56 | Q56: =A56*L56 | R56: =1-P56 | S56: =1-Q56
C57: 7 Physical controls / Mesures physiques
C58: 7.1 Physical security perimeters | D58: ISO/IEC 27002:2022 | E58: 46 | F58: 10000 | G58: 50000 | H58: 10000 | I58: 500 | J58: 0.02 | K58: 0.06 | L58: 0.06 | N58: =A58*((SUM(F58:I58))+(J58*1950*80)) | O58: =A58*J58 | P58: =A58*K58 | Q58: =A58*L58 | R58: =1-P58 | S58: =1-Q58
C59: 7.2 Physical entry | D59: ISO/IEC 27002:2022 | E59: 47 | F59: 10000 | G59: 50000 | H59: 10000 | I59: 500 | J59: 0.02 | K59: 0.06 | L59: 0.06 | N59: =A59*((SUM(F59:I59))+(J59*1950*80)) | O59: =A59*J59 | P59: =A59*K59 | Q59: =A59*L59 | R59: =1-P59 | S59: =1-Q59
C60: 7.3 Securing offices, rooms and facilities | D60: ISO/IEC 27002:2022 | E60: 48 | F60: 10000 | G60: 50000 | H60: 10000 | I60: 500 | J60: 0.02 | K60: 0.01 | L60: 0.01 | N60: =A60*((SUM(F60:I60))+(J60*1950*80)) | O60: =A60*J60 | P60: =A60*K60 | Q60: =A60*L60 | R60: =1-P60 | S60: =1-Q60
C61: 7.4 Physical security monitoring | D61: ISO/IEC 27002:2022 | E61: 49 | H61: 10000 | I61: 1000 | J61: 0.02 | K61: 0.01 | L61: 0.01 | N61: =A61*((SUM(F61:I61))+(J61*1950*80)) | O61: =A61*J61 | P61: =A61*K61 | Q61: =A61*L61 | R61: =1-P61 | S61: =1-Q61
C62: 7.5 Protecting against physical and environmental threats | D62: ISO/IEC 27002:2022 | E62: 50 | F62: 10000 | G62: 50000 | H62: 10000 | I62: 100 | J62: 0.02 | K62: 0.06 | L62: 0.06 | N62: =A62*((SUM(F62:I62))+(J62*1950*80)) | O62: =A62*J62 | P62: =A62*K62 | Q62: =A62*L62 | R62: =1-P62 | S62: =1-Q62
C63: 7.6 Working in secure areas | D63: ISO/IEC 27002:2022 | E63: 51 | F63: 10000 | G63: 50000 | H63: 10000 | I63: 100 | J63: 0.02 | K63: 0.01 | L63: 0.01 | N63: =A63*((SUM(F63:I63))+(J63*1950*80)) | O63: =A63*J63 | P63: =A63*K63 | Q63: =A63*L63 | R63: =1-P63 | S63: =1-Q63
C64: 7.7 Clear desk and clear screen | D64: ISO/IEC 27002:2022 | E64: 52 | H64: 5000 | I64: 100 | J64: 0.01 | K64: 0.01 | L64: 0.01 | N64: =A64*((SUM(F64:I64))+(J64*1950*80)) | O64: =A64*J64 | P64: =A64*K64 | Q64: =A64*L64 | R64: =1-P64 | S64: =1-Q64
C65: 7.8 Equipment siting and protection | D65: ISO/IEC 27002:2022 | E65: 53 | F65: 10000 | H65: 10000 | I65: 500 | J65: 0.02 | K65: 0.06 | L65: 0.06 | N65: =A65*((SUM(F65:I65))+(J65*1950*80)) | O65: =A65*J65 | P65: =A65*K65 | Q65: =A65*L65 | R65: =1-P65 | S65: =1-Q65
C66: 7.9 Security of assets off-premises | D66: ISO/IEC 27002:2022 | E66: 54 | G66: 50000 | H66: 10000 | I66: 100 | J66: 0.01 | K66: 0.01 | L66: 0.01 | N66: =A66*((SUM(F66:I66))+(J66*1950*80)) | O66: =A66*J66 | P66: =A66*K66 | Q66: =A66*L66 | R66: =1-P66 | S66: =1-Q66
C67: 7.10 Storage media | D67: ISO/IEC 27002:2022 | E67: 55 | G67: 5000 | H67: 5000 | I67: 100 | J67: 0.02 | K67: 0.01 | L67: 0.01 | N67: =A67*((SUM(F67:I67))+(J67*1950*80)) | O67: =A67*J67 | P67: =A67*K67 | Q67: =A67*L67 | R67: =1-P67 | S67: =1-Q67
C68: 7.11 Supporting utilities | D68: ISO/IEC 27002:2022 | E68: 56 | F68: 10000 | G68: 50000 | H68: 10000 | I68: 100 | J68: 0.01 | K68: 0.01 | L68: 0.01 | N68: =A68*((SUM(F68:I68))+(J68*1950*80)) | O68: =A68*J68 | P68: =A68*K68 | Q68: =A68*L68 | R68: =1-P68 | S68: =1-Q68
C69: 7.12 Cabling security | D69: ISO/IEC 27002:2022 | E69: 57 | F69: 10000 | G69: 50000 | H69: 10000 | I69: 100 | J69: 0.01 | K69: 0.01 | L69: 0.01 | N69: =A69*((SUM(F69:I69))+(J69*1950*80)) | O69: =A69*J69 | P69: =A69*K69 | Q69: =A69*L69 | R69: =1-P69 | S69: =1-Q69
C70: 7.13 Equipment maintenance | D70: ISO/IEC 27002:2022 | E70: 58 | F70: 10000 | G70: 50000 | H70: 10000 | I70: 500 | J70: 0.01 | K70: 0.01 | L70: 0.01 | N70: =A70*((SUM(F70:I70))+(J70*1950*80)) | O70: =A70*J70 | P70: =A70*K70 | Q70: =A70*L70 | R70: =1-P70 | S70: =1-Q70
C71: 7.14 Secure disposal or re-use of equipment | D71: ISO/IEC 27002:2022 | E71: 59 | G71: 50000 | H71: 10000 | I71: 100 | J71: 0.01 | K71: 0.01 | L71: 0.01 | N71: =A71*((SUM(F71:I71))+(J71*1950*80)) | O71: =A71*J71 | P71: =A71*K71 | Q71: =A71*L71 | R71: =1-P71 | S71: =1-Q71
C72: 8 Technological controls / Mesures technologiques
C73: 8.1 User end point devices | D73: ISO/IEC 27002:2022 | E73: 60 | H73: 5000 | I73: 500 | J73: 0.01 | K73: 0.01 | L73: 0.01 | N73: =A73*((SUM(F73:I73))+(J73*1950*80)) | O73: =A73*J73 | P73: =A73*K73 | Q73: =A73*L73 | R73: =1-P73 | S73: =1-Q73
C74: 8.2 Privileged access rights | D74: ISO/IEC 27002:2022 | E74: 61 | G74: 5000 | H74: 5000 | I74: 100 | J74: 0.01 | K74: 0.06 | L74: 0.06 | N74: =A74*((SUM(F74:I74))+(J74*1950*80)) | O74: =A74*J74 | P74: =A74*K74 | Q74: =A74*L74 | R74: =1-P74 | S74: =1-Q74
C75: 8.3 Information access restriction | D75: ISO/IEC 27002:2022 | E75: 62 | G75: 5000 | H75: 5000 | I75: 100 | J75: 0.01 | K75: 0.065 | L75: 0.06 | N75: =A75*((SUM(F75:I75))+(J75*1950*80)) | O75: =A75*J75 | P75: =A75*K75 | Q75: =A75*L75 | R75: =1-P75 | S75: =1-Q75
C76: 8.4 Access to source code | D76: ISO/IEC 27002:2022 | E76: 63 | G76: 5000 | H76: 5000 | I76: 100 | J76: 0.01 | K76: 0.01 | L76: 0.01 | N76: =A76*((SUM(F76:I76))+(J76*1950*80)) | O76: =A76*J76 | P76: =A76*K76 | Q76: =A76*L76 | R76: =1-P76 | S76: =1-Q76
C77: 8.5 Secure authentication | D77: ISO/IEC 27002:2022 | E77: 64 | G77: 5000 | H77: 5000 | I77: 100 | J77: 0.01 | K77: 0.01 | L77: 0.01 | N77: =A77*((SUM(F77:I77))+(J77*1950*80)) | O77: =A77*J77 | P77: =A77*K77 | Q77: =A77*L77 | R77: =1-P77 | S77: =1-Q77
C78: 8.6 Capacity management | D78: ISO/IEC 27002:2022 | E78: 65 | H78: 50000 | I78: 100 | J78: 0.01 | K78: 0.01 | L78: 0.01 | N78: =A78*((SUM(F78:I78))+(J78*1950*80)) | O78: =A78*J78 | P78: =A78*K78 | Q78: =A78*L78 | R78: =1-P78 | S78: =1-Q78
C79: 8.7 Protection against malware | D79: ISO/IEC 27002:2022 | E79: 66 | G79: 5000 | H79: 25000 | I79: 200 | J79: 0.06 | K79: 0.08 | L79: 0.08 | N79: =A79*((SUM(F79:I79))+(J79*1950*80)) | O79: =A79*J79 | P79: =A79*K79 | Q79: =A79*L79 | R79: =1-P79 | S79: =1-Q79
C80: 8.8 Management of technical vulnerabilities | D80: ISO/IEC 27002:2022 | E80: 67 | F80: 5000 | G80: 25000 | H80: 50000 | I80: 10000 | J80: 0.06 | K80: 0.065 | L80: 0.065 | N80: =A80*((SUM(F80:I80))+(J80*1950*80)) | O80: =A80*J80 | P80: =A80*K80 | Q80: =A80*L80 | R80: =1-P80 | S80: =1-Q80
C81: 8.9 Configuration management | D81: ISO/IEC 27002:2022 | E81: 68 | H81: 10000 | I81: 1000 | J81: 0.02 | K81: 0.01 | L81: 0.01 | N81: =A81*((SUM(F81:I81))+(J81*1950*80)) | O81: =A81*J81 | P81: =A81*K81 | Q81: =A81*L81 | R81: =1-P81 | S81: =1-Q81
C82: 8.10 Information deletion | D82: ISO/IEC 27002:2022 | E82: 69 | H82: 10000 | I82: 1000 | J82: 0.02 | K82: 0.01 | L82: 0.01 | N82: =A82*((SUM(F82:I82))+(J82*1950*80)) | O82: =A82*J82 | P82: =A82*K82 | Q82: =A82*L82 | R82: =1-P82 | S82: =1-Q82
C83: 8.11 Data masking | D83: ISO/IEC 27002:2022 | E83: 70 | H83: 10000 | I83: 1000 | J83: 0.02 | K83: 0.01 | L83: 0.01 | N83: =A83*((SUM(F83:I83))+(J83*1950*80)) | O83: =A83*J83 | P83: =A83*K83 | Q83: =A83*L83 | R83: =1-P83 | S83: =1-Q83
C84: 8.12 Data leakage prevention | D84: ISO/IEC 27002:2022 | E84: 71 | H84: 10000 | I84: 1000 | J84: 0.02 | K84: 0.01 | L84: 0.01 | N84: =A84*((SUM(F84:I84))+(J84*1950*80)) | O84: =A84*J84 | P84: =A84*K84 | Q84: =A84*L84 | R84: =1-P84 | S84: =1-Q84
C85: 8.13 Information backup | D85: ISO/IEC 27002:2022 | E85: 72 | F85: 50000 | G85: 10000 | H85: 50000 | I85: 10000 | J85: 0.06 | K85: 0.065 | L85: 0.06 | N85: =A85*((SUM(F85:I85))+(J85*1950*80)) | O85: =A85*J85 | P85: =A85*K85 | Q85: =A85*L85 | R85: =1-P85 | S85: =1-Q85
C86: 8.14 Redundancy of information processing facilities | D86: ISO/IEC 27002:2022 | E86: 73 | H86: 20000 | I86: 50000 | J86: 0.02 | K86: 0.065 | L86: 0.065 | N86: =A86*((SUM(F86:I86))+(J86*1950*80)) | O86: =A86*J86 | P86: =A86*K86 | Q86: =A86*L86 | R86: =1-P86 | S86: =1-Q86
C87: 8.15 Logging | D87: ISO/IEC 27002:2022 | E87: 74 | F87: 10000 | G87: 5000 | H87: 50000 | I87: 10000 | J87: 0.01 | K87: 0.06 | L87: 0.06 | N87: =A87*((SUM(F87:I87))+(J87*1950*80)) | O87: =A87*J87 | P87: =A87*K87 | Q87: =A87*L87 | R87: =1-P87 | S87: =1-Q87
C88: 8.16 Monitoring activities | D88: ISO/IEC 27002:2022 | E88: 75 | H88: 10000 | I88: 1000 | J88: 0.02 | K88: 0.01 | L88: 0.01 | N88: =A88*((SUM(F88:I88))+(J88*1950*80)) | O88: =A88*J88 | P88: =A88*K88 | Q88: =A88*L88 | R88: =1-P88 | S88: =1-Q88
C89: 8.17 Clock synchronization | D89: ISO/IEC 27002:2022 | E89: 76 | H89: 10000 | I89: 1000 | J89: 0.02 | K89: 0.01 | L89: 0.01 | N89: =A89*((SUM(F89:I89))+(J89*1950*80)) | O89: =A89*J89 | P89: =A89*K89 | Q89: =A89*L89 | R89: =1-P89 | S89: =1-Q89
C90: 8.18 Use of privileged utility programs | D90: ISO/IEC 27002:2022 | E90: 77 | G90: 5000 | H90: 5000 | I90: 100 | J90: 0.01 | K90: 0.01 | L90: 0.01 | N90: =A90*((SUM(F90:I90))+(J90*1950*80)) | O90: =A90*J90 | P90: =A90*K90 | Q90: =A90*L90 | R90: =1-P90 | S90: =1-Q90
C91: 8.19 Installation of software on operational systems | D91: ISO/IEC 27002:2022 | E91: 78 | F91: 10000 | G91: 5000 | I91: 500 | J91: 0.02 | K91: 0.06 | L91: 0.06 | N91: =A91*((SUM(F91:I91))+(J91*1950*80)) | O91: =A91*J91 | P91: =A91*K91 | Q91: =A91*L91 | R91: =1-P91 | S91: =1-Q91
C92: 8.20 Networks security | D92: ISO/IEC 27002:2022 | E92: 79 | F92: 5000 | G92: 25000 | H92: 50000 | I92: 10000 | J92: 0.06 | K92: 0.02 | L92: 0.02 | N92: =A92*((SUM(F92:I92))+(J92*1950*80)) | O92: =A92*J92 | P92: =A92*K92 | Q92: =A92*L92 | R92: =1-P92 | S92: =1-Q92
C93: 8.21 Security of network services | D93: ISO/IEC 27002:2022 | E93: 80 | F93: 5000 | G93: 25000 | H93: 50000 | I93: 10000 | J93: 0.06 | K93: 0.02 | L93: 0.02 | N93: =A93*((SUM(F93:I93))+(J93*1950*80)) | O93: =A93*J93 | P93: =A93*K93 | Q93: =A93*L93 | R93: =1-P93 | S93: =1-Q93
C94: 8.22 Segregation of networks | D94: ISO/IEC 27002:2022 | E94: 81 | F94: 5000 | G94: 25000 | H94: 50000 | I94: 10000 | J94: 0.06 | K94: 0.02 | L94: 0.02 | N94: =A94*((SUM(F94:I94))+(J94*1950*80)) | O94: =A94*J94 | P94: =A94*K94 | Q94: =A94*L94 | R94: =1-P94 | S94: =1-Q94
C95: 8.23 Web filtering | D95: ISO/IEC 27002:2022 | E95: 82 | H95: 10000 | I95: 1000 | J95: 0.02 | K95: 0.01 | L95: 0.01 | N95: =A95*((SUM(F95:I95))+(J95*1950*80)) | O95: =A95*J95 | P95: =A95*K95 | Q95: =A95*L95 | R95: =1-P95 | S95: =1-Q95
C96: 8.24 Use of cryptography | D96: ISO/IEC 27002:2022 | E96: 83 | G96: 5000 | H96: 5000 | I96: 100 | J96: 0.01 | K96: 0.01 | L96: 0.01 | N96: =A96*((SUM(F96:I96))+(J96*1950*80)) | O96: =A96*J96 | P96: =A96*K96 | Q96: =A96*L96 | R96: =1-P96 | S96: =1-Q96
C97: 8.25 Secure development life cycle | D97: ISO/IEC 27002:2022 | E97: 84 | H97: 20000 | I97: 1000 | J97: 0.02 | K97: 0.01 | L97: 0.01 | N97: =A97*((SUM(F97:I97))+(J97*1950*80)) | O97: =A97*J97 | P97: =A97*K97 | Q97: =A97*L97 | R97: =1-P97 | S97: =1-Q97
C98: 8.26 Application security requirements | D98: ISO/IEC 27002:2022 | E98: 85 | H98: 20000 | I98: 1000 | J98: 0.02 | K98: 0.02 | L98: 0.02 | N98: =A98*((SUM(F98:I98))+(J98*1950*80)) | O98: =A98*J98 | P98: =A98*K98 | Q98: =A98*L98 | R98: =1-P98 | S98: =1-Q98
C99: 8.27 Secure system architecture and engineering principles | D99: ISO/IEC 27002:2022 | E99: 86 | H99: 20000 | I99: 1000 | J99: 0.02 | K99: 0.01 | L99: 0.01 | N99: =A99*((SUM(F99:I99))+(J99*1950*80)) | O99: =A99*J99 | P99: =A99*K99 | Q99: =A99*L99 | R99: =1-P99 | S99: =1-Q99
C100: 8.28 Secure coding | D100: ISO/IEC 27002:2022 | E100: 87 | H100: 10000 | I100: 1000 | J100: 0.02 | K100: 0.01 | L100: 0.01 | N100: =A100*((SUM(F100:I100))+(J100*1950*80)) | O100: =A100*J100 | P100: =A100*K100 | Q100: =A100*L100 | R100: =1-P100 | S100: =1-Q100
...

Sheet S6
A1: Risk scenario number 6 / Scénario de risque 6
A2: Scenario number / Numéro : | B2: 6
A3: Scenario name / Nom du scénario :
A4: Date of creation / Date de création du scénario :
A6: Probability that the threat will be present = Probabilité de réalisation : Pb(A)
A7: Probability of exploitation = Probabilité d’exploitation: Pb(ψ,A)
A8: Estimated expected damages = Dommage estimé: δe(ψ,A)
A9: Maximal damages = Dommage maximal: δm(ψ,A) | C9: =IF(AND(ISNUMBER(B8),ISNUMBER(B9),B9<B8),"δm should be ≥ δe / δm devrait être ≥ δe","")
A10: Level of organizational resilience = Niveau de résilience: θ(ψ,A) | C10: =IF(AND(B10<>"",OR(NOT(ISNUMBER(B10)),B10<=0,B10>1)),"θ must be in (0, 1] / θ doit être dans ]0, 1]","")
A11: Organizational criticality (expected utility) = Criticité organisationnelle (utilité espérée) : μ(E)
A14: 3. Renseigner les scénarios de risque (feuilles S1 à S10)
A15: 3. Populate the risk scenarios (Sheets S1 to S10)
A16: Values 0-1; θ > 0 and ≤ 1; δm ≥ δe. Horizon: 12 months. Each value: rationale, evidence (E-number), confidence — Analytical estimate — validation required.
A17: Valeurs 0-1; θ > 0 et ≤ 1; δm ≥ δe. Horizon : 12 mois. Chaque valeur : justification, preuve (n° E), confiance — Estimation analytique — validation requise.

Sheet M6
A1: Other / autre | C1: Proposed risk mitigation measure / mesure de mitigation des risques proposés | D1: Source | F1: Immobilisations | G1: Logiciels | H1: Mise en œuvre | I1: Exploitation | J1: ÉTC | K1: Réduc impacts | L1: Réduction Pb | N1: Coût | O1: ETC | P1: Impact | Q1: Pb | R1: 1 − impact | S1: 1 − Pb
N2: =A2*((SUM(F2:I2))+(J2*1950*80)) | O2: =A2*J2 | P2: =A2*K2 | Q2: =A2*L2 | R2: =1-P2 | S2: =1-Q2
N3: =A3*((SUM(F3:I3))+(J3*1950*80)) | O3: =A3*J3 | P3: =A3*K3 | Q3: =A3*L3 | R3: =1-P3 | S3: =1-Q3
N4: =A4*((SUM(F4:I4))+(J4*1950*80)) | O4: =A4*J4 | P4: =A4*K4 | Q4: =A4*L4 | R4: =1-P4 | S4: =1-Q4
N5: =A5*((SUM(F5:I5))+(J5*1950*80)) | O5: =A5*J5 | P5: =A5*K5 | Q5: =A5*L5 | R5: =1-P5 | S5: =1-Q5
N6: =A6*((SUM(F6:I6))+(J6*1950*80)) | O6: =A6*J6 | P6: =A6*K6 | Q6: =A6*L6 | R6: =1-P6 | S6: =1-Q6
N7: =SUM(N2:N6) | O7: =SUM(O2:O6) | P7: =1-PRODUCT(R2:R6) | Q7: =1-PRODUCT(S2:S6)
A8: Include | C8: Control / Contrôle | D8: Source | F8: Immobilisations | G8: Logiciels | H8: Mise en œuvre | I8: Exploitation | J8: ÉTC | K8: Réduc impacts | L8: Réduction Pb | N8: Coût | O8: ETC | P8: Impact | Q8: Pb | R8: 1 − impact | S8: 1 − Pb
A9: Inclure | C9: ISO/IEC 27002:2022 — information security controls (93) / mesures de sécurité de l'information | F9: CAPEX | G9: Software | H9: Implementation | I9: Exploitation | J9: FTE | K9: Reduce impacts | L9: Reduce Pb | N9: Cost | O9: FTE | P9: Impact | Q9: Pb
C10: 5 Organizational controls / Mesures organisationnelles
C11: 5.1 Policies for information security | D11: ISO/IEC 27002:2022 | E11: 1 | H11: 25000 | I11: 3000 | J11: 0.01 | K11: 0.06 | L11: 0.06 | N11: =A11*((SUM(F11:I11))+(J11*1950*80)) | O11: =A11*J11 | P11: =A11*K11 | Q11: =A11*L11 | R11: =1-P11 | S11: =1-Q11
C12: 5.2 Information security roles and responsibilities | D12: ISO/IEC 27002:2022 | E12: 2 | H12: 5000 | I12: 500 | J12: 0.01 | K12: 0.01 | L12: 0.01 | N12: =A12*((SUM(F12:I12))+(J12*1950*80)) | O12: =A12*J12 | P12: =A12*K12 | Q12: =A12*L12 | R12: =1-P12 | S12: =1-Q12
C13: 5.3 Segregation of duties | D13: ISO/IEC 27002:2022 | E13: 3 | H13: 5000 | I13: 500 | J13: 0.01 | K13: 0.01 | L13: 0.01 | N13: =A13*((SUM(F13:I13))+(J13*1950*80)) | O13: =A13*J13 | P13: =A13*K13 | Q13: =A13*L13 | R13: =1-P13 | S13: =1-Q13 | U13: 4. Définir les mesures de mitigation (feuilles M1 à M10)
C14: 5.4 Management responsibilities | D14: ISO/IEC 27002:2022 | E14: 4 | H14: 5000 | I14: 500 | J14: 0.01 | K14: 0.01 | L14: 0.01 | N14: =A14*((SUM(F14:I14))+(J14*1950*80)) | O14: =A14*J14 | P14: =A14*K14 | Q14: =A14*L14 | R14: =1-P14 | S14: =1-Q14 | U14: dans la colonne A Inclure Mesure
C15: 5.5 Contact with authorities | D15: ISO/IEC 27002:2022 | E15: 5 | H15: 5000 | J15: =1/50 | K15: 0.01 | L15: 0.01 | N15: =A15*((SUM(F15:I15))+(J15*1950*80)) | O15: =A15*J15 | P15: =A15*K15 | Q15: =A15*L15 | R15: =1-P15 | S15: =1-Q15 | U15: 0 ou vide = non sélectionné
C16: 5.6 Contact with special interest groups | D16: ISO/IEC 27002:2022 | E16: 6 | H16: 5000 | J16: =3/50 | K16: 0.01 | L16: 0.01 | N16: =A16*((SUM(F16:I16))+(J16*1950*80)) | O16: =A16*J16 | P16: =A16*K16 | Q16: =A16*L16 | R16: =1-P16 | S16: =1-Q16 | U16: 6. Define the risk mitigation measures (Sheets M1 to M10)
C17: 5.7 Threat intelligence | D17: ISO/IEC 27002:2022 | E17: 7 | H17: 10000 | I17: 1000 | J17: 0.02 | K17: 0.01 | L17: 0.01 | N17: =A17*((SUM(F17:I17))+(J17*1950*80)) | O17: =A17*J17 | P17: =A17*K17 | Q17: =A17*L17 | R17: =1-P17 | S17: =1-Q17
C18: 5.8 Information security in project management | D18: ISO/IEC 27002:2022 | E18: 8 | H18: 5000 | J18: 0.06 | K18: 0.06 | L18: 0.06 | N18: =A18*((SUM(F18:I18))+(J18*1950*80)) | O18: =A18*J18 | P18: =A18*K18 | Q18: =A18*L18 | R18: =1-P18 | S18: =1-Q18 | U18: 4. Define the risk mitigation measures (Sheets M1 to M10)
C19: 5.9 Inventory of information and other associated assets | D19: ISO/IEC 27002:2022 | E19: 9 | G19: 10000 | H19: 50000 | I19: 100 | J19: 0.04 | K19: 0.06 | L19: 0.06 | N19: =A19*((SUM(F19:I19))+(J19*1950*80)) | O19: =A19*J19 | P19: =A19*K19 | Q19: =A19*L19 | R19: =1-P19 | S19: =1-Q19 | U19: indicate the selected mitigation measures or controls in Column A
C20: 5.10 Acceptable use of information and other associated assets | D20: ISO/IEC 27002:2022 | E20: 10 | H20: 10000 | I20: 100 | J20: 0.02 | K20: 0.03 | L20: 0.03 | N20: =A20*((SUM(F20:I20))+(J20*1950*80)) | O20: =A20*J20 | P20: =A20*K20 | Q20: =A20*L20 | R20: =1-P20 | S20: =1-Q20 | U20: 0 or empty = not selected
C21: 5.11 Return of assets | D21: ISO/IEC 27002:2022 | E21: 11 | H21: 20000 | I21: 100 | J21: 0.02 | K21: 0.01 | L21: 0.01 | N21: =A21*((SUM(F21:I21))+(J21*1950*80)) | O21: =A21*J21 | P21: =A21*K21 | Q21: =A21*L21 | R21: =1-P21 | S21: =1-Q21 | U21: Combination rule / Règle de combinaison :
C22: 5.12 Classification of information | D22: ISO/IEC 27002:2022 | E22: 12 | G22: 5000 | H22: 50000 | I22: 100 | J22: 0.02 | K22: 0.06 | L22: 0.06 | N22: =A22*((SUM(F22:I22))+(J22*1950*80)) | O22: =A22*J22 | P22: =A22*K22 | Q22: =A22*L22 | R22: =1-P22 | S22: =1-Q22 | U22: Selected coefficients combine per column (K impact, L probability) with the product rule:
C23: 5.13 Labelling of information | D23: ISO/IEC 27002:2022 | E23: 13 | H23: 10000 | I23: 50 | J23: 0.02 | K23: 0.01 | L23: 0.01 | N23: =A23*((SUM(F23:I23))+(J23*1950*80)) | O23: =A23*J23 | P23: =A23*K23 | Q23: =A23*L23 | R23: =1-P23 | S23: =1-Q23 | U23: package reduction = 1 − ∏(1 − rᵢ). Each rᵢ must be 0-1, so the package can never exceed 1;
C24: 5.14 Information transfer | D24: ISO/IEC 27002:2022 | E24: 14 | H24: 20000 | I24: 1000 | J24: 0.02 | K24: 0.02 | L24: 0.02 | N24: =A24*((SUM(F24:I24))+(J24*1950*80)) | O24: =A24*J24 | P24: =A24*K24 | Q24: =A24*L24 | R24: =1-P24 | S24: =1-Q24 | U24: the 'Other' rows count as additional factors. A warning appears under the TOTAL row if a coefficient is outside 0-1.
C25: 5.15 Access control | D25: ISO/IEC 27002:2022 | E25: 15 | G25: 5000 | H25: 5000 | I25: 100 | J25: 0.02 | K25: 0.06 | L25: 0.06 | N25: =A25*((SUM(F25:I25))+(J25*1950*80)) | O25: =A25*J25 | P25: =A25*K25 | Q25: =A25*L25 | R25: =1-P25 | S25: =1-Q25 | U25: Prefer a few well-justified controls, or enter ONE package-level
C26: 5.16 Identity management | D26: ISO/IEC 27002:2022 | E26: 16 | G26: 5000 | H26: 5000 | I26: 100 | J26: 0.01 | K26: 0.01 | L26: 0.01 | N26: =A26*((SUM(F26:I26))+(J26*1950*80)) | O26: =A26*J26 | P26: =A26*K26 | Q26: =A26*L26 | R26: =1-P26 | S26: =1-Q26 | U26: estimate (cost, impact and Pb reduction) in an 'Other' row, with its rationale.
C27: 5.17 Authentication information | D27: ISO/IEC 27002:2022 | E27: 17 | G27: 5000 | H27: 5000 | I27: 100 | J27: 0.01 | K27: 0.01 | L27: 0.01 | N27: =A27*((SUM(F27:I27))+(J27*1950*80)) | O27: =A27*J27 | P27: =A27*K27 | Q27: =A27*L27 | R27: =1-P27 | S27: =1-Q27 | U27: Les coefficients retenus se combinent par colonne selon la règle du produit :
C28: 5.18 Access rights | D28: ISO/IEC 27002:2022 | E28: 18 | G28: 5000 | H28: 5000 | I28: 100 | J28: 0.01 | K28: 0.01 | L28: 0.01 | N28: =A28*((SUM(F28:I28))+(J28*1950*80)) | O28: =A28*J28 | P28: =A28*K28 | Q28: =A28*L28 | R28: =1-P28 | S28: =1-Q28 | U28: réduction du bouquet = 1 − ∏(1 − rᵢ); chaque rᵢ entre 0 et 1, donc jamais plus de 1;
C29: 5.19 Information security in supplier relationships | D29: ISO/IEC 27002:2022 | E29: 19 | H29: 20000 | I29: 1000 | J29: 0.02 | K29: 0.06 | L29: 0.06 | N29: =A29*((SUM(F29:I29))+(J29*1950*80)) | O29: =A29*J29 | P29: =A29*K29 | Q29: =A29*L29 | R29: =1-P29 | S29: =1-Q29 | U29: les lignes « Other / autre » comptent comme facteurs. Privilégier peu de mesures bien justifiées,
C30: 5.20 Addressing information security within supplier agreements | D30: ISO/IEC 27002:2022 | E30: 20 | H30: 20000 | I30: 1000 | J30: 0.02 | K30: 0.06 | L30: 0.06 | N30: =A30*((SUM(F30:I30))+(J30*1950*80)) | O30: =A30*J30 | P30: =A30*K30 | Q30: =A30*L30 | R30: =1-P30 | S30: =1-Q30 | U30: ou saisir une estimation globale du bouquet dans une ligne « Other / autre ».
C31: 5.21 Managing information security in the ICT supply chain | D31: ISO/IEC 27002:2022 | E31: 21 | H31: 20000 | I31: 1000 | J31: 0.02 | K31: 0.01 | L31: 0.01 | N31: =A31*((SUM(F31:I31))+(J31*1950*80)) | O31: =A31*J31 | P31: =A31*K31 | Q31: =A31*L31 | R31: =1-P31 | S31: =1-Q31 | U31: dépasse 1. Privilégier peu de mesures bien justifiées, ou saisir une
C32: 5.22 Monitoring, review and change management of supplier services | D32: ISO/IEC 27002:2022 | E32: 22 | H32: 20000 | I32: 1000 | J32: 0.02 | K32: 0.06 | L32: 0.06 | N32: =A32*((SUM(F32:I32))+(J32*1950*80)) | O32: =A32*J32 | P32: =A32*K32 | Q32: =A32*L32 | R32: =1-P32 | S32: =1-Q32 | U32: estimation globale du bouquet dans une ligne « Other / autre ».
C33: 5.23 Information security for use of cloud services | D33: ISO/IEC 27002:2022 | E33: 23 | H33: 10000 | I33: 1000 | J33: 0.02 | K33: 0.01 | L33: 0.01 | N33: =A33*((SUM(F33:I33))+(J33*1950*80)) | O33: =A33*J33 | P33: =A33*K33 | Q33: =A33*L33 | R33: =1-P33 | S33: =1-Q33
C34: 5.24 Information security incident management planning and preparation | D34: ISO/IEC 27002:2022 | E34: 24 | H34: 10000 | I34: 1000 | J34: 0.02 | K34: 0.01 | L34: 0.01 | N34: =A34*((SUM(F34:I34))+(J34*1950*80)) | O34: =A34*J34 | P34: =A34*K34 | Q34: =A34*L34 | R34: =1-P34 | S34: =1-Q34 | U34: Catalogues: ISO/IEC 27002:2022 (93), NIST CSF 2.0 (106), CIS Controls v8.1 (18).
C35: 5.25 Assessment and decision on information security events | D35: ISO/IEC 27002:2022 | E35: 25 | H35: 10000 | I35: 1000 | J35: 0.02 | K35: 0.01 | L35: 0.01 | N35: =A35*((SUM(F35:I35))+(J35*1950*80)) | O35: =A35*J35 | P35: =A35*K35 | Q35: =A35*L35 | R35: =1-P35 | S35: =1-Q35 | U35: Default costs and coefficients are generic placeholders: recalibrate them.
C36: 5.26 Response to information security incidents | D36: ISO/IEC 27002:2022 | E36: 26 | H36: 10000 | I36: 1000 | J36: 0.02 | K36: 0.06 | L36: 0.06 | N36: =A36*((SUM(F36:I36))+(J36*1950*80)) | O36: =A36*J36 | P36: =A36*K36 | Q36: =A36*L36 | R36: =1-P36 | S36: =1-Q36 | U36: Coûts et coefficients par défaut génériques : à recalibrer.
C37: 5.27 Learning from information security incidents | D37: ISO/IEC 27002:2022 | E37: 27 | H37: 10000 | I37: 1000 | J37: 0.02 | K37: 0.01 | L37: 0.01 | N37: =A37*((SUM(F37:I37))+(J37*1950*80)) | O37: =A37*J37 | P37: =A37*K37 | Q37: =A37*L37 | R37: =1-P37 | S37: =1-Q37
C38: 5.28 Collection of evidence | D38: ISO/IEC 27002:2022 | E38: 28 | H38: 10000 | I38: 10000 | J38: 0.02 | K38: 0.01 | L38: 0.01 | N38: =A38*((SUM(F38:I38))+(J38*1950*80)) | O38: =A38*J38 | P38: =A38*K38 | Q38: =A38*L38 | R38: =1-P38 | S38: =1-Q38
C39: 5.29 Information security during disruption | D39: ISO/IEC 27002:2022 | E39: 29 | H39: 20000 | I39: 1000 | J39: 0.02 | K39: 0.01 | L39: 0.01 | N39: =A39*((SUM(F39:I39))+(J39*1950*80)) | O39: =A39*J39 | P39: =A39*K39 | Q39: =A39*L39 | R39: =1-P39 | S39: =1-Q39
C40: 5.30 ICT readiness for business continuity | D40: ISO/IEC 27002:2022 | E40: 30 | H40: 10000 | I40: 1000 | J40: 0.02 | K40: 0.01 | L40: 0.01 | N40: =A40*((SUM(F40:I40))+(J40*1950*80)) | O40: =A40*J40 | P40: =A40*K40 | Q40: =A40*L40 | R40: =1-P40 | S40: =1-Q40
C41: 5.31 Legal, statutory, regulatory and contractual requirements | D41: ISO/IEC 27002:2022 | E41: 31 | H41: 10000 | I41: 1000 | J41: 0.02 | K41: 0.01 | L41: 0.01 | N41: =A41*((SUM(F41:I41))+(J41*1950*80)) | O41: =A41*J41 | P41: =A41*K41 | Q41: =A41*L41 | R41: =1-P41 | S41: =1-Q41
C42: 5.32 Intellectual property rights | D42: ISO/IEC 27002:2022 | E42: 32 | H42: 10000 | I42: 1000 | J42: 0.02 | K42: 0.01 | L42: 0.01 | N42: =A42*((SUM(F42:I42))+(J42*1950*80)) | O42: =A42*J42 | P42: =A42*K42 | Q42: =A42*L42 | R42: =1-P42 | S42: =1-Q42
C43: 5.33 Protection of records | D43: ISO/IEC 27002:2022 | E43: 33 | H43: 10000 | I43: 1000 | J43: 0.02 | K43: 0.01 | L43: 0.01 | N43: =A43*((SUM(F43:I43))+(J43*1950*80)) | O43: =A43*J43 | P43: =A43*K43 | Q43: =A43*L43 | R43: =1-P43 | S43: =1-Q43
C44: 5.34 Privacy and protection of PII | D44: ISO/IEC 27002:2022 | E44: 34 | H44: 10000 | I44: 1000 | J44: 0.02 | K44: 0.01 | L44: 0.01 | N44: =A44*((SUM(F44:I44))+(J44*1950*80)) | O44: =A44*J44 | P44: =A44*K44 | Q44: =A44*L44 | R44: =1-P44 | S44: =1-Q44
C45: 5.35 Independent review of information security | D45: ISO/IEC 27002:2022 | E45: 35 | H45: 10000 | I45: 10000 | J45: 0.02 | K45: 0.01 | L45: 0.01 | N45: =A45*((SUM(F45:I45))+(J45*1950*80)) | O45: =A45*J45 | P45: =A45*K45 | Q45: =A45*L45 | R45: =1-P45 | S45: =1-Q45
C46: 5.36 Compliance with policies, rules and standards for information security | D46: ISO/IEC 27002:2022 | E46: 36 | H46: 10000 | I46: 10000 | J46: 0.02 | K46: 0.01 | L46: 0.01 | N46: =A46*((SUM(F46:I46))+(J46*1950*80)) | O46: =A46*J46 | P46: =A46*K46 | Q46: =A46*L46 | R46: =1-P46 | S46: =1-Q46
C47: 5.37 Documented operating procedures | D47: ISO/IEC 27002:2022 | E47: 37 | H47: 50000 | I47: 100 | J47: 0.01 | K47: 0.06 | L47: 0.06 | N47: =A47*((SUM(F47:I47))+(J47*1950*80)) | O47: =A47*J47 | P47: =A47*K47 | Q47: =A47*L47 | R47: =1-P47 | S47: =1-Q47
C48: 6 People controls / Mesures liées aux personnes
C49: 6.1 Screening | D49: ISO/IEC 27002:2022 | E49: 38 | H49: 5000 | I49: 500 | J49: 0.01 | K49: 0.01 | L49: 0.01 | N49: =A49*((SUM(F49:I49))+(J49*1950*80)) | O49: =A49*J49 | P49: =A49*K49 | Q49: =A49*L49 | R49: =1-P49 | S49: =1-Q49
C50: 6.2 Terms and conditions of employment | D50: ISO/IEC 27002:2022 | E50: 39 | H50: 5000 | J50: 0.01 | K50: 0.01 | L50: 0.01 | N50: =A50*((SUM(F50:I50))+(J50*1950*80)) | O50: =A50*J50 | P50: =A50*K50 | Q50: =A50*L50 | R50: =1-P50 | S50: =1-Q50
C51: 6.3 Information security awareness, education and training | D51: ISO/IEC 27002:2022 | E51: 40 | H51: 30000 | I51: 500 | J51: 0.01 | K51: 0.06 | L51: 0.06 | N51: =A51*((SUM(F51:I51))+(J51*1950*80)) | O51: =A51*J51 | P51: =A51*K51 | Q51: =A51*L51 | R51: =1-P51 | S51: =1-Q51
C52: 6.4 Disciplinary process | D52: ISO/IEC 27002:2022 | E52: 41 | H52: 10000 | I52: 500 | J52: 0.01 | K52: 0.01 | L52: 0.01 | N52: =A52*((SUM(F52:I52))+(J52*1950*80)) | O52: =A52*J52 | P52: =A52*K52 | Q52: =A52*L52 | R52: =1-P52 | S52: =1-Q52
C53: 6.5 Responsibilities after termination or change of employment | D53: ISO/IEC 27002:2022 | E53: 42 | H53: 5000 | I53: 500 | J53: 0.01 | K53: 0.05 | L53: 0.02 | N53: =A53*((SUM(F53:I53))+(J53*1950*80)) | O53: =A53*J53 | P53: =A53*K53 | Q53: =A53*L53 | R53: =1-P53 | S53: =1-Q53
C54: 6.6 Confidentiality or non-disclosure agreements | D54: ISO/IEC 27002:2022 | E54: 43 | H54: 20000 | I54: 1000 | J54: 0.02 | K54: 0.02 | L54: 0.02 | N54: =A54*((SUM(F54:I54))+(J54*1950*80)) | O54: =A54*J54 | P54: =A54*K54 | Q54: =A54*L54 | R54: =1-P54 | S54: =1-Q54
C55: 6.7 Remote working | D55: ISO/IEC 27002:2022 | E55: 44 | H55: 5000 | I55: 2000 | J55: 0.05 | K55: 0.01 | L55: 0.01 | N55: =A55*((SUM(F55:I55))+(J55*1950*80)) | O55: =A55*J55 | P55: =A55*K55 | Q55: =A55*L55 | R55: =1-P55 | S55: =1-Q55
C56: 6.8 Information security event reporting | D56: ISO/IEC 27002:2022 | E56: 45 | H56: 10000 | I56: 1000 | J56: 0.02 | K56: 0.01 | L56: 0.01 | N56: =A56*((SUM(F56:I56))+(J56*1950*80)) | O56: =A56*J56 | P56: =A56*K56 | Q56: =A56*L56 | R56: =1-P56 | S56: =1-Q56
C57: 7 Physical controls / Mesures physiques
C58: 7.1 Physical security perimeters | D58: ISO/IEC 27002:2022 | E58: 46 | F58: 10000 | G58: 50000 | H58: 10000 | I58: 500 | J58: 0.02 | K58: 0.06 | L58: 0.06 | N58: =A58*((SUM(F58:I58))+(J58*1950*80)) | O58: =A58*J58 | P58: =A58*K58 | Q58: =A58*L58 | R58: =1-P58 | S58: =1-Q58
C59: 7.2 Physical entry | D59: ISO/IEC 27002:2022 | E59: 47 | F59: 10000 | G59: 50000 | H59: 10000 | I59: 500 | J59: 0.02 | K59: 0.06 | L59: 0.06 | N59: =A59*((SUM(F59:I59))+(J59*1950*80)) | O59: =A59*J59 | P59: =A59*K59 | Q59: =A59*L59 | R59: =1-P59 | S59: =1-Q59
C60: 7.3 Securing offices, rooms and facilities | D60: ISO/IEC 27002:2022 | E60: 48 | F60: 10000 | G60: 50000 | H60: 10000 | I60: 500 | J60: 0.02 | K60: 0.01 | L60: 0.01 | N60: =A60*((SUM(F60:I60))+(J60*1950*80)) | O60: =A60*J60 | P60: =A60*K60 | Q60: =A60*L60 | R60: =1-P60 | S60: =1-Q60
C61: 7.4 Physical security monitoring | D61: ISO/IEC 27002:2022 | E61: 49 | H61: 10000 | I61: 1000 | J61: 0.02 | K61: 0.01 | L61: 0.01 | N61: =A61*((SUM(F61:I61))+(J61*1950*80)) | O61: =A61*J61 | P61: =A61*K61 | Q61: =A61*L61 | R61: =1-P61 | S61: =1-Q61
C62: 7.5 Protecting against physical and environmental threats | D62: ISO/IEC 27002:2022 | E62: 50 | F62: 10000 | G62: 50000 | H62: 10000 | I62: 100 | J62: 0.02 | K62: 0.06 | L62: 0.06 | N62: =A62*((SUM(F62:I62))+(J62*1950*80)) | O62: =A62*J62 | P62: =A62*K62 | Q62: =A62*L62 | R62: =1-P62 | S62: =1-Q62
C63: 7.6 Working in secure areas | D63: ISO/IEC 27002:2022 | E63: 51 | F63: 10000 | G63: 50000 | H63: 10000 | I63: 100 | J63: 0.02 | K63: 0.01 | L63: 0.01 | N63: =A63*((SUM(F63:I63))+(J63*1950*80)) | O63: =A63*J63 | P63: =A63*K63 | Q63: =A63*L63 | R63: =1-P63 | S63: =1-Q63
C64: 7.7 Clear desk and clear screen | D64: ISO/IEC 27002:2022 | E64: 52 | H64: 5000 | I64: 100 | J64: 0.01 | K64: 0.01 | L64: 0.01 | N64: =A64*((SUM(F64:I64))+(J64*1950*80)) | O64: =A64*J64 | P64: =A64*K64 | Q64: =A64*L64 | R64: =1-P64 | S64: =1-Q64
C65: 7.8 Equipment siting and protection | D65: ISO/IEC 27002:2022 | E65: 53 | F65: 10000 | H65: 10000 | I65: 500 | J65: 0.02 | K65: 0.06 | L65: 0.06 | N65: =A65*((SUM(F65:I65))+(J65*1950*80)) | O65: =A65*J65 | P65: =A65*K65 | Q65: =A65*L65 | R65: =1-P65 | S65: =1-Q65
C66: 7.9 Security of assets off-premises | D66: ISO/IEC 27002:2022 | E66: 54 | G66: 50000 | H66: 10000 | I66: 100 | J66: 0.01 | K66: 0.01 | L66: 0.01 | N66: =A66*((SUM(F66:I66))+(J66*1950*80)) | O66: =A66*J66 | P66: =A66*K66 | Q66: =A66*L66 | R66: =1-P66 | S66: =1-Q66
C67: 7.10 Storage media | D67: ISO/IEC 27002:2022 | E67: 55 | G67: 5000 | H67: 5000 | I67: 100 | J67: 0.02 | K67: 0.01 | L67: 0.01 | N67: =A67*((SUM(F67:I67))+(J67*1950*80)) | O67: =A67*J67 | P67: =A67*K67 | Q67: =A67*L67 | R67: =1-P67 | S67: =1-Q67
C68: 7.11 Supporting utilities | D68: ISO/IEC 27002:2022 | E68: 56 | F68: 10000 | G68: 50000 | H68: 10000 | I68: 100 | J68: 0.01 | K68: 0.01 | L68: 0.01 | N68: =A68*((SUM(F68:I68))+(J68*1950*80)) | O68: =A68*J68 | P68: =A68*K68 | Q68: =A68*L68 | R68: =1-P68 | S68: =1-Q68
C69: 7.12 Cabling security | D69: ISO/IEC 27002:2022 | E69: 57 | F69: 10000 | G69: 50000 | H69: 10000 | I69: 100 | J69: 0.01 | K69: 0.01 | L69: 0.01 | N69: =A69*((SUM(F69:I69))+(J69*1950*80)) | O69: =A69*J69 | P69: =A69*K69 | Q69: =A69*L69 | R69: =1-P69 | S69: =1-Q69
C70: 7.13 Equipment maintenance | D70: ISO/IEC 27002:2022 | E70: 58 | F70: 10000 | G70: 50000 | H70: 10000 | I70: 500 | J70: 0.01 | K70: 0.01 | L70: 0.01 | N70: =A70*((SUM(F70:I70))+(J70*1950*80)) | O70: =A70*J70 | P70: =A70*K70 | Q70: =A70*L70 | R70: =1-P70 | S70: =1-Q70
C71: 7.14 Secure disposal or re-use of equipment | D71: ISO/IEC 27002:2022 | E71: 59 | G71: 50000 | H71: 10000 | I71: 100 | J71: 0.01 | K71: 0.01 | L71: 0.01 | N71: =A71*((SUM(F71:I71))+(J71*1950*80)) | O71: =A71*J71 | P71: =A71*K71 | Q71: =A71*L71 | R71: =1-P71 | S71: =1-Q71
C72: 8 Technological controls / Mesures technologiques
C73: 8.1 User end point devices | D73: ISO/IEC 27002:2022 | E73: 60 | H73: 5000 | I73: 500 | J73: 0.01 | K73: 0.01 | L73: 0.01 | N73: =A73*((SUM(F73:I73))+(J73*1950*80)) | O73: =A73*J73 | P73: =A73*K73 | Q73: =A73*L73 | R73: =1-P73 | S73: =1-Q73
C74: 8.2 Privileged access rights | D74: ISO/IEC 27002:2022 | E74: 61 | G74: 5000 | H74: 5000 | I74: 100 | J74: 0.01 | K74: 0.06 | L74: 0.06 | N74: =A74*((SUM(F74:I74))+(J74*1950*80)) | O74: =A74*J74 | P74: =A74*K74 | Q74: =A74*L74 | R74: =1-P74 | S74: =1-Q74
C75: 8.3 Information access restriction | D75: ISO/IEC 27002:2022 | E75: 62 | G75: 5000 | H75: 5000 | I75: 100 | J75: 0.01 | K75: 0.065 | L75: 0.06 | N75: =A75*((SUM(F75:I75))+(J75*1950*80)) | O75: =A75*J75 | P75: =A75*K75 | Q75: =A75*L75 | R75: =1-P75 | S75: =1-Q75
C76: 8.4 Access to source code | D76: ISO/IEC 27002:2022 | E76: 63 | G76: 5000 | H76: 5000 | I76: 100 | J76: 0.01 | K76: 0.01 | L76: 0.01 | N76: =A76*((SUM(F76:I76))+(J76*1950*80)) | O76: =A76*J76 | P76: =A76*K76 | Q76: =A76*L76 | R76: =1-P76 | S76: =1-Q76
C77: 8.5 Secure authentication | D77: ISO/IEC 27002:2022 | E77: 64 | G77: 5000 | H77: 5000 | I77: 100 | J77: 0.01 | K77: 0.01 | L77: 0.01 | N77: =A77*((SUM(F77:I77))+(J77*1950*80)) | O77: =A77*J77 | P77: =A77*K77 | Q77: =A77*L77 | R77: =1-P77 | S77: =1-Q77
C78: 8.6 Capacity management | D78: ISO/IEC 27002:2022 | E78: 65 | H78: 50000 | I78: 100 | J78: 0.01 | K78: 0.01 | L78: 0.01 | N78: =A78*((SUM(F78:I78))+(J78*1950*80)) | O78: =A78*J78 | P78: =A78*K78 | Q78: =A78*L78 | R78: =1-P78 | S78: =1-Q78
C79: 8.7 Protection against malware | D79: ISO/IEC 27002:2022 | E79: 66 | G79: 5000 | H79: 25000 | I79: 200 | J79: 0.06 | K79: 0.08 | L79: 0.08 | N79: =A79*((SUM(F79:I79))+(J79*1950*80)) | O79: =A79*J79 | P79: =A79*K79 | Q79: =A79*L79 | R79: =1-P79 | S79: =1-Q79
C80: 8.8 Management of technical vulnerabilities | D80: ISO/IEC 27002:2022 | E80: 67 | F80: 5000 | G80: 25000 | H80: 50000 | I80: 10000 | J80: 0.06 | K80: 0.065 | L80: 0.065 | N80: =A80*((SUM(F80:I80))+(J80*1950*80)) | O80: =A80*J80 | P80: =A80*K80 | Q80: =A80*L80 | R80: =1-P80 | S80: =1-Q80
C81: 8.9 Configuration management | D81: ISO/IEC 27002:2022 | E81: 68 | H81: 10000 | I81: 1000 | J81: 0.02 | K81: 0.01 | L81: 0.01 | N81: =A81*((SUM(F81:I81))+(J81*1950*80)) | O81: =A81*J81 | P81: =A81*K81 | Q81: =A81*L81 | R81: =1-P81 | S81: =1-Q81
C82: 8.10 Information deletion | D82: ISO/IEC 27002:2022 | E82: 69 | H82: 10000 | I82: 1000 | J82: 0.02 | K82: 0.01 | L82: 0.01 | N82: =A82*((SUM(F82:I82))+(J82*1950*80)) | O82: =A82*J82 | P82: =A82*K82 | Q82: =A82*L82 | R82: =1-P82 | S82: =1-Q82
C83: 8.11 Data masking | D83: ISO/IEC 27002:2022 | E83: 70 | H83: 10000 | I83: 1000 | J83: 0.02 | K83: 0.01 | L83: 0.01 | N83: =A83*((SUM(F83:I83))+(J83*1950*80)) | O83: =A83*J83 | P83: =A83*K83 | Q83: =A83*L83 | R83: =1-P83 | S83: =1-Q83
C84: 8.12 Data leakage prevention | D84: ISO/IEC 27002:2022 | E84: 71 | H84: 10000 | I84: 1000 | J84: 0.02 | K84: 0.01 | L84: 0.01 | N84: =A84*((SUM(F84:I84))+(J84*1950*80)) | O84: =A84*J84 | P84: =A84*K84 | Q84: =A84*L84 | R84: =1-P84 | S84: =1-Q84
C85: 8.13 Information backup | D85: ISO/IEC 27002:2022 | E85: 72 | F85: 50000 | G85: 10000 | H85: 50000 | I85: 10000 | J85: 0.06 | K85: 0.065 | L85: 0.06 | N85: =A85*((SUM(F85:I85))+(J85*1950*80)) | O85: =A85*J85 | P85: =A85*K85 | Q85: =A85*L85 | R85: =1-P85 | S85: =1-Q85
C86: 8.14 Redundancy of information processing facilities | D86: ISO/IEC 27002:2022 | E86: 73 | H86: 20000 | I86: 50000 | J86: 0.02 | K86: 0.065 | L86: 0.065 | N86: =A86*((SUM(F86:I86))+(J86*1950*80)) | O86: =A86*J86 | P86: =A86*K86 | Q86: =A86*L86 | R86: =1-P86 | S86: =1-Q86
C87: 8.15 Logging | D87: ISO/IEC 27002:2022 | E87: 74 | F87: 10000 | G87: 5000 | H87: 50000 | I87: 10000 | J87: 0.01 | K87: 0.06 | L87: 0.06 | N87: =A87*((SUM(F87:I87))+(J87*1950*80)) | O87: =A87*J87 | P87: =A87*K87 | Q87: =A87*L87 | R87: =1-P87 | S87: =1-Q87
C88: 8.16 Monitoring activities | D88: ISO/IEC 27002:2022 | E88: 75 | H88: 10000 | I88: 1000 | J88: 0.02 | K88: 0.01 | L88: 0.01 | N88: =A88*((SUM(F88:I88))+(J88*1950*80)) | O88: =A88*J88 | P88: =A88*K88 | Q88: =A88*L88 | R88: =1-P88 | S88: =1-Q88
C89: 8.17 Clock synchronization | D89: ISO/IEC 27002:2022 | E89: 76 | H89: 10000 | I89: 1000 | J89: 0.02 | K89: 0.01 | L89: 0.01 | N89: =A89*((SUM(F89:I89))+(J89*1950*80)) | O89: =A89*J89 | P89: =A89*K89 | Q89: =A89*L89 | R89: =1-P89 | S89: =1-Q89
C90: 8.18 Use of privileged utility programs | D90: ISO/IEC 27002:2022 | E90: 77 | G90: 5000 | H90: 5000 | I90: 100 | J90: 0.01 | K90: 0.01 | L90: 0.01 | N90: =A90*((SUM(F90:I90))+(J90*1950*80)) | O90: =A90*J90 | P90: =A90*K90 | Q90: =A90*L90 | R90: =1-P90 | S90: =1-Q90
C91: 8.19 Installation of software on operational systems | D91: ISO/IEC 27002:2022 | E91: 78 | F91: 10000 | G91: 5000 | I91: 500 | J91: 0.02 | K91: 0.06 | L91: 0.06 | N91: =A91*((SUM(F91:I91))+(J91*1950*80)) | O91: =A91*J91 | P91: =A91*K91 | Q91: =A91*L91 | R91: =1-P91 | S91: =1-Q91
C92: 8.20 Networks security | D92: ISO/IEC 27002:2022 | E92: 79 | F92: 5000 | G92: 25000 | H92: 50000 | I92: 10000 | J92: 0.06 | K92: 0.02 | L92: 0.02 | N92: =A92*((SUM(F92:I92))+(J92*1950*80)) | O92: =A92*J92 | P92: =A92*K92 | Q92: =A92*L92 | R92: =1-P92 | S92: =1-Q92
C93: 8.21 Security of network services | D93: ISO/IEC 27002:2022 | E93: 80 | F93: 5000 | G93: 25000 | H93: 50000 | I93: 10000 | J93: 0.06 | K93: 0.02 | L93: 0.02 | N93: =A93*((SUM(F93:I93))+(J93*1950*80)) | O93: =A93*J93 | P93: =A93*K93 | Q93: =A93*L93 | R93: =1-P93 | S93: =1-Q93
C94: 8.22 Segregation of networks | D94: ISO/IEC 27002:2022 | E94: 81 | F94: 5000 | G94: 25000 | H94: 50000 | I94: 10000 | J94: 0.06 | K94: 0.02 | L94: 0.02 | N94: =A94*((SUM(F94:I94))+(J94*1950*80)) | O94: =A94*J94 | P94: =A94*K94 | Q94: =A94*L94 | R94: =1-P94 | S94: =1-Q94
C95: 8.23 Web filtering | D95: ISO/IEC 27002:2022 | E95: 82 | H95: 10000 | I95: 1000 | J95: 0.02 | K95: 0.01 | L95: 0.01 | N95: =A95*((SUM(F95:I95))+(J95*1950*80)) | O95: =A95*J95 | P95: =A95*K95 | Q95: =A95*L95 | R95: =1-P95 | S95: =1-Q95
C96: 8.24 Use of cryptography | D96: ISO/IEC 27002:2022 | E96: 83 | G96: 5000 | H96: 5000 | I96: 100 | J96: 0.01 | K96: 0.01 | L96: 0.01 | N96: =A96*((SUM(F96:I96))+(J96*1950*80)) | O96: =A96*J96 | P96: =A96*K96 | Q96: =A96*L96 | R96: =1-P96 | S96: =1-Q96
C97: 8.25 Secure development life cycle | D97: ISO/IEC 27002:2022 | E97: 84 | H97: 20000 | I97: 1000 | J97: 0.02 | K97: 0.01 | L97: 0.01 | N97: =A97*((SUM(F97:I97))+(J97*1950*80)) | O97: =A97*J97 | P97: =A97*K97 | Q97: =A97*L97 | R97: =1-P97 | S97: =1-Q97
C98: 8.26 Application security requirements | D98: ISO/IEC 27002:2022 | E98: 85 | H98: 20000 | I98: 1000 | J98: 0.02 | K98: 0.02 | L98: 0.02 | N98: =A98*((SUM(F98:I98))+(J98*1950*80)) | O98: =A98*J98 | P98: =A98*K98 | Q98: =A98*L98 | R98: =1-P98 | S98: =1-Q98
C99: 8.27 Secure system architecture and engineering principles | D99: ISO/IEC 27002:2022 | E99: 86 | H99: 20000 | I99: 1000 | J99: 0.02 | K99: 0.01 | L99: 0.01 | N99: =A99*((SUM(F99:I99))+(J99*1950*80)) | O99: =A99*J99 | P99: =A99*K99 | Q99: =A99*L99 | R99: =1-P99 | S99: =1-Q99
C100: 8.28 Secure coding | D100: ISO/IEC 27002:2022 | E100: 87 | H100: 10000 | I100: 1000 | J100: 0.02 | K100: 0.01 | L100: 0.01 | N100: =A100*((SUM(F100:I100))+(J100*1950*80)) | O100: =A100*J100 | P100: =A100*K100 | Q100: =A100*L100 | R100: =1-P100 | S100: =1-Q100
...

Sheet S7
A1: Risk scenario number 7 / Scénario de risque 7
A2: Scenario number / Numéro : | B2: 7
A3: Scenario name / Nom du scénario :
A4: Date of creation / Date de création du scénario :
A6: Probability that the threat will be present = Probabilité de réalisation : Pb(A)
A7: Probability of exploitation = Probabilité d’exploitation: Pb(ψ,A)
A8: Estimated expected damages = Dommage estimé: δe(ψ,A)
A9: Maximal damages = Dommage maximal: δm(ψ,A) | C9: =IF(AND(ISNUMBER(B8),ISNUMBER(B9),B9<B8),"δm should be ≥ δe / δm devrait être ≥ δe","")
A10: Level of organizational resilience = Niveau de résilience: θ(ψ,A) | C10: =IF(AND(B10<>"",OR(NOT(ISNUMBER(B10)),B10<=0,B10>1)),"θ must be in (0, 1] / θ doit être dans ]0, 1]","")
A11: Organizational criticality (expected utility) = Criticité organisationnelle (utilité espérée) : μ(E)
A14: 3. Renseigner les scénarios de risque (feuilles S1 à S10)
A15: 3. Populate the risk scenarios (Sheets S1 to S10)
A16: Values 0-1; θ > 0 and ≤ 1; δm ≥ δe. Horizon: 12 months. Each value: rationale, evidence (E-number), confidence — Analytical estimate — validation required.
A17: Valeurs 0-1; θ > 0 et ≤ 1; δm ≥ δe. Horizon : 12 mois. Chaque valeur : justification, preuve (n° E), confiance — Estimation analytique — validation requise.

Sheet M7
A1: Other / autre | C1: Proposed risk mitigation measure / mesure de mitigation des risques proposés | D1: Source | F1: Immobilisations | G1: Logiciels | H1: Mise en œuvre | I1: Exploitation | J1: ÉTC | K1: Réduc impacts | L1: Réduction Pb | N1: Coût | O1: ETC | P1: Impact | Q1: Pb | R1: 1 − impact | S1: 1 − Pb
N2: =A2*((SUM(F2:I2))+(J2*1950*80)) | O2: =A2*J2 | P2: =A2*K2 | Q2: =A2*L2 | R2: =1-P2 | S2: =1-Q2
N3: =A3*((SUM(F3:I3))+(J3*1950*80)) | O3: =A3*J3 | P3: =A3*K3 | Q3: =A3*L3 | R3: =1-P3 | S3: =1-Q3
N4: =A4*((SUM(F4:I4))+(J4*1950*80)) | O4: =A4*J4 | P4: =A4*K4 | Q4: =A4*L4 | R4: =1-P4 | S4: =1-Q4
N5: =A5*((SUM(F5:I5))+(J5*1950*80)) | O5: =A5*J5 | P5: =A5*K5 | Q5: =A5*L5 | R5: =1-P5 | S5: =1-Q5
N6: =A6*((SUM(F6:I6))+(J6*1950*80)) | O6: =A6*J6 | P6: =A6*K6 | Q6: =A6*L6 | R6: =1-P6 | S6: =1-Q6
N7: =SUM(N2:N6) | O7: =SUM(O2:O6) | P7: =1-PRODUCT(R2:R6) | Q7: =1-PRODUCT(S2:S6)
A8: Include | C8: Control / Contrôle | D8: Source | F8: Immobilisations | G8: Logiciels | H8: Mise en œuvre | I8: Exploitation | J8: ÉTC | K8: Réduc impacts | L8: Réduction Pb | N8: Coût | O8: ETC | P8: Impact | Q8: Pb | R8: 1 − impact | S8: 1 − Pb
A9: Inclure | C9: ISO/IEC 27002:2022 — information security controls (93) / mesures de sécurité de l'information | F9: CAPEX | G9: Software | H9: Implementation | I9: Exploitation | J9: FTE | K9: Reduce impacts | L9: Reduce Pb | N9: Cost | O9: FTE | P9: Impact | Q9: Pb
C10: 5 Organizational controls / Mesures organisationnelles
C11: 5.1 Policies for information security | D11: ISO/IEC 27002:2022 | E11: 1 | H11: 25000 | I11: 3000 | J11: 0.01 | K11: 0.06 | L11: 0.06 | N11: =A11*((SUM(F11:I11))+(J11*1950*80)) | O11: =A11*J11 | P11: =A11*K11 | Q11: =A11*L11 | R11: =1-P11 | S11: =1-Q11
C12: 5.2 Information security roles and responsibilities | D12: ISO/IEC 27002:2022 | E12: 2 | H12: 5000 | I12: 500 | J12: 0.01 | K12: 0.01 | L12: 0.01 | N12: =A12*((SUM(F12:I12))+(J12*1950*80)) | O12: =A12*J12 | P12: =A12*K12 | Q12: =A12*L12 | R12: =1-P12 | S12: =1-Q12
C13: 5.3 Segregation of duties | D13: ISO/IEC 27002:2022 | E13: 3 | H13: 5000 | I13: 500 | J13: 0.01 | K13: 0.01 | L13: 0.01 | N13: =A13*((SUM(F13:I13))+(J13*1950*80)) | O13: =A13*J13 | P13: =A13*K13 | Q13: =A13*L13 | R13: =1-P13 | S13: =1-Q13 | U13: 4. Définir les mesures de mitigation (feuilles M1 à M10)
C14: 5.4 Management responsibilities | D14: ISO/IEC 27002:2022 | E14: 4 | H14: 5000 | I14: 500 | J14: 0.01 | K14: 0.01 | L14: 0.01 | N14: =A14*((SUM(F14:I14))+(J14*1950*80)) | O14: =A14*J14 | P14: =A14*K14 | Q14: =A14*L14 | R14: =1-P14 | S14: =1-Q14 | U14: dans la colonne A Inclure Mesure
C15: 5.5 Contact with authorities | D15: ISO/IEC 27002:2022 | E15: 5 | H15: 5000 | J15: =1/50 | K15: 0.01 | L15: 0.01 | N15: =A15*((SUM(F15:I15))+(J15*1950*80)) | O15: =A15*J15 | P15: =A15*K15 | Q15: =A15*L15 | R15: =1-P15 | S15: =1-Q15 | U15: 0 ou vide = non sélectionné
C16: 5.6 Contact with special interest groups | D16: ISO/IEC 27002:2022 | E16: 6 | H16: 5000 | J16: =3/50 | K16: 0.01 | L16: 0.01 | N16: =A16*((SUM(F16:I16))+(J16*1950*80)) | O16: =A16*J16 | P16: =A16*K16 | Q16: =A16*L16 | R16: =1-P16 | S16: =1-Q16 | U16: 6. Define the risk mitigation measures (Sheets M1 to M10)
C17: 5.7 Threat intelligence | D17: ISO/IEC 27002:2022 | E17: 7 | H17: 10000 | I17: 1000 | J17: 0.02 | K17: 0.01 | L17: 0.01 | N17: =A17*((SUM(F17:I17))+(J17*1950*80)) | O17: =A17*J17 | P17: =A17*K17 | Q17: =A17*L17 | R17: =1-P17 | S17: =1-Q17
C18: 5.8 Information security in project management | D18: ISO/IEC 27002:2022 | E18: 8 | H18: 5000 | J18: 0.06 | K18: 0.06 | L18: 0.06 | N18: =A18*((SUM(F18:I18))+(J18*1950*80)) | O18: =A18*J18 | P18: =A18*K18 | Q18: =A18*L18 | R18: =1-P18 | S18: =1-Q18 | U18: 4. Define the risk mitigation measures (Sheets M1 to M10)
